Workbook
Name FID_1: [1]AGR_Fuels!$A$2

Sheet Cover
A3: Colour code
B4: Referenced data (columns and rows headers)
B5: Own calculations (columns and rows headers)
B6: Own assumptions (columns and rows headers)
A7: aaa | B7: Results
B8: Sheets which contains input tables for the RES BY-Template
B9: Sheets which contains input tables (not activated) for the building retrofit SubRes (SubRES_RsdRetrofits_Trans.xlsx)

Sheet TechComm
T1: Vintages
B2: MovedToSysSettings | K2: ~FI_Process | T2: 1 | U2: < 1945 | V2: 1940 | Y2: 12 | Z2: kw equipment
B3: Csets | C3: CommName | D3: CommDesc | E3: Unit | F3: LimType | G3: CTSLvl | H3: PeakTS | I3: Ctype | K3: Sets | L3: TechName | M3: TechDesc | N3: Tact | O3: Tcap | P3: Tslvl | Q3: PrimaryCG | R3: Vintage | T3: 2 | U3: 1945-1969 | V3: 1957 | Y3: 0.25 | Z3: utilization
B4: DEM | C4: ="R_"&U11 -> R_Flat | D4: =M4 & " (DEM)" -> Residential Dwelling - Flat (DEM) | E4: =O4 -> 000units | K4: DMD | L4: ="Rdw_"&U11 -> Rdw_Flat | M4: ="Residential Dwelling - "&T11 -> Residential Dwelling - Flat | N4: 000units | O4: 000units | R4: Yes | T4: 3 | U4: 1970-1979 | V4: 1975 | Y4: =Y2*8.76*Y3*3.6 -> 94.608 | Z4: GJ
C5: ="R_"&U13 -> R_DetH | D5: =M5 & " (DEM)" -> Residential Dwelling - Detached house 1945 to 1969 (DEM) | E5: =O5 -> 000units | L5: ="Rdw_"&U13 -> Rdw_DetH | M5: ="Residential Dwelling - "&T13 -> Residential Dwelling - Detached house 1945 to 1969 | N5: 000units | O5: 000units | R5: Yes | T5: 4 | U5: 1980-1989 | V5: 1985
C6: ="R_"&U15 -> R_SDetH | D6: =M7 & " (DEM)" -> Residential Dwelling - Semi-detached house (DEM) | E6: =O7 -> 000units | L6: ="Rdw_"&U14 -> Rdw_DetH-70 | M6: ="Residential Dwelling - "&T14 -> Residential Dwelling - Detached house 1970 to 2010 | N6: 000units | O6: 000units | R6: Yes | T6: 5 | U6: 1990-1999 | V6: 1995
C7: ='TechELC-RES'!E4 -> RLIG | D7: ="Residential - "&X15& " (DEM)" -> Residential - Lighting (DEM) | E7: =N90 -> M_appliances | L7: ="Rdw_"&U15 -> Rdw_SDetH | M7: ="Residential Dwelling - "&T15 -> Residential Dwelling - Semi-detached house | N7: 000units | O7: 000units | R7: Yes | T7: 6 | U7: 2000-2008 | V7: 2004
C8: ='TechELC-RES'!E21 -> RREF | D8: ="Residential - "&X16& " (DEM)" -> Residential - Refrigerators and freezers (DEM) | E8: =N91 -> M_appliances | K8: PRE | L8: ="R_ES-SH-FL_"&RIGHT(U23,3)&"-R" -> R_ES-SH-FL_ELC-R | M8: ="Residential boiler for sp heat - "&$T$11&" : "&T23&" Resistance" -> Residential boiler for sp heat - Flat : Electricity Resistance | N8: PJ | O8: GW | R8: Yes
C9: ='TechELC-RES'!E38 -> RCWA | D9: ="Residential - "&X17& " (DEM)" -> Residential - Washing machine (DEM) | E9: =N92 -> M_appliances | L9: ="R_ES-SH-FL_"&RIGHT(U23,3)&"-HPA" -> R_ES-SH-FL_ELC-HPA | M9: ="Residential boiler for sp heat - "&$T$11&" : "&T23&" Heat Pump Air" -> Residential boiler for sp heat - Flat : Electricity Heat Pump Air | N9: PJ | O9: GW | R9: Yes
C10: ='TechELC-RES'!E55 -> RCDR | D10: ="Residential - "&X18& " (DEM)" -> Residential - Clothes dryer (DEM) | E10: =N93 -> M_appliances | L10: ="R_ES-SH-FL_"&RIGHT(U23,3)&"-HPG" -> R_ES-SH-FL_ELC-HPG | M10: ="Residential boiler for sp heat - "&$T$11&" : "&T23&" Heat Pump Ground" -> Residential boiler for sp heat - Flat : Electricity Heat Pump Ground | N10: PJ | O10: GW | R10: Yes
C11: ='TechELC-RES'!E72 -> RDWA | D11: ="Residential - "&X19& " (DEM)" -> Residential - Dishwasher (DEM) | E11: =N94 -> M_appliances | L11: ="R_ES-SH-FL_"&RIGHT(U24,3) -> R_ES-SH-FL_GAS | M11: ="Residential boiler for sp heat - "&$T$11&" : "&T24 -> Residential boiler for sp heat - Flat : Gases | N11: PJ | O11: GW | R11: Yes | T11: Flat | U11: Flat | V11: FL
C12: ='TechELC-RES'!E89 -> ROEL | D12: ="Residential - "&X20& " (DEM)" -> Residential - Other ELC (DEM) | E12: =N95 -> M_appliances | L12: ="R_ES-SH-FL_"&RIGHT(U25,3) -> R_ES-SH-FL_HET | M12: ="Residential boiler for sp heat - "&$T$11&" : "&T25 -> Residential boiler for sp heat - Flat : Derived heat | N12: PJ | O12: GW | R12: Yes | T12: Detached house
B13: NRG | C13: ="R_ES-"&V11&"-"&$U$18 -> R_ES-FL-Cook | D13: ="Residential Energy Service for - "&T11&" - "&$T$18 -> Residential Energy Service for - Flat - Cooking | E13: PJ | L13: ="R_ES-SH-FL_"&RIGHT(U26,3) -> R_ES-SH-FL_OIL | M13: ="Residential boiler for sp heat - "&$T$11&" : "&T26 -> Residential boiler for sp heat - Flat : GDO and other liquids (incl. liq. bio.) | N13: PJ | O13: GW | R13: Yes | T13: Detached house 1945 to 1969 | U13: DetH | V13: DH
C14: ="R_ES-"&V13&"-"&$U$18 -> R_ES-DH-Cook | D14: ="Residential Energy Service for - "&T12&" - "&$T$18 -> Residential Energy Service for - Detached house - Cooking | E14: PJ | L14: ="R_ES-SH-FL_"&RIGHT(U27,3) -> R_ES-SH-FL_BIO | M14: ="Residential boiler for sp heat - "&$T$11&" : "&T27 -> Residential boiler for sp heat - Flat : Biomass and wastes | N14: PJ | O14: GW | R14: Yes | T14: Detached house 1970 to 2010 | U14: DetH-70 | V14: DH-70
C15: ="R_ES-"&V15&"-"&$U$18 -> R_ES-SD-Cook | D15: ="Residential Energy Service for - "&T15&" - "&$T$18 -> Residential Energy Service for - Semi-detached house - Cooking | E15: PJ | L15: ="R_ES-SH-FL_"&RIGHT(U28,3) -> R_ES-SH-FL_COA | M15: ="Residential boiler for sp heat - "&$T$11&" : "&T28 -> Residential boiler for sp heat - Flat : Solids | N15: PJ | O15: GW | R15: Yes | T15: Semi-detached house | U15: SDetH | V15: SD | X15: ='TechELC-RES'!A3 -> Lighting
C16: ="R_ES-"&V11&"-"&$U$19 -> R_ES-FL-SpCool | D16: ="Residential Energy Service for - "&T11&" - "&$T$19 -> Residential Energy Service for - Flat - Cooling | E16: PJ | L16: ="R_ES-SH-FL_"&RIGHT(U29,3) -> R_ES-SH-FL_LPG | M16: ="Residential boiler for sp heat - "&$T$11&" : "&T29 -> Residential boiler for sp heat - Flat : LPG | N16: PJ | O16: GW | R16: Yes | X16: ='TechELC-RES'!A20 -> Refrigerators and freezers
C17: ="R_ES-"&V13&"-"&$U$19 -> R_ES-DH-SpCool | D17: ="Residential Energy Service for - "&T12&" - "&$T$19 -> Residential Energy Service for - Detached house - Cooling | E17: PJ | L17: ="R_ES-SH-FL_"&RIGHT(U31,3) -> R_ES-SH-FL_GEO | M17: ="Residential boiler for sp heat - "&$T$11&" : "&T31 -> Residential boiler for sp heat - Flat : Geothermal Energy | N17: PJ | O17: GW | R17: Yes | X17: ='TechELC-RES'!A37 -> Washing machine
C18: ="R_ES-"&V15&"-"&$U$19 -> R_ES-SD-SpCool | D18: ="Residential Energy Service for - "&T15&" - "&$T$19 -> Residential Energy Service for - Semi-detached house - Cooling | E18: PJ | L18: ="R_ES-SH-DH_"&RIGHT(U23,3)&"-R" -> R_ES-SH-DH_ELC-R | M18: ="Residential boiler for sp heat - "&$T$13&" : "&T23&" Resistance" -> Residential boiler for sp heat - Detached house 1945 to 1969 : Electricity Resistance | N18: PJ | O18: GW | R18: Yes | T18: Cooking | U18: Cook | V18: CK | X18: ='TechELC-RES'!A54 -> Clothes dryer
C19: ="R_ES-"&V11&"-"&$U$21 -> R_ES-FL-WatHeat | D19: ="Residential Energy Service for - "&T11&" - "&$T$21 -> Residential Energy Service for - Flat - Water heating | E19: PJ | L19: ="R_ES-SH-DH_"&RIGHT(U23,3)&"-HPA" -> R_ES-SH-DH_ELC-HPA | M19: ="Residential boiler for sp heat - "&$T$13&" : "&T23&" Heat Pump Air" -> Residential boiler for sp heat - Detached house 1945 to 1969 : Electricity Heat Pump Air | N19: PJ | O19: GW | R19: Yes | T19: Cooling | U19: SpCool | V19: SC | X19: ='TechELC-RES'!A71 -> Dishwasher
C20: ="R_ES-"&V13&"-"&$U$21 -> R_ES-DH-WatHeat | D20: ="Residential Energy Service for - "&T12&" - "&$T$21 -> Residential Energy Service for - Detached house - Water heating | E20: PJ | L20: ="R_ES-SH-DH_"&RIGHT(U23,3)&"-HPG" -> R_ES-SH-DH_ELC-HPG | M20: ="Residential boiler for sp heat - "&$T$13&" : "&T23&" Heat Pump Ground" -> Residential boiler for sp heat - Detached house 1945 to 1969 : Electricity Heat Pump Ground | N20: PJ | O20: GW | R20: Yes | T20: Space heating | U20: SpHeat | V20: SH | X20: ='TechELC-RES'!A88 -> Other ELC
C21: ="R_ES-"&V15&"-"&$U$21 -> R_ES-SD-WatHeat | D21: ="Residential Energy Service for - "&T15&" - "&$T$21 -> Residential Energy Service for - Semi-detached house - Water heating | E21: PJ | L21: ="R_ES-SH-DH_"&RIGHT(U24,3) -> R_ES-SH-DH_GAS | M21: ="Residential boiler for sp heat - "&$T$13&" : "&T24 -> Residential boiler for sp heat - Detached house 1945 to 1969 : Gases | N21: PJ | O21: GW | R21: Yes | T21: Water heating | U21: WatHeat | V21: WH
C22: ="R_ES-"&V11&"-"&$U$20 -> R_ES-FL-SpHeat | D22: ="Residential Energy Service for - "&T11&" - "&$T$20 -> Residential Energy Service for - Flat - Space heating | E22: PJ | L22: ="R_ES-SH-DH_"&RIGHT(U25,3) -> R_ES-SH-DH_HET | M22: ="Residential boiler for sp heat - "&$T$13&" : "&T25 -> Residential boiler for sp heat - Detached house 1945 to 1969 : Derived heat | N22: PJ | O22: GW | R22: Yes
C23: ="R_ES-"&V13&"-"&$U$20 -> R_ES-DH-SpHeat | D23: ="Residential Energy Service for - "&T12&" - "&$T$20 -> Residential Energy Service for - Detached house - Space heating | E23: PJ | L23: ="R_ES-SH-DH_"&RIGHT(U26,3) -> R_ES-SH-DH_OIL | M23: ="Residential boiler for sp heat - "&$T$13&" : "&T26 -> Residential boiler for sp heat - Detached house 1945 to 1969 : GDO and other liquids (incl. liq. bio.) | N23: PJ | O23: GW | R23: Yes | T23: Electricity | U23: RSDELC
C24: ="R_ES-"&V15&"-"&$U$20 -> R_ES-SD-SpHeat | D24: ="Residential Energy Service for - "&T15&" - "&$T$20 -> Residential Energy Service for - Semi-detached house - Space heating | E24: PJ | L24: ="R_ES-SH-DH_"&RIGHT(U27,3) -> R_ES-SH-DH_BIO | M24: ="Residential boiler for sp heat - "&$T$13&" : "&T27 -> Residential boiler for sp heat - Detached house 1945 to 1969 : Biomass and wastes | N24: PJ | O24: GW | R24: Yes | T24: Gases | U24: RSDGAS
C25: =U23 -> RSDELC | D25: ="Residential Fuel - "&T23 -> Residential Fuel - Electricity | E25: PJ | G25: DAYNITE | I25: ELC | L25: ="R_ES-SH-DH_"&RIGHT(U28,3) -> R_ES-SH-DH_COA | M25: ="Residential boiler for sp heat - "&$T$13&" : "&T28 -> Residential boiler for sp heat - Detached house 1945 to 1969 : Solids | N25: PJ | O25: GW | R25: Yes | T25: Derived heat | U25: RSDHET
C26: =U24 -> RSDGAS | D26: ="Residential Fuel - "&T24 -> Residential Fuel - Gases | E26: PJ | G26: SEASON | L26: ="R_ES-SH-DH_"&RIGHT(U29,3) -> R_ES-SH-DH_LPG | M26: ="Residential boiler for sp heat - "&$T$13&" : "&T29 -> Residential boiler for sp heat - Detached house 1945 to 1969 : LPG | N26: PJ | O26: GW | R26: Yes | T26: GDO and other liquids (incl. liq. bio.) | U26: RSDOIL
C27: =U25 -> RSDHET | D27: ="Residential Fuel - "&T25 -> Residential Fuel - Derived heat | E27: PJ | G27: SEASON | L27: ="R_ES-SH-DH_"&RIGHT(U31,3) -> R_ES-SH-DH_GEO | M27: ="Residential boiler for sp heat - "&$T$13&" : "&T31 -> Residential boiler for sp heat - Detached house 1945 to 1969 : Geothermal Energy | N27: PJ | O27: GW | R27: Yes | T27: Biomass and wastes | U27: RSDBIO
C28: =U26 -> RSDOIL | D28: ="Residential Fuel - "&T26 -> Residential Fuel - GDO and other liquids (incl. liq. bio.) | E28: PJ | L28: ="R_ES-SH-DH-70_"&RIGHT(U23,3)&"-R" -> R_ES-SH-DH-70_ELC-R | M28: ="Residential boiler for sp heat - "&$T$14&" : "&T23&" Resistance" -> Residential boiler for sp heat - Detached house 1970 to 2010 : Electricity Resistance | N28: PJ | O28: GW | R28: Yes | T28: Solids | U28: RSDCOA
C29: =U27 -> RSDBIO | D29: ="Residential Fuel - "&T27 -> Residential Fuel - Biomass and wastes | E29: PJ | L29: ="R_ES-SH-DH-70_"&RIGHT(U23,3)&"-HPA" -> R_ES-SH-DH-70_ELC-HPA | M29: ="Residential boiler for sp heat - "&$T$14&" : "&T23&" Heat Pump Air" -> Residential boiler for sp heat - Detached house 1970 to 2010 : Electricity Heat Pump Air | N29: PJ | O29: GW | R29: Yes | T29: LPG | U29: RSDLPG
C30: =U28 -> RSDCOA | D30: ="Residential Fuel - "&T28 -> Residential Fuel - Solids | E30: PJ | L30: ="R_ES-SH-DH-70_"&RIGHT(U23,3)&"-HPG" -> R_ES-SH-DH-70_ELC-HPG | M30: ="Residential boiler for sp heat - "&$T$14&" : "&T23&" Heat Pump Ground" -> Residential boiler for sp heat - Detached house 1970 to 2010 : Electricity Heat Pump Ground | N30: PJ | O30: GW | R30: Yes | T30: Solar | U30: RSDSOL
C31: =U29 -> RSDLPG | D31: ="Residential Fuel - "&T29 -> Residential Fuel - LPG | E31: PJ | L31: ="R_ES-SH-DH-70_"&RIGHT(U24,3) -> R_ES-SH-DH-70_GAS | M31: ="Residential boiler for sp heat - "&$T$14&" : "&T24 -> Residential boiler for sp heat - Detached house 1970 to 2010 : Gases | N31: PJ | O31: GW | R31: Yes | T31: Geothermal Energy | U31: RSDGEO
C32: =U30 -> RSDSOL | D32: ="Residential Fuel - "&T30 -> Residential Fuel - Solar | E32: PJ | L32: ="R_ES-SH-DH-70_"&RIGHT(U25,3) -> R_ES-SH-DH-70_HET | M32: ="Residential boiler for sp heat - "&$T$14&" : "&T25 -> Residential boiler for sp heat - Detached house 1970 to 2010 : Derived heat | N32: PJ | O32: GW | R32: Yes
B33: ENV | C33: RSDCO2N | D33: Carbon Dioxide - RSDbustion (RSD) | E33: kt | L33: ="R_ES-SH-DH-70_"&RIGHT(U26,3) -> R_ES-SH-DH-70_OIL | M33: ="Residential boiler for sp heat - "&$T$14&" : "&T26 -> Residential boiler for sp heat - Detached house 1970 to 2010 : GDO and other liquids (incl. liq. bio.) | N33: PJ | O33: GW | R33: Yes
C34: RSDCOXN | D34: Carbon Monoxide - RSDbustion (RSD) | E34: kt | L34: ="R_ES-SH-DH-70_"&RIGHT(U27,3) -> R_ES-SH-DH-70_BIO | M34: ="Residential boiler for sp heat - "&$T$14&" : "&T27 -> Residential boiler for sp heat - Detached house 1970 to 2010 : Biomass and wastes | N34: PJ | O34: GW | R34: Yes
C35: RSDCH4N | D35: Methane - RSDbustion (RSD) | E35: kt | L35: ="R_ES-SH-DH-70_"&RIGHT(U28,3) -> R_ES-SH-DH-70_COA | M35: ="Residential boiler for sp heat - "&$T$14&" : "&T28 -> Residential boiler for sp heat - Detached house 1970 to 2010 : Solids | N35: PJ | O35: GW | R35: Yes
C36: RSDSO2N | D36: Sulphur Dioxide - RSDbustion (RSD) | E36: kt | L36: ="R_ES-SH-DH-70_"&RIGHT(U29,3) -> R_ES-SH-DH-70_LPG | M36: ="Residential boiler for sp heat - "&$T$14&" : "&T29 -> Residential boiler for sp heat - Detached house 1970 to 2010 : LPG | N36: PJ | O36: GW | R36: Yes
C37: RSDNOXN | D37: Nitrogen Oxides - RSDbustion (RSD) | E37: kt | L37: ="R_ES-SH-DH-70_"&RIGHT(U31,3) -> R_ES-SH-DH-70_GEO | M37: ="Residential boiler for sp heat - "&$T$14&" : "&T31 -> Residential boiler for sp heat - Detached house 1970 to 2010 : Geothermal Energy | N37: PJ | O37: GW | R37: Yes
C38: RSDN2ON | D38: Nitrous Oxide - RSDbustion (RSD) | E38: kt | L38: ="R_ES-SH-SD_"&RIGHT(U23,3)&"-R" -> R_ES-SH-SD_ELC-R | M38: ="Residential boiler for sp heat - "&$T$15&" : "&T23&" Resistance" -> Residential boiler for sp heat - Semi-detached house : Electricity Resistance | N38: PJ | O38: GW | R38: Yes
C39: RSDPMAN | D39: Particulate 2.5 - RSDbustion (RSD) | E39: kt | L39: ="R_ES-SH-SD_"&RIGHT(U23,3)&"-HPA" -> R_ES-SH-SD_ELC-HPA | M39: ="Residential boiler for sp heat - "&$T$15&" : "&T23&" Heat Pump Air" -> Residential boiler for sp heat - Semi-detached house : Electricity Heat Pump Air | N39: PJ | O39: GW | R39: Yes
C40: RSDPMBN | D40: Particulate 10 - RSDbustion (RSD) | E40: kt | L40: ="R_ES-SH-SD_"&RIGHT(U23,3)&"-HPG" -> R_ES-SH-SD_ELC-HPG | M40: ="Residential boiler for sp heat - "&$T$15&" : "&T23&" Heat Pump Ground" -> Residential boiler for sp heat - Semi-detached house : Electricity Heat Pump Ground | N40: PJ | O40: GW | R40: Yes
C41: RSDVOCN | D41: Volatile Organic RSDpounds - RSDbustion (RSD) | E41: kt | L41: ="R_ES-SH-SD_"&RIGHT(U24,3) -> R_ES-SH-SD_GAS | M41: ="Residential boiler for sp heat - "&$T$15&" : "&T24 -> Residential boiler for sp heat - Semi-detached house : Gases | N41: PJ | O41: GW | R41: Yes
C42: RSDSF6N | D42: Sulphur Hexafluoride - RSDbustion (RSD) | E42: kg | L42: ="R_ES-SH-SD_"&RIGHT(U25,3) -> R_ES-SH-SD_HET | M42: ="Residential boiler for sp heat - "&$T$15&" : "&T25 -> Residential boiler for sp heat - Semi-detached house : Derived heat | N42: PJ | O42: GW | R42: Yes
C43: RSDCXFN | D43: Fluoro Carbons - RSDbustion (RSD) | E43: kg | L43: ="R_ES-SH-SD_"&RIGHT(U26,3) -> R_ES-SH-SD_OIL | M43: ="Residential boiler for sp heat - "&$T$15&" : "&T26 -> Residential boiler for sp heat - Semi-detached house : GDO and other liquids (incl. liq. bio.) | N43: PJ | O43: GW | R43: Yes
B44: NRG | C44: COOFRE | D44: Free cooling source (RSD) | E44: PJ | L44: ="R_ES-SH-SD_"&RIGHT(U27,3) -> R_ES-SH-SD_BIO | M44: ="Residential boiler for sp heat - "&$T$15&" : "&T27 -> Residential boiler for sp heat - Semi-detached house : Biomass and wastes | N44: PJ | O44: GW | R44: Yes
C45: RSDCOO | D45: Cooling agent (RSD) | E45: PJ | G45: DAYNITE | L45: ="R_ES-SH-SD_"&RIGHT(U28,3) -> R_ES-SH-SD_COA | M45: ="Residential boiler for sp heat - "&$T$15&" : "&T28 -> Residential boiler for sp heat - Semi-detached house : Solids | N45: PJ | O45: GW | R45: Yes
C46: ='TechHeat-RES'!E307 -> R_ES-FL-SpHeat-I | D46: =CONCATENATE(D22,"-Input to dwelling") -> Residential Energy Service for - Flat - Space heating-Input to dwelling | E46: =E22 -> PJ | L46: ="R_ES-SH-SD_"&RIGHT(U29,3) -> R_ES-SH-SD_LPG | M46: ="Residential boiler for sp heat - "&$T$15&" : "&T29 -> Residential boiler for sp heat - Semi-detached house : LPG | N46: PJ | O46: GW | R46: Yes
C47: ='TechHeat-RES'!E308 -> R_ES-DH-SpHeat-I | D47: =CONCATENATE(D23,"-Input to dwelling") -> Residential Energy Service for - Detached house - Space heating-Input to dwelling | E47: =E23 -> PJ | L47: ="R_ES-SH-SD_"&RIGHT(U31,3) -> R_ES-SH-SD_GEO | M47: ="Residential boiler for sp heat - "&$T$15&" : "&T31 -> Residential boiler for sp heat - Semi-detached house : Geothermal Energy | N47: PJ | O47: GW | R47: Yes
C48: ='TechHeat-RES'!E309 -> R_ES-SD-SpHeat-I | D48: =CONCATENATE(D24,"-Input to dwelling") -> Residential Energy Service for - Semi-detached house - Space heating-Input to dwelling | E48: =E24 -> PJ | L48: ="R_ES-WH-FL_"&RIGHT(U23,3) -> R_ES-WH-FL_ELC | M48: ="Residential boiler for water heat - "&$T$11&" : "&T23 -> Residential boiler for water heat - Flat : Electricity | N48: PJ | O48: GW | R48: Yes
L49: ="R_ES-WH-FL_"&RIGHT(U24,3) -> R_ES-WH-FL_GAS | M49: ="Residential boiler for water heat - "&$T$11&" : "&T24 -> Residential boiler for water heat - Flat : Gases | N49: PJ | O49: GW | R49: Yes
L50: ="R_ES-WH-FL_"&RIGHT(U25,3) -> R_ES-WH-FL_HET | M50: ="Residential boiler for water heat - "&$T$11&" : "&T25 -> Residential boiler for water heat - Flat : Derived heat | N50: PJ | O50: GW | R50: Yes
L51: ="R_ES-WH-FL_"&RIGHT(U26,3) -> R_ES-WH-FL_OIL | M51: ="Residential boiler for water heat - "&$T$11&" : "&T26 -> Residential boiler for water heat - Flat : GDO and other liquids (incl. liq. bio.) | N51: PJ | O51: GW | R51: Yes
L52: ="R_ES-WH-FL_"&RIGHT(U27,3) -> R_ES-WH-FL_BIO | M52: ="Residential boiler for water heat - "&$T$11&" : "&T27 -> Residential boiler for water heat - Flat : Biomass and wastes | N52: PJ | O52: GW | R52: Yes
L53: ="R_ES-WH-FL_"&RIGHT(U28,3) -> R_ES-WH-FL_COA | M53: ="Residential boiler for water heat - "&$T$11&" : "&T28 -> Residential boiler for water heat - Flat : Solids | N53: PJ | O53: GW | R53: Yes
L54: ="R_ES-WH-FL_"&RIGHT(U29,3) -> R_ES-WH-FL_LPG | M54: ="Residential boiler for water heat - "&$T$11&" : "&T29 -> Residential boiler for water heat - Flat : LPG | N54: PJ | O54: GW | R54: Yes
L55: ="R_ES-WH-FL_"&RIGHT(U30,3) -> R_ES-WH-FL_SOL | M55: ="Residential boiler for water heat - "&$T$11&" : "&T30 -> Residential boiler for water heat - Flat : Solar | N55: PJ | O55: GW | R55: Yes
L56: ="R_ES-WH-DH_"&RIGHT(U23,3) -> R_ES-WH-DH_ELC | M56: ="Residential boiler for water heat - "&$T$12&" : "&T23 -> Residential boiler for water heat - Detached house : Electricity | N56: PJ | O56: GW | R56: Yes
L57: ="R_ES-WH-DH_"&RIGHT(U24,3) -> R_ES-WH-DH_GAS | M57: ="Residential boiler for water heat - "&$T$12&" : "&T24 -> Residential boiler for water heat - Detached house : Gases | N57: PJ | O57: GW | R57: Yes
L58: ="R_ES-WH-DH_"&RIGHT(U25,3) -> R_ES-WH-DH_HET | M58: ="Residential boiler for water heat - "&$T$12&" : "&T25 -> Residential boiler for water heat - Detached house : Derived heat | N58: PJ | O58: GW | R58: Yes
L59: ="R_ES-WH-DH_"&RIGHT(U26,3) -> R_ES-WH-DH_OIL | M59: ="Residential boiler for water heat - "&$T$12&" : "&T26 -> Residential boiler for water heat - Detached house : GDO and other liquids (incl. liq. bio.) | N59: PJ | O59: GW | R59: Yes
L60: ="R_ES-WH-DH_"&RIGHT(U27,3) -> R_ES-WH-DH_BIO | M60: ="Residential boiler for water heat - "&$T$12&" : "&T27 -> Residential boiler for water heat - Detached house : Biomass and wastes | N60: PJ | O60: GW | R60: Yes
L61: ="R_ES-WH-DH_"&RIGHT(U28,3) -> R_ES-WH-DH_COA | M61: ="Residential boiler for water heat - "&$T$12&" : "&T28 -> Residential boiler for water heat - Detached house : Solids | N61: PJ | O61: GW | R61: Yes
L62: ="R_ES-WH-DH_"&RIGHT(U29,3) -> R_ES-WH-DH_LPG | M62: ="Residential boiler for water heat - "&$T$12&" : "&T29 -> Residential boiler for water heat - Detached house : LPG | N62: PJ | O62: GW | R62: Yes
L63: ="R_ES-WH-DH_"&RIGHT(U30,3) -> R_ES-WH-DH_SOL | M63: ="Residential boiler for water heat - "&$T$12&" : "&T30 -> Residential boiler for water heat - Detached house : Solar | N63: PJ | O63: GW | R63: Yes
L64: ="R_ES-WH-SD_"&RIGHT(U23,3) -> R_ES-WH-SD_ELC | M64: ="Residential boiler for water heat - "&$T$15&" : "&T23 -> Residential boiler for water heat - Semi-detached house : Electricity | N64: PJ | O64: GW | R64: Yes
L65: ="R_ES-WH-SD_"&RIGHT(U24,3) -> R_ES-WH-SD_GAS | M65: ="Residential boiler for water heat - "&$T$15&" : "&T24 -> Residential boiler for water heat - Semi-detached house : Gases | N65: PJ | O65: GW | R65: Yes
L66: ="R_ES-WH-SD_"&RIGHT(U25,3) -> R_ES-WH-SD_HET | M66: ="Residential boiler for water heat - "&$T$15&" : "&T25 -> Residential boiler for water heat - Semi-detached house : Derived heat | N66: PJ | O66: GW | R66: Yes
L67: ="R_ES-WH-SD_"&RIGHT(U26,3) -> R_ES-WH-SD_OIL | M67: ="Residential boiler for water heat - "&$T$15&" : "&T26 -> Residential boiler for water heat - Semi-detached house : GDO and other liquids (incl. liq. bio.) | N67: PJ | O67: GW | R67: Yes
L68: ="R_ES-WH-SD_"&RIGHT(U27,3) -> R_ES-WH-SD_BIO | M68: ="Residential boiler for water heat - "&$T$15&" : "&T27 -> Residential boiler for water heat - Semi-detached house : Biomass and wastes | N68: PJ | O68: GW | R68: Yes
L69: ="R_ES-WH-SD_"&RIGHT(U28,3) -> R_ES-WH-SD_COA | M69: ="Residential boiler for water heat - "&$T$15&" : "&T28 -> Residential boiler for water heat - Semi-detached house : Solids | N69: PJ | O69: GW | R69: Yes
L70: ="R_ES-WH-SD_"&RIGHT(U29,3) -> R_ES-WH-SD_LPG | M70: ="Residential boiler for water heat - "&$T$15&" : "&T29 -> Residential boiler for water heat - Semi-detached house : LPG | N70: PJ | O70: GW | R70: Yes
L71: ="R_ES-WH-SD_"&RIGHT(U30,3) -> R_ES-WH-SD_SOL | M71: ="Residential boiler for water heat - "&$T$15&" : "&T30 -> Residential boiler for water heat - Semi-detached house : Solar | N71: PJ | O71: GW | R71: Yes
L72: ="R_ES-SC-FL_"&RIGHT(U23,3) -> R_ES-SC-FL_ELC | M72: ="Residential boiler for sp cooling - "&$T$11&" : "&T23 -> Residential boiler for sp cooling - Flat : Electricity | N72: PJ | O72: GW | R72: Yes
L73: ="R_ES-SC-DH_"&RIGHT(U23,3) -> R_ES-SC-DH_ELC | M73: ="Residential boiler for sp cooling - "&$T$12&" : "&T23 -> Residential boiler for sp cooling - Detached house : Electricity | N73: PJ | O73: GW | R73: Yes
L74: ="R_ES-SC-SD_"&RIGHT(U23,3) -> R_ES-SC-SD_ELC | M74: ="Residential boiler for sp cooling - "&$T$15&" : "&T23 -> Residential boiler for sp cooling - Semi-detached house : Electricity | N74: PJ | O74: GW | R74: Yes
L75: ="R_ES-CK-FL_"&RIGHT(U23,3) -> R_ES-CK-FL_ELC | M75: ="Residential boiler for cooking - "&$T$11&" : "&T23 -> Residential boiler for cooking - Flat : Electricity | N75: PJ | O75: GW | R75: Yes
L76: ="R_ES-CK-FL_"&RIGHT(U24,3) -> R_ES-CK-FL_GAS | M76: ="Residential boiler for cooking - "&$T$11&" : "&T24 -> Residential boiler for cooking - Flat : Gases | N76: PJ | O76: GW | R76: Yes
L77: ="R_ES-CK-FL_"&RIGHT(U27,3) -> R_ES-CK-FL_BIO | M77: ="Residential boiler for cooking - "&$T$11&" : "&T27 -> Residential boiler for cooking - Flat : Biomass and wastes | N77: PJ | O77: GW | R77: Yes
L78: ="R_ES-CK-FL_"&RIGHT(U28,3) -> R_ES-CK-FL_COA | M78: ="Residential boiler for cooking - "&$T$11&" : "&T28 -> Residential boiler for cooking - Flat : Solids | N78: PJ | O78: GW | R78: Yes
L79: ="R_ES-CK-FL_"&RIGHT(U29,3) -> R_ES-CK-FL_LPG | M79: ="Residential boiler for cooking - "&$T$11&" : "&T29 -> Residential boiler for cooking - Flat : LPG | N79: PJ | O79: GW | R79: Yes
L80: ="R_ES-CK-DH_"&RIGHT(U23,3) -> R_ES-CK-DH_ELC | M80: ="Residential boiler for cooking - "&$T$12&" : "&T23 -> Residential boiler for cooking - Detached house : Electricity | N80: PJ | O80: 000units | R80: Yes
L81: ="R_ES-CK-DH_"&RIGHT(U24,3) -> R_ES-CK-DH_GAS | M81: ="Residential boiler for cooking - "&$T$12&" : "&T24 -> Residential boiler for cooking - Detached house : Gases | N81: PJ | O81: 000units | R81: Yes
L82: ="R_ES-CK-DH_"&RIGHT(U27,3) -> R_ES-CK-DH_BIO | M82: ="Residential boiler for cooking - "&$T$12&" : "&T27 -> Residential boiler for cooking - Detached house : Biomass and wastes | N82: PJ | O82: 000units | R82: Yes
L83: ="R_ES-CK-DH_"&RIGHT(U28,3) -> R_ES-CK-DH_COA | M83: ="Residential boiler for cooking - "&$T$12&" : "&T28 -> Residential boiler for cooking - Detached house : Solids | N83: PJ | O83: 000units | R83: Yes
L84: ="R_ES-CK-DH_"&RIGHT(U29,3) -> R_ES-CK-DH_LPG | M84: ="Residential boiler for cooking - "&$T$12&" : "&T29 -> Residential boiler for cooking - Detached house : LPG | N84: PJ | O84: 000units | R84: Yes
L85: ="R_ES-CK-SD_"&RIGHT(U23,3) -> R_ES-CK-SD_ELC | M85: ="Residential boiler for cooking - "&$T$15&" : "&T23 -> Residential boiler for cooking - Semi-detached house : Electricity | N85: PJ | O85: 000units | R85: Yes
L86: ="R_ES-CK-SD_"&RIGHT(U24,3) -> R_ES-CK-SD_GAS | M86: ="Residential boiler for cooking - "&$T$15&" : "&T24 -> Residential boiler for cooking - Semi-detached house : Gases | N86: PJ | O86: 000units | R86: Yes
L87: ="R_ES-CK-SD_"&RIGHT(U27,3) -> R_ES-CK-SD_BIO | M87: ="Residential boiler for cooking - "&$T$15&" : "&T27 -> Residential boiler for cooking - Semi-detached house : Biomass and wastes | N87: PJ | O87: 000units | R87: Yes
L88: ="R_ES-CK-SD_"&RIGHT(U28,3) -> R_ES-CK-SD_COA | M88: ="Residential boiler for cooking - "&$T$15&" : "&T28 -> Residential boiler for cooking - Semi-detached house : Solids | N88: PJ | O88: 000units | R88: Yes
L89: ="R_ES-CK-SD_"&RIGHT(U29,3) -> R_ES-CK-SD_LPG | M89: ="Residential boiler for cooking - "&$T$15&" : "&T29 -> Residential boiler for cooking - Semi-detached house : LPG | N89: PJ | O89: 000units | R89: Yes
L90: ='TechELC-RES'!C4 -> RLIGELC00 | M90: ="Residential techs- "&X15 -> Residential techs- Lighting | N90: M_appliances | O90: =N90&"-y" -> M_appliances-y
L91: ='TechELC-RES'!C21 -> RREFELC00 | M91: ="Residential techs- "&X16 -> Residential techs- Refrigerators and freezers | N91: M_appliances | O91: =N91&"-y" -> M_appliances-y
K92: DMD | L92: ='TechELC-RES'!C38 -> RCWAELC00 | M92: ="Residential techs- "&X17 -> Residential techs- Washing machine | N92: M_appliances | O92: =N92&"-y" -> M_appliances-y
L93: ='TechELC-RES'!C55 -> RCDRELC00 | M93: ="Residential techs- "&X18 -> Residential techs- Clothes dryer | N93: M_appliances | O93: =N93&"-y" -> M_appliances-y
L94: ='TechELC-RES'!C72 -> RDWAELC00 | M94: ="Residential techs- "&X19 -> Residential techs- Dishwasher | N94: M_appliances | O94: =N94&"-y" -> M_appliances-y
L95: ='TechELC-RES'!C89 -> ROELELC00 | M95: ="Residential techs- "&X20 -> Residential techs- Other ELC | N95: M_appliances | O95: =N95&"-y" -> M_appliances-y
L96: =RES_Fuel!F6 -> RSDCOA00 | M96: Fuel Tech Base-year - Coal (RSD) | N96: PJ | O96: PJa
L97: =RES_Fuel!F7 -> RSDLPG00 | M97: Fuel Tech Base-year - Liquified Petroleum Gas (RSD) | N97: PJ | O97: PJa
K98: PRE | L98: =RES_Fuel!F8 -> RSDOIL00 | M98: Fuel Tech Base-year - Oil (RSD) | N98: PJ | O98: PJa
L99: =RES_Fuel!F9 -> RSDGAS00 | M99: Fuel Tech Base-year - Natural Gas (RSD) | N99: PJ | O99: PJa | P99: SEASON
L100: =RES_Fuel!F10 -> RSDBIO00 | M100: Fuel Tech Base-year - Biomass (RSD) | N100: PJ | O100: PJa
...

Sheet Dwelling stock
A1: Dwellings stock according to construction date | M1: Dwellings stock according to construction date and dwelling type
A2: Source: ENTRANZE | O2: =E3 -> < 1945 | R2: =F3 -> 1945-1969 | U2: =G3 -> 1970-1979 | X2: =H3 -> 1980-1989 | AA2: =I3 -> 1990-1999 | AD2: =J3 -> 2000-2008 | AI2: TOTAL
A3: Code | B3: Country | C3: Source | D3: Unit | E3: < 1945 | F3: 1945-1969 | G3: 1970-1979 | H3: 1980-1989 | I3: 1990-1999 | J3: 2000-2008 | K3: Total dwelling | M3: Country | N3: Unit | O3: ='Data by dwelling type'!H3 -> Flat | P3: ='Data by dwelling type'!I3 -> Detached house | Q3: ='Data by dwelling type'!J3 -> Semi-detached house | R3: =O3 -> Flat | S3: =P3 -> Detached house | T3: =Q3 -> Semi-detached house | U3: =R3 -> Flat | V3: =S3 -> Detached house | W3: =T3 -> Semi-detached house | X3: =U3 -> Flat | Y3: =V3 -> Detached house | ... AF3: =AC3 -> Semi-detached house | AI3: Flat | AJ3: Detached house | AK3: Semi-detached house | AL3: Check
A4: AL | B4: Albania | C4: own assumptions | D4: thousands | E4: =$K$4*(E15/$K$15) -> 88.574382 | F4: =$K$4*(F15/$K$15) -> 322.35404 | G4: =$K$4*(G15/$K$15) -> 256.857 | H4: =$K$4*(H15/$K$15) -> 196.62105 | I4: =$K$4*(I15/$K$15) -> 132.27652 | J4: =$K$4*(J15/$K$15) -> 67.363711 | K4: =Population!E48/(Population!$E$49/'Dwelling stock'!$K$36) -> 1064.0467 | M4: Albania | N4: thousands | O4: =E4*'Data by dwelling type'!AA4 -> 52.739169 | P4: =E4*'Data by dwelling type'!AB4 -> 22.891748 | Q4: =E4*'Data by dwelling type'!AC4 -> 12.943465 | R4: =F4*'Data by dwelling type'!AA4 -> 191.93681 | S4: =F4*'Data by dwelling type'!AB4 -> 83.311308 | T4: =F4*'Data by dwelling type'!AC4 -> 47.105927 | U4: =G4*'Data by dwelling type'!AA4 -> 152.9384 | V4: =G4*'Data by dwelling type'!AB4 -> 66.38382 | W4: =G4*'Data by dwelling type'!AC4 -> 37.534777 | X4: =H4*'Data by dwelling type'!AA4 -> 117.07257 | Y4: =H4*'Data by dwelling type'!AB4 -> 50.816043 | Z4: =H4*'Data by dwelling type'!AC4 -> 28.732436 | AA4: =I4*'Data by dwelling type'!AA4 -> 78.760401 | AB4: =I4*'Data by dwelling type'!AB4 -> 34.186418 | AC4: =I4*'Data by dwelling type'!AC4 -> 19.329704 | AD4: =J4*'Data by dwelling type'!AA4 -> 40.10986 | AE4: =J4*'Data by dwelling type'!AB4 -> 17.409923 | AF4: =J4*'Data by dwelling type'!AC4 -> 9.8439281 | AI4: =O4+R4+U4+X4+AA4+AD4 -> 633.55721 | AJ4: =P4+S4+V4+Y4+AB4+AE4 -> 274.99926 | AK4: =Q4+T4+W4+Z4+AC4+AF4 -> 155.49024 | AL4: =AI4-'Data by dwelling type'!W4 -> 0 | AM4: =AJ4-'Data by dwelling type'!Y4 -> 0 | AN4: =AK4-'Data by dwelling type'!Z4 -> 0
A5: AT | B5: Austria | C5: ENTRANZE | D5: thousands | E5: 858.82293 | F5: 1036.1925 | G5: 533.14752 | H5: 423.02085 | I5: 504.88341 | J5: 206.42195 | K5: =SUM(E5:J5) -> 3562.4891 | M5: Austria | N5: thousands | O5: =E5*'Data by dwelling type'!AA5 -> 426.88055 | P5: =E5*'Data by dwelling type'!AB5 -> 295.16062 | Q5: =E5*'Data by dwelling type'!AC5 -> 136.78175 | R5: =F5*'Data by dwelling type'!AA5 -> 515.04262 | S5: =F5*'Data by dwelling type'!AB5 -> 356.11906 | T5: =F5*'Data by dwelling type'!AC5 -> 165.03078 | U5: =G5*'Data by dwelling type'!AA5 -> 265.0026 | V5: =G5*'Data by dwelling type'!AB5 -> 183.23236 | W5: =G5*'Data by dwelling type'!AC5 -> 84.912558 | X5: =H5*'Data by dwelling type'!AA5 -> 210.2638 | Y5: =H5*'Data by dwelling type'!AB5 -> 145.38398 | Z5: =H5*'Data by dwelling type'!AC5 -> 67.373065 | AA5: =I5*'Data by dwelling type'!AA5 -> 250.95384 | AB5: =I5*'Data by dwelling type'!AB5 -> 173.51854 | AC5: =I5*'Data by dwelling type'!AC5 -> 80.411032 | AD5: =J5*'Data by dwelling type'!AA5 -> 102.60266 | AE5: =J5*'Data by dwelling type'!AB5 -> 70.943181 | AF5: =J5*'Data by dwelling type'!AC5 -> 32.876108 | AI5: =O5+R5+U5+X5+AA5+AD5 -> 1770.7461 | AJ5: =P5+S5+V5+Y5+AB5+AE5 -> 1224.3578 | AK5: =Q5+T5+W5+Z5+AC5+AF5 -> 567.3853 | AL5: =AI5-'Data by dwelling type'!W5 -> -0.25393595 | AM5: =AJ5-'Data by dwelling type'!Y5 -> -0.17558048 | AN5: =AK5-'Data by dwelling type'!Z5 -> -0.081366566
A6: BA | B6: Bosnia | C6: own assumptions | D6: thousands | E6: =$K$6*(E36/$K$36) -> 168.33106 | F6: =$K$6*(F36/$K$36) -> 384.31833 | G6: =$K$6*(G36/$K$36) -> 286.93488 | H6: =$K$6*(H36/$K$36) -> 242.50514 | I6: =$K$6*(I36/$K$36) -> 118.8608 | J6: =$K$6*(J36/$K$36) -> 89.260258 | K6: =Population!E53/(Population!$E$49/'Dwelling stock'!$K$36) -> 1290.2105 | M6: Bosnia | N6: thousands | O6: =E6*'Data by dwelling type'!AA6 -> 79.510186 | P6: =E6*'Data by dwelling type'!AB6 -> 65.41159 | Q6: =E6*'Data by dwelling type'!AC6 -> 23.409285 | R6: =F6*'Data by dwelling type'!AA6 -> 181.5305 | S6: =F6*'Data by dwelling type'!AB6 -> 149.34186 | T6: =F6*'Data by dwelling type'!AC6 -> 53.445972 | U6: =G6*'Data by dwelling type'!AA6 -> 135.532 | V6: =G6*'Data by dwelling type'!AB6 -> 111.49972 | W6: =G6*'Data by dwelling type'!AC6 -> 39.903154 | X6: =H6*'Data by dwelling type'!AA6 -> 114.54588 | Y6: =H6*'Data by dwelling type'!AB6 -> 94.234818 | Z6: =H6*'Data by dwelling type'!AC6 -> 33.724447 | AA6: =I6*'Data by dwelling type'!AA6 -> 56.1432 | AB6: =I6*'Data by dwelling type'!AB6 -> 46.187994 | AC6: =I6*'Data by dwelling type'!AC6 -> 16.529608 | AD6: =J6*'Data by dwelling type'!AA6 -> 42.161557 | AE6: =J6*'Data by dwelling type'!AB6 -> 34.68555 | AF6: =J6*'Data by dwelling type'!AC6 -> 12.413151 | AI6: =O6+R6+U6+X6+AA6+AD6 -> 609.42332 | AJ6: =P6+S6+V6+Y6+AB6+AE6 -> 501.36153 | AK6: =Q6+T6+W6+Z6+AC6+AF6 -> 179.42562 | AL6: =AI6-'Data by dwelling type'!W6 -> 0 | AM6: =AJ6-'Data by dwelling type'!Y6 -> 0 | AN6: =AK6-'Data by dwelling type'!Z6 -> 0
A7: BE | B7: Belgium | C7: ENTRANZE | D7: thousands | E7: 1789.7143 | F7: 994.28571 | G7: 538.09524 | H7: 538.09524 | I7: 396.37202 | J7: 266.4375 | K7: =SUM(E7:J7) -> 4523 | M7: Belgium | N7: thousands | O7: =E7*'Data by dwelling type'!AA7 -> 470.89407 | P7: =E7*'Data by dwelling type'!AB7 -> 494.22455 | Q7: =E7*'Data by dwelling type'!AC7 -> 824.59567 | R7: =F7*'Data by dwelling type'!AA7 -> 261.60781 | S7: =F7*'Data by dwelling type'!AB7 -> 274.56919 | T7: =F7*'Data by dwelling type'!AC7 -> 458.10871 | U7: =G7*'Data by dwelling type'!AA7 -> 141.57894 | V7: =G7*'Data by dwelling type'!AB7 -> 148.59348 | W7: =G7*'Data by dwelling type'!AC7 -> 247.92282 | X7: =H7*'Data by dwelling type'!AA7 -> 141.57894 | Y7: =H7*'Data by dwelling type'!AB7 -> 148.59348 | Z7: =H7*'Data by dwelling type'!AC7 -> 247.92282 | AA7: =I7*'Data by dwelling type'!AA7 -> 104.28996 | AB7: =I7*'Data by dwelling type'!AB7 -> 109.45702 | AC7: =I7*'Data by dwelling type'!AC7 -> 182.62505 | AD7: =J7*'Data by dwelling type'!AA7 -> 70.102719 | AE7: =J7*'Data by dwelling type'!AB7 -> 73.575963 | AF7: =J7*'Data by dwelling type'!AC7 -> 122.75882 | AI7: =O7+R7+U7+X7+AA7+AD7 -> 1190.0524 | AJ7: =P7+S7+V7+Y7+AB7+AE7 -> 1249.0137 | AK7: =Q7+T7+W7+Z7+AC7+AF7 -> 2083.9339 | AL7: =AI7-'Data by dwelling type'!W7 -> 1.0524452 | AM7: =AJ7-'Data by dwelling type'!Y7 -> 1.1045887 | AN7: =AK7-'Data by dwelling type'!Z7 -> 1.8429661
A8: BG | B8: Bulgaria | C8: ENTRANZE | D8: thousands | E8: 435.86831 | F8: 902.31451 | G8: 523.15295 | H8: 492.98588 | I8: 284.70819 | J8: 442.97017 | K8: =SUM(E8:J8) -> 3082 | M8: Bulgaria | N8: thousands | O8: =E8*'Data by dwelling type'!AA8 -> 195.86716 | P8: =E8*'Data by dwelling type'!AB8 -> 155.4937 | Q8: =E8*'Data by dwelling type'!AC8 -> 84.507446 | R8: =F8*'Data by dwelling type'!AA8 -> 405.47518 | S8: =F8*'Data by dwelling type'!AB8 -> 321.8959 | T8: =F8*'Data by dwelling type'!AC8 -> 174.94342 | U8: =G8*'Data by dwelling type'!AA8 -> 235.09046 | V8: =G8*'Data by dwelling type'!AB8 -> 186.63203 | W8: =G8*'Data by dwelling type'!AC8 -> 101.43045 | X8: =H8*'Data by dwelling type'!AA8 -> 221.53422 | Y8: =H8*'Data by dwelling type'!AB8 -> 175.87009 | Z8: =H8*'Data by dwelling type'!AC8 -> 95.58157 | AA8: =I8*'Data by dwelling type'!AA8 -> 127.93999 | AB8: =I8*'Data by dwelling type'!AB8 -> 101.56813 | AC8: =I8*'Data by dwelling type'!AC8 -> 55.200072 | AD8: =J8*'Data by dwelling type'!AA8 -> 199.05854 | AE8: =J8*'Data by dwelling type'!AB8 -> 158.02725 | AF8: =J8*'Data by dwelling type'!AC8 -> 85.884377 | AI8: =O8+R8+U8+X8+AA8+AD8 -> 1384.9655 | AJ8: =P8+S8+V8+Y8+AB8+AE8 -> 1099.4871 | AK8: =Q8+T8+W8+Z8+AC8+AF8 -> 597.54734 | AL8: =AI8-'Data by dwelling type'!W8 -> 0 | AM8: =AJ8-'Data by dwelling type'!Y8 -> 0 | AN8: =AK8-'Data by dwelling type'!Z8 -> 0
A9: CH | B9: Switzerland | C9: ODYSSEE | D9: thousands | E9: =$K$9*(E5/$K$5) -> 933.00397 | F9: =$K$9*(F5/$K$5) -> 1125.6938 | G9: =$K$9*(G5/$K$5) -> 579.19827 | H9: =$K$9*(H5/$K$5) -> 459.55938 | I9: =$K$9*(I5/$K$5) -> 548.49284 | J9: =$K$9*(J5/$K$5) -> 224.25169 | K9: 3870.2 | M9: Switzerland | N9: thousands | O9: =E9*'Data by dwelling type'!AA9 -> 447.84191 | P9: =E9*'Data by dwelling type'!AB9 -> 228.65064 | Q9: =E9*'Data by dwelling type'!AC9 -> 256.51143 | R9: =F9*'Data by dwelling type'!AA9 -> 540.33305 | S9: =F9*'Data by dwelling type'!AB9 -> 275.87301 | T9: =F9*'Data by dwelling type'!AC9 -> 309.48779 | U9: =G9*'Data by dwelling type'!AA9 -> 278.01517 | V9: =G9*'Data by dwelling type'!AB9 -> 141.94372 | W9: =G9*'Data by dwelling type'!AC9 -> 159.23938 | X9: =H9*'Data by dwelling type'!AA9 -> 220.5885 | Y9: =H9*'Data by dwelling type'!AB9 -> 112.6239 | Z9: =H9*'Data by dwelling type'!AC9 -> 126.34698 | AA9: =I9*'Data by dwelling type'!AA9 -> 263.27656 | AB9: =I9*'Data by dwelling type'!AB9 -> 134.41876 | AC9: =I9*'Data by dwelling type'!AC9 -> 150.79752 | AD9: =J9*'Data by dwelling type'!AA9 -> 107.64081 | AE9: =J9*'Data by dwelling type'!AB9 -> 54.957207 | AF9: =J9*'Data by dwelling type'!AC9 -> 61.653674 | AI9: =O9+R9+U9+X9+AA9+AD9 -> 1857.696 | AJ9: =P9+S9+V9+Y9+AB9+AE9 -> 948.46723 | AK9: =Q9+T9+W9+Z9+AC9+AF9 -> 1064.0368 | AL9: =AI9-'Data by dwelling type'!W9 -> 0 | AM9: =AJ9-'Data by dwelling type'!Y9 -> 0 | AN9: =AK9-'Data by dwelling type'!Z9 -> 0
A10: CY | B10: Cyprus | C10: ENTRANZE | D10: thousands | E10: 9.054403 | F10: 30.167848 | G10: 40.839057 | H10: 58.956254 | I10: 50.836032 | J10: 109.3034 | K10: =SUM(E10:J10) -> 299.157 | M10: Cyprus | N10: thousands | O10: =E10*'Data by dwelling type'!AA10 -> 2.5426748 | P10: =E10*'Data by dwelling type'!AB10 -> 3.2215918 | Q10: =E10*'Data by dwelling type'!AC10 -> 3.2901364 | R10: =F10*'Data by dwelling type'!AA10 -> 8.4717929 | S10: =F10*'Data by dwelling type'!AB10 -> 10.733838 | T10: =F10*'Data by dwelling type'!AC10 -> 10.962217 | U10: =G10*'Data by dwelling type'!AA10 -> 11.468502 | V10: =G10*'Data by dwelling type'!AB10 -> 14.530696 | W10: =G10*'Data by dwelling type'!AC10 -> 14.839859 | X10: =H10*'Data by dwelling type'!AA10 -> 16.556208 | Y10: =H10*'Data by dwelling type'!AB10 -> 20.976865 | Z10: =H10*'Data by dwelling type'!AC10 -> 21.423181 | AA10: =I10*'Data by dwelling type'!AA10 -> 14.275872 | AB10: =I10*'Data by dwelling type'!AB10 -> 18.087658 | AC10: =I10*'Data by dwelling type'!AC10 -> 18.472502 | AD10: =J10*'Data by dwelling type'!AA10 -> 30.694792 | AE10: =J10*'Data by dwelling type'!AB10 -> 38.890577 | AF10: =J10*'Data by dwelling type'!AC10 -> 39.718036 | AI10: =O10+R10+U10+X10+AA10+AD10 -> 84.009842 | AJ10: =P10+S10+V10+Y10+AB10+AE10 -> 106.44123 | AK10: =Q10+T10+W10+Z10+AC10+AF10 -> 108.70593 | AL10: =AI10-'Data by dwelling type'!W10 -> -2.8082191e-07 | AM10: =AJ10-'Data by dwelling type'!Y10 -> -3.5580389e-07 | AN10: =AK10-'Data by dwelling type'!Z10 -> -3.6337418e-07
A11: CZ | B11: Czech Rep. | C11: ENTRANZE | D11: thousands | E11: 963.51411 | F11: 1308.6011 | G11: 536.20286 | H11: 621.51031 | I11: 320.81903 | J11: 242.35264 | K11: =SUM(E11:J11) -> 3993 | M11: Czech Rep. | N11: thousands | O11: =E11*'Data by dwelling type'!AA11 -> 553.47062 | P11: =E11*'Data by dwelling type'!AB11 -> 257.44503 | Q11: =E11*'Data by dwelling type'!AC11 -> 152.59846 | R11: =F11*'Data by dwelling type'!AA11 -> 751.69863 | S11: =F11*'Data by dwelling type'!AB11 -> 349.65013 | T11: =F11*'Data by dwelling type'!AC11 -> 207.25229 | U11: =G11*'Data by dwelling type'!AA11 -> 308.01057 | V11: =G11*'Data by dwelling type'!AB11 -> 143.27009 | W11: =G11*'Data by dwelling type'!AC11 -> 84.922193 | X11: =H11*'Data by dwelling type'!AA11 -> 357.01366 | Y11: =H11*'Data by dwelling type'!AB11 -> 166.06372 | Z11: =H11*'Data by dwelling type'!AC11 -> 98.43293 | AA11: =I11*'Data by dwelling type'!AA11 -> 184.28781 | AB11: =I11*'Data by dwelling type'!AB11 -> 85.720864 | AC11: =I11*'Data by dwelling type'!AC11 -> 50.810351 | AD11: =J11*'Data by dwelling type'!AA11 -> 139.21443 | AE11: =J11*'Data by dwelling type'!AB11 -> 64.755131 | AF11: =J11*'Data by dwelling type'!AC11 -> 38.383082 | AI11: =O11+R11+U11+X11+AA11+AD11 -> 2293.6957 | AJ11: =P11+S11+V11+Y11+AB11+AE11 -> 1066.905 | AK11: =Q11+T11+W11+Z11+AC11+AF11 -> 632.39931 | AL11: =AI11-'Data by dwelling type'!W11 -> 0 | AM11: =AJ11-'Data by dwelling type'!Y11 -> 0 | AN11: =AK11-'Data by dwelling type'!Z11 -> 0
A12: DE | B12: Germany | C12: ENTRANZE | D12: thousands | E12: 8480.6087 | F12: 12872.758 | G12: 6635.2386 | H12: 4624.6154 | I12: 4256.3214 | J12: 2340.5295 | K12: =SUM(E12:J12) -> 39210.072 | M12: Germany | N12: thousands | O12: =E12*'Data by dwelling type'!AA12 -> 4572.4328 | P12: =E12*'Data by dwelling type'!AB12 -> 1910.6638 | Q12: =E12*'Data by dwelling type'!AC12 -> 1997.5122 | R12: =F12*'Data by dwelling type'!AA12 -> 6940.5184 | S12: =F12*'Data by dwelling type'!AB12 -> 2900.2061 | T12: =F12*'Data by dwelling type'!AC12 -> 3032.0336 | U12: =G12*'Data by dwelling type'!AA12 -> 3577.477 | V12: =G12*'Data by dwelling type'!AB12 -> 1494.9057 | W12: =G12*'Data by dwelling type'!AC12 -> 1562.8559 | X12: =H12*'Data by dwelling type'!AA12 -> 2493.4228 | Y12: =H12*'Data by dwelling type'!AB12 -> 1041.9164 | Z12: =H12*'Data by dwelling type'!AC12 -> 1089.2762 | AA12: =I12*'Data by dwelling type'!AA12 -> 2294.8522 | AB12: =I12*'Data by dwelling type'!AB12 -> 958.94049 | AC12: =I12*'Data by dwelling type'!AC12 -> 1002.5287 | AD12: =J12*'Data by dwelling type'!AA12 -> 1261.9275 | AE12: =J12*'Data by dwelling type'!AB12 -> 527.31651 | AF12: =J12*'Data by dwelling type'!AC12 -> 551.28544 | AI12: =O12+R12+U12+X12+AA12+AD12 -> 21140.631 | AJ12: =P12+S12+V12+Y12+AB12+AE12 -> 8833.9489 | AK12: =Q12+T12+W12+Z12+AC12+AF12 -> 9235.4921 | AL12: =AI12-'Data by dwelling type'!W12 -> 86.39575 | AM12: =AJ12-'Data by dwelling type'!Y12 -> 36.101839 | AN12: =AK12-'Data by dwelling type'!Z12 -> 37.742831
A13: DK | B13: Denmark | C13: ENTRANZE | D13: thousands | E13: 958.79185 | F13: 696.22 | G13: 430.06494 | H13: 176.1512 | I13: 176.29084 | J13: 233.17129 | K13: =SUM(E13:J13) -> 2670.6901 | M13: Denmark | N13: thousands | O13: =E13*'Data by dwelling type'!AA13 -> 394.10243 | P13: =E13*'Data by dwelling type'!AB13 -> 368.50018 | Q13: =E13*'Data by dwelling type'!AC13 -> 196.18924 | R13: =F13*'Data by dwelling type'!AA13 -> 286.17472 | S13: =F13*'Data by dwelling type'!AB13 -> 267.58383 | T13: =F13*'Data by dwelling type'!AC13 -> 142.46144 | U13: =G13*'Data by dwelling type'!AA13 -> 176.77418 | V13: =G13*'Data by dwelling type'!AB13 -> 165.29032 | W13: =G13*'Data by dwelling type'!AC13 -> 88.000449 | X13: =H13*'Data by dwelling type'!AA13 -> 72.405306 | Y13: =H13*'Data by dwelling type'!AB13 -> 67.701608 | Z13: =H13*'Data by dwelling type'!AC13 -> 36.044289 | AA13: =I13*'Data by dwelling type'!AA13 -> 72.462702 | AB13: =I13*'Data by dwelling type'!AB13 -> 67.755275 | AC13: =I13*'Data by dwelling type'!AC13 -> 36.072861 | AD13: =J13*'Data by dwelling type'!AA13 -> 95.84288 | AE13: =J13*'Data by dwelling type'!AB13 -> 89.616596 | AF13: =J13*'Data by dwelling type'!AC13 -> 47.711813 | AI13: =O13+R13+U13+X13+AA13+AD13 -> 1097.7622 | AJ13: =P13+S13+V13+Y13+AB13+AE13 -> 1026.4478 | AK13: =Q13+T13+W13+Z13+AC13+AF13 -> 546.48009 | AL13: =AI13-'Data by dwelling type'!W13 -> -4.2377811 | AM13: =AJ13-'Data by dwelling type'!Y13 -> -3.9624802 | AN13: =AK13-'Data by dwelling type'!Z13 -> -2.1096217
A14: EE | B14: Estonia | C14: ENTRANZE | D14: thousands | E14: 122.19269 | F14: 180.63845 | G14: 140.31282 | H14: 131.95672 | I14: 42.814177 | J14: 33.705142 | K14: =SUM(E14:J14) -> 651.62 | M14: Estonia | N14: thousands | O14: =E14*'Data by dwelling type'!AA14 -> 91.537889 | P14: =E14*'Data by dwelling type'!AB14 -> 20.940128 | Q14: =E14*'Data by dwelling type'!AC14 -> 9.7146734 | R14: =F14*'Data by dwelling type'!AA14 -> 135.32121 | S14: =F14*'Data by dwelling type'!AB14 -> 30.955962 | T14: =F14*'Data by dwelling type'!AC14 -> 14.361281 | U14: =G14*'Data by dwelling type'!AA14 -> 105.11218 | V14: =G14*'Data by dwelling type'!AB14 -> 24.04537 | W14: =G14*'Data by dwelling type'!AC14 -> 11.155277 | X14: =H14*'Data by dwelling type'!AA14 -> 98.852387 | Y14: =H14*'Data by dwelling type'!AB14 -> 22.613386 | Z14: =H14*'Data by dwelling type'!AC14 -> 10.490942 | AA14: =I14*'Data by dwelling type'!AA14 -> 32.073272 | AB14: =I14*'Data by dwelling type'!AB14 -> 7.3370538 | AC14: =I14*'Data by dwelling type'!AC14 -> 3.4038513 | AD14: =J14*'Data by dwelling type'!AA14 -> 25.249444 | AE14: =J14*'Data by dwelling type'!AB14 -> 5.7760409 | AF14: =J14*'Data by dwelling type'!AC14 -> 2.6796566 | AI14: =O14+R14+U14+X14+AA14+AD14 -> 488.14638 | AJ14: =P14+S14+V14+Y14+AB14+AE14 -> 111.66794 | AK14: =Q14+T14+W14+Z14+AC14+AF14 -> 51.805681 | AL14: =AI14-'Data by dwelling type'!W14 -> -1.1836212 | AM14: =AJ14-'Data by dwelling type'!Y14 -> -0.27076417 | AN14: =AK14-'Data by dwelling type'!Z14 -> -0.12561458
A15: EL | B15: Greece | C15: ENTRANZE | D15: thousands | E15: 320.25842 | F15: 1165.5356 | G15: 928.71793 | H15: 710.92279 | I15: 478.27226 | J15: 243.56699 | K15: =SUM(E15:J15) -> 3847.274 | M15: Greece | N15: thousands | O15: =E15*'Data by dwelling type'!AA15 -> 190.68903 | P15: =E15*'Data by dwelling type'!AB15 -> 82.769702 | Q15: =E15*'Data by dwelling type'!AC15 -> 46.799691 | R15: =F15*'Data by dwelling type'!AA15 -> 693.98597 | S15: =F15*'Data by dwelling type'!AB15 -> 301.22872 | T15: =F15*'Data by dwelling type'!AC15 -> 170.32091 | U15: =G15*'Data by dwelling type'!AA15 -> 552.97943 | V15: =G15*'Data by dwelling type'!AB15 -> 240.024 | W15: =G15*'Data by dwelling type'!AC15 -> 135.7145 | X15: =H15*'Data by dwelling type'!AA15 -> 423.29933 | Y15: =H15*'Data by dwelling type'!AB15 -> 183.73558 | Z15: =H15*'Data by dwelling type'!AC15 -> 103.88788 | AA15: =I15*'Data by dwelling type'!AA15 -> 284.774 | AB15: =I15*'Data by dwelling type'!AB15 -> 123.60784 | AC15: =I15*'Data by dwelling type'!AC15 -> 69.890416 | AD15: =J15*'Data by dwelling type'!AA15 -> 145.02523 | AE15: =J15*'Data by dwelling type'!AB15 -> 62.949062 | AF15: =J15*'Data by dwelling type'!AC15 -> 35.592694 | AI15: =O15+R15+U15+X15+AA15+AD15 -> 2290.753 | AJ15: =P15+S15+V15+Y15+AB15+AE15 -> 994.31491 | AK15: =Q15+T15+W15+Z15+AC15+AF15 -> 562.20609 | AL15: =AI15-'Data by dwelling type'!W15 -> 5.9542208e-07 | AM15: =AJ15-'Data by dwelling type'!Y15 -> 2.5844645e-07 | AN15: =AK15-'Data by dwelling type'!Z15 -> 1.461309e-07
A16: ES | B16: Spain | C16: ENTRANZE | D16: thousands | E16: 2185.8745 | F16: 3885.6862 | G16: 3208.2017 | H16: 2032.6827 | I16: 2012.6953 | J16: 3416.2386 | K16: =SUM(E16:J16) -> 16741.379 | M16: Spain | N16: thousands | O16: =E16*'Data by dwelling type'!AA16 -> 1538.1678 | P16: =E16*'Data by dwelling type'!AB16 -> 201.34424 | Q16: =E16*'Data by dwelling type'!AC16 -> 446.36241 | R16: =F16*'Data by dwelling type'!AA16 -> 2734.3004 | S16: =F16*'Data by dwelling type'!AB16 -> 357.9165 | T16: =F16*'Data by dwelling type'!AC16 -> 793.46929 | U16: =G16*'Data by dwelling type'!AA16 -> 2257.5645 | V16: =G16*'Data by dwelling type'!AB16 -> 295.51236 | W16: =G16*'Data by dwelling type'!AC16 -> 655.12483 | X16: =H16*'Data by dwelling type'!AA16 -> 1430.369 | Y16: =H16*'Data by dwelling type'!AB16 -> 187.23351 | Z16: =H16*'Data by dwelling type'!AC16 -> 415.08016 | AA16: =I16*'Data by dwelling type'!AA16 -> 1416.3042 | AB16: =I16*'Data by dwelling type'!AB16 -> 185.39244 | AC16: =I16*'Data by dwelling type'!AC16 -> 410.99868 | AD16: =J16*'Data by dwelling type'!AA16 -> 2403.9571 | AE16: =J16*'Data by dwelling type'!AB16 -> 314.67496 | AF16: =J16*'Data by dwelling type'!AC16 -> 697.60662 | AI16: =O16+R16+U16+X16+AA16+AD16 -> 11780.663 | AJ16: =P16+S16+V16+Y16+AB16+AE16 -> 1542.074 | AK16: =Q16+T16+W16+Z16+AC16+AF16 -> 3418.642 | AL16: =AI16-'Data by dwelling type'!W16 -> 0 | AM16: =AJ16-'Data by dwelling type'!Y16 -> 0 | AN16: =AK16-'Data by dwelling type'!Z16 -> 0
A17: FI | B17: Finland | C17: ENTRANZE | D17: thousands | E17: 352.23629 | F17: 644.24645 | G17: 511.75318 | H17: 405.4967 | I17: 296.07562 | J17: 289.19176 | K17: =SUM(E17:J17) -> 2499 | M17: Finland | N17: thousands | O17: =E17*'Data by dwelling type'!AA17 -> 156.19788 | P17: =E17*'Data by dwelling type'!AB17 -> 111.65023 | Q17: =E17*'Data by dwelling type'!AC17 -> 84.388178 | R17: =F17*'Data by dwelling type'!AA17 -> 285.68871 | S17: =F17*'Data by dwelling type'!AB17 -> 204.21026 | T17: =F17*'Data by dwelling type'!AC17 -> 154.34748 | U17: =G17*'Data by dwelling type'!AA17 -> 226.93506 | V17: =G17*'Data by dwelling type'!AB17 -> 162.21316 | W17: =G17*'Data by dwelling type'!AC17 -> 122.60497 | X17: =H17*'Data by dwelling type'!AA17 -> 179.81601 | Y17: =H17*'Data by dwelling type'!AB17 -> 128.53247 | Z17: =H17*'Data by dwelling type'!AC17 -> 97.148216 | AA17: =I17*'Data by dwelling type'!AA17 -> 131.29364 | AB17: =I17*'Data by dwelling type'!AB17 -> 93.848682 | AC17: =I17*'Data by dwelling type'!AC17 -> 70.9333 | AD17: =J17*'Data by dwelling type'!AA17 -> 128.24102 | AE17: =J17*'Data by dwelling type'!AB17 -> 91.666666 | AF17: =J17*'Data by dwelling type'!AC17 -> 69.284074 | AI17: =O17+R17+U17+X17+AA17+AD17 -> 1108.1723 | AJ17: =P17+S17+V17+Y17+AB17+AE17 -> 792.12147 | AK17: =Q17+T17+W17+Z17+AC17+AF17 -> 598.70622 | AL17: =AI17-'Data by dwelling type'!W17 -> 22.172315 | AM17: =AJ17-'Data by dwelling type'!Y17 -> 15.848769 | AN17: =AK17-'Data by dwelling type'!Z17 -> 11.978916
A18: FR | B18: France | C18: ENTRANZE | D18: thousands | E18: 7195.8684 | F18: 4866.948 | G18: 5375.9451 | H18: 3961.7485 | I18: 2386.5085 | J18: 3251.5815 | K18: =SUM(E18:J18) -> 27038.6 | M18: France | N18: thousands | O18: =E18*'Data by dwelling type'!AA18 -> 3136.7254 | P18: =E18*'Data by dwelling type'!AB18 -> 2148.6721 | Q18: =E18*'Data by dwelling type'!AC18 -> 1910.4709 | R18: =F18*'Data by dwelling type'!AA18 -> 2121.534 | S18: =F18*'Data by dwelling type'!AB18 -> 1453.2611 | T18: =F18*'Data by dwelling type'!AC18 -> 1292.1529 | U18: =G18*'Data by dwelling type'!AA18 -> 2343.4091 | V18: =G18*'Data by dwelling type'!AB18 -> 1605.2466 | W18: =G18*'Data by dwelling type'!AC18 -> 1427.2894 | X18: =H18*'Data by dwelling type'!AA18 -> 1726.9517 | Y18: =H18*'Data by dwelling type'!AB18 -> 1182.9703 | Z18: =H18*'Data by dwelling type'!AC18 -> 1051.8265 | AA18: =I18*'Data by dwelling type'!AA18 -> 1040.2944 | AB18: =I18*'Data by dwelling type'!AB18 -> 712.60673 | AC18: =I18*'Data by dwelling type'!AC18 -> 633.60735 | AD18: =J18*'Data by dwelling type'!AA18 -> 1417.3853 | AE18: =J18*'Data by dwelling type'!AB18 -> 970.91582 | AF18: =J18*'Data by dwelling type'!AC18 -> 863.28036 | AI18: =O18+R18+U18+X18+AA18+AD18 -> 11786.3 | AJ18: =P18+S18+V18+Y18+AB18+AE18 -> 8073.6726 | AK18: =Q18+T18+W18+Z18+AC18+AF18 -> 7178.6274 | AL18: =AI18-'Data by dwelling type'!W18 -> 0 | AM18: =AJ18-'Data by dwelling type'!Y18 -> 0 | AN18: =AK18-'Data by dwelling type'!Z18 -> 0
A19: HR | B19: Croatia | C19: ENTRANZE | D19: thousands | E19: 220 | F19: 399.72727 | G19: 308.77273 | H19: 244.8 | I19: 131.03333 | J19: 179.66667 | K19: =SUM(E19:J19) -> 1484 | M19: Croatia | N19: thousands | O19: =E19*'Data by dwelling type'!AA19 -> 81.173032 | P19: =E19*'Data by dwelling type'!AB19 -> 102.23827 | Q19: =E19*'Data by dwelling type'!AC19 -> 36.588696 | R19: =F19*'Data by dwelling type'!AA19 -> 147.4867 | S19: =F19*'Data by dwelling type'!AB19 -> 185.76102 | T19: =F19*'Data by dwelling type'!AC19 -> 66.479545 | U19: =G19*'Data by dwelling type'!AA19 -> 113.92736 | V19: =G19*'Data by dwelling type'!AB19 -> 143.49268 | W19: =G19*'Data by dwelling type'!AC19 -> 51.352689 | X19: =H19*'Data by dwelling type'!AA19 -> 90.323447 | Y19: =H19*'Data by dwelling type'!AB19 -> 113.76331 | Z19: =H19*'Data by dwelling type'!AC19 -> 40.71324 | AA19: =I19*'Data by dwelling type'!AA19 -> 48.34715 | AB19: =I19*'Data by dwelling type'!AB19 -> 60.893734 | AC19: =I19*'Data by dwelling type'!AC19 -> 21.792449 | AD19: =J19*'Data by dwelling type'!AA19 -> 66.29131 | AE19: =J19*'Data by dwelling type'!AB19 -> 83.494588 | AF19: =J19*'Data by dwelling type'!AC19 -> 29.880769 | AI19: =O19+R19+U19+X19+AA19+AD19 -> 547.549 | AJ19: =P19+S19+V19+Y19+AB19+AE19 -> 689.64361 | AK19: =Q19+T19+W19+Z19+AC19+AF19 -> 246.80739 | AL19: =AI19-'Data by dwelling type'!W19 -> 0 | AM19: =AJ19-'Data by dwelling type'!Y19 -> 0 | AN19: =AK19-'Data by dwelling type'!Z19 -> 0
A20: HU | B20: Hungary | C20: ENTRANZE | D20: thousands | E20: 768.51013 | F20: 1035.4304 | G20: 620.99765 | H20: 844.19135 | I20: 348.18951 | J20: 410.68093 | K20: =SUM(E20:J20) -> 4028 | M20: Hungary | N20: thousands | O20: =E20*'Data by dwelling type'!AA20 -> 295.53679 | P20: =E20*'Data by dwelling type'!AB20 -> 345.40567 | Q20: =E20*'Data by dwelling type'!AC20 -> 127.56767 | R20: =F20*'Data by dwelling type'!AA20 -> 398.18315 | S20: =F20*'Data by dwelling type'!AB20 -> 465.37258 | T20: =F20*'Data by dwelling type'!AC20 -> 171.87469 | U20: =G20*'Data by dwelling type'!AA20 -> 238.80967 | V20: =G20*'Data by dwelling type'!AB20 -> 279.10642 | W20: =G20*'Data by dwelling type'!AC20 -> 103.08156 | X20: =H20*'Data by dwelling type'!AA20 -> 324.64062 | Y20: =H20*'Data by dwelling type'!AB20 -> 379.42048 | Z20: =H20*'Data by dwelling type'!AC20 -> 140.13026 | AA20: =I20*'Data by dwelling type'!AA20 -> 133.89909 | AB20: =I20*'Data by dwelling type'!AB20 -> 156.49323 | AC20: =I20*'Data by dwelling type'!AC20 -> 57.797186 | AD20: =J20*'Data by dwelling type'!AA20 -> 157.93068 | AE20: =J20*'Data by dwelling type'!AB20 -> 184.5799 | AF20: =J20*'Data by dwelling type'!AC20 -> 68.170355 | AI20: =O20+R20+U20+X20+AA20+AD20 -> 1549 | AJ20: =P20+S20+V20+Y20+AB20+AE20 -> 1810.3783 | AK20: =Q20+T20+W20+Z20+AC20+AF20 -> 668.62171 | AL20: =AI20-'Data by dwelling type'!W20 -> 0 | AM20: =AJ20-'Data by dwelling type'!Y20 -> 0 | AN20: =AK20-'Data by dwelling type'!Z20 -> 0
A21: IE | B21: Ireland | C21: ENTRANZE | D21: thousands | E21: 277.86702 | F21: 252.13665 | G21: 213.07386 | H21: 185.43696 | I21: 240.93846 | J21: 479.95507 | K21: =SUM(E21:J21) -> 1649.408 | M21: Ireland | N21: thousands | O21: =E21*'Data by dwelling type'!AA21 -> 31.327021 | P21: =E21*'Data by dwelling type'!AB21 -> 98.451964 | Q21: =E21*'Data by dwelling type'!AC21 -> 148.08803 | R21: =F21*'Data by dwelling type'!AA21 -> 28.426152 | S21: =F21*'Data by dwelling type'!AB21 -> 89.335354 | T21: =F21*'Data by dwelling type'!AC21 -> 134.37514 | U21: =G21*'Data by dwelling type'!AA21 -> 24.022172 | V21: =G21*'Data by dwelling type'!AB21 -> 75.494889 | W21: =G21*'Data by dwelling type'!AC21 -> 113.5568 | X21: =H21*'Data by dwelling type'!AA21 -> 20.906358 | Y21: =H21*'Data by dwelling type'!AB21 -> 65.702769 | Z21: =H21*'Data by dwelling type'!AC21 -> 98.827828 | AA21: =I21*'Data by dwelling type'!AA21 -> 27.163656 | AB21: =I21*'Data by dwelling type'!AB21 -> 85.367686 | AC21: =I21*'Data by dwelling type'!AC21 -> 128.40711 | AD21: =J21*'Data by dwelling type'!AA21 -> 54.110641 | AE21: =J21*'Data by dwelling type'!AB21 -> 170.05444 | AF21: =J21*'Data by dwelling type'!AC21 -> 255.78999 | AI21: =O21+R21+U21+X21+AA21+AD21 -> 185.956 | AJ21: =P21+S21+V21+Y21+AB21+AE21 -> 584.4071 | AK21: =Q21+T21+W21+Z21+AC21+AF21 -> 879.0449 | AL21: =AI21-'Data by dwelling type'!W21 -> 1.1274105e-07 | AM21: =AJ21-'Data by dwelling type'!Y21 -> 3.5431333e-07 | AN21: =AK21-'Data by dwelling type'!Z21 -> 5.3294559e-07
A22: IS | B22: Iceland | C22: own assumptions | D22: thousands | E22: =$K$22*(E17/$K$17) -> 21.34771 | F22: =$K$22*(F17/$K$17) -> 39.045342 | G22: =$K$22*(G17/$K$17) -> 31.015426 | H22: =$K$22*(H17/$K$17) -> 24.575622 | I22: =$K$22*(I17/$K$17) -> 17.944024 | J22: =$K$22*(J17/$K$17) -> 17.526819 | K22: =Population!E42/(Population!$E$44/'Dwelling stock'!$K$32) -> 151.45494 | M22: Iceland | N22: thousands | O22: =E22*'Data by dwelling type'!AA22 -> 9.4665631 | P22: =E22*'Data by dwelling type'!AB22 -> 6.1429929 | Q22: =E22*'Data by dwelling type'!AC22 -> 5.7381539 | R22: =F22*'Data by dwelling type'!AA22 -> 17.314513 | S22: =F22*'Data by dwelling type'!AB22 -> 11.235644 | T22: =F22*'Data by dwelling type'!AC22 -> 10.495186 | U22: =G22*'Data by dwelling type'!AA22 -> 13.753676 | V22: =G22*'Data by dwelling type'!AB22 -> 8.924964 | W22: =G22*'Data by dwelling type'!AC22 -> 8.3367859 | X22: =H22*'Data by dwelling type'!AA22 -> 10.897969 | Y22: =H22*'Data by dwelling type'!AB22 -> 7.0718532 | Z22: =H22*'Data by dwelling type'!AC22 -> 6.6057999 | AA22: =I22*'Data by dwelling type'!AA22 -> 7.9572112 | AB22: =I22*'Data by dwelling type'!AB22 -> 5.1635522 | AC22: =I22*'Data by dwelling type'!AC22 -> 4.8232608 | AD22: =J22*'Data by dwelling type'!AA22 -> 7.7722031 | AE22: =J22*'Data by dwelling type'!AB22 -> 5.0434977 | AF22: =J22*'Data by dwelling type'!AC22 -> 4.7111182 | AI22: =O22+R22+U22+X22+AA22+AD22 -> 67.162135 | AJ22: =P22+S22+V22+Y22+AB22+AE22 -> 43.582504 | AK22: =Q22+T22+W22+Z22+AC22+AF22 -> 40.710304 | AL22: =AI22-'Data by dwelling type'!W22 -> 0 | AM22: =AJ22-'Data by dwelling type'!Y22 -> 0 | AN22: =AK22-'Data by dwelling type'!Z22 -> 0
A23: IT | B23: Italy | C23: ENTRANZE | D23: thousands | E23: 6492 | F23: 9106.3636 | G23: 5152.0364 | H23: 3732.2 | I23: 1380.9 | J23: 1080.5 | K23: =SUM(E23:J23) -> 26944 | M23: Italy | N23: thousands | O23: =E23*'Data by dwelling type'!AA23 -> 4829.7261 | P23: =E23*'Data by dwelling type'!AB23 -> 598.28263 | Q23: =E23*'Data by dwelling type'!AC23 -> 1063.9913 | R23: =F23*'Data by dwelling type'!AA23 -> 6774.683 | S23: =F23*'Data by dwelling type'!AB23 -> 839.21429 | T23: =F23*'Data by dwelling type'!AC23 -> 1492.4663 | U23: =G23*'Data by dwelling type'!AA23 -> 3832.8596 | V23: =G23*'Data by dwelling type'!AB23 -> 474.79573 | W23: =G23*'Data by dwelling type'!AC23 -> 844.38104 | X23: =H23*'Data by dwelling type'!AA23 -> 2776.5717 | Y23: =H23*'Data by dwelling type'!AB23 -> 343.948 | Z23: =H23*'Data by dwelling type'!AC23 -> 611.68026 | AA23: =I23*'Data by dwelling type'!AA23 -> 1027.3211 | AB23: =I23*'Data by dwelling type'!AB23 -> 127.25947 | AC23: =I23*'Data by dwelling type'!AC23 -> 226.3194 | AD23: =J23*'Data by dwelling type'!AA23 -> 803.83842 | AE23: =J23*'Data by dwelling type'!AB23 -> 99.575537 | AF23: =J23*'Data by dwelling type'!AC23 -> 177.08604 | AI23: =O23+R23+U23+X23+AA23+AD23 -> 20045 | AJ23: =P23+S23+V23+Y23+AB23+AE23 -> 2483.0757 | AK23: =Q23+T23+W23+Z23+AC23+AF23 -> 4415.9243 | AL23: =AI23-'Data by dwelling type'!W23 -> 0 | AM23: =AJ23-'Data by dwelling type'!Y23 -> 0 | AN23: =AK23-'Data by dwelling type'!Z23 -> 0
A24: KS | B24: Kosovo | C24: own estimates | D24: thousands | E24: =$K$24*(E36/$K$36) -> 94.291023 | F24: =$K$24*(F36/$K$36) -> 215.27678 | G24: =$K$24*(G36/$K$36) -> 160.72722 | H24: =$K$24*(H36/$K$36) -> 135.8398 | I24: =$K$24*(I36/$K$36) -> 66.580146 | J24: =$K$24*(J36/$K$36) -> 49.999335 | K24: =Population!E54/(Population!$E$49/'Dwelling stock'!$K$36) -> 722.7143 | M24: Kosovo | N24: thousands | O24: =E24*'Data by dwelling type'!AA24 -> 44.53781 | P24: =E24*'Data by dwelling type'!AB24 -> 36.64045 | Q24: =E24*'Data by dwelling type'!AC24 -> 13.112764 | R24: =F24*'Data by dwelling type'!AA24 -> 101.68472 | S24: =F24*'Data by dwelling type'!AB24 -> 83.654177 | T24: =F24*'Data by dwelling type'!AC24 -> 29.937882 | U24: =G24*'Data by dwelling type'!AA24 -> 75.918555 | V24: =G24*'Data by dwelling type'!AB24 -> 62.456821 | W24: =G24*'Data by dwelling type'!AC24 -> 22.351842 | X24: =H24*'Data by dwelling type'!AA24 -> 64.16313 | Y24: =H24*'Data by dwelling type'!AB24 -> 52.785846 | Z24: =H24*'Data by dwelling type'!AC24 -> 18.890825 | AA24: =I24*'Data by dwelling type'!AA24 -> 31.44874 | AB24: =I24*'Data by dwelling type'!AB24 -> 25.872309 | AC24: =I24*'Data by dwelling type'!AC24 -> 9.2590969 | AD24: =J24*'Data by dwelling type'!AA24 -> 23.616891 | AE24: =J24*'Data by dwelling type'!AB24 -> 19.429189 | AF24: =J24*'Data by dwelling type'!AC24 -> 6.9532543 | AI24: =O24+R24+U24+X24+AA24+AD24 -> 341.36985 | AJ24: =P24+S24+V24+Y24+AB24+AE24 -> 280.83879 | AK24: =Q24+T24+W24+Z24+AC24+AF24 -> 100.50566 | AL24: =AI24-'Data by dwelling type'!W24 -> 0 | AM24: =AJ24-'Data by dwelling type'!Y24 -> 0 | AN24: =AK24-'Data by dwelling type'!Z24 -> 0
A25: LT | B25: Lithuania | C25: ENTRANZE | D25: thousands | E25: 395.49378 | F25: 422.65282 | G25: 278.21591 | H25: 278.21591 | I25: 86.516165 | J25: 75.823214 | K25: =SUM(E25:J25) -> 1536.9178 | M25: Lithuania | N25: thousands | O25: =E25*'Data by dwelling type'!AA25 -> 256.67024 | P25: =E25*'Data by dwelling type'!AB25 -> 92.199782 | Q25: =E25*'Data by dwelling type'!AC25 -> 46.623753 | R25: =F25*'Data by dwelling type'!AA25 -> 274.2961 | S25: =F25*'Data by dwelling type'!AB25 -> 98.531254 | T25: =F25*'Data by dwelling type'!AC25 -> 49.825464 | U25: =G25*'Data by dwelling type'!AA25 -> 180.55845 | V25: =G25*'Data by dwelling type'!AB25 -> 64.859291 | W25: =G25*'Data by dwelling type'!AC25 -> 32.798164 | X25: =H25*'Data by dwelling type'!AA25 -> 180.55845 | Y25: =H25*'Data by dwelling type'!AB25 -> 64.859291 | Z25: =H25*'Data by dwelling type'!AC25 -> 32.798164 | AA25: =I25*'Data by dwelling type'!AA25 -> 56.147849 | AB25: =I25*'Data by dwelling type'!AB25 -> 20.169146 | AC25: =I25*'Data by dwelling type'!AC25 -> 10.19917 | AD25: =J25*'Data by dwelling type'!AA25 -> 49.208265 | AE25: =J25*'Data by dwelling type'!AB25 -> 17.676343 | AF25: =J25*'Data by dwelling type'!AC25 -> 8.9386054 | AI25: =O25+R25+U25+X25+AA25+AD25 -> 997.43936 | AJ25: =P25+S25+V25+Y25+AB25+AE25 -> 358.29511 | AK25: =Q25+T25+W25+Z25+AC25+AF25 -> 181.18332 | AL25: =AI25-'Data by dwelling type'!W25 -> -4.7615006 | AM25: =AJ25-'Data by dwelling type'!Y25 -> -1.7104021 | AN25: =AK25-'Data by dwelling type'!Z25 -> -0.86491925
A26: LU | B26: Luxembourg | C26: ENTRANZE | D26: thousands | E26: 53.226568 | F26: 48.955233 | G26: 26.436617 | H26: 20.547526 | I26: 16.34799 | J26: 22.486065 | K26: =SUM(E26:J26) -> 188 | M26: Luxembourg | N26: thousands | O26: =E26*'Data by dwelling type'!AA26 -> 19.252163 | P26: =E26*'Data by dwelling type'!AB26 -> 14.810399 | Q26: =E26*'Data by dwelling type'!AC26 -> 19.164006 | R26: =F26*'Data by dwelling type'!AA26 -> 17.707212 | S26: =F26*'Data by dwelling type'!AB26 -> 13.621892 | T26: =F26*'Data by dwelling type'!AC26 -> 17.626129 | U26: =G26*'Data by dwelling type'!AA26 -> 9.5621806 | V26: =G26*'Data by dwelling type'!AB26 -> 7.3560417 | W26: =G26*'Data by dwelling type'!AC26 -> 9.5183947 | X26: =H26*'Data by dwelling type'!AA26 -> 7.4320839 | Y26: =H26*'Data by dwelling type'!AB26 -> 5.7173903 | Z26: =H26*'Data by dwelling type'!AC26 -> 7.3980518 | AA26: =I26*'Data by dwelling type'!AA26 -> 5.9131028 | AB26: =I26*'Data by dwelling type'!AB26 -> 4.548861 | AC26: =I26*'Data by dwelling type'!AC26 -> 5.8860262 | AD26: =J26*'Data by dwelling type'!AA26 -> 8.1332576 | AE26: =J26*'Data by dwelling type'!AB26 -> 6.2567927 | AF26: =J26*'Data by dwelling type'!AC26 -> 8.0960147 | AI26: =O26+R26+U26+X26+AA26+AD26 -> 68 | AJ26: =P26+S26+V26+Y26+AB26+AE26 -> 52.311377 | AK26: =Q26+T26+W26+Z26+AC26+AF26 -> 67.688622 | AL26: =AI26-'Data by dwelling type'!W26 -> -3.6170212e-07 | AM26: =AJ26-'Data by dwelling type'!Y26 -> -2.7825201e-07 | AN26: =AK26-'Data by dwelling type'!Z26 -> -3.6004586e-07
A27: LV | B27: Latvia | C27: ENTRANZE | D27: thousands | E27: 206.75285 | F27: 250.74519 | G27: 202.71631 | H27: 195.68071 | I27: 61.251311 | J27: 71.061633 | K27: =SUM(E27:J27) -> 988.208 | M27: Latvia | N27: thousands | O27: =E27*'Data by dwelling type'!AA27 -> 142.81512 | P27: =E27*'Data by dwelling type'!AB27 -> 45.690331 | Q27: =E27*'Data by dwelling type'!AC27 -> 18.247396 | R27: =F27*'Data by dwelling type'!AA27 -> 173.20295 | S27: =F27*'Data by dwelling type'!AB27 -> 55.412202 | T27: =F27*'Data by dwelling type'!AC27 -> 22.13003 | U27: =G27*'Data by dwelling type'!AA27 -> 140.02687 | V27: =G27*'Data by dwelling type'!AB27 -> 44.798296 | W27: =G27*'Data by dwelling type'!AC27 -> 17.891144 | X27: =H27*'Data by dwelling type'!AA27 -> 135.16701 | Y27: =H27*'Data by dwelling type'!AB27 -> 43.243498 | Z27: =H27*'Data by dwelling type'!AC27 -> 17.270202 | AA27: =I27*'Data by dwelling type'!AA27 -> 42.309518 | AB27: =I27*'Data by dwelling type'!AB27 -> 13.535933 | AC27: =I27*'Data by dwelling type'!AC27 -> 5.40586 | AD27: =J27*'Data by dwelling type'!AA27 -> 49.086026 | AE27: =J27*'Data by dwelling type'!AB27 -> 15.703917 | AF27: =J27*'Data by dwelling type'!AC27 -> 6.2716901 | AI27: =O27+R27+U27+X27+AA27+AD27 -> 682.6075 | AJ27: =P27+S27+V27+Y27+AB27+AE27 -> 218.38418 | AK27: =Q27+T27+W27+Z27+AC27+AF27 -> 87.216322 | AL27: =AI27-'Data by dwelling type'!W27 -> 0 | AM27: =AJ27-'Data by dwelling type'!Y27 -> 0 | AN27: =AK27-'Data by dwelling type'!Z27 -> 0
A28: ME | B28: Montenegro | C28: own assumptions | D28: thousands | E28: =$K$28*(E36/$K$36) -> 26.956076 | F28: =$K$28*(F36/$K$36) -> 61.543688 | G28: =$K$28*(G36/$K$36) -> 45.948967 | H28: =$K$28*(H36/$K$36) -> 38.834111 | I28: =$K$28*(I36/$K$36) -> 19.034044 | J28: =$K$28*(J36/$K$36) -> 14.293894 | K28: =Population!E46/(Population!$E$49/'Dwelling stock'!$K$36) -> 206.61078 | M28: Montenegro | N28: thousands | O28: =E28*'Data by dwelling type'!AA28 -> 16.050251 | P28: =E28*'Data by dwelling type'!AB28 -> 6.9667064 | Q28: =E28*'Data by dwelling type'!AC28 -> 3.9391191 | R28: =F28*'Data by dwelling type'!AA28 -> 36.644488 | S28: =F28*'Data by dwelling type'!AB28 -> 15.905757 | T28: =F28*'Data by dwelling type'!AC28 -> 8.9934421 | U28: =G28*'Data by dwelling type'!AA28 -> 27.359043 | V28: =G28*'Data by dwelling type'!AB28 -> 11.875355 | W28: =G28*'Data by dwelling type'!AC28 -> 6.7145697 | X28: =H28*'Data by dwelling type'!AA28 -> 23.122698 | Y28: =H28*'Data by dwelling type'!AB28 -> 10.036544 | Z28: =H28*'Data by dwelling type'!AC28 -> 5.6748684 | AA28: =I28*'Data by dwelling type'!AA28 -> 11.333296 | AB28: =I28*'Data by dwelling type'!AB28 -> 4.9192841 | AC28: =I28*'Data by dwelling type'!AC28 -> 2.7814644 | AD28: =J28*'Data by dwelling type'!AA28 -> 8.5109042 | AE28: =J28*'Data by dwelling type'!AB28 -> 3.6942084 | AF28: =J28*'Data by dwelling type'!AC28 -> 2.0887814 | AI28: =O28+R28+U28+X28+AA28+AD28 -> 123.02068 | AJ28: =P28+S28+V28+Y28+AB28+AE28 -> 53.397855 | AK28: =Q28+T28+W28+Z28+AC28+AF28 -> 30.192245 | AL28: =AI28-'Data by dwelling type'!W28 -> 0 | AM28: =AJ28-'Data by dwelling type'!Y28 -> 0 | AN28: =AK28-'Data by dwelling type'!Z28 -> 0
A29: MK | B29: Macedonia | C29: own assumptions | D29: thousands | E29: =$K$29*(E8/$K$8) -> 97.084107 | F29: =$K$29*(F8/$K$8) -> 200.97905 | G29: =$K$29*(G8/$K$8) -> 116.52565 | H29: =$K$29*(H8/$K$8) -> 109.80632 | I29: =$K$29*(I8/$K$8) -> 63.415118 | J29: =$K$29*(J8/$K$8) -> 98.665956 | K29: =Population!E47/(Population!$E$49/'Dwelling stock'!$K$36) -> 686.47619 | M29: Macedonia | N29: thousands | O29: =E29*'Data by dwelling type'!AA29 -> 45.857106 | P29: =E29*'Data by dwelling type'!AB29 -> 33.189324 | Q29: =E29*'Data by dwelling type'!AC29 -> 18.037676 | R29: =F29*'Data by dwelling type'!AA29 -> 94.931271 | S29: =F29*'Data by dwelling type'!AB29 -> 68.707011 | T29: =F29*'Data by dwelling type'!AC29 -> 37.340767 | U29: =G29*'Data by dwelling type'!AA29 -> 55.040203 | V29: =G29*'Data by dwelling type'!AB29 -> 39.835639 | W29: =G29*'Data by dwelling type'!AC29 -> 21.649804 | X29: =H29*'Data by dwelling type'!AA29 -> 51.866367 | Y29: =H29*'Data by dwelling type'!AB29 -> 37.538559 | Z29: =H29*'Data by dwelling type'!AC29 -> 20.401391 | AA29: =I29*'Data by dwelling type'!AA29 -> 29.953758 | AB29: =I29*'Data by dwelling type'!AB29 -> 21.679191 | AC29: =I29*'Data by dwelling type'!AC29 -> 11.782169 | AD29: =J29*'Data by dwelling type'!AA29 -> 46.604284 | AE29: =J29*'Data by dwelling type'!AB29 -> 33.730098 | AF29: =J29*'Data by dwelling type'!AC29 -> 18.331575 | AI29: =O29+R29+U29+X29+AA29+AD29 -> 324.25299 | AJ29: =P29+S29+V29+Y29+AB29+AE29 -> 234.67982 | AK29: =Q29+T29+W29+Z29+AC29+AF29 -> 127.54338 | AL29: =AI29-'Data by dwelling type'!W29 -> 0 | AM29: =AJ29-'Data by dwelling type'!Y29 -> 0 | AN29: =AK29-'Data by dwelling type'!Z29 -> 0
A30: MT | B30: Malta | C30: ENTRANZE | D30: thousands | E30: 30.9648 | F30: 32.46368 | G30: 21.3312 | H30: 24.5022 | I30: 23.7292 | J30: 8.84892 | K30: =SUM(E30:J30) -> 141.84 | M30: Malta | N30: thousands | O30: =E30*'Data by dwelling type'!AA30 -> 7.7229495 | P30: =E30*'Data by dwelling type'!AB30 -> 1.6869085 | Q30: =E30*'Data by dwelling type'!AC30 -> 21.554942 | R30: =F30*'Data by dwelling type'!AA30 -> 8.096786 | S30: =F30*'Data by dwelling type'!AB30 -> 1.7685649 | T30: =F30*'Data by dwelling type'!AC30 -> 22.598329 | U30: =G30*'Data by dwelling type'!AA30 -> 5.3202275 | V30: =G30*'Data by dwelling type'!AB30 -> 1.1620867 | W30: =G30*'Data by dwelling type'!AC30 -> 14.848886 | X30: =H30*'Data by dwelling type'!AA30 -> 6.1111085 | Y30: =H30*'Data by dwelling type'!AB30 -> 1.3348373 | Z30: =H30*'Data by dwelling type'!AC30 -> 17.056254 | AA30: =I30*'Data by dwelling type'!AA30 -> 5.9183141 | AB30: =I30*'Data by dwelling type'!AB30 -> 1.2927256 | AC30: =I30*'Data by dwelling type'!AC30 -> 16.51816 | AD30: =J30*'Data by dwelling type'!AA30 -> 2.2070145 | AE30: =J30*'Data by dwelling type'!AB30 -> 0.48207379 | AF30: =J30*'Data by dwelling type'!AC30 -> 6.1598317 | AI30: =O30+R30+U30+X30+AA30+AD30 -> 35.3764 | AJ30: =P30+S30+V30+Y30+AB30+AE30 -> 7.7271968 | AK30: =Q30+T30+W30+Z30+AC30+AF30 -> 98.736403 | AL30: =AI30-'Data by dwelling type'!W30 -> 0 | AM30: =AJ30-'Data by dwelling type'!Y30 -> 0 | AN30: =AK30-'Data by dwelling type'!Z30 -> 0
A31: NL | B31: Netherlands | C31: ENTRANZE | D31: thousands | E31: 1588.7156 | F31: 1788.1028 | G31: 1101.6833 | H31: 1071.5752 | I31: 945.3141 | J31: 491.43182 | K31: =SUM(E31:J31) -> 6986.8227 | M31: Netherlands | N31: thousands | O31: =E31*'Data by dwelling type'!AA31 -> 479.97394 | P31: =E31*'Data by dwelling type'!AB31 -> 176.52692 | Q31: =E31*'Data by dwelling type'!AC31 -> 932.21469 | R31: =F31*'Data by dwelling type'!AA31 -> 540.21172 | S31: =F31*'Data by dwelling type'!AB31 -> 198.68143 | T31: =F31*'Data by dwelling type'!AC31 -> 1049.2097 | U31: =G31*'Data by dwelling type'!AA31 -> 332.83445 | V31: =G31*'Data by dwelling type'!AB31 -> 122.41131 | W31: =G31*'Data by dwelling type'!AC31 -> 646.43752 | X31: =H31*'Data by dwelling type'!AA31 -> 323.73835 | Y31: =H31*'Data by dwelling type'!AB31 -> 119.06591 | Z31: =H31*'Data by dwelling type'!AC31 -> 628.7709 | AA31: =I31*'Data by dwelling type'!AA31 -> 285.59306 | AB31: =I31*'Data by dwelling type'!AB31 -> 105.03667 | AC31: =I31*'Data by dwelling type'!AC31 -> 554.68437 | AD31: =J31*'Data by dwelling type'!AA31 -> 148.46866 | AE31: =J31*'Data by dwelling type'!AB31 -> 54.604454 | AF31: =J31*'Data by dwelling type'!AC31 -> 288.35871 | AI31: =O31+R31+U31+X31+AA31+AD31 -> 2110.8202 | AJ31: =P31+S31+V31+Y31+AB31+AE31 -> 776.3267 | AK31: =Q31+T31+W31+Z31+AC31+AF31 -> 4099.6759 | AL31: =AI31-'Data by dwelling type'!W31 -> 3.0211459e-07 | AM31: =AJ31-'Data by dwelling type'!Y31 -> 1.1111308e-07 | AN31: =AK31-'Data by dwelling type'!Z31 -> 5.8677233e-07
A32: NO | B32: Norway | C32: ODYSSEE/BPIE | D32: thousands | E32: =$K$32*(54588886.2631579/286723521.350877) -> 433.01257 | F32: =$K$32*(72624823.8947368/286723521.350877) -> 576.07809 | G32: =$K$32*(46618636.8421053/286723521.350877) -> 369.79058 | H32: =$K$32*(39211256.5263158/286723521.350877) -> 311.0334 | I32: =$K$32*(43186741.0526316/286723521.350877) -> 342.56793 | J32: =$K$32*(30493176.7719298/286723521.350877) -> 241.87943 | K32: 2274.362 | M32: Norway | N32: thousands | O32: =E32*'Data by dwelling type'!AA32 -> 251.93644 | P32: =E32*'Data by dwelling type'!AB32 -> 101.41934 | Q32: =E32*'Data by dwelling type'!AC32 -> 79.656789 | R32: =F32*'Data by dwelling type'!AA32 -> 335.17518 | S32: =F32*'Data by dwelling type'!AB32 -> 134.92786 | T32: =F32*'Data by dwelling type'!AC32 -> 105.97506 | U32: =G32*'Data by dwelling type'!AA32 -> 215.15246 | V32: =G32*'Data by dwelling type'!AB32 -> 86.611612 | W32: =G32*'Data by dwelling type'!AC32 -> 68.026501 | X32: =H32*'Data by dwelling type'!AA32 -> 180.96622 | Y32: =H32*'Data by dwelling type'!AB32 -> 72.849623 | Z32: =H32*'Data by dwelling type'!AC32 -> 57.217558 | AA32: =I32*'Data by dwelling type'!AA32 -> 199.31372 | AB32: =I32*'Data by dwelling type'!AB32 -> 80.235577 | AC32: =I32*'Data by dwelling type'!AC32 -> 63.018635 | AD32: =J32*'Data by dwelling type'!AA32 -> 140.73089 | AE32: =J32*'Data by dwelling type'!AB32 -> 56.652519 | AF32: =J32*'Data by dwelling type'!AC32 -> 44.496027 | AI32: =O32+R32+U32+X32+AA32+AD32 -> 1323.2749 | AJ32: =P32+S32+V32+Y32+AB32+AE32 -> 532.69653 | AK32: =Q32+T32+W32+Z32+AC32+AF32 -> 418.39056 | AL32: =AI32-'Data by dwelling type'!W32 -> 0 | AM32: =AJ32-'Data by dwelling type'!Y32 -> 0 | AN32: =AK32-'Data by dwelling type'!Z32 -> 0
A33: PL | B33: Poland | C33: ENTRANZE | D33: thousands | E33: 2747 | F33: 3048.0769 | G33: 1751.7668 | H33: 1810.9375 | I33: 1810.9375 | J33: 2253.2812 | K33: =SUM(E33:J33) -> 13422 | M33: Poland | N33: thousands | O33: =E33*'Data by dwelling type'!AA33 -> 1636.0839 | P33: =E33*'Data by dwelling type'!AB33 -> 807.78881 | Q33: =E33*'Data by dwelling type'!AC33 -> 303.12729 | R33: =F33*'Data by dwelling type'!AA33 -> 1815.4021 | S33: =F33*'Data by dwelling type'!AB33 -> 896.32415 | T33: =F33*'Data by dwelling type'!AC33 -> 336.35068 | U33: =G33*'Data by dwelling type'!AA33 -> 1043.3336 | V33: =G33*'Data by dwelling type'!AB33 -> 515.12837 | W33: =G33*'Data by dwelling type'!AC33 -> 193.30482 | X33: =H33*'Data by dwelling type'!AA33 -> 1078.5751 | Y33: =H33*'Data by dwelling type'!AB33 -> 532.52823 | Z33: =H33*'Data by dwelling type'!AC33 -> 199.83421 | AA33: =I33*'Data by dwelling type'!AA33 -> 1078.5751 | AB33: =I33*'Data by dwelling type'!AB33 -> 532.52823 | AC33: =I33*'Data by dwelling type'!AC33 -> 199.83421 | AD33: =J33*'Data by dwelling type'!AA33 -> 1342.0303 | AE33: =J33*'Data by dwelling type'!AB33 -> 662.6048 | AF33: =J33*'Data by dwelling type'!AC33 -> 248.64618 | AI33: =O33+R33+U33+X33+AA33+AD33 -> 7994 | AJ33: =P33+S33+V33+Y33+AB33+AE33 -> 3946.9026 | AK33: =Q33+T33+W33+Z33+AC33+AF33 -> 1481.0974 | AL33: =AI33-'Data by dwelling type'!W33 -> 0 | AM33: =AJ33-'Data by dwelling type'!Y33 -> 0 | AN33: =AK33-'Data by dwelling type'!Z33 -> 0
A34: PT | B34: Portugal | C34: ENTRANZE | D34: thousands | E34: 514.25647 | F34: 695.66012 | G34: 779.63406 | H34: 666.34974 | I34: 725.69858 | J34: 412.12078 | K34: =SUM(E34:J34) -> 3793.7197 | M34: Portugal | N34: thousands | O34: =E34*'Data by dwelling type'!AA34 -> 210.84515 | P34: =E34*'Data by dwelling type'!AB34 -> 167.88415 | Q34: =E34*'Data by dwelling type'!AC34 -> 135.52717 | R34: =F34*'Data by dwelling type'!AA34 -> 285.22065 | S34: =F34*'Data by dwelling type'!AB34 -> 227.10518 | T34: =F34*'Data by dwelling type'!AC34 -> 183.33429 | U34: =G34*'Data by dwelling type'!AA34 -> 319.64996 | V34: =G34*'Data by dwelling type'!AB34 -> 254.51931 | W34: =G34*'Data by dwelling type'!AC34 -> 205.46479 | X34: =H34*'Data by dwelling type'!AA34 -> 273.20339 | Y34: =H34*'Data by dwelling type'!AB34 -> 217.53651 | Z34: =H34*'Data by dwelling type'!AC34 -> 175.60983 | AA34: =I34*'Data by dwelling type'!AA34 -> 297.53642 | AB34: =I34*'Data by dwelling type'!AB34 -> 236.91153 | AC34: =I34*'Data by dwelling type'!AC34 -> 191.25063 | AD34: =J34*'Data by dwelling type'!AA34 -> 168.96952 | AE34: =J34*'Data by dwelling type'!AB34 -> 134.54093 | AF34: =J34*'Data by dwelling type'!AC34 -> 108.61032 | AI34: =O34+R34+U34+X34+AA34+AD34 -> 1555.4251 | AJ34: =P34+S34+V34+Y34+AB34+AE34 -> 1238.4976 | AK34: =Q34+T34+W34+Z34+AC34+AF34 -> 999.79703 | AL34: =AI34-'Data by dwelling type'!W34 -> 0.00033333 | AM34: =AJ34-'Data by dwelling type'!Y34 -> 0.00026541195 | AN34: =AK34-'Data by dwelling type'!Z34 -> 0.00021425805
A35: RO | B35: Romania | C35: ENTRANZE | D35: thousands | E35: 764.5437 | F35: 2215.2927 | G35: 1598.2233 | H35: 2186.514 | I35: 301.1058 | J35: 295.9524 | K35: =SUM(E35:J35) -> 7361.6319 | M35: Romania | N35: thousands | O35: =E35*'Data by dwelling type'!AA35 -> 329.51833 | P35: =E35*'Data by dwelling type'!AB35 -> 337.96513 | Q35: =E35*'Data by dwelling type'!AC35 -> 97.060234 | R35: =F35*'Data by dwelling type'!AA35 -> 954.79117 | S35: =F35*'Data by dwelling type'!AB35 -> 979.26606 | T35: =F35*'Data by dwelling type'!AC35 -> 281.2355 | U35: =G35*'Data by dwelling type'!AA35 -> 688.83423 | V35: =G35*'Data by dwelling type'!AB35 -> 706.49165 | W35: =G35*'Data by dwelling type'!AC35 -> 202.89739 | X35: =H35*'Data by dwelling type'!AA35 -> 942.38753 | Y35: =H35*'Data by dwelling type'!AB35 -> 966.54448 | Z35: =H35*'Data by dwelling type'!AC35 -> 277.58199 | AA35: =I35*'Data by dwelling type'!AA35 -> 129.7766 | AB35: =I35*'Data by dwelling type'!AB35 -> 133.10326 | AC35: =I35*'Data by dwelling type'!AC35 -> 38.225937 | AD35: =J35*'Data by dwelling type'!AA35 -> 127.55548 | AE35: =J35*'Data by dwelling type'!AB35 -> 130.82521 | AF35: =J35*'Data by dwelling type'!AC35 -> 37.571703 | AI35: =O35+R35+U35+X35+AA35+AD35 -> 3172.8633 | AJ35: =P35+S35+V35+Y35+AB35+AE35 -> 3254.1958 | AK35: =Q35+T35+W35+Z35+AC35+AF35 -> 934.57276 | AL35: =AI35-'Data by dwelling type'!W35 -> -0.1586511 | AM35: =AJ35-'Data by dwelling type'!Y35 -> -0.16271793 | AN35: =AK35-'Data by dwelling type'!Z35 -> -0.046730974
A36: RS | B36: Serbia | C36: ENTRANZE | D36: thousands | E36: 322.55288 | F36: 736.42371 | G36: 549.81933 | H36: 464.68389 | I36: 227.75888 | J36: 171.03886 | K36: =SUM(E36:J36) -> 2472.2776 | M36: Serbia | N36: thousands | O36: =E36*'Data by dwelling type'!AA36 -> 152.35596 | P36: =E36*'Data by dwelling type'!AB36 -> 125.34049 | Q36: =E36*'Data by dwelling type'!AC36 -> 44.856441 | R36: =F36*'Data by dwelling type'!AA36 -> 347.84541 | S36: =F36*'Data by dwelling type'!AB36 -> 286.16612 | T36: =F36*'Data by dwelling type'!AC36 -> 102.41219 | U36: =G36*'Data by dwelling type'!AA36 -> 259.70393 | V36: =G36*'Data by dwelling type'!AB36 -> 213.65372 | W36: =G36*'Data by dwelling type'!AC36 -> 76.46169 | X36: =H36*'Data by dwelling type'!AA36 -> 219.4907 | Y36: =H36*'Data by dwelling type'!AB36 -> 180.57102 | Z36: =H36*'Data by dwelling type'!AC36 -> 64.622165 | AA36: =I36*'Data by dwelling type'!AA36 -> 107.58057 | AB36: =I36*'Data by dwelling type'!AB36 -> 88.504585 | AC36: =I36*'Data by dwelling type'!AC36 -> 31.67373 | AD36: =J36*'Data by dwelling type'!AA36 -> 80.789201 | AE36: =J36*'Data by dwelling type'!AB36 -> 66.463813 | AF36: =J36*'Data by dwelling type'!AC36 -> 23.785851 | AI36: =O36+R36+U36+X36+AA36+AD36 -> 1167.7658 | AJ36: =P36+S36+V36+Y36+AB36+AE36 -> 960.69974 | AK36: =Q36+T36+W36+Z36+AC36+AF36 -> 343.81207 | AL36: =AI36-'Data by dwelling type'!W36 -> 1.627626 | AM36: =AJ36-'Data by dwelling type'!Y36 -> 1.3390185 | AN36: =AK36-'Data by dwelling type'!Z36 -> 0.47920352
A37: SE | B37: Sweden | C37: ENTRANZE | D37: thousands | E37: 1347.0281 | F37: 1221.6481 | G37: 664.78476 | H37: 457.95682 | I37: 374.96889 | J37: 104.61333 | K37: =SUM(E37:J37) -> 4171 | M37: Sweden | N37: thousands | O37: =E37*'Data by dwelling type'!AA37 -> 783.73121 | P37: =E37*'Data by dwelling type'!AB37 -> 380.67209 | Q37: =E37*'Data by dwelling type'!AC37 -> 182.6248 | R37: =F37*'Data by dwelling type'!AA37 -> 710.7823 | S37: =F37*'Data by dwelling type'!AB37 -> 345.23952 | T37: =F37*'Data by dwelling type'!AC37 -> 165.62627 | U37: =G37*'Data by dwelling type'!AA37 -> 386.78671 | V37: =G37*'Data by dwelling type'!AB37 -> 187.86914 | W37: =G37*'Data by dwelling type'!AC37 -> 90.128918 | X37: =H37*'Data by dwelling type'!AA37 -> 266.44957 | Y37: =H37*'Data by dwelling type'!AB37 -> 129.41926 | Z37: =H37*'Data by dwelling type'!AC37 -> 62.087996 | AA37: =I37*'Data by dwelling type'!AA37 -> 218.16532 | AB37: =I37*'Data by dwelling type'!AB37 -> 105.96675 | AC37: =I37*'Data by dwelling type'!AC37 -> 50.836816 | AD37: =J37*'Data by dwelling type'!AA37 -> 60.866387 | AE37: =J37*'Data by dwelling type'!AB37 -> 29.563879 | AF37: =J37*'Data by dwelling type'!AC37 -> 14.183067 | AI37: =O37+R37+U37+X37+AA37+AD37 -> 2426.7815 | AJ37: =P37+S37+V37+Y37+AB37+AE37 -> 1178.7306 | AK37: =Q37+T37+W37+Z37+AC37+AF37 -> 565.48787 | AL37: =AI37-'Data by dwelling type'!W37 -> -44.218508 | AM37: =AJ37-'Data by dwelling type'!Y37 -> -21.47771 | AN37: =AK37-'Data by dwelling type'!Z37 -> -10.303783
A38: SI | B38: Slovenia | C38: ENTRANZE | D38: thousands | E38: 243.50695 | F38: 162.76737 | G38: 140.12268 | H38: 76.121637 | I38: 76.121637 | J38: 66.559114 | K38: =SUM(E38:J38) -> 765.19939 | M38: Slovenia | N38: thousands | O38: =E38*'Data by dwelling type'!AA38 -> 155.75981 | P38: =E38*'Data by dwelling type'!AB38 -> 65.84743 | Q38: =E38*'Data by dwelling type'!AC38 -> 21.899708 | R38: =F38*'Data by dwelling type'!AA38 -> 104.11454 | S38: =F38*'Data by dwelling type'!AB38 -> 44.014403 | T38: =F38*'Data by dwelling type'!AC38 -> 14.638424 | U38: =G38*'Data by dwelling type'!AA38 -> 89.629814 | V38: =G38*'Data by dwelling type'!AB38 -> 37.890987 | W38: =G38*'Data by dwelling type'!AC38 -> 12.601882 | X38: =H38*'Data by dwelling type'!AA38 -> 48.69139 | Y38: =H38*'Data by dwelling type'!AB38 -> 20.584276 | Z38: =H38*'Data by dwelling type'!AC38 -> 6.8459716 | AA38: =I38*'Data by dwelling type'!AA38 -> 48.69139 | AB38: =I38*'Data by dwelling type'!AB38 -> 20.584276 | AC38: =I38*'Data by dwelling type'!AC38 -> 6.8459716 | AD38: =J38*'Data by dwelling type'!AA38 -> 42.574699 | AE38: =J38*'Data by dwelling type'!AB38 -> 17.998446 | AF38: =J38*'Data by dwelling type'!AC38 -> 5.9859696 | AI38: =O38+R38+U38+X38+AA38+AD38 -> 489.46164 | AJ38: =P38+S38+V38+Y38+AB38+AE38 -> 206.91982 | AK38: =Q38+T38+W38+Z38+AC38+AF38 -> 68.817927 | AL38: =AI38-'Data by dwelling type'!W38 -> -4.6263591 | AM38: =AJ38-'Data by dwelling type'!Y38 -> -1.9557924 | AN38: =AK38-'Data by dwelling type'!Z38 -> -0.6504625
A39: SK | B39: Slovakia | C39: ENTRANZE | D39: thousands | E39: 416.97972 | F39: 535.75491 | G39: 219.29488 | H39: 254.37872 | I39: 135.34265 | J39: 167.24913 | K39: =SUM(E39:J39) -> 1729 | M39: Slovakia | N39: thousands | O39: =E39*'Data by dwelling type'!AA39 -> 212.22797 | P39: =E39*'Data by dwelling type'!AB39 -> 157.79324 | Q39: =E39*'Data by dwelling type'!AC39 -> 46.958511 | R39: =F39*'Data by dwelling type'!AA39 -> 272.68034 | S39: =F39*'Data by dwelling type'!AB39 -> 202.74009 | T39: =F39*'Data by dwelling type'!AC39 -> 60.334474 | U39: =G39*'Data by dwelling type'!AA39 -> 111.61336 | V39: =G39*'Data by dwelling type'!AB39 -> 82.98545 | W39: =G39*'Data by dwelling type'!AC39 -> 24.696071 | X39: =H39*'Data by dwelling type'!AA39 -> 129.46979 | Y39: =H39*'Data by dwelling type'!AB39 -> 96.261859 | Z39: =H39*'Data by dwelling type'!AC39 -> 28.647066 | AA39: =I39*'Data by dwelling type'!AA39 -> 68.884632 | AB39: =I39*'Data by dwelling type'!AB39 -> 51.216292 | AC39: =I39*'Data by dwelling type'!AC39 -> 15.241722 | AD39: =J39*'Data by dwelling type'!AA39 -> 85.123909 | AE39: =J39*'Data by dwelling type'!AB39 -> 63.290328 | AF39: =J39*'Data by dwelling type'!AC39 -> 18.834897 | AI39: =O39+R39+U39+X39+AA39+AD39 -> 880 | AJ39: =P39+S39+V39+Y39+AB39+AE39 -> 654.28726 | AK39: =Q39+T39+W39+Z39+AC39+AF39 -> 194.71274 | AL39: =AI39-'Data by dwelling type'!W39 -> 0 | AM39: =AJ39-'Data by dwelling type'!Y39 -> 0 | AN39: =AK39-'Data by dwelling type'!Z39 -> 0
A40: UK | B40: UK | C40: ENTRANZE | D40: thousands | E40: 10370.564 | F40: 6525.5089 | G40: 2866.8247 | H40: 2035.4241 | I40: 2035.4241 | J40: 1683.2185 | K40: =SUM(E40:J40) -> 25516.964 | M40: UK | N40: thousands | O40: =E40*'Data by dwelling type'!AA40 -> 1942.6772 | P40: =E40*'Data by dwelling type'!AB40 -> 1884.6923 | Q40: =E40*'Data by dwelling type'!AC40 -> 6543.1942 | R40: =F40*'Data by dwelling type'!AA40 -> 1222.3981 | S40: =F40*'Data by dwelling type'!AB40 -> 1185.912 | T40: =F40*'Data by dwelling type'!AC40 -> 4117.1988 | U40: =G40*'Data by dwelling type'!AA40 -> 537.03108 | V40: =G40*'Data by dwelling type'!AB40 -> 521.00181 | W40: =G40*'Data by dwelling type'!AC40 -> 1808.7918 | X40: =H40*'Data by dwelling type'!AA40 -> 381.28805 | Y40: =H40*'Data by dwelling type'!AB40 -> 369.90739 | Z40: =H40*'Data by dwelling type'!AC40 -> 1284.2287 | AA40: =I40*'Data by dwelling type'!AA40 -> 381.28805 | AB40: =I40*'Data by dwelling type'!AB40 -> 369.90739 | AC40: =I40*'Data by dwelling type'!AC40 -> 1284.2287 | AD40: =J40*'Data by dwelling type'!AA40 -> 315.31074 | AE40: =J40*'Data by dwelling type'!AB40 -> 305.89936 | AF40: =J40*'Data by dwelling type'!AC40 -> 1062.0084 | AI40: =O40+R40+U40+X40+AA40+AD40 -> 4779.9933 | AJ40: =P40+S40+V40+Y40+AB40+AE40 -> 4637.3202 | AK40: =Q40+T40+W40+Z40+AC40+AF40 -> 16099.651 | AL40: =AI40-'Data by dwelling type'!W40 -> -0.0067437395 | AM40: =AJ40-'Data by dwelling type'!Y40 -> -0.0065424526 | AN40: =AK40-'Data by dwelling type'!Z40 -> -0.022713808
A42: Black value: original data | E42: 8 | F42: 5 | G42: 3 | H42: 1 | I42: 1 | J42: 1 | K42: =SUMPRODUCT(E18:J18,E42:J42)/K18 -> 3.9805819 | P42: 8 | S42: 5 | V42: 3 | Y42: 1 | AB42: 1 | AE42: 1
A43: Red value: estimated data | O43: =SUMPRODUCT(O18:AF18,O42:AF42) -> 32137.915 | P43: =O43/SUM(P18,S18,V18,Y18,AB18,AE18) -> 3.9805819
F44: ~FI_T: PASTI
D45: TechName | E45: Comm-OUT | F45: Year | G45: ='All Stock'!D2 -> AT | H45: ='All Stock'!E2 -> BE | I45: ='All Stock'!F2 -> BG | J45: ='All Stock'!G2 -> CH | K45: ='All Stock'!H2 -> CY | L45: ='All Stock'!I2 -> CZ | M45: ='All Stock'!J2 -> DE | N45: ='All Stock'!K2 -> DK | ... AQ45: ='All Stock'!AN2 -> KS | AR45: AF~FX | AS45: AF~FX~0 | AT45: LIFE
A46: 1 | B46: flat | C46: < 1945 | D46: Rdw_Flat | E46: =TechComm!C4 -> R_Flat | F46: =VLOOKUP(C46,TechComm!$U$2:$V$7,2,FALSE) -> 1940 | G46: =OFFSET($N$3,MATCH(G$45,$A$4:$A$40,0),$A46)*G$67 -> 353.94296 | H46: =OFFSET($N$3,MATCH(H$45,$A$4:$A$40,0),$A46)*H$67 -> 358.30809 | I46: =OFFSET($N$3,MATCH(I$45,$A$4:$A$40,0),$A46)*I$67 -> 109.91712 | J46: =OFFSET($N$3,MATCH(J$45,$A$4:$A$40,0),$A46)*J$67 -> 397.35844 | K46: =OFFSET($N$3,MATCH(K$45,$A$4:$A$40,0),$A46)*K$67 -> 2.5286019 | L46: =OFFSET($N$3,MATCH(L$45,$A$4:$A$40,0),$A46)*L$67 -> 532.79971 | M46: =OFFSET($N$3,MATCH(M$45,$A$4:$A$40,0),$A46)*M$67 -> 4002.9176 | N46: =OFFSET($N$3,MATCH(N$45,$A$4:$A$40,0),$A46)*N$67 -> 382.9424 | ... AQ46: =OFFSET($N$3,MATCH(AQ$45,$A$4:$A$40,0),$A46)*AQ$67 -> 20.827151 | AR46: 1 | AS46: 3 | AT46: 200 | AV46: =D46&F46 -> Rdw_Flat1940
A47: 2 | B47: detached | C47: < 1945 | D47: Rdw_DetH | E47: =TechComm!C5 -> R_DetH | F47: =VLOOKUP(C47,TechComm!$U$2:$V$7,2,FALSE) -> 1940 | G47: =OFFSET($N$3,MATCH(G$45,$A$4:$A$40,0),$A47)*G$67 -> 244.72894 | H47: =OFFSET($N$3,MATCH(H$45,$A$4:$A$40,0),$A47)*H$67 -> 376.06049 | I47: =OFFSET($N$3,MATCH(I$45,$A$4:$A$40,0),$A47)*I$67 -> 87.260262 | J47: =OFFSET($N$3,MATCH(J$45,$A$4:$A$40,0),$A47)*J$67 -> 202.87575 | K47: =OFFSET($N$3,MATCH(K$45,$A$4:$A$40,0),$A47)*K$67 -> 3.2037613 | L47: =OFFSET($N$3,MATCH(L$45,$A$4:$A$40,0),$A47)*L$67 -> 247.83002 | M47: =OFFSET($N$3,MATCH(M$45,$A$4:$A$40,0),$A47)*M$67 -> 1672.6828 | N47: =OFFSET($N$3,MATCH(N$45,$A$4:$A$40,0),$A47)*N$67 -> 358.06515 | ... AQ47: =OFFSET($N$3,MATCH(AQ$45,$A$4:$A$40,0),$A47)*AQ$67 -> 17.13412 | AR47: 1 | AS47: 3 | AT47: 200 | AV47: =D47&F47 -> Rdw_DetH1940
A48: 3 | B48: semidetached | C48: < 1945 | D48: Rdw_SDetH | E48: =TechComm!C6 -> R_SDetH | F48: =VLOOKUP(C48,TechComm!$U$2:$V$7,2,FALSE) -> 1940 | G48: =OFFSET($N$3,MATCH(G$45,$A$4:$A$40,0),$A48)*G$67 -> 113.41097 | H48: =OFFSET($N$3,MATCH(H$45,$A$4:$A$40,0),$A48)*H$67 -> 627.44324 | I48: =OFFSET($N$3,MATCH(I$45,$A$4:$A$40,0),$A48)*I$67 -> 47.424056 | J48: =OFFSET($N$3,MATCH(J$45,$A$4:$A$40,0),$A48)*J$67 -> 227.5959 | K48: =OFFSET($N$3,MATCH(K$45,$A$4:$A$40,0),$A48)*K$67 -> 3.2719265 | L48: =OFFSET($N$3,MATCH(L$45,$A$4:$A$40,0),$A48)*L$67 -> 146.89924 | M48: =OFFSET($N$3,MATCH(M$45,$A$4:$A$40,0),$A48)*M$67 -> 1748.7139 | N48: =OFFSET($N$3,MATCH(N$45,$A$4:$A$40,0),$A48)*N$67 -> 190.63363 | ... AQ48: =OFFSET($N$3,MATCH(AQ$45,$A$4:$A$40,0),$A48)*AQ$67 -> 6.1319025 | AR48: 1 | AS48: 3 | AT48: 200 | AV48: =D48&F48 -> Rdw_SDetH1940
A49: 4 | B49: flat | C49: 1945-1969 | D49: =D46 -> Rdw_Flat | F49: =VLOOKUP(C49,TechComm!$U$2:$V$7,2,FALSE) -> 1957 | G49: =OFFSET($N$3,MATCH(G$45,$A$4:$A$40,0),$A49)*G$67 -> 427.04149 | H49: =OFFSET($N$3,MATCH(H$45,$A$4:$A$40,0),$A49)*H$67 -> 199.06005 | I49: =OFFSET($N$3,MATCH(I$45,$A$4:$A$40,0),$A49)*I$67 -> 227.54536 | J49: =OFFSET($N$3,MATCH(J$45,$A$4:$A$40,0),$A49)*J$67 -> 479.42342 | K49: =OFFSET($N$3,MATCH(K$45,$A$4:$A$40,0),$A49)*K$67 -> 8.4249042 | L49: =OFFSET($N$3,MATCH(L$45,$A$4:$A$40,0),$A49)*L$67 -> 723.62433 | M49: =OFFSET($N$3,MATCH(M$45,$A$4:$A$40,0),$A49)*M$67 -> 6076.0486 | N49: =OFFSET($N$3,MATCH(N$45,$A$4:$A$40,0),$A49)*N$67 -> 278.07095 | ... AQ49: =OFFSET($N$3,MATCH(AQ$45,$A$4:$A$40,0),$A49)*AQ$67 -> 47.550677 | AR49: 1 | AS49: 3 | AT49: 200 | AV49: =D49&F49 -> Rdw_Flat1957
A50: 5 | B50: detached | C50: 1945-1969 | D50: =D47 -> Rdw_DetH | F50: =VLOOKUP(C50,TechComm!$U$2:$V$7,2,FALSE) -> 1957 | G50: =OFFSET($N$3,MATCH(G$45,$A$4:$A$40,0),$A50)*G$67 -> 295.27191 | H50: =OFFSET($N$3,MATCH(H$45,$A$4:$A$40,0),$A50)*H$67 -> 208.92249 | I50: =OFFSET($N$3,MATCH(I$45,$A$4:$A$40,0),$A50)*I$67 -> 180.64218 | J50: =OFFSET($N$3,MATCH(J$45,$A$4:$A$40,0),$A50)*J$67 -> 244.77493 | K50: =OFFSET($N$3,MATCH(K$45,$A$4:$A$40,0),$A50)*K$67 -> 10.674429 | L50: =OFFSET($N$3,MATCH(L$45,$A$4:$A$40,0),$A50)*L$67 -> 336.59146 | M50: =OFFSET($N$3,MATCH(M$45,$A$4:$A$40,0),$A50)*M$67 -> 2538.9736 | N50: =OFFSET($N$3,MATCH(N$45,$A$4:$A$40,0),$A50)*N$67 -> 260.0065 | ... AQ50: =OFFSET($N$3,MATCH(AQ$45,$A$4:$A$40,0),$A50)*AQ$67 -> 39.119081 | AR50: 1 | AS50: 3 | AT50: 200 | AV50: =D50&F50 -> Rdw_DetH1957
A51: 6 | B51: semidetached | C51: 1945-1969 | D51: =D48 -> Rdw_SDetH | F51: =VLOOKUP(C51,TechComm!$U$2:$V$7,2,FALSE) -> 1957 | G51: =OFFSET($N$3,MATCH(G$45,$A$4:$A$40,0),$A51)*G$67 -> 136.83332 | H51: =OFFSET($N$3,MATCH(H$45,$A$4:$A$40,0),$A51)*H$67 -> 348.57958 | I51: =OFFSET($N$3,MATCH(I$45,$A$4:$A$40,0),$A51)*I$67 -> 98.175097 | J51: =OFFSET($N$3,MATCH(J$45,$A$4:$A$40,0),$A51)*J$67 -> 274.60044 | K51: =OFFSET($N$3,MATCH(K$45,$A$4:$A$40,0),$A51)*K$67 -> 10.901545 | L51: =OFFSET($N$3,MATCH(L$45,$A$4:$A$40,0),$A51)*L$67 -> 199.51187 | M51: =OFFSET($N$3,MATCH(M$45,$A$4:$A$40,0),$A51)*M$67 -> 2654.3815 | N51: =OFFSET($N$3,MATCH(N$45,$A$4:$A$40,0),$A51)*N$67 -> 138.42728 | ... AQ51: =OFFSET($N$3,MATCH(AQ$45,$A$4:$A$40,0),$A51)*AQ$67 -> 13.999808 | AR51: 1 | AS51: 3 | AT51: 200 | AV51: =D51&F51 -> Rdw_SDetH1957
A52: 7 | B52: flat | C52: 1970-1979 | D52: =D49 -> Rdw_Flat | F52: =VLOOKUP(C52,TechComm!$U$2:$V$7,2,FALSE) -> 1975 | G52: =OFFSET($N$3,MATCH(G$45,$A$4:$A$40,0),$A52)*G$67 -> 219.72377 | H52: =OFFSET($N$3,MATCH(H$45,$A$4:$A$40,0),$A52)*H$67 -> 107.72886 | I52: =OFFSET($N$3,MATCH(I$45,$A$4:$A$40,0),$A52)*I$67 -> 131.92853 | J52: =OFFSET($N$3,MATCH(J$45,$A$4:$A$40,0),$A52)*J$67 -> 246.67561 | K52: =OFFSET($N$3,MATCH(K$45,$A$4:$A$40,0),$A52)*K$67 -> 11.405028 | L52: =OFFSET($N$3,MATCH(L$45,$A$4:$A$40,0),$A52)*L$67 -> 296.50705 | M52: =OFFSET($N$3,MATCH(M$45,$A$4:$A$40,0),$A52)*M$67 -> 3131.8876 | N52: =OFFSET($N$3,MATCH(N$45,$A$4:$A$40,0),$A52)*N$67 -> 171.76836 | ... AQ52: =OFFSET($N$3,MATCH(AQ$45,$A$4:$A$40,0),$A52)*AQ$67 -> 35.501683 | AR52: 1 | AS52: 3 | AT52: 200 | AV52: =D52&F52 -> Rdw_Flat1975
A53: 8 | B53: detached | C53: 1970-1979 | D53: Rdw_DetH-70 | E53: =E47 -> R_DetH | F53: =VLOOKUP(C53,TechComm!$U$2:$V$7,2,FALSE) -> 1975 | G53: =OFFSET($N$3,MATCH(G$45,$A$4:$A$40,0),$A53)*G$67 -> 151.92494 | H53: =OFFSET($N$3,MATCH(H$45,$A$4:$A$40,0),$A53)*H$67 -> 113.06629 | I53: =OFFSET($N$3,MATCH(I$45,$A$4:$A$40,0),$A53)*I$67 -> 104.73453 | J53: =OFFSET($N$3,MATCH(J$45,$A$4:$A$40,0),$A53)*J$67 -> 125.94296 | K53: =OFFSET($N$3,MATCH(K$45,$A$4:$A$40,0),$A53)*K$67 -> 14.450273 | L53: =OFFSET($N$3,MATCH(L$45,$A$4:$A$40,0),$A53)*L$67 -> 137.91927 | M53: =OFFSET($N$3,MATCH(M$45,$A$4:$A$40,0),$A53)*M$67 -> 1308.7091 | N53: =OFFSET($N$3,MATCH(N$45,$A$4:$A$40,0),$A53)*N$67 -> 160.6097 | ... AQ53: =OFFSET($N$3,MATCH(AQ$45,$A$4:$A$40,0),$A53)*AQ$67 -> 29.206592 | AR53: 1 | AS53: 3 | AT53: 200 | AV53: =D53&F53 -> Rdw_DetH-701975
A54: 9 | B54: semidetached | C54: 1970-1979 | D54: =D51 -> Rdw_SDetH | F54: =VLOOKUP(C54,TechComm!$U$2:$V$7,2,FALSE) -> 1975 | G54: =OFFSET($N$3,MATCH(G$45,$A$4:$A$40,0),$A54)*G$67 -> 70.404243 | H54: =OFFSET($N$3,MATCH(H$45,$A$4:$A$40,0),$A54)*H$67 -> 188.64699 | I54: =OFFSET($N$3,MATCH(I$45,$A$4:$A$40,0),$A54)*I$67 -> 56.920942 | J54: =OFFSET($N$3,MATCH(J$45,$A$4:$A$40,0),$A54)*J$67 -> 141.28895 | K54: =OFFSET($N$3,MATCH(K$45,$A$4:$A$40,0),$A54)*K$67 -> 14.757725 | L54: =OFFSET($N$3,MATCH(L$45,$A$4:$A$40,0),$A54)*L$67 -> 81.750535 | M54: =OFFSET($N$3,MATCH(M$45,$A$4:$A$40,0),$A54)*M$67 -> 1368.1959 | N54: =OFFSET($N$3,MATCH(N$45,$A$4:$A$40,0),$A54)*N$67 -> 85.508489 | ... AQ54: =OFFSET($N$3,MATCH(AQ$45,$A$4:$A$40,0),$A54)*AQ$67 -> 10.452359 | AR54: 1 | AS54: 3 | AT54: 200 | AV54: =D54&F54 -> Rdw_SDetH1975
A55: 10 | B55: flat | C55: 1980-1989 | D55: =D52 -> Rdw_Flat | F55: =VLOOKUP(C55,TechComm!$U$2:$V$7,2,FALSE) -> 1985 | G55: =OFFSET($N$3,MATCH(G$45,$A$4:$A$40,0),$A55)*G$67 -> 174.33774 | H55: =OFFSET($N$3,MATCH(H$45,$A$4:$A$40,0),$A55)*H$67 -> 107.72886 | I55: =OFFSET($N$3,MATCH(I$45,$A$4:$A$40,0),$A55)*I$67 -> 124.32101 | J55: =OFFSET($N$3,MATCH(J$45,$A$4:$A$40,0),$A55)*J$67 -> 195.72242 | K55: =OFFSET($N$3,MATCH(K$45,$A$4:$A$40,0),$A55)*K$67 -> 16.464575 | L55: =OFFSET($N$3,MATCH(L$45,$A$4:$A$40,0),$A55)*L$67 -> 343.67998 | M55: =OFFSET($N$3,MATCH(M$45,$A$4:$A$40,0),$A55)*M$67 -> 2182.8568 | N55: =OFFSET($N$3,MATCH(N$45,$A$4:$A$40,0),$A55)*N$67 -> 70.354963 | ... AQ55: =OFFSET($N$3,MATCH(AQ$45,$A$4:$A$40,0),$A55)*AQ$67 -> 30.004511 | AR55: 1 | AS55: 3 | AT55: 200 | AV55: =D55&F55 -> Rdw_Flat1985
A56: 11 | B56: detached | C56: 1980-1989 | D56: =D53 -> Rdw_DetH-70 | F56: =VLOOKUP(C56,TechComm!$U$2:$V$7,2,FALSE) -> 1985 | G56: =OFFSET($N$3,MATCH(G$45,$A$4:$A$40,0),$A56)*G$67 -> 120.54341 | H56: =OFFSET($N$3,MATCH(H$45,$A$4:$A$40,0),$A56)*H$67 -> 113.06629 | I56: =OFFSET($N$3,MATCH(I$45,$A$4:$A$40,0),$A56)*I$67 -> 98.695125 | J56: =OFFSET($N$3,MATCH(J$45,$A$4:$A$40,0),$A56)*J$67 -> 99.928247 | K56: =OFFSET($N$3,MATCH(K$45,$A$4:$A$40,0),$A56)*K$67 -> 20.860764 | L56: =OFFSET($N$3,MATCH(L$45,$A$4:$A$40,0),$A56)*L$67 -> 159.8616 | M56: =OFFSET($N$3,MATCH(M$45,$A$4:$A$40,0),$A56)*M$67 -> 912.14145 | N56: =OFFSET($N$3,MATCH(N$45,$A$4:$A$40,0),$A56)*N$67 -> 65.784463 | ... AQ56: =OFFSET($N$3,MATCH(AQ$45,$A$4:$A$40,0),$A56)*AQ$67 -> 24.684168 | AR56: 1 | AS56: 3 | AT56: 200 | AV56: =D56&F56 -> Rdw_DetH-701985
A57: 12 | B57: semidetached | C57: 1980-1989 | D57: =D54 -> Rdw_SDetH | F57: =VLOOKUP(C57,TechComm!$U$2:$V$7,2,FALSE) -> 1985 | G57: =OFFSET($N$3,MATCH(G$45,$A$4:$A$40,0),$A57)*G$67 -> 55.861579 | H57: =OFFSET($N$3,MATCH(H$45,$A$4:$A$40,0),$A57)*H$67 -> 188.64699 | I57: =OFFSET($N$3,MATCH(I$45,$A$4:$A$40,0),$A57)*I$67 -> 53.638655 | J57: =OFFSET($N$3,MATCH(J$45,$A$4:$A$40,0),$A57)*J$67 -> 112.10438 | K57: =OFFSET($N$3,MATCH(K$45,$A$4:$A$40,0),$A57)*K$67 -> 21.30461 | L57: =OFFSET($N$3,MATCH(L$45,$A$4:$A$40,0),$A57)*L$67 -> 94.756676 | M57: =OFFSET($N$3,MATCH(M$45,$A$4:$A$40,0),$A57)*M$67 -> 953.60243 | N57: =OFFSET($N$3,MATCH(N$45,$A$4:$A$40,0),$A57)*N$67 -> 35.023602 | ... AQ57: =OFFSET($N$3,MATCH(AQ$45,$A$4:$A$40,0),$A57)*AQ$67 -> 8.8338888 | AR57: 1 | AS57: 3 | AT57: 200 | AV57: =D57&F57 -> Rdw_SDetH1985
A58: 13 | B58: flat | C58: 1990-1999 | D58: =D55 -> Rdw_Flat | F58: =VLOOKUP(C58,TechComm!$U$2:$V$7,2,FALSE) -> 1995 | G58: =OFFSET($N$3,MATCH(G$45,$A$4:$A$40,0),$A58)*G$67 -> 208.0754 | H58: =OFFSET($N$3,MATCH(H$45,$A$4:$A$40,0),$A58)*H$67 -> 79.355293 | I58: =OFFSET($N$3,MATCH(I$45,$A$4:$A$40,0),$A58)*I$67 -> 71.797614 | J58: =OFFSET($N$3,MATCH(J$45,$A$4:$A$40,0),$A58)*J$67 -> 233.59843 | K58: =OFFSET($N$3,MATCH(K$45,$A$4:$A$40,0),$A58)*K$67 -> 14.196859 | L58: =OFFSET($N$3,MATCH(L$45,$A$4:$A$40,0),$A58)*L$67 -> 177.40507 | M58: =OFFSET($N$3,MATCH(M$45,$A$4:$A$40,0),$A58)*M$67 -> 2009.019 | N58: =OFFSET($N$3,MATCH(N$45,$A$4:$A$40,0),$A58)*N$67 -> 70.410734 | ... AQ58: =OFFSET($N$3,MATCH(AQ$45,$A$4:$A$40,0),$A58)*AQ$67 -> 14.706328 | AR58: 1 | AS58: 3 | AT58: 200 | AV58: =D58&F58 -> Rdw_Flat1995
A59: 14 | B59: detached | C59: 1990-1999 | D59: =D56 -> Rdw_DetH-70 | F59: =VLOOKUP(C59,TechComm!$U$2:$V$7,2,FALSE) -> 1995 | G59: =OFFSET($N$3,MATCH(G$45,$A$4:$A$40,0),$A59)*G$67 -> 143.87085 | H59: =OFFSET($N$3,MATCH(H$45,$A$4:$A$40,0),$A59)*H$67 -> 83.286957 | I59: =OFFSET($N$3,MATCH(I$45,$A$4:$A$40,0),$A59)*I$67 -> 56.998206 | J59: =OFFSET($N$3,MATCH(J$45,$A$4:$A$40,0),$A59)*J$67 -> 119.26626 | K59: =OFFSET($N$3,MATCH(K$45,$A$4:$A$40,0),$A59)*K$67 -> 17.987549 | L59: =OFFSET($N$3,MATCH(L$45,$A$4:$A$40,0),$A59)*L$67 -> 82.519378 | M59: =OFFSET($N$3,MATCH(M$45,$A$4:$A$40,0),$A59)*M$67 -> 839.50055 | N59: =OFFSET($N$3,MATCH(N$45,$A$4:$A$40,0),$A59)*N$67 -> 65.83661 | ... AQ59: =OFFSET($N$3,MATCH(AQ$45,$A$4:$A$40,0),$A59)*AQ$67 -> 12.09863 | AR59: 1 | AS59: 3 | AT59: 200 | AV59: =D59&F59 -> Rdw_DetH-701995
A60: 15 | B60: semidetached | C60: 1990-1999 | D60: =D57 -> Rdw_SDetH | F60: =VLOOKUP(C60,TechComm!$U$2:$V$7,2,FALSE) -> 1995 | G60: =OFFSET($N$3,MATCH(G$45,$A$4:$A$40,0),$A60)*G$67 -> 66.671855 | H60: =OFFSET($N$3,MATCH(H$45,$A$4:$A$40,0),$A60)*H$67 -> 138.96126 | I60: =OFFSET($N$3,MATCH(I$45,$A$4:$A$40,0),$A60)*I$67 -> 30.977286 | J60: =OFFSET($N$3,MATCH(J$45,$A$4:$A$40,0),$A60)*J$67 -> 133.7987 | K60: =OFFSET($N$3,MATCH(K$45,$A$4:$A$40,0),$A60)*K$67 -> 18.370262 | L60: =OFFSET($N$3,MATCH(L$45,$A$4:$A$40,0),$A60)*L$67 -> 48.912696 | M60: =OFFSET($N$3,MATCH(M$45,$A$4:$A$40,0),$A60)*M$67 -> 877.65966 | N60: =OFFSET($N$3,MATCH(N$45,$A$4:$A$40,0),$A60)*N$67 -> 35.051365 | ... AQ60: =OFFSET($N$3,MATCH(AQ$45,$A$4:$A$40,0),$A60)*AQ$67 -> 4.329818 | AR60: 1 | AS60: 3 | AT60: 200 | AV60: =D60&F60 -> Rdw_SDetH1995
A61: 16 | B61: flat | C61: 2000-2008 | D61: =D58 -> Rdw_Flat | F61: =VLOOKUP(C61,TechComm!$U$2:$V$7,2,FALSE) -> 2004 | G61: =OFFSET($N$3,MATCH(G$45,$A$4:$A$40,0),$A61)*G$67 -> 85.071779 | H61: =OFFSET($N$3,MATCH(H$45,$A$4:$A$40,0),$A61)*H$67 -> 53.341872 | I61: =OFFSET($N$3,MATCH(I$45,$A$4:$A$40,0),$A61)*I$67 -> 111.70807 | J61: =OFFSET($N$3,MATCH(J$45,$A$4:$A$40,0),$A61)*J$67 -> 95.506886 | K61: =OFFSET($N$3,MATCH(K$45,$A$4:$A$40,0),$A61)*K$67 -> 30.524906 | L61: =OFFSET($N$3,MATCH(L$45,$A$4:$A$40,0),$A61)*L$67 -> 134.01508 | M61: =OFFSET($N$3,MATCH(M$45,$A$4:$A$40,0),$A61)*M$67 -> 1104.7493 | N61: =OFFSET($N$3,MATCH(N$45,$A$4:$A$40,0),$A61)*N$67 -> 93.128841 | ... AQ61: =OFFSET($N$3,MATCH(AQ$45,$A$4:$A$40,0),$A61)*AQ$67 -> 11.043932 | AR61: 1 | AS61: 3 | AT61: 200 | AV61: =D61&F61 -> Rdw_Flat2004
A62: 17 | B62: detached | C62: 2000-2008 | D62: =D59 -> Rdw_DetH-70 | F62: =VLOOKUP(C62,TechComm!$U$2:$V$7,2,FALSE) -> 2004 | G62: =OFFSET($N$3,MATCH(G$45,$A$4:$A$40,0),$A62)*G$67 -> 58.821699 | H62: =OFFSET($N$3,MATCH(H$45,$A$4:$A$40,0),$A62)*H$67 -> 55.984699 | I62: =OFFSET($N$3,MATCH(I$45,$A$4:$A$40,0),$A62)*I$67 -> 88.682046 | J62: =OFFSET($N$3,MATCH(J$45,$A$4:$A$40,0),$A62)*J$67 -> 48.762097 | K62: =OFFSET($N$3,MATCH(K$45,$A$4:$A$40,0),$A62)*K$67 -> 38.67533 | L62: =OFFSET($N$3,MATCH(L$45,$A$4:$A$40,0),$A62)*L$67 -> 62.336669 | M62: =OFFSET($N$3,MATCH(M$45,$A$4:$A$40,0),$A62)*M$67 -> 461.63709 | N62: =OFFSET($N$3,MATCH(N$45,$A$4:$A$40,0),$A62)*N$67 -> 87.078871 | ... AQ62: =OFFSET($N$3,MATCH(AQ$45,$A$4:$A$40,0),$A62)*AQ$67 -> 9.0856432 | AR62: 1 | AS62: 3 | AT62: 200 | AV62: =D62&F62 -> Rdw_DetH-702004
A63: 18 | B63: semidetached | C63: 2000-2008 | D63: =D60 -> Rdw_SDetH | F63: =VLOOKUP(C63,TechComm!$U$2:$V$7,2,FALSE) -> 2004 | G63: =OFFSET($N$3,MATCH(G$45,$A$4:$A$40,0),$A63)*G$67 -> 27.258836 | H63: =OFFSET($N$3,MATCH(H$45,$A$4:$A$40,0),$A63)*H$67 -> 93.408433 | I63: =OFFSET($N$3,MATCH(I$45,$A$4:$A$40,0),$A63)*I$67 -> 48.196764 | J63: =OFFSET($N$3,MATCH(J$45,$A$4:$A$40,0),$A63)*J$67 -> 54.703697 | K63: =OFFSET($N$3,MATCH(K$45,$A$4:$A$40,0),$A63)*K$67 -> 39.498209 | L63: =OFFSET($N$3,MATCH(L$45,$A$4:$A$40,0),$A63)*L$67 -> 36.949558 | M63: =OFFSET($N$3,MATCH(M$45,$A$4:$A$40,0),$A63)*M$67 -> 482.62059 | N63: =OFFSET($N$3,MATCH(N$45,$A$4:$A$40,0),$A63)*N$67 -> 46.36073 | ... AQ63: =OFFSET($N$3,MATCH(AQ$45,$A$4:$A$40,0),$A63)*AQ$67 -> 3.2515401 | AR63: 1 | AS63: 3 | AT63: 200 | AV63: =D63&F63 -> Rdw_SDetH2004
G65: =SUM(G46:G63) -> 2953.7957 | H65: =SUM(H46:H63) -> 3441.5967 | I65: =SUM(I46:I63) -> 1729.5629 | J65: =SUM(J46:J63) -> 3433.9275 | K65: =SUM(K46:K63) -> 297.50126 | L65: =SUM(L46:L63) -> 3843.8702 | M65: =SUM(M46:M63) -> 34326.297 | N65: =SUM(N46:N63) -> 2595.0626 | ... AQ65: =SUM(AQ46:AQ63) -> 337.96183
D66: CHECK | G66: =SUM('TechHeat-RES'!F5:F44)-'Dwelling stock'!G65 -> 0 | H66: =SUM('TechHeat-RES'!G5:G44)-'Dwelling stock'!H65 -> 0 | I66: =SUM('TechHeat-RES'!H5:H44)-'Dwelling stock'!I65 -> 0 | J66: =SUM('TechHeat-RES'!I5:I44)-'Dwelling stock'!J65 -> 0 | K66: =SUM('TechHeat-RES'!J5:J44)-'Dwelling stock'!K65 -> 0 | L66: =SUM('TechHeat-RES'!K5:K44)-'Dwelling stock'!L65 -> 0 | M66: =SUM('TechHeat-RES'!L5:L44)-'Dwelling stock'!M65 -> 0 | N66: =SUM('TechHeat-RES'!M5:M44)-'Dwelling stock'!N65 -> 0 | ... AQ66: =SUM('TechHeat-RES'!AP5:AP44)-'Dwelling stock'!AQ65 -> 0
D67: Stock Component of ATT | G67: =IF(INDEX('All Stock'!$D$23:$AN$23,1,MATCH(G$45,'All Stock'!$D$19:$AN$19,0))=0,1,INDEX('All Stock'!$D$23:$AN$23,1,MATCH(G$45,'All Stock'!$D$19:$AN$19,0))) -> 0.82913817 | H67: =IF(INDEX('All Stock'!$D$23:$AN$23,1,MATCH(H$45,'All Stock'!$D$19:$AN$19,0))=0,1,INDEX('All Stock'!$D$23:$AN$23,1,MATCH(H$45,'All Stock'!$D$19:$AN$19,0))) -> 0.76091018 | I67: =IF(INDEX('All Stock'!$D$23:$AN$23,1,MATCH(I$45,'All Stock'!$D$19:$AN$19,0))=0,1,INDEX('All Stock'!$D$23:$AN$23,1,MATCH(I$45,'All Stock'!$D$19:$AN$19,0))) -> 0.56118198 | J67: =IF(INDEX('All Stock'!$D$23:$AN$23,1,MATCH(J$45,'All Stock'!$D$19:$AN$19,0))=0,1,INDEX('All Stock'!$D$23:$AN$23,1,MATCH(J$45,'All Stock'!$D$19:$AN$19,0))) -> 0.88727392 | K67: =IF(INDEX('All Stock'!$D$23:$AN$23,1,MATCH(K$45,'All Stock'!$D$19:$AN$19,0))=0,1,INDEX('All Stock'!$D$23:$AN$23,1,MATCH(K$45,'All Stock'!$D$19:$AN$19,0))) -> 0.99446531 | L67: =IF(INDEX('All Stock'!$D$23:$AN$23,1,MATCH(L$45,'All Stock'!$D$19:$AN$19,0))=0,1,INDEX('All Stock'!$D$23:$AN$23,1,MATCH(L$45,'All Stock'!$D$19:$AN$19,0))) -> 0.96265219 | M67: =IF(INDEX('All Stock'!$D$23:$AN$23,1,MATCH(M$45,'All Stock'!$D$19:$AN$19,0))=0,1,INDEX('All Stock'!$D$23:$AN$23,1,MATCH(M$45,'All Stock'!$D$19:$AN$19,0))) -> 0.87544592 | N67: =IF(INDEX('All Stock'!$D$23:$AN$23,1,MATCH(N$45,'All Stock'!$D$19:$AN$19,0))=0,1,INDEX('All Stock'!$D$23:$AN$23,1,MATCH(N$45,'All Stock'!$D$19:$AN$19,0))) -> 0.97168242 | ... AQ67: =IF(INDEX('All Stock'!$D$23:$AN$23,1,MATCH(AQ$45,'All Stock'!$D$19:$AN$19,0))=0,1,INDEX('All Stock'!$D$23:$AN$23,1,MATCH(AQ$45,'All Stock'!$D$19:$AN$19,0))) -> 0.46762854
G70: =G46*'All Stock'!D112 -> 7.9996664 | H70: =H46*'All Stock'!E112 -> 7.3845971 | I70: =I46*'All Stock'!F112 -> 0.97545895 | J70: =J46*'All Stock'!G112 -> 9.3632383 | K70: =K46*'All Stock'!H112 -> 0.022713131 | L70: =L46*'All Stock'!I112 -> 9.7760727 | M70: =M46*'All Stock'!J112 -> 94.765581 | N70: =N46*'All Stock'!K112 -> 5.9927224 | ... AQ70: =AQ46*'All Stock'!AN112 -> 0.18323836
G71: =G49*'All Stock'!D113 -> 8.7185475 | H71: =H49*'All Stock'!E113 -> 4.1025539 | I71: =I49*'All Stock'!F113 -> 2.0193502 | J71: =J49*'All Stock'!G113 -> 10.204655 | K71: =K49*'All Stock'!H113 -> 0.069487941 | L71: =L49*'All Stock'!I113 -> 11.966701 | M71: =M49*'All Stock'!J113 -> 118.72568 | N71: =N49*'All Stock'!K113 -> 4.2740896 | ... AQ71: =AQ49*'All Stock'!AN113 -> 0.41835334
G72: =G52*'All Stock'!D114 -> 3.6625115 | H72: =H52*'All Stock'!E114 -> 2.2202519 | I72: =I52*'All Stock'!F114 -> 1.1091771 | J72: =J52*'All Stock'!G114 -> 4.2867997 | K72: =K52*'All Stock'!H114 -> 0.094833395 | L72: =L52*'All Stock'!I114 -> 4.9033886 | M72: =M52*'All Stock'!J114 -> 41.684124 | N72: =N52*'All Stock'!K114 -> 1.9007672 | ... AQ72: =AQ52*'All Stock'!AN114 -> 0.31234566
G73: =G55*'All Stock'!D115 -> 2.053841 | H73: =H55*'All Stock'!E115 -> 1.9143597 | I73: =I55*'All Stock'!F115 -> 0.9094905 | J73: =J55*'All Stock'!G115 -> 2.4039256 | K73: =K55*'All Stock'!H115 -> 0.13429298 | L73: =L55*'All Stock'!I115 -> 5.1826581 | M73: =M55*'All Stock'!J115 -> 24.847084 | N73: =N55*'All Stock'!K115 -> 0.66061272 | ... AQ73: =AQ55*'All Stock'!AN115 -> 0.23086886
G74: =G58*'All Stock'!D116 -> 2.0634094 | H74: =H58*'All Stock'!E116 -> 1.4101568 | I74: =I58*'All Stock'!F116 -> 0.42962931 | J74: =J58*'All Stock'!G116 -> 2.4151249 | K74: =K58*'All Stock'!H116 -> 0.10001216 | L74: =L58*'All Stock'!I116 -> 2.0329334 | M74: =M58*'All Stock'!J116 -> 13.053819 | N74: =N58*'All Stock'!K116 -> 0.66113639 | ... AQ74: =AQ58*'All Stock'!AN116 -> 0.10746044
G75: =G61*'All Stock'!D117 -> 0.76264963 | H75: =H61*'All Stock'!E117 -> 0.56585955 | I75: =I61*'All Stock'!F117 -> 0.45053248 | J75: =J61*'All Stock'!G117 -> 0.892646 | K75: =K61*'All Stock'!H117 -> 0.19872314 | L75: =L61*'All Stock'!I117 -> 1.2336706 | M75: =M61*'All Stock'!J117 -> 7.8982345 | N75: =N61*'All Stock'!K117 -> 0.64601816 | ... AQ75: =AQ61*'All Stock'!AN117 -> 0.069375511
E77: Flat | G77: =SUM(G70:G75) -> 25.260625 | H77: =SUM(H70:H75) -> 17.597779 | I77: =SUM(I70:I75) -> 5.8936386 | J77: =SUM(J70:J75) -> 29.56639 | K77: =SUM(K70:K75) -> 0.62006274 | L77: =SUM(L70:L75) -> 35.095425 | M77: =SUM(M70:M75) -> 300.97452 | N77: =SUM(N70:N75) -> 14.135346 | ... AQ77: =SUM(AQ70:AQ75) -> 1.3216422
E78: check | G78: =SUMPRODUCT('TechHeat-RES'!F5:F14,'TechHeat-RES'!F93:F102,'TechHeat-RES'!F137:F146,'TechHeat-RES'!F182:F191) -> 29.049719 | H78: =SUMPRODUCT('TechHeat-RES'!G5:G14,'TechHeat-RES'!G93:G102,'TechHeat-RES'!G137:G146,'TechHeat-RES'!G182:G191) -> 20.237446 | I78: =SUMPRODUCT('TechHeat-RES'!H5:H14,'TechHeat-RES'!H93:H102,'TechHeat-RES'!H137:H146,'TechHeat-RES'!H182:H191) -> 6.7776844 | J78: =SUMPRODUCT('TechHeat-RES'!I5:I14,'TechHeat-RES'!I93:I102,'TechHeat-RES'!I137:I146,'TechHeat-RES'!I182:I191) -> 34.001348 | K78: =SUMPRODUCT('TechHeat-RES'!J5:J14,'TechHeat-RES'!J93:J102,'TechHeat-RES'!J137:J146,'TechHeat-RES'!J182:J191) -> 0.71307215 | L78: =SUMPRODUCT('TechHeat-RES'!K5:K14,'TechHeat-RES'!K93:K102,'TechHeat-RES'!K137:K146,'TechHeat-RES'!K182:K191) -> 40.359739 | M78: =SUMPRODUCT('TechHeat-RES'!L5:L14,'TechHeat-RES'!L93:L102,'TechHeat-RES'!L137:L146,'TechHeat-RES'!L182:L191) -> 346.1207 | N78: =SUMPRODUCT('TechHeat-RES'!M5:M14,'TechHeat-RES'!M93:M102,'TechHeat-RES'!M137:M146,'TechHeat-RES'!M182:M191) -> 16.255648 | ... AQ78: =SUMPRODUCT('TechHeat-RES'!AP5:AP14,'TechHeat-RES'!AP93:AP102,'TechHeat-RES'!AP137:AP146,'TechHeat-RES'!AP182:AP191) -> 1.5198885
G80: =G47*'All Stock'!D100 -> 23.521383 | H80: =H47*'All Stock'!E100 -> 31.955518 | I80: =I47*'All Stock'!F100 -> 2.8965089 | J80: =J47*'All Stock'!G100 -> 20.328845 | K80: =K47*'All Stock'!H100 -> 0.10990532 | L80: =L47*'All Stock'!I100 -> 20.586739 | M80: =M47*'All Stock'!J100 -> 173.10306 | N80: =N47*'All Stock'!K100 -> 28.021061 | ... AQ80: =AQ47*'All Stock'!AN100 -> 0.47826874
G81: =G50*'All Stock'!D101 -> 26.430332 | H81: =H50*'All Stock'!E101 -> 17.753065 | I81: =I50*'All Stock'!F101 -> 5.9962194 | J81: =J50*'All Stock'!G101 -> 22.842964 | K81: =K50*'All Stock'!H101 -> 0.34514732 | L81: =L50*'All Stock'!I101 -> 23.989491 | M81: =M50*'All Stock'!J101 -> 226.96618 | N81: =N50*'All Stock'!K101 -> 19.770962 | ... AQ81: =AQ50*'All Stock'!AN101 -> 1.0919401
E83: Det 1945-1969 | G83: =SUM(G80:G81) -> 49.951715 | H83: =SUM(H80:H81) -> 49.708583 | I83: =SUM(I80:I81) -> 8.8927284 | J83: =SUM(J80:J81) -> 43.171808 | K83: =SUM(K80:K81) -> 0.45505263 | L83: =SUM(L80:L81) -> 44.57623 | M83: =SUM(M80:M81) -> 400.06924 | N83: =SUM(N80:N81) -> 47.792022 | ... AQ83: =SUM(AQ80:AQ81) -> 1.5702089
E84: check | G84: =SUMPRODUCT('TechHeat-RES'!F15:F24,'TechHeat-RES'!F103:F112,'TechHeat-RES'!F147:F156,'TechHeat-RES'!F192:F201) -> 57.444472 | H84: =SUMPRODUCT('TechHeat-RES'!G15:G24,'TechHeat-RES'!G103:G112,'TechHeat-RES'!G147:G156,'TechHeat-RES'!G192:G201) -> 57.16487 | I84: =SUMPRODUCT('TechHeat-RES'!H15:H24,'TechHeat-RES'!H103:H112,'TechHeat-RES'!H147:H156,'TechHeat-RES'!H192:H201) -> 10.226638 | J84: =SUMPRODUCT('TechHeat-RES'!I15:I24,'TechHeat-RES'!I103:I112,'TechHeat-RES'!I147:I156,'TechHeat-RES'!I192:I201) -> 49.647579 | K84: =SUMPRODUCT('TechHeat-RES'!J15:J24,'TechHeat-RES'!J103:J112,'TechHeat-RES'!J147:J156,'TechHeat-RES'!J192:J201) -> 0.52331053 | L84: =SUMPRODUCT('TechHeat-RES'!K15:K24,'TechHeat-RES'!K103:K112,'TechHeat-RES'!K147:K156,'TechHeat-RES'!K192:K201) -> 51.262665 | M84: =SUMPRODUCT('TechHeat-RES'!L15:L24,'TechHeat-RES'!L103:L112,'TechHeat-RES'!L147:L156,'TechHeat-RES'!L192:L201) -> 460.07962 | N84: =SUMPRODUCT('TechHeat-RES'!M15:M24,'TechHeat-RES'!M103:M112,'TechHeat-RES'!M147:M156,'TechHeat-RES'!M192:M201) -> 54.960826 | ... AQ84: =SUMPRODUCT('TechHeat-RES'!AP15:AP24,'TechHeat-RES'!AP103:AP112,'TechHeat-RES'!AP147:AP156,'TechHeat-RES'!AP192:AP201) -> 1.8057402
G86: =G53*'All Stock'!D102 -> 10.921985 | H86: =H53*'All Stock'!E102 -> 9.6077413 | I86: =I53*'All Stock'!F102 -> 3.2983617 | J86: =J53*'All Stock'!G102 -> 9.4395528 | K86: =K53*'All Stock'!H102 -> 0.48803697 | L86: =L53*'All Stock'!I102 -> 9.8297596 | M86: =M53*'All Stock'!J102 -> 77.976473 | N86: =N53*'All Stock'!K102 -> 8.646037 | ... AQ86: =AQ53*'All Stock'!AN102 -> 0.8152505
G87: =G56*'All Stock'!D103 -> 6.0495311 | H87: =H56*'All Stock'!E103 -> 8.2089172 | I87: =I56*'All Stock'!F103 -> 2.7203452 | J87: =J56*'All Stock'!G103 -> 5.228433 | K87: =K56*'All Stock'!H103 -> 0.68617997 | L87: =L56*'All Stock'!I103 -> 10.306502 | M87: =M56*'All Stock'!J103 -> 44.040128 | N87: =N56*'All Stock'!K103 -> 3.0125285 | ... AQ87: =AQ56*'All Stock'!AN103 -> 0.6069682
G88: =G59*'All Stock'!D104 -> 6.18269 | H88: =H59*'All Stock'!E104 -> 6.0468573 | I88: =I59*'All Stock'!F104 -> 1.2836618 | J88: =J59*'All Stock'!G104 -> 5.3435184 | K88: =K59*'All Stock'!H104 -> 0.50720921 | L88: =L59*'All Stock'!I104 -> 4.1011613 | M88: =M59*'All Stock'!J104 -> 24.163145 | N88: =N59*'All Stock'!K104 -> 3.0149166 | ... AQ88: =AQ59*'All Stock'!AN104 -> 0.28444407
G89: =G62*'All Stock'!D105 -> 2.2479626 | H89: =H62*'All Stock'!E105 -> 2.43919 | I89: =I62*'All Stock'!F105 -> 1.390698 | J89: =J62*'All Stock'!G105 -> 1.9428484 | K89: =K62*'All Stock'!H105 -> 0.95960882 | L89: =L62*'All Stock'!I105 -> 2.4375515 | M89: =M62*'All Stock'!J105 -> 14.31446 | N89: =N62*'All Stock'!K105 -> 2.9113579 | ... AQ89: =AQ62*'All Stock'!AN105 -> 0.18504909
E91: Det 1970-2010 | G91: =SUM(G86:G89) -> 25.402169 | H91: =SUM(H86:H89) -> 26.302706 | I91: =SUM(I86:I89) -> 8.6930667 | J91: =SUM(J86:J89) -> 21.954353 | K91: =SUM(K86:K89) -> 2.641035 | L91: =SUM(L86:L89) -> 26.674975 | M91: =SUM(M86:M89) -> 160.49421 | N91: =SUM(N86:N89) -> 17.58484 | ... AQ91: =SUM(AQ86:AQ89) -> 1.8917119
E92: check | G92: =SUMPRODUCT('TechHeat-RES'!F25:F34,'TechHeat-RES'!F113:F122,'TechHeat-RES'!F157:F166,'TechHeat-RES'!F202:F211) -> 29.212494 | H92: =SUMPRODUCT('TechHeat-RES'!G25:G34,'TechHeat-RES'!G113:G122,'TechHeat-RES'!G157:G166,'TechHeat-RES'!G202:G211) -> 30.248112 | I92: =SUMPRODUCT('TechHeat-RES'!H25:H34,'TechHeat-RES'!H113:H122,'TechHeat-RES'!H157:H166,'TechHeat-RES'!H202:H211) -> 9.9970267 | J92: =SUMPRODUCT('TechHeat-RES'!I25:I34,'TechHeat-RES'!I113:I122,'TechHeat-RES'!I157:I166,'TechHeat-RES'!I202:I211) -> 25.247505 | K92: =SUMPRODUCT('TechHeat-RES'!J25:J34,'TechHeat-RES'!J113:J122,'TechHeat-RES'!J157:J166,'TechHeat-RES'!J202:J211) -> 3.0371902 | L92: =SUMPRODUCT('TechHeat-RES'!K25:K34,'TechHeat-RES'!K113:K122,'TechHeat-RES'!K157:K166,'TechHeat-RES'!K202:K211) -> 30.676221 | M92: =SUMPRODUCT('TechHeat-RES'!L25:L34,'TechHeat-RES'!L113:L122,'TechHeat-RES'!L157:L166,'TechHeat-RES'!L202:L211) -> 184.56834 | N92: =SUMPRODUCT('TechHeat-RES'!M25:M34,'TechHeat-RES'!M113:M122,'TechHeat-RES'!M157:M166,'TechHeat-RES'!M202:M211) -> 20.222566 | ... AQ92: =SUMPRODUCT('TechHeat-RES'!AP25:AP34,'TechHeat-RES'!AP113:AP122,'TechHeat-RES'!AP157:AP166,'TechHeat-RES'!AP202:AP211) -> 2.1754686
G94: =G48*'All Stock'!D106 -> 5.8005171 | H94: =H48*'All Stock'!E106 -> 29.545375 | I94: =I48*'All Stock'!F106 -> 0.83189981 | J94: =J48*'All Stock'!G106 -> 12.545539 | K94: =K48*'All Stock'!H106 -> 0.066533402 | L94: =L48*'All Stock'!I106 -> 6.6384043 | M94: =M48*'All Stock'!J106 -> 99.576539 | N94: =N48*'All Stock'!K106 -> 7.6651813 | ... AQ94: =AQ48*'All Stock'!AN106 -> 0.087913381
G95: =G51*'All Stock'!D107 -> 6.5771335 | H95: =H51*'All Stock'!E107 -> 16.414097 | I95: =I51*'All Stock'!F107 -> 1.7221607 | J95: =J51*'All Stock'!G107 -> 14.236084 | K95: =K51*'All Stock'!H107 -> 0.21067722 | L95: =L51*'All Stock'!I107 -> 7.397012 | M95: =M51*'All Stock'!J107 -> 134.53139 | N95: =N51*'All Stock'!K107 -> 5.3578636 | ... AQ95: =AQ51*'All Stock'!AN107 -> 0.20071592
G96: =G54*'All Stock'!D108 -> 2.6584495 | H96: =H54*'All Stock'!E108 -> 8.8831082 | I96: =I54*'All Stock'!F108 -> 0.94076664 | J96: =J54*'All Stock'!G108 -> 5.7478988 | K96: =K54*'All Stock'!H108 -> 0.28487526 | L96: =L54*'All Stock'!I108 -> 3.0309459 | M96: =M54*'All Stock'!J108 -> 43.402847 | N96: =N54*'All Stock'!K108 -> 2.2143192 | ... AQ96: =AQ54*'All Stock'!AN108 -> 0.14985597
G97: =G57*'All Stock'!D109 -> 1.4373045 | H97: =H57*'All Stock'!E109 -> 7.4801618 | I97: =I57*'All Stock'!F109 -> 0.76228967 | J97: =J57*'All Stock'!G109 -> 3.1040369 | K97: =K57*'All Stock'!H109 -> 0.39763396 | L97: =L57*'All Stock'!I109 -> 3.1116318 | M97: =M57*'All Stock'!J109 -> 23.232734 | N97: =N57*'All Stock'!K109 -> 0.75523786 | ... AQ97: =AQ57*'All Stock'!AN109 -> 0.10925414
G98: =G60*'All Stock'!D110 -> 1.4708771 | H98: =H60*'All Stock'!E110 -> 5.5100411 | I98: =I60*'All Stock'!F110 -> 0.34198485 | J98: =J60*'All Stock'!G110 -> 3.1774841 | K98: =K60*'All Stock'!H110 -> 0.31783126 | L98: =L60*'All Stock'!I110 -> 1.2153465 | M98: =M60*'All Stock'!J110 -> 12.741066 | N98: =N60*'All Stock'!K110 -> 0.75583654 | ... AQ98: =AQ60*'All Stock'!AN110 -> 0.050561063
G99: =G63*'All Stock'!D111 -> 0.52542607 | H99: =H63*'All Stock'!E111 -> 2.1682884 | I99: =I63*'All Stock'!F111 -> 0.36170188 | J99: =J63*'All Stock'!G111 -> 1.1339577 | K99: =K63*'All Stock'!H111 -> 0.56561595 | L99: =L63*'All Stock'!I111 -> 0.72204679 | M99: =M63*'All Stock'!J111 -> 7.5800765 | N99: =N63*'All Stock'!K111 -> 0.71733423 | ... AQ99: =AQ63*'All Stock'!AN111 -> 0.033070505
E101: Semidet | G101: =SUM(G94:G99) -> 18.469708 | H101: =SUM(H94:H99) -> 70.001072 | I101: =SUM(I94:I99) -> 4.9608036 | J101: =SUM(J94:J99) -> 39.945 | K101: =SUM(K94:K99) -> 1.843167 | L101: =SUM(L94:L99) -> 22.115387 | M101: =SUM(M94:M99) -> 321.06465 | N101: =SUM(N94:N99) -> 17.465773 | ... AQ101: =SUM(AQ94:AQ99) -> 0.63137098
E102: check | G102: =SUMPRODUCT('TechHeat-RES'!F35:F44,'TechHeat-RES'!F123:F132,'TechHeat-RES'!F167:F176,'TechHeat-RES'!F212:F221) -> 21.240164 | H102: =SUMPRODUCT('TechHeat-RES'!G35:G44,'TechHeat-RES'!G123:G132,'TechHeat-RES'!G167:G176,'TechHeat-RES'!G212:G221) -> 80.501233 | I102: =SUMPRODUCT('TechHeat-RES'!H35:H44,'TechHeat-RES'!H123:H132,'TechHeat-RES'!H167:H176,'TechHeat-RES'!H212:H221) -> 5.7049241 | J102: =SUMPRODUCT('TechHeat-RES'!I35:I44,'TechHeat-RES'!I123:I132,'TechHeat-RES'!I167:I176,'TechHeat-RES'!I212:I221) -> 45.936751 | K102: =SUMPRODUCT('TechHeat-RES'!J35:J44,'TechHeat-RES'!J123:J132,'TechHeat-RES'!J167:J176,'TechHeat-RES'!J212:J221) -> 2.1196421 | L102: =SUMPRODUCT('TechHeat-RES'!K35:K44,'TechHeat-RES'!K123:K132,'TechHeat-RES'!K167:K176,'TechHeat-RES'!K212:K221) -> 25.432695 | M102: =SUMPRODUCT('TechHeat-RES'!L35:L44,'TechHeat-RES'!L123:L132,'TechHeat-RES'!L167:L176,'TechHeat-RES'!L212:L221) -> 369.22435 | N102: =SUMPRODUCT('TechHeat-RES'!M35:M44,'TechHeat-RES'!M123:M132,'TechHeat-RES'!M167:M176,'TechHeat-RES'!M212:M221) -> 20.085639 | ... AQ102: =SUMPRODUCT('TechHeat-RES'!AP35:AP44,'TechHeat-RES'!AP123:AP132,'TechHeat-RES'!AP167:AP176,'TechHeat-RES'!AP212:AP221) -> 0.72607663
E105: Total | G105: =G77+G83+G91+G101 -> 119.08422 | H105: =H77+H83+H91+H101 -> 163.61014 | I105: =I77+I83+I91+I101 -> 28.440237 | J105: =J77+J83+J91+J101 -> 134.63755 | K105: =K77+K83+K91+K101 -> 5.5593174 | L105: =L77+L83+L91+L101 -> 128.46202 | M105: =M77+M83+M91+M101 -> 1182.6026 | N105: =N77+N83+N91+N101 -> 96.977981 | ... AQ105: =AQ77+AQ83+AQ91+AQ101 -> 5.4149339
G106: =G78+G84+G91+G102 -> 133.13652 | H106: =H78+H84+H91+H102 -> 184.20625 | I106: =I78+I84+I91+I102 -> 31.402313 | J106: =J78+J84+J91+J102 -> 151.54003 | K106: =K78+K84+K91+K102 -> 5.9970598 | L106: =L78+L84+L91+L102 -> 143.73007 | M106: =M78+M84+M91+M102 -> 1335.9189 | N106: =N78+N84+N91+N102 -> 108.88695 | ... AQ106: =AQ78+AQ84+AQ91+AQ102 -> 5.9434172
E107: IDEES average HDD | G107: ='IDEES okt 2017 template'!D110*'TechHeat-RES'!F307 -> 119.08422 | H107: ='IDEES okt 2017 template'!E110*'TechHeat-RES'!G307 -> 163.61014 | I107: ='IDEES okt 2017 template'!F110*'TechHeat-RES'!H307 -> 28.440237 | J107: ='IDEES okt 2017 template'!G110*'TechHeat-RES'!I307 -> 134.63755 | K107: ='IDEES okt 2017 template'!H110*'TechHeat-RES'!J307 -> 5.5593174 | L107: ='IDEES okt 2017 template'!I110*'TechHeat-RES'!K307 -> 128.46202 | M107: ='IDEES okt 2017 template'!J110*'TechHeat-RES'!L307 -> 1182.6026 | N107: ='IDEES okt 2017 template'!K110*'TechHeat-RES'!M307 -> 96.977981 | ... AQ107: ='IDEES okt 2017 template'!AN110*'TechHeat-RES'!AP307 -> 5.4149339
C109: Average HDD and heated buildings | F109: PJ/000dwellings | G109: =G105/G65 -> 0.040315658 | H109: =H105/H65 -> 0.047539021 | I109: =I105/I65 -> 0.016443599 | J109: =J105/J65 -> 0.039208035 | K109: =K105/K65 -> 0.018686702 | L109: =L105/L65 -> 0.033419968 | M109: =M105/M65 -> 0.034451797 | N109: =N105/N65 -> 0.037370189 | ... AQ109: =AQ105/AQ65 -> 0.016022324
G121: =G45 -> AT | H121: =H45 -> BE | I121: =I45 -> BG | J121: =J45 -> CH | K121: =K45 -> CY | L121: =L45 -> CZ | M121: =M45 -> DE | N121: =N45 -> DK | ... AQ121: =AQ45 -> KS
A122: 1 | B122: flat | C122: < 1945 | D122: Rdw_Flat | F122: =VLOOKUP(C122,TechComm!$U$2:$V$7,2,FALSE) -> 1940 | G122: =OFFSET($N$3,MATCH(G$121,$A$4:$A$40,0),$A122) -> 426.88055 | H122: =OFFSET($N$3,MATCH(H$121,$A$4:$A$40,0),$A122) -> 470.89407 | I122: =OFFSET($N$3,MATCH(I$121,$A$4:$A$40,0),$A122) -> 195.86716 | J122: =OFFSET($N$3,MATCH(J$121,$A$4:$A$40,0),$A122) -> 447.84191 | K122: =OFFSET($N$3,MATCH(K$121,$A$4:$A$40,0),$A122) -> 2.5426748 | L122: =OFFSET($N$3,MATCH(L$121,$A$4:$A$40,0),$A122) -> 553.47062 | M122: =OFFSET($N$3,MATCH(M$121,$A$4:$A$40,0),$A122) -> 4572.4328 | N122: =OFFSET($N$3,MATCH(N$121,$A$4:$A$40,0),$A122) -> 394.10243 | ... AQ122: =OFFSET($N$3,MATCH(AQ$121,$A$4:$A$40,0),$A122) -> 44.53781
A123: 2 | B123: detached | C123: < 1945 | D123: Rdw_DetH | F123: =VLOOKUP(C123,TechComm!$U$2:$V$7,2,FALSE) -> 1940 | G123: =OFFSET($N$3,MATCH(G$121,$A$4:$A$40,0),$A123) -> 295.16062 | H123: =OFFSET($N$3,MATCH(H$121,$A$4:$A$40,0),$A123) -> 494.22455 | I123: =OFFSET($N$3,MATCH(I$121,$A$4:$A$40,0),$A123) -> 155.4937 | J123: =OFFSET($N$3,MATCH(J$121,$A$4:$A$40,0),$A123) -> 228.65064 | K123: =OFFSET($N$3,MATCH(K$121,$A$4:$A$40,0),$A123) -> 3.2215918 | L123: =OFFSET($N$3,MATCH(L$121,$A$4:$A$40,0),$A123) -> 257.44503 | M123: =OFFSET($N$3,MATCH(M$121,$A$4:$A$40,0),$A123) -> 1910.6638 | N123: =OFFSET($N$3,MATCH(N$121,$A$4:$A$40,0),$A123) -> 368.50018 | ... AQ123: =OFFSET($N$3,MATCH(AQ$121,$A$4:$A$40,0),$A123) -> 36.64045
A124: 3 | B124: semidetached | C124: < 1945 | D124: Rdw_SDetH | F124: =VLOOKUP(C124,TechComm!$U$2:$V$7,2,FALSE) -> 1940 | G124: =OFFSET($N$3,MATCH(G$121,$A$4:$A$40,0),$A124) -> 136.78175 | H124: =OFFSET($N$3,MATCH(H$121,$A$4:$A$40,0),$A124) -> 824.59567 | I124: =OFFSET($N$3,MATCH(I$121,$A$4:$A$40,0),$A124) -> 84.507446 | J124: =OFFSET($N$3,MATCH(J$121,$A$4:$A$40,0),$A124) -> 256.51143 | K124: =OFFSET($N$3,MATCH(K$121,$A$4:$A$40,0),$A124) -> 3.2901364 | L124: =OFFSET($N$3,MATCH(L$121,$A$4:$A$40,0),$A124) -> 152.59846 | M124: =OFFSET($N$3,MATCH(M$121,$A$4:$A$40,0),$A124) -> 1997.5122 | N124: =OFFSET($N$3,MATCH(N$121,$A$4:$A$40,0),$A124) -> 196.18924 | ... AQ124: =OFFSET($N$3,MATCH(AQ$121,$A$4:$A$40,0),$A124) -> 13.112764
A125: 4 | B125: flat | C125: 1945-1969 | D125: =D122 -> Rdw_Flat | F125: =VLOOKUP(C125,TechComm!$U$2:$V$7,2,FALSE) -> 1957 | G125: =OFFSET($N$3,MATCH(G$121,$A$4:$A$40,0),$A125) -> 515.04262 | H125: =OFFSET($N$3,MATCH(H$121,$A$4:$A$40,0),$A125) -> 261.60781 | I125: =OFFSET($N$3,MATCH(I$121,$A$4:$A$40,0),$A125) -> 405.47518 | J125: =OFFSET($N$3,MATCH(J$121,$A$4:$A$40,0),$A125) -> 540.33305 | K125: =OFFSET($N$3,MATCH(K$121,$A$4:$A$40,0),$A125) -> 8.4717929 | L125: =OFFSET($N$3,MATCH(L$121,$A$4:$A$40,0),$A125) -> 751.69863 | M125: =OFFSET($N$3,MATCH(M$121,$A$4:$A$40,0),$A125) -> 6940.5184 | N125: =OFFSET($N$3,MATCH(N$121,$A$4:$A$40,0),$A125) -> 286.17472 | ... AQ125: =OFFSET($N$3,MATCH(AQ$121,$A$4:$A$40,0),$A125) -> 101.68472
...

Sheet All Stock
A1: Building type: | B1: Whole stock | D1: (weighted average) | G1: 1e-05 | H1: threshold
A2: Description | C2: Unit | D2: AT | E2: BE | F2: BG | G2: CH | H2: CY | I2: CZ | J2: DE | K2: DK | L2: EE | M2: ES | N2: FI | O2: FR | P2: EL | Q2: HR | R2: HU | S2: IE | T2: IS | U2: IT | V2: LT | W2: LU | X2: LV | Y2: MT | Z2: NL | AA2: NO | AB2: PL | AC2: PT | AD2: RO | AE2: SE | AF2: SI | AG2: SK | AH2: UK | AI2: AL | AJ2: BA | AK2: ME | AL2: MK | AM2: RS | AN2: KS
A3: Specific requirement (corrected) | B3: < 1945 | C3: kWh/m2-a | D3: =(Detached!D47*LOOKUP(Detached!D$2,'Data by dwelling type'!$A$4:$A$40,'Data by dwelling type'!$P$4:$P$40)+Semidetached!D48*LOOKUP(Semidetached!D$2,'Data by dwelling type'!$A$4:$A$40,'Data by dwelling type'!$Q$4:$Q$40)+Flat!D48*LOOKUP(Flat!D$2,'Data by dwelling type'!$A$4:$A$40,'Data by dwelling type'!$N$4:$N$40))/LOOKUP(Detached!D$2,'Data by dwelling type'!$A$4:$A$40,'Data by dwelling type'!$R$4:$R$40) -> 170.08726 | E3: =(Detached!E47*LOOKUP(Detached!E$2,'Data by dwelling type'!$A$4:$A$40,'Data by dwelling type'!$P$4:$P$40)+Semidetached!E48*LOOKUP(Semidetached!E$2,'Data by dwelling type'!$A$4:$A$40,'Data by dwelling type'!$Q$4:$Q$40)+Flat!E48*LOOKUP(Flat!E$2,'Data by dwelling type'!$A$4:$A$40,'Data by dwelling type'!$N$4:$N$40))/LOOKUP(Detached!E$2,'Data by dwelling type'!$A$4:$A$40,'Data by dwelling type'!$R$4:$R$40) -> 173.52807 | F3: =(Detached!F47*LOOKUP(Detached!F$2,'Data by dwelling type'!$A$4:$A$40,'Data by dwelling type'!$P$4:$P$40)+Semidetached!F48*LOOKUP(Semidetached!F$2,'Data by dwelling type'!$A$4:$A$40,'Data by dwelling type'!$Q$4:$Q$40)+Flat!F48*LOOKUP(Flat!F$2,'Data by dwelling type'!$A$4:$A$40,'Data by dwelling type'!$N$4:$N$40))/LOOKUP(Detached!F$2,'Data by dwelling type'!$A$4:$A$40,'Data by dwelling type'!$R$4:$R$40) -> 138.93462 | G3: =(Detached!G47*LOOKUP(Detached!G$2,'Data by dwelling type'!$A$4:$A$40,'Data by dwelling type'!$P$4:$P$40)+Semidetached!G48*LOOKUP(Semidetached!G$2,'Data by dwelling type'!$A$4:$A$40,'Data by dwelling type'!$Q$4:$Q$40)+Flat!G48*LOOKUP(Flat!G$2,'Data by dwelling type'!$A$4:$A$40,'Data by dwelling type'!$N$4:$N$40))/LOOKUP(Detached!G$2,'Data by dwelling type'!$A$4:$A$40,'Data by dwelling type'!$R$4:$R$40) -> 158.80187 | H3: =(Detached!H47*LOOKUP(Detached!H$2,'Data by dwelling type'!$A$4:$A$40,'Data by dwelling type'!$P$4:$P$40)+Semidetached!H48*LOOKUP(Semidetached!H$2,'Data by dwelling type'!$A$4:$A$40,'Data by dwelling type'!$Q$4:$Q$40)+Flat!H48*LOOKUP(Flat!H$2,'Data by dwelling type'!$A$4:$A$40,'Data by dwelling type'!$N$4:$N$40))/LOOKUP(Detached!H$2,'Data by dwelling type'!$A$4:$A$40,'Data by dwelling type'!$R$4:$R$40) -> 67.96053 | I3: =(Detached!I47*LOOKUP(Detached!I$2,'Data by dwelling type'!$A$4:$A$40,'Data by dwelling type'!$P$4:$P$40)+Semidetached!I48*LOOKUP(Semidetached!I$2,'Data by dwelling type'!$A$4:$A$40,'Data by dwelling type'!$Q$4:$Q$40)+Flat!I48*LOOKUP(Flat!I$2,'Data by dwelling type'!$A$4:$A$40,'Data by dwelling type'!$N$4:$N$40))/LOOKUP(Detached!I$2,'Data by dwelling type'!$A$4:$A$40,'Data by dwelling type'!$R$4:$R$40) -> 139.65981 | J3: =(Detached!J47*LOOKUP(Detached!J$2,'Data by dwelling type'!$A$4:$A$40,'Data by dwelling type'!$P$4:$P$40)+Semidetached!J48*LOOKUP(Semidetached!J$2,'Data by dwelling type'!$A$4:$A$40,'Data by dwelling type'!$Q$4:$Q$40)+Flat!J48*LOOKUP(Flat!J$2,'Data by dwelling type'!$A$4:$A$40,'Data by dwelling type'!$N$4:$N$40))/LOOKUP(Detached!J$2,'Data by dwelling type'!$A$4:$A$40,'Data by dwelling type'!$R$4:$R$40) -> 181.07983 | K3: =(Detached!K47*LOOKUP(Detached!K$2,'Data by dwelling type'!$A$4:$A$40,'Data by dwelling type'!$P$4:$P$40)+Semidetached!K48*LOOKUP(Semidetached!K$2,'Data by dwelling type'!$A$4:$A$40,'Data by dwelling type'!$Q$4:$Q$40)+Flat!K48*LOOKUP(Flat!K$2,'Data by dwelling type'!$A$4:$A$40,'Data by dwelling type'!$N$4:$N$40))/LOOKUP(Detached!K$2,'Data by dwelling type'!$A$4:$A$40,'Data by dwelling type'!$R$4:$R$40) -> 107.13055 | ... AN3: =(Detached!AN47*LOOKUP(Detached!AN$2,'Data by dwelling type'!$A$4:$A$40,'Data by dwelling type'!$P$4:$P$40)+Semidetached!AN48*LOOKUP(Semidetached!AN$2,'Data by dwelling type'!$A$4:$A$40,'Data by dwelling type'!$Q$4:$Q$40)+Flat!AN48*LOOKUP(Flat!AN$2,'Data by dwelling type'!$A$4:$A$40,'Data by dwelling type'!$N$4:$N$40))/LOOKUP(Detached!AN$2,'Data by dwelling type'!$A$4:$A$40,'Data by dwelling type'!$R$4:$R$40) -> 140.7288
B4: 1945-1969 | C4: kWh/m2-a | D4: =(Detached!D48*LOOKUP(Detached!D$2,'Data by dwelling type'!$A$4:$A$40,'Data by dwelling type'!$P$4:$P$40)+Semidetached!D49*LOOKUP(Semidetached!D$2,'Data by dwelling type'!$A$4:$A$40,'Data by dwelling type'!$Q$4:$Q$40)+Flat!D49*LOOKUP(Flat!D$2,'Data by dwelling type'!$A$4:$A$40,'Data by dwelling type'!$N$4:$N$40))/LOOKUP(Detached!D$2,'Data by dwelling type'!$A$4:$A$40,'Data by dwelling type'!$R$4:$R$40) -> 157.43673 | E4: =(Detached!E48*LOOKUP(Detached!E$2,'Data by dwelling type'!$A$4:$A$40,'Data by dwelling type'!$P$4:$P$40)+Semidetached!E49*LOOKUP(Semidetached!E$2,'Data by dwelling type'!$A$4:$A$40,'Data by dwelling type'!$Q$4:$Q$40)+Flat!E49*LOOKUP(Flat!E$2,'Data by dwelling type'!$A$4:$A$40,'Data by dwelling type'!$N$4:$N$40))/LOOKUP(Detached!E$2,'Data by dwelling type'!$A$4:$A$40,'Data by dwelling type'!$R$4:$R$40) -> 173.52807 | F4: =(Detached!F48*LOOKUP(Detached!F$2,'Data by dwelling type'!$A$4:$A$40,'Data by dwelling type'!$P$4:$P$40)+Semidetached!F49*LOOKUP(Semidetached!F$2,'Data by dwelling type'!$A$4:$A$40,'Data by dwelling type'!$Q$4:$Q$40)+Flat!F49*LOOKUP(Flat!F$2,'Data by dwelling type'!$A$4:$A$40,'Data by dwelling type'!$N$4:$N$40))/LOOKUP(Detached!F$2,'Data by dwelling type'!$A$4:$A$40,'Data by dwelling type'!$R$4:$R$40) -> 138.93462 | G4: =(Detached!G48*LOOKUP(Detached!G$2,'Data by dwelling type'!$A$4:$A$40,'Data by dwelling type'!$P$4:$P$40)+Semidetached!G49*LOOKUP(Semidetached!G$2,'Data by dwelling type'!$A$4:$A$40,'Data by dwelling type'!$Q$4:$Q$40)+Flat!G49*LOOKUP(Flat!G$2,'Data by dwelling type'!$A$4:$A$40,'Data by dwelling type'!$N$4:$N$40))/LOOKUP(Detached!G$2,'Data by dwelling type'!$A$4:$A$40,'Data by dwelling type'!$R$4:$R$40) -> 147.26182 | H4: =(Detached!H48*LOOKUP(Detached!H$2,'Data by dwelling type'!$A$4:$A$40,'Data by dwelling type'!$P$4:$P$40)+Semidetached!H49*LOOKUP(Semidetached!H$2,'Data by dwelling type'!$A$4:$A$40,'Data by dwelling type'!$Q$4:$Q$40)+Flat!H49*LOOKUP(Flat!H$2,'Data by dwelling type'!$A$4:$A$40,'Data by dwelling type'!$N$4:$N$40))/LOOKUP(Detached!H$2,'Data by dwelling type'!$A$4:$A$40,'Data by dwelling type'!$R$4:$R$40) -> 64.016051 | I4: =(Detached!I48*LOOKUP(Detached!I$2,'Data by dwelling type'!$A$4:$A$40,'Data by dwelling type'!$P$4:$P$40)+Semidetached!I49*LOOKUP(Semidetached!I$2,'Data by dwelling type'!$A$4:$A$40,'Data by dwelling type'!$Q$4:$Q$40)+Flat!I49*LOOKUP(Flat!I$2,'Data by dwelling type'!$A$4:$A$40,'Data by dwelling type'!$N$4:$N$40))/LOOKUP(Detached!I$2,'Data by dwelling type'!$A$4:$A$40,'Data by dwelling type'!$R$4:$R$40) -> 120.85609 | J4: =(Detached!J48*LOOKUP(Detached!J$2,'Data by dwelling type'!$A$4:$A$40,'Data by dwelling type'!$P$4:$P$40)+Semidetached!J49*LOOKUP(Semidetached!J$2,'Data by dwelling type'!$A$4:$A$40,'Data by dwelling type'!$Q$4:$Q$40)+Flat!J49*LOOKUP(Flat!J$2,'Data by dwelling type'!$A$4:$A$40,'Data by dwelling type'!$N$4:$N$40))/LOOKUP(Detached!J$2,'Data by dwelling type'!$A$4:$A$40,'Data by dwelling type'!$R$4:$R$40) -> 155.69379 | K4: =(Detached!K48*LOOKUP(Detached!K$2,'Data by dwelling type'!$A$4:$A$40,'Data by dwelling type'!$P$4:$P$40)+Semidetached!K49*LOOKUP(Semidetached!K$2,'Data by dwelling type'!$A$4:$A$40,'Data by dwelling type'!$Q$4:$Q$40)+Flat!K49*LOOKUP(Flat!K$2,'Data by dwelling type'!$A$4:$A$40,'Data by dwelling type'!$N$4:$N$40))/LOOKUP(Detached!K$2,'Data by dwelling type'!$A$4:$A$40,'Data by dwelling type'!$R$4:$R$40) -> 104.15176 | ... AN4: =(Detached!AN48*LOOKUP(Detached!AN$2,'Data by dwelling type'!$A$4:$A$40,'Data by dwelling type'!$P$4:$P$40)+Semidetached!AN49*LOOKUP(Semidetached!AN$2,'Data by dwelling type'!$A$4:$A$40,'Data by dwelling type'!$Q$4:$Q$40)+Flat!AN49*LOOKUP(Flat!AN$2,'Data by dwelling type'!$A$4:$A$40,'Data by dwelling type'!$N$4:$N$40))/LOOKUP(Detached!AN$2,'Data by dwelling type'!$A$4:$A$40,'Data by dwelling type'!$R$4:$R$40) -> 140.7288
B5: 1970-1979 | C5: kWh/m2-a | D5: =(Detached!D49*LOOKUP(Detached!D$2,'Data by dwelling type'!$A$4:$A$40,'Data by dwelling type'!$P$4:$P$40)+Semidetached!D50*LOOKUP(Semidetached!D$2,'Data by dwelling type'!$A$4:$A$40,'Data by dwelling type'!$Q$4:$Q$40)+Flat!D50*LOOKUP(Flat!D$2,'Data by dwelling type'!$A$4:$A$40,'Data by dwelling type'!$N$4:$N$40))/LOOKUP(Detached!D$2,'Data by dwelling type'!$A$4:$A$40,'Data by dwelling type'!$R$4:$R$40) -> 126.66239 | E5: =(Detached!E49*LOOKUP(Detached!E$2,'Data by dwelling type'!$A$4:$A$40,'Data by dwelling type'!$P$4:$P$40)+Semidetached!E50*LOOKUP(Semidetached!E$2,'Data by dwelling type'!$A$4:$A$40,'Data by dwelling type'!$Q$4:$Q$40)+Flat!E50*LOOKUP(Flat!E$2,'Data by dwelling type'!$A$4:$A$40,'Data by dwelling type'!$N$4:$N$40))/LOOKUP(Detached!E$2,'Data by dwelling type'!$A$4:$A$40,'Data by dwelling type'!$R$4:$R$40) -> 173.52807 | F5: =(Detached!F49*LOOKUP(Detached!F$2,'Data by dwelling type'!$A$4:$A$40,'Data by dwelling type'!$P$4:$P$40)+Semidetached!F50*LOOKUP(Semidetached!F$2,'Data by dwelling type'!$A$4:$A$40,'Data by dwelling type'!$Q$4:$Q$40)+Flat!F50*LOOKUP(Flat!F$2,'Data by dwelling type'!$A$4:$A$40,'Data by dwelling type'!$N$4:$N$40))/LOOKUP(Detached!F$2,'Data by dwelling type'!$A$4:$A$40,'Data by dwelling type'!$R$4:$R$40) -> 131.66292 | G5: =(Detached!G49*LOOKUP(Detached!G$2,'Data by dwelling type'!$A$4:$A$40,'Data by dwelling type'!$P$4:$P$40)+Semidetached!G50*LOOKUP(Semidetached!G$2,'Data by dwelling type'!$A$4:$A$40,'Data by dwelling type'!$Q$4:$Q$40)+Flat!G50*LOOKUP(Flat!G$2,'Data by dwelling type'!$A$4:$A$40,'Data by dwelling type'!$N$4:$N$40))/LOOKUP(Detached!G$2,'Data by dwelling type'!$A$4:$A$40,'Data by dwelling type'!$R$4:$R$40) -> 117.97338 | H5: =(Detached!H49*LOOKUP(Detached!H$2,'Data by dwelling type'!$A$4:$A$40,'Data by dwelling type'!$P$4:$P$40)+Semidetached!H50*LOOKUP(Semidetached!H$2,'Data by dwelling type'!$A$4:$A$40,'Data by dwelling type'!$Q$4:$Q$40)+Flat!H50*LOOKUP(Flat!H$2,'Data by dwelling type'!$A$4:$A$40,'Data by dwelling type'!$N$4:$N$40))/LOOKUP(Detached!H$2,'Data by dwelling type'!$A$4:$A$40,'Data by dwelling type'!$R$4:$R$40) -> 65.712763 | I5: =(Detached!I49*LOOKUP(Detached!I$2,'Data by dwelling type'!$A$4:$A$40,'Data by dwelling type'!$P$4:$P$40)+Semidetached!I50*LOOKUP(Semidetached!I$2,'Data by dwelling type'!$A$4:$A$40,'Data by dwelling type'!$Q$4:$Q$40)+Flat!I50*LOOKUP(Flat!I$2,'Data by dwelling type'!$A$4:$A$40,'Data by dwelling type'!$N$4:$N$40))/LOOKUP(Detached!I$2,'Data by dwelling type'!$A$4:$A$40,'Data by dwelling type'!$R$4:$R$40) -> 120.85609 | J5: =(Detached!J49*LOOKUP(Detached!J$2,'Data by dwelling type'!$A$4:$A$40,'Data by dwelling type'!$P$4:$P$40)+Semidetached!J50*LOOKUP(Semidetached!J$2,'Data by dwelling type'!$A$4:$A$40,'Data by dwelling type'!$Q$4:$Q$40)+Flat!J50*LOOKUP(Flat!J$2,'Data by dwelling type'!$A$4:$A$40,'Data by dwelling type'!$N$4:$N$40))/LOOKUP(Detached!J$2,'Data by dwelling type'!$A$4:$A$40,'Data by dwelling type'!$R$4:$R$40) -> 102.7835 | K5: =(Detached!K49*LOOKUP(Detached!K$2,'Data by dwelling type'!$A$4:$A$40,'Data by dwelling type'!$P$4:$P$40)+Semidetached!K50*LOOKUP(Semidetached!K$2,'Data by dwelling type'!$A$4:$A$40,'Data by dwelling type'!$Q$4:$Q$40)+Flat!K50*LOOKUP(Flat!K$2,'Data by dwelling type'!$A$4:$A$40,'Data by dwelling type'!$N$4:$N$40))/LOOKUP(Detached!K$2,'Data by dwelling type'!$A$4:$A$40,'Data by dwelling type'!$R$4:$R$40) -> 73.439704 | ... AN5: =(Detached!AN49*LOOKUP(Detached!AN$2,'Data by dwelling type'!$A$4:$A$40,'Data by dwelling type'!$P$4:$P$40)+Semidetached!AN50*LOOKUP(Semidetached!AN$2,'Data by dwelling type'!$A$4:$A$40,'Data by dwelling type'!$Q$4:$Q$40)+Flat!AN50*LOOKUP(Flat!AN$2,'Data by dwelling type'!$A$4:$A$40,'Data by dwelling type'!$N$4:$N$40))/LOOKUP(Detached!AN$2,'Data by dwelling type'!$A$4:$A$40,'Data by dwelling type'!$R$4:$R$40) -> 140.7288
B6: 1980-1989 | C6: kWh/m2-a | D6: =(Detached!D50*LOOKUP(Detached!D$2,'Data by dwelling type'!$A$4:$A$40,'Data by dwelling type'!$P$4:$P$40)+Semidetached!D51*LOOKUP(Semidetached!D$2,'Data by dwelling type'!$A$4:$A$40,'Data by dwelling type'!$Q$4:$Q$40)+Flat!D51*LOOKUP(Flat!D$2,'Data by dwelling type'!$A$4:$A$40,'Data by dwelling type'!$N$4:$N$40))/LOOKUP(Detached!D$2,'Data by dwelling type'!$A$4:$A$40,'Data by dwelling type'!$R$4:$R$40) -> 88.483018 | E6: =(Detached!E50*LOOKUP(Detached!E$2,'Data by dwelling type'!$A$4:$A$40,'Data by dwelling type'!$P$4:$P$40)+Semidetached!E51*LOOKUP(Semidetached!E$2,'Data by dwelling type'!$A$4:$A$40,'Data by dwelling type'!$Q$4:$Q$40)+Flat!E51*LOOKUP(Flat!E$2,'Data by dwelling type'!$A$4:$A$40,'Data by dwelling type'!$N$4:$N$40))/LOOKUP(Detached!E$2,'Data by dwelling type'!$A$4:$A$40,'Data by dwelling type'!$R$4:$R$40) -> 147.53298 | F6: =(Detached!F50*LOOKUP(Detached!F$2,'Data by dwelling type'!$A$4:$A$40,'Data by dwelling type'!$P$4:$P$40)+Semidetached!F51*LOOKUP(Semidetached!F$2,'Data by dwelling type'!$A$4:$A$40,'Data by dwelling type'!$Q$4:$Q$40)+Flat!F51*LOOKUP(Flat!F$2,'Data by dwelling type'!$A$4:$A$40,'Data by dwelling type'!$N$4:$N$40))/LOOKUP(Detached!F$2,'Data by dwelling type'!$A$4:$A$40,'Data by dwelling type'!$R$4:$R$40) -> 114.84747 | G6: =(Detached!G50*LOOKUP(Detached!G$2,'Data by dwelling type'!$A$4:$A$40,'Data by dwelling type'!$P$4:$P$40)+Semidetached!G51*LOOKUP(Semidetached!G$2,'Data by dwelling type'!$A$4:$A$40,'Data by dwelling type'!$Q$4:$Q$40)+Flat!G51*LOOKUP(Flat!G$2,'Data by dwelling type'!$A$4:$A$40,'Data by dwelling type'!$N$4:$N$40))/LOOKUP(Detached!G$2,'Data by dwelling type'!$A$4:$A$40,'Data by dwelling type'!$R$4:$R$40) -> 82.039972 | H6: =(Detached!H50*LOOKUP(Detached!H$2,'Data by dwelling type'!$A$4:$A$40,'Data by dwelling type'!$P$4:$P$40)+Semidetached!H51*LOOKUP(Semidetached!H$2,'Data by dwelling type'!$A$4:$A$40,'Data by dwelling type'!$Q$4:$Q$40)+Flat!H51*LOOKUP(Flat!H$2,'Data by dwelling type'!$A$4:$A$40,'Data by dwelling type'!$N$4:$N$40))/LOOKUP(Detached!H$2,'Data by dwelling type'!$A$4:$A$40,'Data by dwelling type'!$R$4:$R$40) -> 63.917093 | I6: =(Detached!I50*LOOKUP(Detached!I$2,'Data by dwelling type'!$A$4:$A$40,'Data by dwelling type'!$P$4:$P$40)+Semidetached!I51*LOOKUP(Semidetached!I$2,'Data by dwelling type'!$A$4:$A$40,'Data by dwelling type'!$Q$4:$Q$40)+Flat!I51*LOOKUP(Flat!I$2,'Data by dwelling type'!$A$4:$A$40,'Data by dwelling type'!$N$4:$N$40))/LOOKUP(Detached!I$2,'Data by dwelling type'!$A$4:$A$40,'Data by dwelling type'!$R$4:$R$40) -> 109.30646 | J6: =(Detached!J50*LOOKUP(Detached!J$2,'Data by dwelling type'!$A$4:$A$40,'Data by dwelling type'!$P$4:$P$40)+Semidetached!J51*LOOKUP(Semidetached!J$2,'Data by dwelling type'!$A$4:$A$40,'Data by dwelling type'!$Q$4:$Q$40)+Flat!J51*LOOKUP(Flat!J$2,'Data by dwelling type'!$A$4:$A$40,'Data by dwelling type'!$N$4:$N$40))/LOOKUP(Detached!J$2,'Data by dwelling type'!$A$4:$A$40,'Data by dwelling type'!$R$4:$R$40) -> 83.487784 | K6: =(Detached!K50*LOOKUP(Detached!K$2,'Data by dwelling type'!$A$4:$A$40,'Data by dwelling type'!$P$4:$P$40)+Semidetached!K51*LOOKUP(Semidetached!K$2,'Data by dwelling type'!$A$4:$A$40,'Data by dwelling type'!$Q$4:$Q$40)+Flat!K51*LOOKUP(Flat!K$2,'Data by dwelling type'!$A$4:$A$40,'Data by dwelling type'!$N$4:$N$40))/LOOKUP(Detached!K$2,'Data by dwelling type'!$A$4:$A$40,'Data by dwelling type'!$R$4:$R$40) -> 62.296717 | ... AN6: =(Detached!AN50*LOOKUP(Detached!AN$2,'Data by dwelling type'!$A$4:$A$40,'Data by dwelling type'!$P$4:$P$40)+Semidetached!AN51*LOOKUP(Semidetached!AN$2,'Data by dwelling type'!$A$4:$A$40,'Data by dwelling type'!$Q$4:$Q$40)+Flat!AN51*LOOKUP(Flat!AN$2,'Data by dwelling type'!$A$4:$A$40,'Data by dwelling type'!$N$4:$N$40))/LOOKUP(Detached!AN$2,'Data by dwelling type'!$A$4:$A$40,'Data by dwelling type'!$R$4:$R$40) -> 123.61793
B7: 1990-1999 | C7: kWh/m2-a | D7: =(Detached!D51*LOOKUP(Detached!D$2,'Data by dwelling type'!$A$4:$A$40,'Data by dwelling type'!$P$4:$P$40)+Semidetached!D52*LOOKUP(Semidetached!D$2,'Data by dwelling type'!$A$4:$A$40,'Data by dwelling type'!$Q$4:$Q$40)+Flat!D52*LOOKUP(Flat!D$2,'Data by dwelling type'!$A$4:$A$40,'Data by dwelling type'!$N$4:$N$40))/LOOKUP(Detached!D$2,'Data by dwelling type'!$A$4:$A$40,'Data by dwelling type'!$R$4:$R$40) -> 75.479208 | E7: =(Detached!E51*LOOKUP(Detached!E$2,'Data by dwelling type'!$A$4:$A$40,'Data by dwelling type'!$P$4:$P$40)+Semidetached!E52*LOOKUP(Semidetached!E$2,'Data by dwelling type'!$A$4:$A$40,'Data by dwelling type'!$Q$4:$Q$40)+Flat!E52*LOOKUP(Flat!E$2,'Data by dwelling type'!$A$4:$A$40,'Data by dwelling type'!$N$4:$N$40))/LOOKUP(Detached!E$2,'Data by dwelling type'!$A$4:$A$40,'Data by dwelling type'!$R$4:$R$40) -> 147.53298 | F7: =(Detached!F51*LOOKUP(Detached!F$2,'Data by dwelling type'!$A$4:$A$40,'Data by dwelling type'!$P$4:$P$40)+Semidetached!F52*LOOKUP(Semidetached!F$2,'Data by dwelling type'!$A$4:$A$40,'Data by dwelling type'!$Q$4:$Q$40)+Flat!F52*LOOKUP(Flat!F$2,'Data by dwelling type'!$A$4:$A$40,'Data by dwelling type'!$N$4:$N$40))/LOOKUP(Detached!F$2,'Data by dwelling type'!$A$4:$A$40,'Data by dwelling type'!$R$4:$R$40) -> 93.323048 | G7: =(Detached!G51*LOOKUP(Detached!G$2,'Data by dwelling type'!$A$4:$A$40,'Data by dwelling type'!$P$4:$P$40)+Semidetached!G52*LOOKUP(Semidetached!G$2,'Data by dwelling type'!$A$4:$A$40,'Data by dwelling type'!$Q$4:$Q$40)+Flat!G52*LOOKUP(Flat!G$2,'Data by dwelling type'!$A$4:$A$40,'Data by dwelling type'!$N$4:$N$40))/LOOKUP(Detached!G$2,'Data by dwelling type'!$A$4:$A$40,'Data by dwelling type'!$R$4:$R$40) -> 70.002916 | H7: =(Detached!H51*LOOKUP(Detached!H$2,'Data by dwelling type'!$A$4:$A$40,'Data by dwelling type'!$P$4:$P$40)+Semidetached!H52*LOOKUP(Semidetached!H$2,'Data by dwelling type'!$A$4:$A$40,'Data by dwelling type'!$Q$4:$Q$40)+Flat!H52*LOOKUP(Flat!H$2,'Data by dwelling type'!$A$4:$A$40,'Data by dwelling type'!$N$4:$N$40))/LOOKUP(Detached!H$2,'Data by dwelling type'!$A$4:$A$40,'Data by dwelling type'!$R$4:$R$40) -> 56.139535 | I7: =(Detached!I51*LOOKUP(Detached!I$2,'Data by dwelling type'!$A$4:$A$40,'Data by dwelling type'!$P$4:$P$40)+Semidetached!I52*LOOKUP(Semidetached!I$2,'Data by dwelling type'!$A$4:$A$40,'Data by dwelling type'!$Q$4:$Q$40)+Flat!I52*LOOKUP(Flat!I$2,'Data by dwelling type'!$A$4:$A$40,'Data by dwelling type'!$N$4:$N$40))/LOOKUP(Detached!I$2,'Data by dwelling type'!$A$4:$A$40,'Data by dwelling type'!$R$4:$R$40) -> 83.723791 | J7: =(Detached!J51*LOOKUP(Detached!J$2,'Data by dwelling type'!$A$4:$A$40,'Data by dwelling type'!$P$4:$P$40)+Semidetached!J52*LOOKUP(Semidetached!J$2,'Data by dwelling type'!$A$4:$A$40,'Data by dwelling type'!$Q$4:$Q$40)+Flat!J52*LOOKUP(Flat!J$2,'Data by dwelling type'!$A$4:$A$40,'Data by dwelling type'!$N$4:$N$40))/LOOKUP(Detached!J$2,'Data by dwelling type'!$A$4:$A$40,'Data by dwelling type'!$R$4:$R$40) -> 49.173254 | K7: =(Detached!K51*LOOKUP(Detached!K$2,'Data by dwelling type'!$A$4:$A$40,'Data by dwelling type'!$P$4:$P$40)+Semidetached!K52*LOOKUP(Semidetached!K$2,'Data by dwelling type'!$A$4:$A$40,'Data by dwelling type'!$Q$4:$Q$40)+Flat!K52*LOOKUP(Flat!K$2,'Data by dwelling type'!$A$4:$A$40,'Data by dwelling type'!$N$4:$N$40))/LOOKUP(Detached!K$2,'Data by dwelling type'!$A$4:$A$40,'Data by dwelling type'!$R$4:$R$40) -> 62.296717 | ... AN7: =(Detached!AN51*LOOKUP(Detached!AN$2,'Data by dwelling type'!$A$4:$A$40,'Data by dwelling type'!$P$4:$P$40)+Semidetached!AN52*LOOKUP(Semidetached!AN$2,'Data by dwelling type'!$A$4:$A$40,'Data by dwelling type'!$Q$4:$Q$40)+Flat!AN52*LOOKUP(Flat!AN$2,'Data by dwelling type'!$A$4:$A$40,'Data by dwelling type'!$N$4:$N$40))/LOOKUP(Detached!AN$2,'Data by dwelling type'!$A$4:$A$40,'Data by dwelling type'!$R$4:$R$40) -> 117.91771
B8: 2000-2008 | C8: kWh/m2-a | D8: =(Detached!D52*LOOKUP(Detached!D$2,'Data by dwelling type'!$A$4:$A$40,'Data by dwelling type'!$P$4:$P$40)+Semidetached!D53*LOOKUP(Semidetached!D$2,'Data by dwelling type'!$A$4:$A$40,'Data by dwelling type'!$Q$4:$Q$40)+Flat!D53*LOOKUP(Flat!D$2,'Data by dwelling type'!$A$4:$A$40,'Data by dwelling type'!$N$4:$N$40))/LOOKUP(Detached!D$2,'Data by dwelling type'!$A$4:$A$40,'Data by dwelling type'!$R$4:$R$40) -> 67.273814 | E8: =(Detached!E52*LOOKUP(Detached!E$2,'Data by dwelling type'!$A$4:$A$40,'Data by dwelling type'!$P$4:$P$40)+Semidetached!E53*LOOKUP(Semidetached!E$2,'Data by dwelling type'!$A$4:$A$40,'Data by dwelling type'!$Q$4:$Q$40)+Flat!E53*LOOKUP(Flat!E$2,'Data by dwelling type'!$A$4:$A$40,'Data by dwelling type'!$N$4:$N$40))/LOOKUP(Detached!E$2,'Data by dwelling type'!$A$4:$A$40,'Data by dwelling type'!$R$4:$R$40) -> 87.600868 | F8: =(Detached!F52*LOOKUP(Detached!F$2,'Data by dwelling type'!$A$4:$A$40,'Data by dwelling type'!$P$4:$P$40)+Semidetached!F53*LOOKUP(Semidetached!F$2,'Data by dwelling type'!$A$4:$A$40,'Data by dwelling type'!$Q$4:$Q$40)+Flat!F53*LOOKUP(Flat!F$2,'Data by dwelling type'!$A$4:$A$40,'Data by dwelling type'!$N$4:$N$40))/LOOKUP(Detached!F$2,'Data by dwelling type'!$A$4:$A$40,'Data by dwelling type'!$R$4:$R$40) -> 64.346529 | G8: =(Detached!G52*LOOKUP(Detached!G$2,'Data by dwelling type'!$A$4:$A$40,'Data by dwelling type'!$P$4:$P$40)+Semidetached!G53*LOOKUP(Semidetached!G$2,'Data by dwelling type'!$A$4:$A$40,'Data by dwelling type'!$Q$4:$Q$40)+Flat!G53*LOOKUP(Flat!G$2,'Data by dwelling type'!$A$4:$A$40,'Data by dwelling type'!$N$4:$N$40))/LOOKUP(Detached!G$2,'Data by dwelling type'!$A$4:$A$40,'Data by dwelling type'!$R$4:$R$40) -> 62.18812 | H8: =(Detached!H52*LOOKUP(Detached!H$2,'Data by dwelling type'!$A$4:$A$40,'Data by dwelling type'!$P$4:$P$40)+Semidetached!H53*LOOKUP(Semidetached!H$2,'Data by dwelling type'!$A$4:$A$40,'Data by dwelling type'!$Q$4:$Q$40)+Flat!H53*LOOKUP(Flat!H$2,'Data by dwelling type'!$A$4:$A$40,'Data by dwelling type'!$N$4:$N$40))/LOOKUP(Detached!H$2,'Data by dwelling type'!$A$4:$A$40,'Data by dwelling type'!$R$4:$R$40) -> 48.779495 | I8: =(Detached!I52*LOOKUP(Detached!I$2,'Data by dwelling type'!$A$4:$A$40,'Data by dwelling type'!$P$4:$P$40)+Semidetached!I53*LOOKUP(Semidetached!I$2,'Data by dwelling type'!$A$4:$A$40,'Data by dwelling type'!$Q$4:$Q$40)+Flat!I53*LOOKUP(Flat!I$2,'Data by dwelling type'!$A$4:$A$40,'Data by dwelling type'!$N$4:$N$40))/LOOKUP(Detached!I$2,'Data by dwelling type'!$A$4:$A$40,'Data by dwelling type'!$R$4:$R$40) -> 66.274845 | J8: =(Detached!J52*LOOKUP(Detached!J$2,'Data by dwelling type'!$A$4:$A$40,'Data by dwelling type'!$P$4:$P$40)+Semidetached!J53*LOOKUP(Semidetached!J$2,'Data by dwelling type'!$A$4:$A$40,'Data by dwelling type'!$Q$4:$Q$40)+Flat!J53*LOOKUP(Flat!J$2,'Data by dwelling type'!$A$4:$A$40,'Data by dwelling type'!$N$4:$N$40))/LOOKUP(Detached!J$2,'Data by dwelling type'!$A$4:$A$40,'Data by dwelling type'!$R$4:$R$40) -> 53.332871 | K8: =(Detached!K52*LOOKUP(Detached!K$2,'Data by dwelling type'!$A$4:$A$40,'Data by dwelling type'!$P$4:$P$40)+Semidetached!K53*LOOKUP(Semidetached!K$2,'Data by dwelling type'!$A$4:$A$40,'Data by dwelling type'!$Q$4:$Q$40)+Flat!K53*LOOKUP(Flat!K$2,'Data by dwelling type'!$A$4:$A$40,'Data by dwelling type'!$N$4:$N$40))/LOOKUP(Detached!K$2,'Data by dwelling type'!$A$4:$A$40,'Data by dwelling type'!$R$4:$R$40) -> 45.480402 | ... AN8: =(Detached!AN52*LOOKUP(Detached!AN$2,'Data by dwelling type'!$A$4:$A$40,'Data by dwelling type'!$P$4:$P$40)+Semidetached!AN53*LOOKUP(Semidetached!AN$2,'Data by dwelling type'!$A$4:$A$40,'Data by dwelling type'!$Q$4:$Q$40)+Flat!AN53*LOOKUP(Flat!AN$2,'Data by dwelling type'!$A$4:$A$40,'Data by dwelling type'!$N$4:$N$40))/LOOKUP(Detached!AN$2,'Data by dwelling type'!$A$4:$A$40,'Data by dwelling type'!$R$4:$R$40) -> 101.9722
B9: Whole Stock | C9: kWh/m2-a | D9: =(Detached!D53*LOOKUP(Detached!D$2,'Data by dwelling type'!$A$4:$A$40,'Data by dwelling type'!$P$4:$P$40)+Semidetached!D54*LOOKUP(Semidetached!D$2,'Data by dwelling type'!$A$4:$A$40,'Data by dwelling type'!$Q$4:$Q$40)+Flat!D54*LOOKUP(Flat!D$2,'Data by dwelling type'!$A$4:$A$40,'Data by dwelling type'!$N$4:$N$40))/LOOKUP(Detached!D$2,'Data by dwelling type'!$A$4:$A$40,'Data by dwelling type'!$R$4:$R$40) -> 130.85359 | E9: =(Detached!E53*LOOKUP(Detached!E$2,'Data by dwelling type'!$A$4:$A$40,'Data by dwelling type'!$P$4:$P$40)+Semidetached!E54*LOOKUP(Semidetached!E$2,'Data by dwelling type'!$A$4:$A$40,'Data by dwelling type'!$Q$4:$Q$40)+Flat!E54*LOOKUP(Flat!E$2,'Data by dwelling type'!$A$4:$A$40,'Data by dwelling type'!$N$4:$N$40))/LOOKUP(Detached!E$2,'Data by dwelling type'!$A$4:$A$40,'Data by dwelling type'!$R$4:$R$40) -> 163.09566 | F9: =(Detached!F53*LOOKUP(Detached!F$2,'Data by dwelling type'!$A$4:$A$40,'Data by dwelling type'!$P$4:$P$40)+Semidetached!F54*LOOKUP(Semidetached!F$2,'Data by dwelling type'!$A$4:$A$40,'Data by dwelling type'!$Q$4:$Q$40)+Flat!F54*LOOKUP(Flat!F$2,'Data by dwelling type'!$A$4:$A$40,'Data by dwelling type'!$N$4:$N$40))/LOOKUP(Detached!F$2,'Data by dwelling type'!$A$4:$A$40,'Data by dwelling type'!$R$4:$R$40) -> 118.91349 | G9: =(Detached!G53*LOOKUP(Detached!G$2,'Data by dwelling type'!$A$4:$A$40,'Data by dwelling type'!$P$4:$P$40)+Semidetached!G54*LOOKUP(Semidetached!G$2,'Data by dwelling type'!$A$4:$A$40,'Data by dwelling type'!$Q$4:$Q$40)+Flat!G54*LOOKUP(Flat!G$2,'Data by dwelling type'!$A$4:$A$40,'Data by dwelling type'!$N$4:$N$40))/LOOKUP(Detached!G$2,'Data by dwelling type'!$A$4:$A$40,'Data by dwelling type'!$R$4:$R$40) -> 122.03726 | H9: =(Detached!H53*LOOKUP(Detached!H$2,'Data by dwelling type'!$A$4:$A$40,'Data by dwelling type'!$P$4:$P$40)+Semidetached!H54*LOOKUP(Semidetached!H$2,'Data by dwelling type'!$A$4:$A$40,'Data by dwelling type'!$Q$4:$Q$40)+Flat!H54*LOOKUP(Flat!H$2,'Data by dwelling type'!$A$4:$A$40,'Data by dwelling type'!$N$4:$N$40))/LOOKUP(Detached!H$2,'Data by dwelling type'!$A$4:$A$40,'Data by dwelling type'!$R$4:$R$40) -> 57.442093 | I9: =(Detached!I53*LOOKUP(Detached!I$2,'Data by dwelling type'!$A$4:$A$40,'Data by dwelling type'!$P$4:$P$40)+Semidetached!I54*LOOKUP(Semidetached!I$2,'Data by dwelling type'!$A$4:$A$40,'Data by dwelling type'!$Q$4:$Q$40)+Flat!I54*LOOKUP(Flat!I$2,'Data by dwelling type'!$A$4:$A$40,'Data by dwelling type'!$N$4:$N$40))/LOOKUP(Detached!I$2,'Data by dwelling type'!$A$4:$A$40,'Data by dwelling type'!$R$4:$R$40) -> 117.29956 | J9: =(Detached!J53*LOOKUP(Detached!J$2,'Data by dwelling type'!$A$4:$A$40,'Data by dwelling type'!$P$4:$P$40)+Semidetached!J54*LOOKUP(Semidetached!J$2,'Data by dwelling type'!$A$4:$A$40,'Data by dwelling type'!$Q$4:$Q$40)+Flat!J54*LOOKUP(Flat!J$2,'Data by dwelling type'!$A$4:$A$40,'Data by dwelling type'!$N$4:$N$40))/LOOKUP(Detached!J$2,'Data by dwelling type'!$A$4:$A$40,'Data by dwelling type'!$R$4:$R$40) -> 126.04139 | K9: =(Detached!K53*LOOKUP(Detached!K$2,'Data by dwelling type'!$A$4:$A$40,'Data by dwelling type'!$P$4:$P$40)+Semidetached!K54*LOOKUP(Semidetached!K$2,'Data by dwelling type'!$A$4:$A$40,'Data by dwelling type'!$Q$4:$Q$40)+Flat!K54*LOOKUP(Flat!K$2,'Data by dwelling type'!$A$4:$A$40,'Data by dwelling type'!$N$4:$N$40))/LOOKUP(Detached!K$2,'Data by dwelling type'!$A$4:$A$40,'Data by dwelling type'!$R$4:$R$40) -> 89.629638 | ... AN9: =(Detached!AN53*LOOKUP(Detached!AN$2,'Data by dwelling type'!$A$4:$A$40,'Data by dwelling type'!$P$4:$P$40)+Semidetached!AN54*LOOKUP(Semidetached!AN$2,'Data by dwelling type'!$A$4:$A$40,'Data by dwelling type'!$Q$4:$Q$40)+Flat!AN54*LOOKUP(Flat!AN$2,'Data by dwelling type'!$A$4:$A$40,'Data by dwelling type'!$N$4:$N$40))/LOOKUP(Detached!AN$2,'Data by dwelling type'!$A$4:$A$40,'Data by dwelling type'!$R$4:$R$40) -> 132.72992
B11: 000dwellings | C11: TOT Building stock | D11: =LOOKUP(D2,'Dwelling stock'!$A$4:$A$40,'Dwelling stock'!$K$4:$K$40) -> 3562.4891 | E11: =LOOKUP(E2,'Dwelling stock'!$A$4:$A$40,'Dwelling stock'!$K$4:$K$40) -> 4523 | F11: =LOOKUP(F2,'Dwelling stock'!$A$4:$A$40,'Dwelling stock'!$K$4:$K$40) -> 3082 | G11: =LOOKUP(G2,'Dwelling stock'!$A$4:$A$40,'Dwelling stock'!$K$4:$K$40) -> 3870.2 | H11: =LOOKUP(H2,'Dwelling stock'!$A$4:$A$40,'Dwelling stock'!$K$4:$K$40) -> 299.157 | I11: =LOOKUP(I2,'Dwelling stock'!$A$4:$A$40,'Dwelling stock'!$K$4:$K$40) -> 3993 | J11: =LOOKUP(J2,'Dwelling stock'!$A$4:$A$40,'Dwelling stock'!$K$4:$K$40) -> 39210.072 | K11: =LOOKUP(K2,'Dwelling stock'!$A$4:$A$40,'Dwelling stock'!$K$4:$K$40) -> 2670.6901 | ... AN11: =LOOKUP(AN2,'Dwelling stock'!$A$4:$A$40,'Dwelling stock'!$K$4:$K$40) -> 722.7143
A12: detached | B12: 000dwellings | C12: Det | D12: =SUMIF('Dwelling stock'!$B$46:$B$63,"="&'All Stock'!$A12,'Dwelling stock'!G$46:G$63) -> 1015.1617 | E12: =SUMIF('Dwelling stock'!$B$46:$B$63,"="&'All Stock'!$A12,'Dwelling stock'!H$46:H$63) -> 950.38722 | F12: =SUMIF('Dwelling stock'!$B$46:$B$63,"="&'All Stock'!$A12,'Dwelling stock'!I$46:I$63) -> 617.01235 | G12: =SUMIF('Dwelling stock'!$B$46:$B$63,"="&'All Stock'!$A12,'Dwelling stock'!J$46:J$63) -> 841.55024 | H12: =SUMIF('Dwelling stock'!$B$46:$B$63,"="&'All Stock'!$A12,'Dwelling stock'!K$46:K$63) -> 105.85211 | I12: =SUMIF('Dwelling stock'!$B$46:$B$63,"="&'All Stock'!$A12,'Dwelling stock'!L$46:L$63) -> 1027.0584 | J12: =SUMIF('Dwelling stock'!$B$46:$B$63,"="&'All Stock'!$A12,'Dwelling stock'!M$46:M$63) -> 7733.6446 | K12: =SUMIF('Dwelling stock'!$B$46:$B$63,"="&'All Stock'!$A12,'Dwelling stock'!N$46:N$63) -> 997.38129 | ... AN12: =SUMIF('Dwelling stock'!$B$46:$B$63,"="&'All Stock'!$A12,'Dwelling stock'!AQ$46:AQ$63) -> 131.32823
A13: detached 1945-1969 | B13: 000dwellings | C13: HEATED ONLY | D13: =SUMIF('Dwelling stock'!$B$46:$B$51,"="&'All Stock'!$A12,'Dwelling stock'!G$46:G$51) -> 540.00084 | E13: =SUMIF('Dwelling stock'!$B$46:$B$51,"="&'All Stock'!$A12,'Dwelling stock'!H$46:H$51) -> 584.98298 | F13: =SUMIF('Dwelling stock'!$B$46:$B$51,"="&'All Stock'!$A12,'Dwelling stock'!I$46:I$51) -> 267.90244 | G13: =SUMIF('Dwelling stock'!$B$46:$B$51,"="&'All Stock'!$A12,'Dwelling stock'!J$46:J$51) -> 447.65068 | H13: =SUMIF('Dwelling stock'!$B$46:$B$51,"="&'All Stock'!$A12,'Dwelling stock'!K$46:K$51) -> 13.878191 | I13: =SUMIF('Dwelling stock'!$B$46:$B$51,"="&'All Stock'!$A12,'Dwelling stock'!L$46:L$51) -> 584.42148 | J13: =SUMIF('Dwelling stock'!$B$46:$B$51,"="&'All Stock'!$A12,'Dwelling stock'!M$46:M$51) -> 4211.6564 | K13: =SUMIF('Dwelling stock'!$B$46:$B$51,"="&'All Stock'!$A12,'Dwelling stock'!N$46:N$51) -> 618.07165 | ... AN13: =SUMIF('Dwelling stock'!$B$46:$B$51,"="&'All Stock'!$A12,'Dwelling stock'!AQ$46:AQ$51) -> 56.253201
A14: detached 1970-2010 | B14: 000dwellings | C14: HEATED ONLY | D14: =SUMIF('Dwelling stock'!$B$52:$B$63,"="&'All Stock'!$A12,'Dwelling stock'!G$52:G$63) -> 475.1609 | E14: =SUMIF('Dwelling stock'!$B$52:$B$63,"="&'All Stock'!$A12,'Dwelling stock'!H$52:H$63) -> 365.40424 | F14: =SUMIF('Dwelling stock'!$B$52:$B$63,"="&'All Stock'!$A12,'Dwelling stock'!I$52:I$63) -> 349.10991 | G14: =SUMIF('Dwelling stock'!$B$52:$B$63,"="&'All Stock'!$A12,'Dwelling stock'!J$52:J$63) -> 393.89956 | H14: =SUMIF('Dwelling stock'!$B$52:$B$63,"="&'All Stock'!$A12,'Dwelling stock'!K$52:K$63) -> 91.973916 | I14: =SUMIF('Dwelling stock'!$B$52:$B$63,"="&'All Stock'!$A12,'Dwelling stock'!L$52:L$63) -> 442.63692 | J14: =SUMIF('Dwelling stock'!$B$52:$B$63,"="&'All Stock'!$A12,'Dwelling stock'!M$52:M$63) -> 3521.9882 | K14: =SUMIF('Dwelling stock'!$B$52:$B$63,"="&'All Stock'!$A12,'Dwelling stock'!N$52:N$63) -> 379.30964 | ... AN14: =SUMIF('Dwelling stock'!$B$52:$B$63,"="&'All Stock'!$A12,'Dwelling stock'!AQ$52:AQ$63) -> 75.075033
A15: semidetached | B15: 000dwellings | C15: HEATED ONLY | D15: =SUMIF('Dwelling stock'!$B$46:$B$63,"="&'All Stock'!$A15,'Dwelling stock'!G$46:G$63) -> 470.44081 | E15: =SUMIF('Dwelling stock'!$B$46:$B$63,"="&'All Stock'!$A15,'Dwelling stock'!H$46:H$63) -> 1585.6865 | F15: =SUMIF('Dwelling stock'!$B$46:$B$63,"="&'All Stock'!$A15,'Dwelling stock'!I$46:I$63) -> 335.3328 | G15: =SUMIF('Dwelling stock'!$B$46:$B$63,"="&'All Stock'!$A15,'Dwelling stock'!J$46:J$63) -> 944.09207 | H15: =SUMIF('Dwelling stock'!$B$46:$B$63,"="&'All Stock'!$A15,'Dwelling stock'!K$46:K$63) -> 108.10428 | I15: =SUMIF('Dwelling stock'!$B$46:$B$63,"="&'All Stock'!$A15,'Dwelling stock'!L$46:L$63) -> 608.78058 | J15: =SUMIF('Dwelling stock'!$B$46:$B$63,"="&'All Stock'!$A15,'Dwelling stock'!M$46:M$63) -> 8085.1739 | K15: =SUMIF('Dwelling stock'!$B$46:$B$63,"="&'All Stock'!$A15,'Dwelling stock'!N$46:N$63) -> 531.0051 | ... AN15: =SUMIF('Dwelling stock'!$B$46:$B$63,"="&'All Stock'!$A15,'Dwelling stock'!AQ$46:AQ$63) -> 46.999316
A16: flat | B16: 000dwellings | C16: HEATED ONLY | D16: =SUMIF('Dwelling stock'!$B$46:$B$63,"="&'All Stock'!$A16,'Dwelling stock'!G$46:G$63) -> 1468.1931 | E16: =SUMIF('Dwelling stock'!$B$46:$B$63,"="&'All Stock'!$A16,'Dwelling stock'!H$46:H$63) -> 905.52301 | F16: =SUMIF('Dwelling stock'!$B$46:$B$63,"="&'All Stock'!$A16,'Dwelling stock'!I$46:I$63) -> 777.21771 | G16: =SUMIF('Dwelling stock'!$B$46:$B$63,"="&'All Stock'!$A16,'Dwelling stock'!J$46:J$63) -> 1648.2852 | H16: =SUMIF('Dwelling stock'!$B$46:$B$63,"="&'All Stock'!$A16,'Dwelling stock'!K$46:K$63) -> 83.544874 | I16: =SUMIF('Dwelling stock'!$B$46:$B$63,"="&'All Stock'!$A16,'Dwelling stock'!L$46:L$63) -> 2208.0312 | J16: =SUMIF('Dwelling stock'!$B$46:$B$63,"="&'All Stock'!$A16,'Dwelling stock'!M$46:M$63) -> 18507.479 | K16: =SUMIF('Dwelling stock'!$B$46:$B$63,"="&'All Stock'!$A16,'Dwelling stock'!N$46:N$63) -> 1066.6763 | ... AN16: =SUMIF('Dwelling stock'!$B$46:$B$63,"="&'All Stock'!$A16,'Dwelling stock'!AQ$46:AQ$63) -> 159.63428
B17: Average | C17: m2 | D17: =LOOKUP(D2,'Data by dwelling type'!$AW$4:$AW$40,'Data by dwelling type'!$AV$4:$AV$40) -> 103.35315 | E17: =LOOKUP(E2,'Data by dwelling type'!$AW$4:$AW$40,'Data by dwelling type'!$AV$4:$AV$40) -> 106.58025 | F17: =LOOKUP(F2,'Data by dwelling type'!$AW$4:$AW$40,'Data by dwelling type'!$AV$4:$AV$40) -> 67.95388 | G17: =LOOKUP(G2,'Data by dwelling type'!$AW$4:$AW$40,'Data by dwelling type'!$AV$4:$AV$40) -> 100.53414 | H17: =LOOKUP(H2,'Data by dwelling type'!$AW$4:$AW$40,'Data by dwelling type'!$AV$4:$AV$40) -> 90.786597 | I17: =LOOKUP(I2,'Data by dwelling type'!$AW$4:$AW$40,'Data by dwelling type'!$AV$4:$AV$40) -> 82.052155 | J17: =LOOKUP(J2,'Data by dwelling type'!$AW$4:$AW$40,'Data by dwelling type'!$AV$4:$AV$40) -> 86.581703 | K17: =LOOKUP(K2,'Data by dwelling type'!$AW$4:$AW$40,'Data by dwelling type'!$AV$4:$AV$40) -> 119.97873 | ... AN17: =LOOKUP(AN2,'Data by dwelling type'!$AW$4:$AW$40,'Data by dwelling type'!$AV$4:$AV$40) -> 71.522245
D19: =D$2 -> AT | E19: =E$2 -> BE | F19: =F$2 -> BG | G19: =G$2 -> CH | H19: =H$2 -> CY | I19: =I$2 -> CZ | J19: =J$2 -> DE | K19: =K$2 -> DK | ... AN19: =AN$2 -> KS
A20: From calibration of end-use eff. (useful energy) | B20: Whole Stock | C20: PJ/000dwellings | D20: ='IDEES okt 2017 template'!D110/D11*'TechHeat-RES'!F307 -> 0.033427251 | E20: ='IDEES okt 2017 template'!E110/E11*'TechHeat-RES'!G307 -> 0.036172925 | F20: ='IDEES okt 2017 template'!F110/F11*'TechHeat-RES'!H307 -> 0.0092278511 | G20: ='IDEES okt 2017 template'!G110/G11*'TechHeat-RES'!I307 -> 0.034788267 | H20: ='IDEES okt 2017 template'!H110/H11*'TechHeat-RES'!J307 -> 0.018583277 | I20: ='IDEES okt 2017 template'!I110/I11*'TechHeat-RES'!K307 -> 0.032171805 | J20: ='IDEES okt 2017 template'!J110/J11*'TechHeat-RES'!L307 -> 0.030160685 | K20: ='IDEES okt 2017 template'!K110/K11*'TechHeat-RES'!M307 -> 0.036311956 | ... AN20: ='IDEES okt 2017 template'!AN110/AN11*'TechHeat-RES'!AP307 -> 0.0074924958
A22: Actual to Theoretical Demand Factor | B22: ATT Factor | C22: Percentage | D22: =D20/D26 -> 0.6874701 | E22: =E20/E26 -> 0.57898429 | F22: =F20/F26 -> 0.31492521 | G22: =G20/G26 -> 0.78725501 | H22: =H20/H26 -> 0.98896126 | I22: =I20/I26 -> 0.92669924 | J22: =J20/J26 -> 0.76640556 | K22: =K20/K26 -> 0.94416673 | ... AN22: =AN20/AN26 -> 0.21867645
A23: Stock Component | C23: Percentage | D23: =IF(D22<1,D22^0.5,1) -> 0.82913817 | E23: =IF(E22<1,E22^0.5,1) -> 0.76091018 | F23: =IF(F22<1,F22^0.5,1) -> 0.56118198 | G23: =IF(G22<1,G22^0.5,1) -> 0.88727392 | H23: =IF(H22<1,H22^0.5,1) -> 0.99446531 | I23: =IF(I22<1,I22^0.5,1) -> 0.96265219 | J23: =IF(J22<1,J22^0.5,1) -> 0.87544592 | K23: =IF(K22<1,K22^0.5,1) -> 0.97168242 | ... AN23: =IF(AN22<1,AN22^0.5,1) -> 0.46762854
A24: Heating intensity component | C24: Percentage | D24: =IFERROR(D22/D23,"") -> 0.82913817 | E24: =IFERROR(E22/E23,"") -> 0.76091018 | F24: =IFERROR(F22/F23,"") -> 0.56118198 | G24: =IFERROR(G22/G23,"") -> 0.88727392 | H24: =IFERROR(H22/H23,"") -> 0.99446531 | I24: =IFERROR(I22/I23,"") -> 0.96265219 | J24: =IFERROR(J22/J23,"") -> 0.87544592 | K24: =IFERROR(K22/K23,"") -> 0.97168242 | ... AN24: =IFERROR(AN22/AN23,"") -> 0.46762854
A26: From geometrical analysis (useful energy) | B26: Whole Stock | C26: PJ/000dwellings | D26: =(Detached!D46*'Dwelling stock'!G142+Semidetached!D47*'Dwelling stock'!G143+Flat!D47*'Dwelling stock'!G141)/'Dwelling stock'!G144/1000000*3.6 -> 0.048623571 | E26: =(Detached!E46*'Dwelling stock'!H142+Semidetached!E47*'Dwelling stock'!H143+Flat!E47*'Dwelling stock'!H141)/'Dwelling stock'!H144/1000000*3.6 -> 0.062476522 | F26: =(Detached!F46*'Dwelling stock'!I142+Semidetached!F47*'Dwelling stock'!I143+Flat!F47*'Dwelling stock'!I141)/'Dwelling stock'!I144/1000000*3.6 -> 0.029301722 | G26: =(Detached!G46*'Dwelling stock'!J142+Semidetached!G47*'Dwelling stock'!J143+Flat!G47*'Dwelling stock'!J141)/'Dwelling stock'!J144/1000000*3.6 -> 0.044189324 | H26: =(Detached!H46*'Dwelling stock'!K142+Semidetached!H47*'Dwelling stock'!K143+Flat!H47*'Dwelling stock'!K141)/'Dwelling stock'!K144/1000000*3.6 -> 0.018790703 | I26: =(Detached!I46*'Dwelling stock'!L142+Semidetached!I47*'Dwelling stock'!L143+Flat!I47*'Dwelling stock'!L141)/'Dwelling stock'!L144/1000000*3.6 -> 0.034716555 | J26: =(Detached!J46*'Dwelling stock'!M142+Semidetached!J47*'Dwelling stock'!M143+Flat!J47*'Dwelling stock'!M141)/'Dwelling stock'!M144/1000000*3.6 -> 0.039353426 | K26: =(Detached!K46*'Dwelling stock'!N142+Semidetached!K47*'Dwelling stock'!N143+Flat!K47*'Dwelling stock'!N141)/'Dwelling stock'!N144/1000000*3.6 -> 0.038459262 | ... AN26: =(Detached!AN46*'Dwelling stock'!AQ142+Semidetached!AN47*'Dwelling stock'!AQ143+Flat!AN47*'Dwelling stock'!AQ141)/'Dwelling stock'!AQ144/1000000*3.6 -> 0.03426293
A27: Alternative based on surface | D27: =D17*D9*3.6/10^6 -> 0.04868687 | E27: =E17*E9*3.6/10^6 -> 0.062577997 | F27: =F17*F9*3.6/10^6 -> 0.029090279 | G27: =G17*G9*3.6/10^6 -> 0.044168082 | H27: =H17*H9*3.6/10^6 -> 0.0187739 | I27: =I17*I9*3.6/10^6 -> 0.034648854 | J27: =J17*J9*3.6/10^6 -> 0.039286361 | K27: =K17*K9*3.6/10^6 -> 0.038713139 | ... AN27: =AN17*AN9*3.6/10^6 -> 0.03417531
A28: Theoretical thermal requirements (useful energy)
A29: Theoretical extra needs | B29: Whole Stock | C29: TJ/000dwellings | D29: =D26-D20 -> 0.01519632 | E29: =E26-E20 -> 0.026303597 | F29: =F26-F20 -> 0.020073871 | G29: =G26-G20 -> 0.0094010574 | H29: =H26-H20 -> 0.00020742564 | I29: =I26-I20 -> 0.0025447499 | J29: =J26-J20 -> 0.0091927415 | K29: =K26-K20 -> 0.0021473064 | ... AN29: =AN26-AN20 -> 0.026770434
B31: EFF | C31: Electricity | D31: 1 | E31: 1 | F31: 1 | G31: 1 | H31: 1 | I31: 1 | J31: 1 | K31: 1 | L31: 1 | M31: 1 | N31: 1 | O31: 1 | P31: 1 | Q31: 1 | R31: 1 | S31: 1 | T31: 1 | U31: 1 | V31: 1 | W31: 1 | X31: 1 | Y31: 1 | Z31: 1 | AA31: 1 | AB31: 1 | AC31: 1 | AD31: 1 | AE31: 1 | AF31: 1 | AG31: 1 | AH31: 1 | AI31: 1 | AJ31: 1 | AK31: 1 | AL31: 1 | AM31: 1 | AN31: 1
C32: HP Air | D32: 2.5 | E32: 2.5 | F32: 2.5 | G32: 2.5 | H32: 2.5 | I32: 2.5 | J32: 2.5 | K32: 2.5 | L32: 2.5 | M32: 2.5 | N32: 2.5 | O32: 2.5 | P32: 2.5 | Q32: 2.5 | R32: 2.5 | S32: 2.5 | T32: 2.5 | U32: 2.5 | V32: 2.5 | W32: 2.5 | X32: 2.5 | Y32: 2.5 | Z32: 2.5 | AA32: 2.5 | AB32: 2.5 | AC32: 2.5 | AD32: 2.5 | AE32: 2.5 | AF32: 2.5 | AG32: 2.5 | AH32: 2.5 | AI32: 2.5 | AJ32: 2.5 | AK32: 2.5 | AL32: 2.5 | AM32: 2.5 | AN32: 2.5
C33: HP Ground | D33: 3 | E33: 3 | F33: 3 | G33: 3 | H33: 3 | I33: 3 | J33: 3 | K33: 3 | L33: 3 | M33: 3 | N33: 3 | O33: 3 | P33: 3 | Q33: 3 | R33: 3 | S33: 3 | T33: 3 | U33: 3 | V33: 3 | W33: 3 | X33: 3 | Y33: 3 | Z33: 3 | AA33: 3 | AB33: 3 | AC33: 3 | AD33: 3 | AE33: 3 | AF33: 3 | AG33: 3 | AH33: 3 | AI33: 3 | AJ33: 3 | AK33: 3 | AL33: 3 | AM33: 3 | AN33: 3
C34: Average | D34: =((D31*SUM('TechHeat-RES'!F5,'TechHeat-RES'!F15,'TechHeat-RES'!F25,'TechHeat-RES'!F35))+(D32*(SUM('TechHeat-RES'!F6,'TechHeat-RES'!F16,'TechHeat-RES'!F26,'TechHeat-RES'!F36)))+(D33*SUM('TechHeat-RES'!F7,'TechHeat-RES'!F17,'TechHeat-RES'!F27,'TechHeat-RES'!F37)))/SUM('TechHeat-RES'!F5:F7,'TechHeat-RES'!F15:F17,'TechHeat-RES'!F25:F27,'TechHeat-RES'!F35:F37) -> 1.5442278 | E34: =((E31*SUM('TechHeat-RES'!G5,'TechHeat-RES'!G15,'TechHeat-RES'!G25,'TechHeat-RES'!G35))+(E32*(SUM('TechHeat-RES'!G6,'TechHeat-RES'!G16,'TechHeat-RES'!G26,'TechHeat-RES'!G36)))+(E33*SUM('TechHeat-RES'!G7,'TechHeat-RES'!G17,'TechHeat-RES'!G27,'TechHeat-RES'!G37)))/SUM('TechHeat-RES'!G5:G7,'TechHeat-RES'!G15:G17,'TechHeat-RES'!G25:G27,'TechHeat-RES'!G35:G37) -> 1.058912 | F34: =((F31*SUM('TechHeat-RES'!H5,'TechHeat-RES'!H15,'TechHeat-RES'!H25,'TechHeat-RES'!H35))+(F32*(SUM('TechHeat-RES'!H6,'TechHeat-RES'!H16,'TechHeat-RES'!H26,'TechHeat-RES'!H36)))+(F33*SUM('TechHeat-RES'!H7,'TechHeat-RES'!H17,'TechHeat-RES'!H27,'TechHeat-RES'!H37)))/SUM('TechHeat-RES'!H5:H7,'TechHeat-RES'!H15:H17,'TechHeat-RES'!H25:H27,'TechHeat-RES'!H35:H37) -> 1 | G34: =((G31*SUM('TechHeat-RES'!I5,'TechHeat-RES'!I15,'TechHeat-RES'!I25,'TechHeat-RES'!I35))+(G32*(SUM('TechHeat-RES'!I6,'TechHeat-RES'!I16,'TechHeat-RES'!I26,'TechHeat-RES'!I36)))+(G33*SUM('TechHeat-RES'!I7,'TechHeat-RES'!I17,'TechHeat-RES'!I27,'TechHeat-RES'!I37)))/SUM('TechHeat-RES'!I5:I7,'TechHeat-RES'!I15:I17,'TechHeat-RES'!I25:I27,'TechHeat-RES'!I35:I37) -> 1.8625706 | H34: =((H31*SUM('TechHeat-RES'!J5,'TechHeat-RES'!J15,'TechHeat-RES'!J25,'TechHeat-RES'!J35))+(H32*(SUM('TechHeat-RES'!J6,'TechHeat-RES'!J16,'TechHeat-RES'!J26,'TechHeat-RES'!J36)))+(H33*SUM('TechHeat-RES'!J7,'TechHeat-RES'!J17,'TechHeat-RES'!J27,'TechHeat-RES'!J37)))/SUM('TechHeat-RES'!J5:J7,'TechHeat-RES'!J15:J17,'TechHeat-RES'!J25:J27,'TechHeat-RES'!J35:J37) -> 1 | I34: =((I31*SUM('TechHeat-RES'!K5,'TechHeat-RES'!K15,'TechHeat-RES'!K25,'TechHeat-RES'!K35))+(I32*(SUM('TechHeat-RES'!K6,'TechHeat-RES'!K16,'TechHeat-RES'!K26,'TechHeat-RES'!K36)))+(I33*SUM('TechHeat-RES'!K7,'TechHeat-RES'!K17,'TechHeat-RES'!K27,'TechHeat-RES'!K37)))/SUM('TechHeat-RES'!K5:K7,'TechHeat-RES'!K15:K17,'TechHeat-RES'!K25:K27,'TechHeat-RES'!K35:K37) -> 1.1540216 | J34: =((J31*SUM('TechHeat-RES'!L5,'TechHeat-RES'!L15,'TechHeat-RES'!L25,'TechHeat-RES'!L35))+(J32*(SUM('TechHeat-RES'!L6,'TechHeat-RES'!L16,'TechHeat-RES'!L26,'TechHeat-RES'!L36)))+(J33*SUM('TechHeat-RES'!L7,'TechHeat-RES'!L17,'TechHeat-RES'!L27,'TechHeat-RES'!L37)))/SUM('TechHeat-RES'!L5:L7,'TechHeat-RES'!L15:L17,'TechHeat-RES'!L25:L27,'TechHeat-RES'!L35:L37) -> 1.3178425 | K34: =((K31*SUM('TechHeat-RES'!M5,'TechHeat-RES'!M15,'TechHeat-RES'!M25,'TechHeat-RES'!M35))+(K32*(SUM('TechHeat-RES'!M6,'TechHeat-RES'!M16,'TechHeat-RES'!M26,'TechHeat-RES'!M36)))+(K33*SUM('TechHeat-RES'!M7,'TechHeat-RES'!M17,'TechHeat-RES'!M27,'TechHeat-RES'!M37)))/SUM('TechHeat-RES'!M5:M7,'TechHeat-RES'!M15:M17,'TechHeat-RES'!M25:M27,'TechHeat-RES'!M35:M37) -> 2.1911077 | ... AN34: =((AN31*SUM('TechHeat-RES'!AP5,'TechHeat-RES'!AP15,'TechHeat-RES'!AP25,'TechHeat-RES'!AP35))+(AN32*(SUM('TechHeat-RES'!AP6,'TechHeat-RES'!AP16,'TechHeat-RES'!AP26,'TechHeat-RES'!AP36)))+(AN33*SUM('TechHeat-RES'!AP7,'TechHeat-RES'!AP17,'TechHeat-RES'!AP27,'TechHeat-RES'!AP37)))/SUM('TechHeat-RES'!AP5:AP7,'TechHeat-RES'!AP15:AP17,'TechHeat-RES'!AP25:AP27,'TechHeat-RES'!AP35:AP37) -> 1
C35: Gases | D35: 0.9 | E35: 0.9 | F35: 0.85 | G35: 0.9 | H35: 0.85 | I35: 0.85 | J35: 0.9 | K35: 0.9 | L35: 0.85 | M35: 0.9 | N35: 0.9 | O35: 0.9 | P35: 0.85 | Q35: =AF35 -> 0.85 | R35: 0.85 | S35: 0.9 | T35: =N35 -> 0.9 | U35: 0.9 | V35: 0.85 | W35: =E35 -> 0.9 | X35: 0.85 | Y35: 0.85 | Z35: 0.9 | AA35: =T35 -> 0.9 | AB35: 0.85 | AC35: 0.85 | AD35: 0.85 | AE35: 0.9 | AF35: 0.85 | AG35: 0.85 | AH35: 0.9 | AI35: 0.85 | AJ35: 0.85 | AK35: 0.85 | AL35: 0.85 | AM35: 0.85 | AN35: 0.85
C36: Derived heat | D36: 0.95 | E36: 0.95 | F36: 0.85 | G36: 0.95 | H36: 0.85 | I36: 0.85 | J36: 0.95 | K36: 0.95 | L36: 0.85 | M36: 0.95 | N36: 0.95 | O36: 0.95 | P36: 0.95 | Q36: =AF36 -> 0.9 | R36: 0.9 | S36: 0.95 | T36: =N36 -> 0.95 | U36: 0.95 | V36: 0.85 | W36: =E36 -> 0.95 | X36: 0.85 | Y36: 0.85 | Z36: 0.95 | AA36: =T36 -> 0.95 | AB36: 0.85 | AC36: 0.9 | AD36: 0.85 | AE36: 0.95 | AF36: 0.9 | AG36: 0.85 | AH36: 0.95 | AI36: 0.85 | AJ36: 0.85 | AK36: 0.85 | AL36: 0.85 | AM36: 0.85 | AN36: 0.85
C37: GDO and other liquids (incl. liq. bio.) | D37: 0.8 | E37: 0.8 | F37: 0.75 | G37: 0.8 | H37: 0.8 | I37: 0.75 | J37: 0.8 | K37: 0.8 | L37: 0.8 | M37: 0.8 | N37: 0.8 | O37: 0.8 | P37: 0.75 | Q37: 0.8 | R37: 0.75 | S37: 0.8 | T37: 0.8 | U37: 0.8 | V37: 0.75 | W37: 0.8 | X37: 0.75 | Y37: 0.75 | Z37: 0.8 | AA37: 0.8 | AB37: 0.75 | AC37: 0.75 | AD37: 0.75 | AE37: 0.8 | AF37: 0.8 | AG37: 0.75 | AH37: 0.8 | AI37: 0.75 | AJ37: 0.75 | AK37: 0.75 | AL37: 0.75 | AM37: 0.75 | AN37: 0.75
C38: Biomass and wastes | D38: 0.7 | E38: 0.7 | F38: 0.65 | G38: 0.7 | H38: 0.7 | I38: 0.65 | J38: 0.7 | K38: 0.7 | L38: 0.7 | M38: 0.7 | N38: 0.7 | O38: 0.7 | P38: 0.65 | Q38: 0.7 | R38: 0.65 | S38: 0.7 | T38: 0.7 | U38: 0.7 | V38: 0.65 | W38: 0.7 | X38: 0.65 | Y38: 0.65 | Z38: 0.7 | AA38: 0.7 | AB38: 0.65 | AC38: 0.65 | AD38: 0.65 | AE38: 0.7 | AF38: 0.7 | AG38: 0.65 | AH38: 0.7 | AI38: 0.65 | AJ38: 0.65 | AK38: 0.65 | AL38: 0.65 | AM38: 0.65 | AN38: 0.65
C39: Solids | D39: 0.65 | E39: 0.65 | F39: 0.6 | G39: 0.65 | H39: 0.65 | I39: 0.6 | J39: 0.65 | K39: 0.65 | L39: 0.65 | M39: 0.65 | N39: 0.65 | O39: 0.65 | P39: 0.6 | Q39: 0.65 | R39: 0.6 | S39: 0.65 | T39: 0.65 | U39: 0.65 | V39: 0.6 | W39: 0.65 | X39: 0.6 | Y39: 0.6 | Z39: 0.65 | AA39: 0.65 | AB39: 0.6 | AC39: 0.6 | AD39: 0.6 | AE39: 0.65 | AF39: 0.65 | AG39: 0.6 | AH39: 0.65 | AI39: 0.6 | AJ39: 0.6 | AK39: 0.6 | AL39: 0.6 | AM39: 0.6 | AN39: 0.6
D40: 2 | E40: 3 | F40: 4 | G40: 5 | H40: 6 | I40: 7 | J40: 8 | K40: 9 | L40: 10 | M40: 11 | N40: 12 | O40: 13 | P40: 14 | Q40: 15 | R40: 16 | S40: 17 | T40: 18 | U40: 19 | V40: 20 | W40: 21 | X40: 22 | Y40: 23 | Z40: 24 | AA40: 25 | AB40: 26 | AC40: 27 | AD40: 28 | AE40: 29 | AF40: 30 | AG40: 31 | AH40: 32 | AI40: 33 | AJ40: 34 | AK40: 35 | AL40: 36 | AM40: 37 | AN40: 38
B41: ACT_FLO | C41: =C31 -> Electricity | D41: =IFERROR(IF(VLOOKUP($C41,'IDEES okt 2017 template'!$C$142:$AN$150,'IDEES okt 2017 template'!D$130,FALSE)/D31=0,"1",VLOOKUP($C41,'IDEES okt 2017 template'!$C$142:$AN$150,'IDEES okt 2017 template'!D$130,FALSE)/D31),"1") -> 0.81928901 | E41: =IFERROR(IF(VLOOKUP($C41,'IDEES okt 2017 template'!$C$142:$AN$150,'IDEES okt 2017 template'!E$130,FALSE)/E31=0,"1",VLOOKUP($C41,'IDEES okt 2017 template'!$C$142:$AN$150,'IDEES okt 2017 template'!E$130,FALSE)/E31),"1") -> 0.799003 | F41: =IFERROR(IF(VLOOKUP($C41,'IDEES okt 2017 template'!$C$142:$AN$150,'IDEES okt 2017 template'!F$130,FALSE)/F31=0,"1",VLOOKUP($C41,'IDEES okt 2017 template'!$C$142:$AN$150,'IDEES okt 2017 template'!F$130,FALSE)/F31),"1") -> 0.7340881 | G41: =IFERROR(IF(VLOOKUP($C41,'IDEES okt 2017 template'!$C$142:$AN$150,'IDEES okt 2017 template'!G$130,FALSE)/G31=0,"1",VLOOKUP($C41,'IDEES okt 2017 template'!$C$142:$AN$150,'IDEES okt 2017 template'!G$130,FALSE)/G31),"1") -> 0.86347572 | H41: =IFERROR(IF(VLOOKUP($C41,'IDEES okt 2017 template'!$C$142:$AN$150,'IDEES okt 2017 template'!H$130,FALSE)/H31=0,"1",VLOOKUP($C41,'IDEES okt 2017 template'!$C$142:$AN$150,'IDEES okt 2017 template'!H$130,FALSE)/H31),"1") -> 0.70618229 | I41: =IFERROR(IF(VLOOKUP($C41,'IDEES okt 2017 template'!$C$142:$AN$150,'IDEES okt 2017 template'!I$130,FALSE)/I31=0,"1",VLOOKUP($C41,'IDEES okt 2017 template'!$C$142:$AN$150,'IDEES okt 2017 template'!I$130,FALSE)/I31),"1") -> 0.70582025 | J41: =IFERROR(IF(VLOOKUP($C41,'IDEES okt 2017 template'!$C$142:$AN$150,'IDEES okt 2017 template'!J$130,FALSE)/J31=0,"1",VLOOKUP($C41,'IDEES okt 2017 template'!$C$142:$AN$150,'IDEES okt 2017 template'!J$130,FALSE)/J31),"1") -> 0.86347572 | K41: =IFERROR(IF(VLOOKUP($C41,'IDEES okt 2017 template'!$C$142:$AN$150,'IDEES okt 2017 template'!K$130,FALSE)/K31=0,"1",VLOOKUP($C41,'IDEES okt 2017 template'!$C$142:$AN$150,'IDEES okt 2017 template'!K$130,FALSE)/K31),"1") -> 0.8001875 | ... AN41: =IFERROR(IF(VLOOKUP($C41,'IDEES okt 2017 template'!$C$142:$AN$150,'IDEES okt 2017 template'!AN$130,FALSE)/AN31=0,"1",VLOOKUP($C41,'IDEES okt 2017 template'!$C$142:$AN$150,'IDEES okt 2017 template'!AN$130,FALSE)/AN31),"1") -> 0.71202455
C42: =C35 -> Gases | D42: =IFERROR(IF(VLOOKUP($C42,'IDEES okt 2017 template'!$C$142:$AN$150,'IDEES okt 2017 template'!D$130,FALSE)/D35=0,"0.7",VLOOKUP($C42,'IDEES okt 2017 template'!$C$142:$AN$150,'IDEES okt 2017 template'!D$130,FALSE)/D35),"0.7") -> 0.75592888 | E42: =IFERROR(IF(VLOOKUP($C42,'IDEES okt 2017 template'!$C$142:$AN$150,'IDEES okt 2017 template'!E$130,FALSE)/E35=0,"0.7",VLOOKUP($C42,'IDEES okt 2017 template'!$C$142:$AN$150,'IDEES okt 2017 template'!E$130,FALSE)/E35),"0.7") -> 0.74380141 | F42: =IFERROR(IF(VLOOKUP($C42,'IDEES okt 2017 template'!$C$142:$AN$150,'IDEES okt 2017 template'!F$130,FALSE)/F35=0,"0.7",VLOOKUP($C42,'IDEES okt 2017 template'!$C$142:$AN$150,'IDEES okt 2017 template'!F$130,FALSE)/F35),"0.7") -> 0.74639155 | G42: =IFERROR(IF(VLOOKUP($C42,'IDEES okt 2017 template'!$C$142:$AN$150,'IDEES okt 2017 template'!G$130,FALSE)/G35=0,"0.7",VLOOKUP($C42,'IDEES okt 2017 template'!$C$142:$AN$150,'IDEES okt 2017 template'!G$130,FALSE)/G35),"0.7") -> 0.81017863 | H42: =IFERROR(IF(VLOOKUP($C42,'IDEES okt 2017 template'!$C$142:$AN$150,'IDEES okt 2017 template'!H$130,FALSE)/H35=0,"0.7",VLOOKUP($C42,'IDEES okt 2017 template'!$C$142:$AN$150,'IDEES okt 2017 template'!H$130,FALSE)/H35),"0.7") -> 0.7 | I42: =IFERROR(IF(VLOOKUP($C42,'IDEES okt 2017 template'!$C$142:$AN$150,'IDEES okt 2017 template'!I$130,FALSE)/I35=0,"0.7",VLOOKUP($C42,'IDEES okt 2017 template'!$C$142:$AN$150,'IDEES okt 2017 template'!I$130,FALSE)/I35),"0.7") -> 0.73442601 | J42: =IFERROR(IF(VLOOKUP($C42,'IDEES okt 2017 template'!$C$142:$AN$150,'IDEES okt 2017 template'!J$130,FALSE)/J35=0,"0.7",VLOOKUP($C42,'IDEES okt 2017 template'!$C$142:$AN$150,'IDEES okt 2017 template'!J$130,FALSE)/J35),"0.7") -> 0.81017863 | K42: =IFERROR(IF(VLOOKUP($C42,'IDEES okt 2017 template'!$C$142:$AN$150,'IDEES okt 2017 template'!K$130,FALSE)/K35=0,"0.7",VLOOKUP($C42,'IDEES okt 2017 template'!$C$142:$AN$150,'IDEES okt 2017 template'!K$130,FALSE)/K35),"0.7") -> 0.78641563 | ... AN42: =IFERROR(IF(VLOOKUP($C42,'IDEES okt 2017 template'!$C$142:$AN$150,'IDEES okt 2017 template'!AN$130,FALSE)/AN35=0,"0.7",VLOOKUP($C42,'IDEES okt 2017 template'!$C$142:$AN$150,'IDEES okt 2017 template'!AN$130,FALSE)/AN35),"0.7") -> 0.7449943
C43: =C36 -> Derived heat | D43: =IFERROR(IF(VLOOKUP($C43,'IDEES okt 2017 template'!$C$142:$AN$150,'IDEES okt 2017 template'!D$130,FALSE)/D36=0,"0.8",VLOOKUP($C43,'IDEES okt 2017 template'!$C$142:$AN$150,'IDEES okt 2017 template'!D$130,FALSE)/D36),"0.8") -> 0.88333199 | E43: =IFERROR(IF(VLOOKUP($C43,'IDEES okt 2017 template'!$C$142:$AN$150,'IDEES okt 2017 template'!E$130,FALSE)/E36=0,"0.8",VLOOKUP($C43,'IDEES okt 2017 template'!$C$142:$AN$150,'IDEES okt 2017 template'!E$130,FALSE)/E36),"0.8") -> 0.83553618 | F43: =IFERROR(IF(VLOOKUP($C43,'IDEES okt 2017 template'!$C$142:$AN$150,'IDEES okt 2017 template'!F$130,FALSE)/F36=0,"0.8",VLOOKUP($C43,'IDEES okt 2017 template'!$C$142:$AN$150,'IDEES okt 2017 template'!F$130,FALSE)/F36),"0.8") -> 0.81206531 | G43: =IFERROR(IF(VLOOKUP($C43,'IDEES okt 2017 template'!$C$142:$AN$150,'IDEES okt 2017 template'!G$130,FALSE)/G36=0,"0.8",VLOOKUP($C43,'IDEES okt 2017 template'!$C$142:$AN$150,'IDEES okt 2017 template'!G$130,FALSE)/G36),"0.8") -> 0.95587493 | H43: =IFERROR(IF(VLOOKUP($C43,'IDEES okt 2017 template'!$C$142:$AN$150,'IDEES okt 2017 template'!H$130,FALSE)/H36=0,"0.8",VLOOKUP($C43,'IDEES okt 2017 template'!$C$142:$AN$150,'IDEES okt 2017 template'!H$130,FALSE)/H36),"0.8") -> 0.8 | I43: =IFERROR(IF(VLOOKUP($C43,'IDEES okt 2017 template'!$C$142:$AN$150,'IDEES okt 2017 template'!I$130,FALSE)/I36=0,"0.8",VLOOKUP($C43,'IDEES okt 2017 template'!$C$142:$AN$150,'IDEES okt 2017 template'!I$130,FALSE)/I36),"0.8") -> 0.85208331 | J43: =IFERROR(IF(VLOOKUP($C43,'IDEES okt 2017 template'!$C$142:$AN$150,'IDEES okt 2017 template'!J$130,FALSE)/J36=0,"0.8",VLOOKUP($C43,'IDEES okt 2017 template'!$C$142:$AN$150,'IDEES okt 2017 template'!J$130,FALSE)/J36),"0.8") -> 0.95587493 | K43: =IFERROR(IF(VLOOKUP($C43,'IDEES okt 2017 template'!$C$142:$AN$150,'IDEES okt 2017 template'!K$130,FALSE)/K36=0,"0.8",VLOOKUP($C43,'IDEES okt 2017 template'!$C$142:$AN$150,'IDEES okt 2017 template'!K$130,FALSE)/K36),"0.8") -> 0.91841114 | ... AN43: =IFERROR(IF(VLOOKUP($C43,'IDEES okt 2017 template'!$C$142:$AN$150,'IDEES okt 2017 template'!AN$130,FALSE)/AN36=0,"0.8",VLOOKUP($C43,'IDEES okt 2017 template'!$C$142:$AN$150,'IDEES okt 2017 template'!AN$130,FALSE)/AN36),"0.8") -> 0.86884496
C44: =C37 -> GDO and other liquids (incl. liq. bio.) | D44: =IFERROR(IF(VLOOKUP($C44,'IDEES okt 2017 template'!$C$142:$AN$150,'IDEES okt 2017 template'!D$130,FALSE)/D37=0,"0.7",VLOOKUP($C44,'IDEES okt 2017 template'!$C$142:$AN$150,'IDEES okt 2017 template'!D$130,FALSE)/D37),"0.7") -> 0.80046714 | E44: =IFERROR(IF(VLOOKUP($C44,'IDEES okt 2017 template'!$C$142:$AN$150,'IDEES okt 2017 template'!E$130,FALSE)/E37=0,"0.7",VLOOKUP($C44,'IDEES okt 2017 template'!$C$142:$AN$150,'IDEES okt 2017 template'!E$130,FALSE)/E37),"0.7") -> 0.78828873 | F44: =IFERROR(IF(VLOOKUP($C44,'IDEES okt 2017 template'!$C$142:$AN$150,'IDEES okt 2017 template'!F$130,FALSE)/F37=0,"0.7",VLOOKUP($C44,'IDEES okt 2017 template'!$C$142:$AN$150,'IDEES okt 2017 template'!F$130,FALSE)/F37),"0.7") -> 0.79832009 | G44: =IFERROR(IF(VLOOKUP($C44,'IDEES okt 2017 template'!$C$142:$AN$150,'IDEES okt 2017 template'!G$130,FALSE)/G37=0,"0.7",VLOOKUP($C44,'IDEES okt 2017 template'!$C$142:$AN$150,'IDEES okt 2017 template'!G$130,FALSE)/G37),"0.7") -> 0.85774115 | H44: =IFERROR(IF(VLOOKUP($C44,'IDEES okt 2017 template'!$C$142:$AN$150,'IDEES okt 2017 template'!H$130,FALSE)/H37=0,"0.7",VLOOKUP($C44,'IDEES okt 2017 template'!$C$142:$AN$150,'IDEES okt 2017 template'!H$130,FALSE)/H37),"0.7") -> 0.58765689 | I44: =IFERROR(IF(VLOOKUP($C44,'IDEES okt 2017 template'!$C$142:$AN$150,'IDEES okt 2017 template'!I$130,FALSE)/I37=0,"0.7",VLOOKUP($C44,'IDEES okt 2017 template'!$C$142:$AN$150,'IDEES okt 2017 template'!I$130,FALSE)/I37),"0.7") -> 0.7 | J44: =IFERROR(IF(VLOOKUP($C44,'IDEES okt 2017 template'!$C$142:$AN$150,'IDEES okt 2017 template'!J$130,FALSE)/J37=0,"0.7",VLOOKUP($C44,'IDEES okt 2017 template'!$C$142:$AN$150,'IDEES okt 2017 template'!J$130,FALSE)/J37),"0.7") -> 0.85774115 | K44: =IFERROR(IF(VLOOKUP($C44,'IDEES okt 2017 template'!$C$142:$AN$150,'IDEES okt 2017 template'!K$130,FALSE)/K37=0,"0.7",VLOOKUP($C44,'IDEES okt 2017 template'!$C$142:$AN$150,'IDEES okt 2017 template'!K$130,FALSE)/K37),"0.7") -> 0.81901204 | ... AN44: =IFERROR(IF(VLOOKUP($C44,'IDEES okt 2017 template'!$C$142:$AN$150,'IDEES okt 2017 template'!AN$130,FALSE)/AN37=0,"0.7",VLOOKUP($C44,'IDEES okt 2017 template'!$C$142:$AN$150,'IDEES okt 2017 template'!AN$130,FALSE)/AN37),"0.7") -> 0.78562799
C45: =C38 -> Biomass and wastes | D45: =IFERROR(IF(VLOOKUP($C45,'IDEES okt 2017 template'!$C$142:$AN$150,'IDEES okt 2017 template'!D$130,FALSE)/D38=0,"0.7",VLOOKUP($C45,'IDEES okt 2017 template'!$C$142:$AN$150,'IDEES okt 2017 template'!D$130,FALSE)/D38),"0.7") -> 0.79425199 | E45: =IFERROR(IF(VLOOKUP($C45,'IDEES okt 2017 template'!$C$142:$AN$150,'IDEES okt 2017 template'!E$130,FALSE)/E38=0,"0.7",VLOOKUP($C45,'IDEES okt 2017 template'!$C$142:$AN$150,'IDEES okt 2017 template'!E$130,FALSE)/E38),"0.7") -> 0.78997503 | F45: =IFERROR(IF(VLOOKUP($C45,'IDEES okt 2017 template'!$C$142:$AN$150,'IDEES okt 2017 template'!F$130,FALSE)/F38=0,"0.7",VLOOKUP($C45,'IDEES okt 2017 template'!$C$142:$AN$150,'IDEES okt 2017 template'!F$130,FALSE)/F38),"0.7") -> 0.72609118 | G45: =IFERROR(IF(VLOOKUP($C45,'IDEES okt 2017 template'!$C$142:$AN$150,'IDEES okt 2017 template'!G$130,FALSE)/G38=0,"0.7",VLOOKUP($C45,'IDEES okt 2017 template'!$C$142:$AN$150,'IDEES okt 2017 template'!G$130,FALSE)/G38),"0.7") -> 0.88939691 | H45: =IFERROR(IF(VLOOKUP($C45,'IDEES okt 2017 template'!$C$142:$AN$150,'IDEES okt 2017 template'!H$130,FALSE)/H38=0,"0.7",VLOOKUP($C45,'IDEES okt 2017 template'!$C$142:$AN$150,'IDEES okt 2017 template'!H$130,FALSE)/H38),"0.7") -> 0.56988643 | I45: =IFERROR(IF(VLOOKUP($C45,'IDEES okt 2017 template'!$C$142:$AN$150,'IDEES okt 2017 template'!I$130,FALSE)/I38=0,"0.7",VLOOKUP($C45,'IDEES okt 2017 template'!$C$142:$AN$150,'IDEES okt 2017 template'!I$130,FALSE)/I38),"0.7") -> 0.75698357 | J45: =IFERROR(IF(VLOOKUP($C45,'IDEES okt 2017 template'!$C$142:$AN$150,'IDEES okt 2017 template'!J$130,FALSE)/J38=0,"0.7",VLOOKUP($C45,'IDEES okt 2017 template'!$C$142:$AN$150,'IDEES okt 2017 template'!J$130,FALSE)/J38),"0.7") -> 0.88939691 | K45: =IFERROR(IF(VLOOKUP($C45,'IDEES okt 2017 template'!$C$142:$AN$150,'IDEES okt 2017 template'!K$130,FALSE)/K38=0,"0.7",VLOOKUP($C45,'IDEES okt 2017 template'!$C$142:$AN$150,'IDEES okt 2017 template'!K$130,FALSE)/K38),"0.7") -> 0.84781454 | ... AD45: =IFERROR(IF(VLOOKUP($C45,'IDEES okt 2017 template'!$C$142:$AN$150,'IDEES okt 2017 template'!AD$130,FALSE)/AD38=0,"0.7",VLOOKUP($C45,'IDEES okt 2017 template'!$C$142:$AN$150,'IDEES okt 2017 template'!AD$130,FALSE)/AD38),"0.7") -> 0.73191705 | AE45: =IFERROR(IF(VLOOKUP($C45,'IDEES okt 2017 template'!$C$138:$AN$145,'IDEES okt 2017 template'!AE$126,FALSE)/AE38=0,"0.7",VLOOKUP($C45,'IDEES okt 2017 template'!$C$138:$AN$145,'IDEES okt 2017 template'!AE$126,FALSE)/AE38),"0.7") -> 0.7 | AF45: =IFERROR(IF(VLOOKUP($C45,'IDEES okt 2017 template'!$C$142:$AN$150,'IDEES okt 2017 template'!AF$130,FALSE)/AF38=0,"0.7",VLOOKUP($C45,'IDEES okt 2017 template'!$C$142:$AN$150,'IDEES okt 2017 template'!AF$130,FALSE)/AF38),"0.7") -> 0.78984393 | AG45: =IFERROR(IF(VLOOKUP($C45,'IDEES okt 2017 template'!$C$142:$AN$150,'IDEES okt 2017 template'!AG$130,FALSE)/AG38=0,"0.7",VLOOKUP($C45,'IDEES okt 2017 template'!$C$142:$AN$150,'IDEES okt 2017 template'!AG$130,FALSE)/AG38),"0.7") -> 0.7395726 | AH45: =IFERROR(IF(VLOOKUP($C45,'IDEES okt 2017 template'!$C$142:$AN$150,'IDEES okt 2017 template'!AH$130,FALSE)/AH38=0,"0.7",VLOOKUP($C45,'IDEES okt 2017 template'!$C$142:$AN$150,'IDEES okt 2017 template'!AH$130,FALSE)/AH38),"0.7") -> 0.81749292 | AI45: =IFERROR(IF(VLOOKUP($C45,'IDEES okt 2017 template'!$C$142:$AN$150,'IDEES okt 2017 template'!AI$130,FALSE)/AI38=0,"0.7",VLOOKUP($C45,'IDEES okt 2017 template'!$C$142:$AN$150,'IDEES okt 2017 template'!AI$130,FALSE)/AI38),"0.7") -> 0.74633079 | AJ45: =IFERROR(IF(VLOOKUP($C45,'IDEES okt 2017 template'!$C$142:$AN$150,'IDEES okt 2017 template'!AJ$130,FALSE)/AJ38=0,"0.7",VLOOKUP($C45,'IDEES okt 2017 template'!$C$142:$AN$150,'IDEES okt 2017 template'!AJ$130,FALSE)/AJ38),"0.7") -> 0.76016377 | AK45: =IFERROR(IF(VLOOKUP($C45,'IDEES okt 2017 template'!$C$142:$AN$150,'IDEES okt 2017 template'!AK$130,FALSE)/AK38=0,"0.7",VLOOKUP($C45,'IDEES okt 2017 template'!$C$142:$AN$150,'IDEES okt 2017 template'!AK$130,FALSE)/AK38),"0.7") -> 0.76016377 | AL45: =IFERROR(IF(VLOOKUP($C45,'IDEES okt 2017 template'!$C$142:$AN$150,'IDEES okt 2017 template'!AL$130,FALSE)/AL38=0,"0.7",VLOOKUP($C45,'IDEES okt 2017 template'!$C$142:$AN$150,'IDEES okt 2017 template'!AL$130,FALSE)/AL38),"0.7") -> 0.74633079 | AM45: =IFERROR(IF(VLOOKUP($C45,'IDEES okt 2017 template'!$C$142:$AN$150,'IDEES okt 2017 template'!AM$130,FALSE)/AM38=0,"0.7",VLOOKUP($C45,'IDEES okt 2017 template'!$C$142:$AN$150,'IDEES okt 2017 template'!AM$130,FALSE)/AM38),"0.7") -> 0.76016377 | AN45: =IFERROR(IF(VLOOKUP($C45,'IDEES okt 2017 template'!$C$142:$AN$150,'IDEES okt 2017 template'!AN$130,FALSE)/AN38=0,"0.7",VLOOKUP($C45,'IDEES okt 2017 template'!$C$142:$AN$150,'IDEES okt 2017 template'!AN$130,FALSE)/AN38),"0.7") -> 0.76016377
C46: =C39 -> Solids | D46: =IFERROR(IF(VLOOKUP($C46,'IDEES okt 2017 template'!$C$142:$AN$150,'IDEES okt 2017 template'!D$130,FALSE)/D39=0,"0.7",VLOOKUP($C46,'IDEES okt 2017 template'!$C$142:$AN$150,'IDEES okt 2017 template'!D$130,FALSE)/D39),"0.7") -> 0.84000944 | E46: =IFERROR(IF(VLOOKUP($C46,'IDEES okt 2017 template'!$C$142:$AN$150,'IDEES okt 2017 template'!E$130,FALSE)/E39=0,"0.7",VLOOKUP($C46,'IDEES okt 2017 template'!$C$142:$AN$150,'IDEES okt 2017 template'!E$130,FALSE)/E39),"0.7") -> 0.81351118 | F46: =IFERROR(IF(VLOOKUP($C46,'IDEES okt 2017 template'!$C$142:$AN$150,'IDEES okt 2017 template'!F$130,FALSE)/F39=0,"0.7",VLOOKUP($C46,'IDEES okt 2017 template'!$C$142:$AN$150,'IDEES okt 2017 template'!F$130,FALSE)/F39),"0.7") -> 0.76823819 | G46: =IFERROR(IF(VLOOKUP($C46,'IDEES okt 2017 template'!$C$142:$AN$150,'IDEES okt 2017 template'!G$130,FALSE)/G39=0,"0.7",VLOOKUP($C46,'IDEES okt 2017 template'!$C$142:$AN$150,'IDEES okt 2017 template'!G$130,FALSE)/G39),"0.7") -> 0.92459294 | H46: =IFERROR(IF(VLOOKUP($C46,'IDEES okt 2017 template'!$C$142:$AN$150,'IDEES okt 2017 template'!H$130,FALSE)/H39=0,"0.7",VLOOKUP($C46,'IDEES okt 2017 template'!$C$142:$AN$150,'IDEES okt 2017 template'!H$130,FALSE)/H39),"0.7") -> 0.7 | I46: =IFERROR(IF(VLOOKUP($C46,'IDEES okt 2017 template'!$C$142:$AN$150,'IDEES okt 2017 template'!I$130,FALSE)/I39=0,"0.7",VLOOKUP($C46,'IDEES okt 2017 template'!$C$142:$AN$150,'IDEES okt 2017 template'!I$130,FALSE)/I39),"0.7") -> 0.80041513 | J46: =IFERROR(IF(VLOOKUP($C46,'IDEES okt 2017 template'!$C$142:$AN$150,'IDEES okt 2017 template'!J$130,FALSE)/J39=0,"0.7",VLOOKUP($C46,'IDEES okt 2017 template'!$C$142:$AN$150,'IDEES okt 2017 template'!J$130,FALSE)/J39),"0.7") -> 0.92459294 | K46: =IFERROR(IF(VLOOKUP($C46,'IDEES okt 2017 template'!$C$142:$AN$150,'IDEES okt 2017 template'!K$130,FALSE)/K39=0,"0.7",VLOOKUP($C46,'IDEES okt 2017 template'!$C$142:$AN$150,'IDEES okt 2017 template'!K$130,FALSE)/K39),"0.7") -> 0.7 | ... AN46: =IFERROR(IF(VLOOKUP($C46,'IDEES okt 2017 template'!$C$142:$AN$150,'IDEES okt 2017 template'!AN$130,FALSE)/AN39=0,"0.7",VLOOKUP($C46,'IDEES okt 2017 template'!$C$142:$AN$150,'IDEES okt 2017 template'!AN$130,FALSE)/AN39),"0.7") -> 0.81118081
A48: TJ/dwelling factors | D48: =D$2 -> AT | E48: =E$2 -> BE | F48: =F$2 -> BG | G48: =G$2 -> CH | H48: =H$2 -> CY | I48: =I$2 -> CZ | J48: =J$2 -> DE | K48: =K$2 -> DK | ... AN48: =AN$2 -> KS
B49: Detached | C49: < 1945 | D49: =Detached!D47/'All Stock'!D$9 -> 1.6427741 | E49: =Detached!E47/'All Stock'!E$9 -> 1.3357405 | F49: =Detached!F47/'All Stock'!F$9 -> 1.7377966 | G49: =Detached!G47/'All Stock'!G$9 -> 1.7161105 | H49: =Detached!H47/'All Stock'!H$9 -> 1.4584438 | I49: =Detached!I47/'All Stock'!I$9 -> 1.6371681 | J49: =Detached!J47/'All Stock'!J$9 -> 1.9411831 | K49: =Detached!K47/'All Stock'!K$9 -> 1.493491 | ... AN49: =Detached!AN47/'All Stock'!AN$9 -> 1.4533998
C50: 1945-1969 | D50: =Detached!D48/'All Stock'!D$9 -> 1.5299626 | E50: =Detached!E48/'All Stock'!E$9 -> 1.3357405 | F50: =Detached!F48/'All Stock'!F$9 -> 1.7377966 | G50: =Detached!G48/'All Stock'!G$9 -> 1.5982629 | H50: =Detached!H48/'All Stock'!H$9 -> 1.3746463 | I50: =Detached!I48/'All Stock'!I$9 -> 1.4046806 | J50: =Detached!J48/'All Stock'!J$9 -> 1.6767887 | K50: =Detached!K48/'All Stock'!K$9 -> 1.451188 | ... AN50: =Detached!AN48/'All Stock'!AN$9 -> 1.4533998
C51: 1970-1979 | D51: =Detached!D49/'All Stock'!D$9 -> 1.2287763 | E51: =Detached!E49/'All Stock'!E$9 -> 1.3357405 | F51: =Detached!F49/'All Stock'!F$9 -> 1.6487278 | G51: =Detached!G49/'All Stock'!G$9 -> 1.2836311 | H51: =Detached!H49/'All Stock'!H$9 -> 1.4358458 | I51: =Detached!I49/'All Stock'!I$9 -> 1.4046806 | J51: =Detached!J49/'All Stock'!J$9 -> 1.1176243 | K51: =Detached!K49/'All Stock'!K$9 -> 1.0273666 | ... AN51: =Detached!AN49/'All Stock'!AN$9 -> 1.4533998
C52: 1980-1989 | D52: =Detached!D50/'All Stock'!D$9 -> 0.85778524 | E52: =Detached!E50/'All Stock'!E$9 -> 1.1412655 | F52: =Detached!F50/'All Stock'!F$9 -> 1.4430086 | G52: =Detached!G50/'All Stock'!G$9 -> 0.89607832 | H52: =Detached!H50/'All Stock'!H$9 -> 1.3984243 | I52: =Detached!I50/'All Stock'!I$9 -> 1.2706525 | J52: =Detached!J50/'All Stock'!J$9 -> 0.90565284 | K52: =Detached!K50/'All Stock'!K$9 -> 0.8739527 | ... AN52: =Detached!AN50/'All Stock'!AN$9 -> 1.2803313
C53: 1990-1999 | D53: =Detached!D51/'All Stock'!D$9 -> 0.73452232 | E53: =Detached!E51/'All Stock'!E$9 -> 1.1412655 | F53: =Detached!F51/'All Stock'!F$9 -> 1.1790441 | G53: =Detached!G51/'All Stock'!G$9 -> 0.76731272 | H53: =Detached!H51/'All Stock'!H$9 -> 1.1987988 | I53: =Detached!I51/'All Stock'!I$9 -> 0.97951376 | J53: =Detached!J51/'All Stock'!J$9 -> 0.53989318 | K53: =Detached!K51/'All Stock'!K$9 -> 0.8739527 | ... AN53: =Detached!AN51/'All Stock'!AN$9 -> 1.2241527
C54: 2000-2008 | D54: =Detached!D52/'All Stock'!D$9 -> 0.6532085 | E54: =Detached!E52/'All Stock'!E$9 -> 0.68487329 | F54: =Detached!F52/'All Stock'!F$9 -> 0.82098968 | G54: =Detached!G52/'All Stock'!G$9 -> 0.68236891 | H54: =Detached!H52/'All Stock'!H$9 -> 1.0548515 | I54: =Detached!I52/'All Stock'!I$9 -> 0.77067249 | J54: =Detached!J52/'All Stock'!J$9 -> 0.5816338 | K54: =Detached!K52/'All Stock'!K$9 -> 0.63806203 | ... AN54: =Detached!AN52/'All Stock'!AN$9 -> 1.060489
B55: Semidetached | C55: < 1945 | D55: =Semidetached!D48/'All Stock'!D$9 -> 1.2794315 | E55: =Semidetached!E48/'All Stock'!E$9 -> 1.0119336 | F55: =Semidetached!F48/'All Stock'!F$9 -> 1.3338854 | G55: =Semidetached!G48/'All Stock'!G$9 -> 1.319077 | H55: =Semidetached!H48/'All Stock'!H$9 -> 1.2142878 | I55: =Semidetached!I48/'All Stock'!I$9 -> 1.2880505 | J55: =Semidetached!J48/'All Stock'!J$9 -> 1.4983129 | K55: =Semidetached!K48/'All Stock'!K$9 -> 1.1156965 | ... AN55: =Semidetached!AN48/'All Stock'!AN$9 -> 1.1049358
C56: 1945-1969 | D56: =Semidetached!D49/'All Stock'!D$9 -> 1.2024034 | E56: =Semidetached!E49/'All Stock'!E$9 -> 1.0119336 | F56: =Semidetached!F49/'All Stock'!F$9 -> 1.3338854 | G56: =Semidetached!G49/'All Stock'!G$9 -> 1.240608 | H56: =Semidetached!H49/'All Stock'!H$9 -> 1.1540243 | I56: =Semidetached!I49/'All Stock'!I$9 -> 1.0567599 | J56: =Semidetached!J49/'All Stock'!J$9 -> 1.3335968 | K56: =Semidetached!K49/'All Stock'!K$9 -> 1.0739724 | ... AN56: =Semidetached!AN49/'All Stock'!AN$9 -> 1.1049358
C57: 1970-1979 | D57: =Semidetached!D50/'All Stock'!D$9 -> 0.94457185 | E57: =Semidetached!E50/'All Stock'!E$9 -> 1.0119336 | F57: =Semidetached!F50/'All Stock'!F$9 -> 1.2567707 | G57: =Semidetached!G50/'All Stock'!G$9 -> 0.97352295 | H57: =Semidetached!H50/'All Stock'!H$9 -> 1.1527118 | I57: =Semidetached!I50/'All Stock'!I$9 -> 1.0567599 | J57: =Semidetached!J50/'All Stock'!J$9 -> 0.83470727 | K57: =Semidetached!K50/'All Stock'!K$9 -> 0.71854531 | ... AN57: =Semidetached!AN50/'All Stock'!AN$9 -> 1.1049358
C58: 1980-1989 | D58: =Semidetached!D51/'All Stock'!D$9 -> 0.643637 | E58: =Semidetached!E51/'All Stock'!E$9 -> 0.85211471 | F58: =Semidetached!F51/'All Stock'!F$9 -> 1.0806582 | G58: =Semidetached!G51/'All Stock'!G$9 -> 0.66259717 | H58: =Semidetached!H51/'All Stock'!H$9 -> 1.1145391 | I58: =Semidetached!I51/'All Stock'!I$9 -> 0.93598124 | J58: =Semidetached!J51/'All Stock'!J$9 -> 0.64105784 | K58: =Semidetached!K51/'All Stock'!K$9 -> 0.59833734 | ... AN58: =Semidetached!AN51/'All Stock'!AN$9 -> 0.9531545
C59: 1990-1999 | D59: =Semidetached!D52/'All Stock'!D$9 -> 0.55187314 | E59: =Semidetached!E52/'All Stock'!E$9 -> 0.85211471 | F59: =Semidetached!F52/'All Stock'!F$9 -> 0.83947875 | G59: =Semidetached!G52/'All Stock'!G$9 -> 0.56829883 | H59: =Semidetached!H52/'All Stock'!H$9 -> 1.0331578 | I59: =Semidetached!I52/'All Stock'!I$9 -> 0.70821853 | J59: =Semidetached!J52/'All Stock'!J$9 -> 0.38198286 | K59: =Semidetached!K52/'All Stock'!K$9 -> 0.59833734 | ... AN59: =Semidetached!AN52/'All Stock'!AN$9 -> 0.89996139
C60: 2000-2008 | D60: =Semidetached!D53/'All Stock'!D$9 -> 0.48218059 | E60: =Semidetached!E53/'All Stock'!E$9 -> 0.49884764 | F60: =Semidetached!F53/'All Stock'!F$9 -> 0.57066216 | G60: =Semidetached!G53/'All Stock'!G$9 -> 0.49605 | H60: =Semidetached!H53/'All Stock'!H$9 -> 0.85512512 | I60: =Semidetached!I53/'All Stock'!I$9 -> 0.55698674 | J60: =Semidetached!J53/'All Stock'!J$9 -> 0.4132682 | K60: =Semidetached!K53/'All Stock'!K$9 -> 0.42933318 | ... AN60: =Semidetached!AN53/'All Stock'!AN$9 -> 0.78384291
B61: Flats | C61: < 1945 | D61: =Flat!D48/'All Stock'!D$9 -> 0.80856103 | E61: =Flat!E48/'All Stock'!E$9 -> 0.62987258 | F61: =Flat!F48/'All Stock'!F$9 -> 0.57290084 | G61: =Flat!G48/'All Stock'!G$9 -> 0.84465665 | H61: =Flat!H48/'All Stock'!H$9 -> 0.59834448 | I61: =Flat!I48/'All Stock'!I$9 -> 0.74010149 | J61: =Flat!J48/'All Stock'!J$9 -> 0.95039326 | K61: =Flat!K48/'All Stock'!K$9 -> 0.63664326 | ... AN61: =Flat!AN48/'All Stock'!AN$9 -> 0.61897476
C62: 1945-1969 | D62: =Flat!D49/'All Stock'!D$9 -> 0.73037898 | E62: =Flat!E49/'All Stock'!E$9 -> 0.62987258 | F62: =Flat!F49/'All Stock'!F$9 -> 0.57290084 | G62: =Flat!G49/'All Stock'!G$9 -> 0.76298442 | H62: =Flat!H49/'All Stock'!H$9 -> 0.54941336 | I62: =Flat!I49/'All Stock'!I$9 -> 0.66704039 | J62: =Flat!J49/'All Stock'!J$9 -> 0.78442747 | K62: =Flat!K49/'All Stock'!K$9 -> 0.62530724 | ... AN62: =Flat!AN49/'All Stock'!AN$9 -> 0.61897476
C63: 1970-1979 | D63: =Flat!D50/'All Stock'!D$9 -> 0.59631559 | E63: =Flat!E50/'All Stock'!E$9 -> 0.62987258 | F63: =Flat!F50/'All Stock'!F$9 -> 0.54274768 | G63: =Flat!G50/'All Stock'!G$9 -> 0.62293619 | H63: =Flat!H50/'All Stock'!H$9 -> 0.55388512 | I63: =Flat!I50/'All Stock'!I$9 -> 0.66704039 | J63: =Flat!J50/'All Stock'!J$9 -> 0.53431071 | K63: =Flat!K50/'All Stock'!K$9 -> 0.45018519 | ... AN63: =Flat!AN50/'All Stock'!AN$9 -> 0.61897476
C64: 1980-1989 | D64: =Flat!D51/'All Stock'!D$9 -> 0.42145346 | E64: =Flat!E51/'All Stock'!E$9 -> 0.54309274 | F64: =Flat!F51/'All Stock'!F$9 -> 0.47226901 | G64: =Flat!G51/'All Stock'!G$9 -> 0.4402679 | H64: =Flat!H51/'All Stock'!H$9 -> 0.54332229 | I64: =Flat!I51/'All Stock'!I$9 -> 0.60825987 | J64: =Flat!J51/'All Stock'!J$9 -> 0.45696145 | K64: =Flat!K51/'All Stock'!K$9 -> 0.38199497 | ... AN64: =Flat!AN51/'All Stock'!AN$9 -> 0.54133389
C65: 1990-1999 | D65: =Flat!D52/'All Stock'!D$9 -> 0.35476344 | E65: =Flat!E52/'All Stock'!E$9 -> 0.54309274 | F65: =Flat!F52/'All Stock'!F$9 -> 0.38629554 | G65: =Flat!G52/'All Stock'!G$9 -> 0.37060072 | H65: =Flat!H52/'All Stock'!H$9 -> 0.46926184 | I65: =Flat!I52/'All Stock'!I$9 -> 0.46221918 | J65: =Flat!J52/'All Stock'!J$9 -> 0.26084525 | K65: =Flat!K52/'All Stock'!K$9 -> 0.38199497 | ... AN65: =Flat!AN52/'All Stock'!AN$9 -> 0.51408007
C66: 2000-2008 | D66: =Flat!D53/'All Stock'!D$9 -> 0.32071092 | E66: =Flat!E53/'All Stock'!E$9 -> 0.32420738 | F66: =Flat!F53/'All Stock'!F$9 -> 0.26036186 | G66: =Flat!G53/'All Stock'!G$9 -> 0.33502804 | H66: =Flat!H53/'All Stock'!H$9 -> 0.4336595 | I66: =Flat!I53/'All Stock'!I$9 -> 0.37130978 | J66: =Flat!J53/'All Stock'!J$9 -> 0.28700909 | K66: =Flat!K53/'All Stock'!K$9 -> 0.28220583 | ... AN66: =Flat!AN53/'All Stock'!AN$9 -> 0.44194564
C68: ~FI_T: INPUT
A69: TechName | B69: Comm-IN | C69: Year | D69: =D$2 -> AT | E69: =E$2 -> BE | F69: =F$2 -> BG | G69: =G$2 -> CH | H69: =H$2 -> CY | I69: =I$2 -> CZ | J69: =J$2 -> DE | K69: =K$2 -> DK | ... AN69: =AN$2 -> KS
A70: \I: | B70: =TechComm!$C$23 -> R_ES-DH-SpHeat | C70: =VLOOKUP(C49,TechComm!$U$2:$V$7,2,FALSE) -> 1940 | D70: =Detached!D40/10^6*3.6 -> 0.11591793 | E70: =Detached!E40/10^6*3.6 -> 0.11167469 | F70: =Detached!F40/10^6*3.6 -> 0.059149985 | G70: =Detached!G40/10^6*3.6 -> 0.11293404 | H70: =Detached!H40/10^6*3.6 -> 0.034496014 | I70: =Detached!I40/10^6*3.6 -> 0.086290751 | J70: =Detached!J40/10^6*3.6 -> 0.11821207 | K70: =Detached!K40/10^6*3.6 -> 0.080537505 | ... AN70: =Detached!AN40/10^6*3.6 -> 0.059691045
A71: \I: | B71: =TechComm!$C$23 -> R_ES-DH-SpHeat | C71: =VLOOKUP(C50,TechComm!$U$2:$V$7,2,FALSE) -> 1957 | D71: =Detached!D41/10^6*3.6 -> 0.10795769 | E71: =Detached!E41/10^6*3.6 -> 0.11167469 | F71: =Detached!F41/10^6*3.6 -> 0.059149985 | G71: =Detached!G41/10^6*3.6 -> 0.1051787 | H71: =Detached!H41/10^6*3.6 -> 0.032513984 | I71: =Detached!I41/10^6*3.6 -> 0.074036954 | J71: =Detached!J41/10^6*3.6 -> 0.10211126 | K71: =Detached!K41/10^6*3.6 -> 0.078256287 | ... AN71: =Detached!AN41/10^6*3.6 -> 0.059691045
A72: \I: | B72: =TechComm!$C$23 -> R_ES-DH-SpHeat | C72: =VLOOKUP(C51,TechComm!$U$2:$V$7,2,FALSE) -> 1975 | D72: =Detached!D42/10^6*3.6 -> 0.08670529 | E72: =Detached!E42/10^6*3.6 -> 0.11167469 | F72: =Detached!F42/10^6*3.6 -> 0.05611832 | G72: =Detached!G42/10^6*3.6 -> 0.084473369 | H72: =Detached!H42/10^6*3.6 -> 0.033961514 | I72: =Detached!I42/10^6*3.6 -> 0.074036954 | J72: =Detached!J42/10^6*3.6 -> 0.068059875 | K72: =Detached!K42/10^6*3.6 -> 0.055401431 | ... AN72: =Detached!AN42/10^6*3.6 -> 0.059691045
A73: \I: | B73: =TechComm!$C$23 -> R_ES-DH-SpHeat | C73: =VLOOKUP(C52,TechComm!$U$2:$V$7,2,FALSE) -> 1985 | D73: =Detached!D43/10^6*3.6 -> 0.060527305 | E73: =Detached!E43/10^6*3.6 -> 0.09541559 | F73: =Detached!F43/10^6*3.6 -> 0.049116183 | G73: =Detached!G43/10^6*3.6 -> 0.058969244 | H73: =Detached!H43/10^6*3.6 -> 0.033076396 | I73: =Detached!I43/10^6*3.6 -> 0.06697269 | J73: =Detached!J43/10^6*3.6 -> 0.055151465 | K73: =Detached!K43/10^6*3.6 -> 0.047128486 | ... AN73: =Detached!AN43/10^6*3.6 -> 0.05258313
A74: \I: | B74: =TechComm!$C$23 -> R_ES-DH-SpHeat | C74: =VLOOKUP(C53,TechComm!$U$2:$V$7,2,FALSE) -> 1995 | D74: =Detached!D44/10^6*3.6 -> 0.05182959 | E74: =Detached!E44/10^6*3.6 -> 0.09541559 | F74: =Detached!F44/10^6*3.6 -> 0.040131531 | G74: =Detached!G44/10^6*3.6 -> 0.05049542 | H74: =Detached!H44/10^6*3.6 -> 0.02835473 | I74: =Detached!I44/10^6*3.6 -> 0.051627548 | J74: =Detached!J44/10^6*3.6 -> 0.03287783 | K74: =Detached!K44/10^6*3.6 -> 0.047128486 | ... AN74: =Detached!AN44/10^6*3.6 -> 0.05027588
A75: \I: | B75: =TechComm!$C$23 -> R_ES-DH-SpHeat | C75: =VLOOKUP(C54,TechComm!$U$2:$V$7,2,FALSE) -> 2004 | D75: =Detached!D45/10^6*3.6 -> 0.046091899 | E75: =Detached!E45/10^6*3.6 -> 0.057258886 | F75: =Detached!F45/10^6*3.6 -> 0.02794431 | G75: =Detached!G45/10^6*3.6 -> 0.044905426 | H75: =Detached!H45/10^6*3.6 -> 0.024950001 | I75: =Detached!I45/10^6*3.6 -> 0.040620084 | J75: =Detached!J45/10^6*3.6 -> 0.035419705 | K75: =Detached!K45/10^6*3.6 -> 0.034407924 | ... AN75: =Detached!AN45/10^6*3.6 -> 0.043554223
A76: \I: | B76: =TechComm!$C$24 -> R_ES-SD-SpHeat | C76: =VLOOKUP(C55,TechComm!$U$2:$V$7,2,FALSE) -> 1940 | D76: =Semidetached!D41/10^6*3.6 -> 0.061685733 | E76: =Semidetached!E41/10^6*3.6 -> 0.06188447 | F76: =Semidetached!F41/10^6*3.6 -> 0.031258535 | G76: =Semidetached!G41/10^6*3.6 -> 0.06212511 | H76: =Semidetached!H41/10^6*3.6 -> 0.020447798 | I76: =Semidetached!I41/10^6*3.6 -> 0.046943421 | J76: =Semidetached!J41/10^6*3.6 -> 0.065044256 | K76: =Semidetached!K41/10^6*3.6 -> 0.041380769 | ... AN76: =Semidetached!AN41/10^6*3.6 -> 0.030659053
A77: \I: | B77: =TechComm!$C$24 -> R_ES-SD-SpHeat | C77: =VLOOKUP(C56,TechComm!$U$2:$V$7,2,FALSE) -> 1957 | D77: =Semidetached!D42/10^6*3.6 -> 0.057971946 | E77: =Semidetached!E42/10^6*3.6 -> 0.06188447 | F77: =Semidetached!F42/10^6*3.6 -> 0.031258535 | G77: =Semidetached!G42/10^6*3.6 -> 0.058429422 | H77: =Semidetached!H42/10^6*3.6 -> 0.019433002 | I77: =Semidetached!I42/10^6*3.6 -> 0.03851396 | J77: =Semidetached!J42/10^6*3.6 -> 0.057893655 | K77: =Semidetached!K42/10^6*3.6 -> 0.039833239 | ... AN77: =Semidetached!AN42/10^6*3.6 -> 0.030659053
A78: \I: | B78: =TechComm!$C$24 -> R_ES-SD-SpHeat | C78: =VLOOKUP(C57,TechComm!$U$2:$V$7,2,FALSE) -> 1975 | D78: =Semidetached!D43/10^6*3.6 -> 0.045541012 | E78: =Semidetached!E43/10^6*3.6 -> 0.06188447 | F78: =Semidetached!F43/10^6*3.6 -> 0.029451412 | G78: =Semidetached!G43/10^6*3.6 -> 0.045850408 | H78: =Semidetached!H43/10^6*3.6 -> 0.0194109 | I78: =Semidetached!I43/10^6*3.6 -> 0.03851396 | J78: =Semidetached!J43/10^6*3.6 -> 0.036236031 | K78: =Semidetached!K43/10^6*3.6 -> 0.026650579 | ... AN78: =Semidetached!AN43/10^6*3.6 -> 0.030659053
A79: \I: | B79: =TechComm!$C$24 -> R_ES-SD-SpHeat | C79: =VLOOKUP(C58,TechComm!$U$2:$V$7,2,FALSE) -> 1985 | D79: =Semidetached!D44/10^6*3.6 -> 0.031031923 | E79: =Semidetached!E44/10^6*3.6 -> 0.052110797 | F79: =Semidetached!F44/10^6*3.6 -> 0.025324358 | G79: =Semidetached!G44/10^6*3.6 -> 0.03120661 | H79: =Semidetached!H44/10^6*3.6 -> 0.018768097 | I79: =Semidetached!I44/10^6*3.6 -> 0.034112142 | J79: =Semidetached!J44/10^6*3.6 -> 0.027829387 | K79: =Semidetached!K44/10^6*3.6 -> 0.02219211 | ... AN79: =Semidetached!AN44/10^6*3.6 -> 0.026447521
A80: \I: | B80: =TechComm!$C$24 -> R_ES-SD-SpHeat | C80: =VLOOKUP(C59,TechComm!$U$2:$V$7,2,FALSE) -> 1995 | D80: =Semidetached!D45/10^6*3.6 -> 0.026607676 | E80: =Semidetached!E45/10^6*3.6 -> 0.052110797 | F80: =Semidetached!F45/10^6*3.6 -> 0.019672511 | G80: =Semidetached!G45/10^6*3.6 -> 0.026765402 | H80: =Semidetached!H45/10^6*3.6 -> 0.017397691 | I80: =Semidetached!I45/10^6*3.6 -> 0.025811255 | J80: =Semidetached!J45/10^6*3.6 -> 0.016582511 | K80: =Semidetached!K45/10^6*3.6 -> 0.02219211 | ... AN80: =Semidetached!AN45/10^6*3.6 -> 0.024971553
A81: \I: | B81: =TechComm!$C$24 -> R_ES-SD-SpHeat | C81: =VLOOKUP(C60,TechComm!$U$2:$V$7,2,FALSE) -> 2004 | D81: =Semidetached!D46/10^6*3.6 -> 0.023247561 | E81: =Semidetached!E46/10^6*3.6 -> 0.030506864 | F81: =Semidetached!F46/10^6*3.6 -> 0.01337301 | G81: =Semidetached!G46/10^6*3.6 -> 0.023362669 | H81: =Semidetached!H46/10^6*3.6 -> 0.014399738 | I81: =Semidetached!I46/10^6*3.6 -> 0.020299563 | J81: =Semidetached!J46/10^6*3.6 -> 0.01794066 | K81: =Semidetached!K46/10^6*3.6 -> 0.015923808 | ... AN81: =Semidetached!AN46/10^6*3.6 -> 0.021749571
A82: \I: | B82: =TechComm!$C$22 -> R_ES-FL-SpHeat | C82: =VLOOKUP(C61,TechComm!$U$2:$V$7,2,FALSE) -> 1940 | D82: =Flat!D41/10^6*3.6 -> 0.027259111 | E82: =Flat!E41/10^6*3.6 -> 0.027085497 | F82: =Flat!F41/10^6*3.6 -> 0.015813935 | G82: =Flat!G41/10^6*3.6 -> 0.026557422 | H82: =Flat!H41/10^6*3.6 -> 0.0090324778 | I82: =Flat!I41/10^6*3.6 -> 0.019060357 | J82: =Flat!J41/10^6*3.6 -> 0.027042364 | K82: =Flat!K41/10^6*3.6 -> 0.016105209 | ... AN82: =Flat!AN41/10^6*3.6 -> 0.01881419
A83: \I: | B83: =TechComm!$C$22 -> R_ES-FL-SpHeat | C83: =VLOOKUP(C62,TechComm!$U$2:$V$7,2,FALSE) -> 1957 | D83: =Flat!D42/10^6*3.6 -> 0.024623351 | E83: =Flat!E42/10^6*3.6 -> 0.027085497 | F83: =Flat!F42/10^6*3.6 -> 0.015813935 | G83: =Flat!G42/10^6*3.6 -> 0.02398951 | H83: =Flat!H42/10^6*3.6 -> 0.0082938243 | I83: =Flat!I42/10^6*3.6 -> 0.017178763 | J83: =Flat!J42/10^6*3.6 -> 0.022319995 | K83: =Flat!K42/10^6*3.6 -> 0.01581844 | ... AN83: =Flat!AN42/10^6*3.6 -> 0.01881419
A84: \I: | B84: =TechComm!$C$22 -> R_ES-FL-SpHeat | C84: =VLOOKUP(C63,TechComm!$U$2:$V$7,2,FALSE) -> 1975 | D84: =Flat!D43/10^6*3.6 -> 0.020103656 | E84: =Flat!E43/10^6*3.6 -> 0.027085497 | F84: =Flat!F43/10^6*3.6 -> 0.014981609 | G84: =Flat!G43/10^6*3.6 -> 0.019586159 | H84: =Flat!H43/10^6*3.6 -> 0.008361329 | I84: =Flat!I43/10^6*3.6 -> 0.017178763 | J84: =Flat!J43/10^6*3.6 -> 0.015203206 | K84: =Flat!K43/10^6*3.6 -> 0.011388366 | ... AN84: =Flat!AN43/10^6*3.6 -> 0.01881419
