Workbook
Name conv: 'common data'!#REF!
Name conv: 'common data'!#REF!
Name discount: 'common data'!#REF!
Name discount: 'common data'!#REF!
Name period: #REF!

Sheet common data
A2: Conversion factors
G5: Tc | H5: 1100
A6: 1 year = | B6: =24*365 -> 8760 | C6: hours | G6: Tf | H6: 30
A7: 1kWh e = | B7: 7 | C7: kWh th | G7: Carnot | H7: =(H5+273-H6-273)/(H5+273) -> 0.77931537
A9: Conversion energy units
B10: 1 | C10: PJ | D10: = | F10: GWh
B11: 1 | C11: GJ | E11: 277.8 | F11: kWh
B12: 1 | C12: MJ | E12: =B12/3600*1000 -> 0.27777778 | F12: kWh
B13: =1000000000000000 -> 1e+15 | C13: Ws
B14: =B13/3600 -> 2.7777778e+11 | C14: wh
B15: =B14/1000000000 -> 277.77778 | C15: GWh
J17: =416/C29 -> 11162.779
A18: Basic Unit Conversion Factors
A19: 1BOE | B19: 6.1 | C19: GJ
A20: 1 MBTU GAS | B20: 1.054 | C20: GJ
A21: 1 TOE | B21: 41.868 | C21: GJ
A22: 1 Kwh | B22: 0.0036 | C22: GJ | E22: 1PJ = | F22: =1/B22 -> 277.77778 | G22: GWh | H22: =F22*1000000 -> 2.7777778e+08 | I22: kWh
A23: 1 t coal | B23: 28.1 | C23: GJ
A24: 10e7kcal | B24: 41.84 | C24: GJ
A25: GW | B25: 31.536 | C25: PJ
A27: IEA source | C27: GJ/L | D27: TOE/TON | E27: KG/L | F27: L/TOE
B28: Gasoline | C28: =$B$21/F28 -> 0.034943033 | D28: 1.07 | E28: 0.78 | F28: =1000/(D28*E28) -> 1198.1788
B29: Diesel | C29: =$B$21/F29 -> 0.037266707 | D29: 1.035 | E29: 0.86 | F29: =1000/(D29*E29) -> 1123.4693
C30: GJ/1000l | D30: TOE/TON | E30: KG/L | F30: L/TOE | G30: GJ/ton
B31: Light fuel | C31: =(B21/F31)*1000 -> 36.375421 | D31: 1.0343 | E31: 0.84 | F31: =1000/(D31*E31) -> 1150.997 | G31: =D31*B21 -> 43.304072
C32: GJ/ton | D32: TOE/TON | E32: KG/L | F32: L/TOE
B33: Heavy Fuel Oil | C33: =D33*B21 -> 40.19328 | D33: 0.96 | E33: 0.95 | F33: =1000/(D33*E33) -> 1096.4912
A37: Exchange Rates
B38: NC/EURO | C38: Conversion Factor for IEA prices in EURO
B39: 2000 | C39: 2000 | D39: 2005
A40: EX_AT | B40: 13.7603 | C40: =1 -> 1
A41: EX_BE | B41: 40.3399 | C41: =1 -> 1
A42: EX_DE | B42: 1.95583 | C42: =1 -> 1
A43: EX_DK | B43: 7.4621835 | C43: =1/B43 -> 0.13400903
A44: EX_FI | B44: 5.94573 | C44: =1 -> 1
A45: EX_FR | B45: 6.55957 | C45: =1 -> 1
A46: EX_EL | B46: 340.75 | C46: =1 -> 1
A47: EX_IE | B47: 0.787564 | C47: =1 -> 1
A48: EX_IT | B48: 1.93627 | C48: =1 -> 1
A49: EX_NL | B49: 2.20371 | C49: =1 -> 1
A50: EX_PT | B50: 200.482 | C50: =1 -> 1
A51: EX_ES | B51: 166.386 | C51: =1 -> 1
A52: EX_SE | B52: 8.4539055 | C52: =1/B52 -> 0.11828852
A53: EX_UK | B53: 0.60996429 | C53: =1/B53 -> 1.6394402
A54: EX_US | B54: 0.9236 | D54: 1.2482 | E54: US$ per EURO
A55: EX_HU | B55: 260.31858 | C55: =1/B55 -> 0.0038414469
A56: EX_PL | B56: 4.010879 | C56: =1/B56 -> 0.2493219
A57: EX_SI | B57: 206.81537 | C57: =1/B57 -> 0.0048352306
A58: EX_CZ | B58: 35.638888 | C58: =1/B58 -> 0.028059237
A59: EX_SK | B59: 42.642461 | C59: =1/B59 -> 0.023450804
A60: EX_CH | B60: 1.5590493 | C60: =1/B60 -> 0.64141653
A61: EX_EE | B61: 15.664212 | C61: =1/B61 -> 0.063839788
A62: EX_LT | B62: 3.6951109 | C62: =1/B62 -> 0.27062787
A63: EX_LV | B63: 0.55966751 | C63: =1/B63 -> 1.7867752
A65: Inflation
A66: price increase 2000/2005= | B66: 1.2

Sheet REF2016 Prices
A1: Energy Trends Reference Scenario 2015
A4: USD of 2010 per boe
B5: 2010 | C5: 2020 | D5: 2030 | E5: 2040 | F5: 2050
A6: Oil
A7: Reference | B7: 79.5 | C7: 84.7 | D7: 106.7 | E7: 117.9 | F7: 123.4
A8: High prices
A9: Low Prices
A10: Gas
A11: Reference | B11: 50.2 | C11: 54.8 | D11: 64.6 | E11: 71.3 | F11: 73.9
A12: High prices
A13: Low Prices
A14: Coal
A15: Reference | B15: 21.2 | C15: 16.2 | D15: 23.3 | E15: 25.8 | F15: 27.4
A16: High prices
A17: Low Prices
B19: 2010 | C19: 2020 | D19: 2030 | E19: 2040 | F19: 2050
A20: Oil P Ref | B20: =B7 -> 79.5 | C20: =C7 -> 84.7 | D20: =D7 -> 106.7 | E20: =E7 -> 117.9 | F20: =F7 -> 123.4
A21: Oil P High | B21: =B8 -> 0 | C21: =C8 -> 0 | D21: =D8 -> 0 | E21: =E8 -> 0 | F21: =F8 -> 0
A22: Oil P Low | B22: =B9 -> 0 | C22: =C9 -> 0 | D22: =D9 -> 0 | E22: =E9 -> 0 | F22: =F9 -> 0
A23: Oil T Ref | B23: =[1]POLES!E33 -> 73.831733 | C23: =[1]POLES!G33 -> 84.358357 | D23: =[1]POLES!I33 -> 98.131828 | E23: =[1]POLES!L33 -> 111.98185 | F23: =[1]POLES!M33 -> 114.64982
A24: Oil T Base | B24: =[1]POLES!E36 -> 73.831733 | C24: =[1]POLES!G36 -> 90.109361 | D24: =[1]POLES!I36 -> 112.99791 | E24: =[1]POLES!L36 -> 153.88672 | F24: =[1]POLES!M36 -> 165.75298
A25: Gas P Ref | B25: =B11 -> 50.2 | C25: =C11 -> 54.8 | D25: =D11 -> 64.6 | E25: =E11 -> 71.3 | F25: =F11 -> 73.9
A26: Gas P High | B26: =B12 -> 0 | C26: =C12 -> 0 | D26: =D12 -> 0 | E26: =E12 -> 0 | F26: =F12 -> 0
A27: Gas P Low | B27: =B13 -> 0 | C27: =C13 -> 0 | D27: =D13 -> 0 | E27: =E13 -> 0 | F27: =F13 -> 0
A28: Gas T Ref | B28: =[1]POLES!E34 -> 23.142718 | C28: =[1]POLES!G34 -> 30.903103 | D28: =[1]POLES!I34 -> 34.341529 | E28: =[1]POLES!L34 -> 40.063973 | F28: =[1]POLES!M34 -> 41.104371
A29: Gas T Base | B29: =[1]POLES!E37 -> 23.212543 | C29: =[1]POLES!G37 -> 32.526848 | D29: =[1]POLES!I37 -> 39.069219 | E29: =[1]POLES!L37 -> 53.876146 | F29: =[1]POLES!M37 -> 60.097385
A30: Coal P Ref | B30: =B15 -> 21.2 | C30: =C15 -> 16.2 | D30: =D15 -> 23.3 | E30: =E15 -> 25.8 | F30: =F15 -> 27.4
A31: Coal P High | B31: =B16 -> 0 | C31: =C16 -> 0 | D31: =D16 -> 0 | E31: =E16 -> 0 | F31: =F16 -> 0
A32: Coal P Low | B32: =B17 -> 0 | C32: =C17 -> 0 | D32: =D17 -> 0 | E32: =E17 -> 0 | F32: =F17 -> 0
A33: Coal T Ref | B33: =[1]POLES!E35 -> 14.942496 | C33: =[1]POLES!G35 -> 16.37357 | D33: =[1]POLES!I35 -> 17.667871 | E33: =[1]POLES!L35 -> 19.549739 | F33: =[1]POLES!M35 -> 20.141291
A34: Coal T Base | B34: =[1]POLES!E38 -> 14.943538 | C34: =[1]POLES!G38 -> 16.961579 | D34: =[1]POLES!I38 -> 18.480519 | E34: =[1]POLES!L38 -> 20.618706 | F34: =[1]POLES!M38 -> 21.306766
A36: Updated from EU 2024
A37: PRIMES in eur 2010/GJ
B38: 2010 | C38: 2020 | D38: 2030 | E38: 2040 | F38: 2050
A39: Oil
A40: Reference | B40: =B53/'common data'!$B$19 -> 9.8196721 | C40: 9.31 | D40: 13.65 | E40: 14.45 | F40: 17.47
A41: High prices
A42: Low Prices
A43: Gas
A44: Reference | B44: =B54/'common data'!$B$19 -> 6.1967213 | C44: 13.39 | D44: 7 | E44: 7 | F44: 7
A45: High prices
A46: Low Prices
A47: Coal
A48: Reference | B48: =B55/'common data'!$B$19 -> 2.6229508 | C48: 3.37 | D48: 2.75 | E48: 2.93 | F48: 3.28
A49: High prices
A50: Low Prices
A51: PRIMES in eur 2010/boe
A52: Reference | B52: 2010 | C52: 2020 | D52: 2030 | E52: 2040 | F52: 2050
A53: Oil | B53: 59.9 | C53: 69.8 | D53: 89.7 | E53: 99.1 | F53: 103.7
A54: Gas | B54: 37.8 | C54: 45.1 | D54: 54.3 | E54: 60 | F54: 62.1
A55: Coal | B55: 16 | C55: 13.4 | D55: 19.6 | E55: 21.7 | F55: 23.1
A56: High prices
A57: Oil | B57: =B41 -> 0 | C57: =C41 -> 0 | D57: =D41 -> 0 | E57: =E41 -> 0 | F57: =F41 -> 0
A58: Gas | B58: =B45 -> 0 | C58: =C45 -> 0 | D58: =D45 -> 0 | E58: =E45 -> 0 | F58: =F45 -> 0
A59: Coal | B59: =B49 -> 0 | C59: =C49 -> 0 | D59: =D49 -> 0 | E59: =E49 -> 0 | F59: =F49 -> 0
A60: Low prices
A61: Oil | B61: =B42 -> 0 | C61: =C42 -> 0 | D61: =D42 -> 0 | E61: =E42 -> 0 | F61: =F42 -> 0
A62: Gas | B62: =B46 -> 0 | C62: =C46 -> 0 | D62: =D46 -> 0 | E62: =E46 -> 0 | F62: =F46 -> 0
A63: Coal | B63: =B50 -> 0 | C63: =C50 -> 0 | D63: =D50 -> 0 | E63: =E50 -> 0 | F63: =F50 -> 0

Sheet PRIMESprices SEC 2011
A1: Energy 2050 Roadmap. Impact assessment 1 - including Part 1 of Annex 1 "Scenarios - assumptions and results" [SEC(2011)1565/1]
A2: http://ec.europa.eu/energy/energy2020/roadmap/doc/sec_2011_1565_part1.pdf
A3: Annex 1 Table 3: Energy import prices in the Reference scenario and low and high price variants
A4: USD of 2008 per boe
B5: 2010 | C5: 2020 | D5: 2030 | E5: 2040 | F5: 2050
A6: Oil
A7: Reference | B7: 84.6 | C7: 88.4 | D7: 105.9 | E7: 116.2 | F7: 126.8
A8: High prices | B8: 84.6 | C8: 132.2 | D8: 149.3 | E8: 148.8 | F8: 162.3
A9: Low Prices | B9: 84.6 | C9: 78.8 | D9: 91.5 | E9: 87.9 | F9: 83.9
A10: Gas
A11: Reference | B11: 53.5 | C11: 62.1 | D11: 76.6 | E11: 86.8 | F11: 98.4
A12: High prices | B12: 53.5 | C12: 85.5 | D12: 101.5 | E12: 111.6 | F12: 129
A13: Low Prices | B13: 53.5 | C13: 43.7 | D13: 50.9 | E13: 49.9 | F13: 54.1
A14: Coal
A15: Reference | B15: 22.6 | C15: 28.7 | D15: 32.6 | E15: 32.6 | F15: 33.5
A16: High prices | B16: 22.6 | C16: 39.3 | D16: 45.7 | E16: 42 | F16: 40
A17: Low Prices | B17: 22.6 | C17: 21.9 | D17: 23.8 | E17: 22.2 | F17: 23.1
B19: 2010 | C19: 2020 | D19: 2030 | E19: 2040 | F19: 2050
A20: Oil P Ref | B20: =B7 -> 84.6 | C20: =C7 -> 88.4 | D20: =D7 -> 105.9 | E20: =E7 -> 116.2 | F20: =F7 -> 126.8
A21: Oil P High | B21: =B8 -> 84.6 | C21: =C8 -> 132.2 | D21: =D8 -> 149.3 | E21: =E8 -> 148.8 | F21: =F8 -> 162.3
A22: Oil P Low | B22: =B9 -> 84.6 | C22: =C9 -> 78.8 | D22: =D9 -> 91.5 | E22: =E9 -> 87.9 | F22: =F9 -> 83.9
A23: Oil T Ref | B23: =[1]POLES!E33 -> 73.831733 | C23: =[1]POLES!G33 -> 84.358357 | D23: =[1]POLES!I33 -> 98.131828 | E23: =[1]POLES!L33 -> 111.98185 | F23: =[1]POLES!M33 -> 114.64982
A24: Oil T Base | B24: =[1]POLES!E36 -> 73.831733 | C24: =[1]POLES!G36 -> 90.109361 | D24: =[1]POLES!I36 -> 112.99791 | E24: =[1]POLES!L36 -> 153.88672 | F24: =[1]POLES!M36 -> 165.75298
A25: Gas P Ref | B25: =B11 -> 53.5 | C25: =C11 -> 62.1 | D25: =D11 -> 76.6 | E25: =E11 -> 86.8 | F25: =F11 -> 98.4
A26: Gas P High | B26: =B12 -> 53.5 | C26: =C12 -> 85.5 | D26: =D12 -> 101.5 | E26: =E12 -> 111.6 | F26: =F12 -> 129
A27: Gas P Low | B27: =B13 -> 53.5 | C27: =C13 -> 43.7 | D27: =D13 -> 50.9 | E27: =E13 -> 49.9 | F27: =F13 -> 54.1
A28: Gas T Ref | B28: =[1]POLES!E34 -> 23.142718 | C28: =[1]POLES!G34 -> 30.903103 | D28: =[1]POLES!I34 -> 34.341529 | E28: =[1]POLES!L34 -> 40.063973 | F28: =[1]POLES!M34 -> 41.104371
A29: Gas T Base | B29: =[1]POLES!E37 -> 23.212543 | C29: =[1]POLES!G37 -> 32.526848 | D29: =[1]POLES!I37 -> 39.069219 | E29: =[1]POLES!L37 -> 53.876146 | F29: =[1]POLES!M37 -> 60.097385
A30: Coal P Ref | B30: =B15 -> 22.6 | C30: =C15 -> 28.7 | D30: =D15 -> 32.6 | E30: =E15 -> 32.6 | F30: =F15 -> 33.5
A31: Coal P High | B31: =B16 -> 22.6 | C31: =C16 -> 39.3 | D31: =D16 -> 45.7 | E31: =E16 -> 42 | F31: =F16 -> 40
A32: Coal P Low | B32: =B17 -> 22.6 | C32: =C17 -> 21.9 | D32: =D17 -> 23.8 | E32: =E17 -> 22.2 | F32: =F17 -> 23.1
A33: Coal T Ref | B33: =[1]POLES!E35 -> 14.942496 | C33: =[1]POLES!G35 -> 16.37357 | D33: =[1]POLES!I35 -> 17.667871 | E33: =[1]POLES!L35 -> 19.549739 | F33: =[1]POLES!M35 -> 20.141291
A34: Coal T Base | B34: =[1]POLES!E38 -> 14.943538 | C34: =[1]POLES!G38 -> 16.961579 | D34: =[1]POLES!I38 -> 18.480519 | E34: =[1]POLES!L38 -> 20.618706 | F34: =[1]POLES!M38 -> 21.306766
A37: PRIMES in eur 2000/GJ
B38: 2010 | C38: 2020 | D38: 2030 | E38: 2040 | F38: 2050
A39: Oil
A40: Reference | B40: =B7*[1]Price_conversion!$C$25*[1]Price_conversion!$C$31/[1]Price_conversion!$B$46 -> 12.188662 | C40: =C7*[1]Price_conversion!$C$25*[1]Price_conversion!$C$31/[1]Price_conversion!$B$46 -> 12.736144 | D40: =D7*[1]Price_conversion!$C$25*[1]Price_conversion!$C$31/[1]Price_conversion!$B$46 -> 15.257439 | E40: =E7*[1]Price_conversion!$C$25*[1]Price_conversion!$C$31/[1]Price_conversion!$B$46 -> 16.741402 | F40: =F7*[1]Price_conversion!$C$25*[1]Price_conversion!$C$31/[1]Price_conversion!$B$46 -> 18.268586
A41: High prices | B41: =B8*[1]Price_conversion!$C$25*[1]Price_conversion!$C$31/[1]Price_conversion!$B$46 -> 12.188662 | C41: =C8*[1]Price_conversion!$C$25*[1]Price_conversion!$C$31/[1]Price_conversion!$B$46 -> 19.046586 | D41: =D8*[1]Price_conversion!$C$25*[1]Price_conversion!$C$31/[1]Price_conversion!$B$46 -> 21.510252 | E41: =E8*[1]Price_conversion!$C$25*[1]Price_conversion!$C$31/[1]Price_conversion!$B$46 -> 21.438215 | F41: =F8*[1]Price_conversion!$C$25*[1]Price_conversion!$C$31/[1]Price_conversion!$B$46 -> 23.383214
A42: Low Prices | B42: =B9*[1]Price_conversion!$C$25*[1]Price_conversion!$C$31/[1]Price_conversion!$B$46 -> 12.188662 | C42: =C9*[1]Price_conversion!$C$25*[1]Price_conversion!$C$31/[1]Price_conversion!$B$46 -> 11.353033 | D42: =D9*[1]Price_conversion!$C$25*[1]Price_conversion!$C$31/[1]Price_conversion!$B$46 -> 13.182773 | E42: =E9*[1]Price_conversion!$C$25*[1]Price_conversion!$C$31/[1]Price_conversion!$B$46 -> 12.664107 | F42: =F9*[1]Price_conversion!$C$25*[1]Price_conversion!$C$31/[1]Price_conversion!$B$46 -> 12.087811
A43: Gas
A44: Reference | B44: =B11*[1]Price_conversion!$C$25*[1]Price_conversion!$C$31/[1]Price_conversion!$B$46 -> 7.7079603 | C44: =C11*[1]Price_conversion!$C$25*[1]Price_conversion!$C$31/[1]Price_conversion!$B$46 -> 8.9469969 | D44: =D11*[1]Price_conversion!$C$25*[1]Price_conversion!$C$31/[1]Price_conversion!$B$46 -> 11.03607 | E44: =E11*[1]Price_conversion!$C$25*[1]Price_conversion!$C$31/[1]Price_conversion!$B$46 -> 12.505625 | F44: =F11*[1]Price_conversion!$C$25*[1]Price_conversion!$C$31/[1]Price_conversion!$B$46 -> 14.176884
A45: High prices | B45: =B12*[1]Price_conversion!$C$25*[1]Price_conversion!$C$31/[1]Price_conversion!$B$46 -> 7.7079603 | C45: =C12*[1]Price_conversion!$C$25*[1]Price_conversion!$C$31/[1]Price_conversion!$B$46 -> 12.318329 | D45: =D12*[1]Price_conversion!$C$25*[1]Price_conversion!$C$31/[1]Price_conversion!$B$46 -> 14.623513 | E45: =E12*[1]Price_conversion!$C$25*[1]Price_conversion!$C$31/[1]Price_conversion!$B$46 -> 16.078661 | F45: =F12*[1]Price_conversion!$C$25*[1]Price_conversion!$C$31/[1]Price_conversion!$B$46 -> 18.585549
A46: Low Prices | B46: =B13*[1]Price_conversion!$C$25*[1]Price_conversion!$C$31/[1]Price_conversion!$B$46 -> 7.7079603 | C46: =C13*[1]Price_conversion!$C$25*[1]Price_conversion!$C$31/[1]Price_conversion!$B$46 -> 6.2960349 | D46: =D13*[1]Price_conversion!$C$25*[1]Price_conversion!$C$31/[1]Price_conversion!$B$46 -> 7.3333678 | E46: =E13*[1]Price_conversion!$C$25*[1]Price_conversion!$C$31/[1]Price_conversion!$B$46 -> 7.1892938 | F46: =F13*[1]Price_conversion!$C$25*[1]Price_conversion!$C$31/[1]Price_conversion!$B$46 -> 7.7944047
A47: Coal
A48: Reference | B48: =B15*[1]Price_conversion!$C$25*[1]Price_conversion!$C$31/[1]Price_conversion!$B$46 -> 3.256073 | C48: =C15*[1]Price_conversion!$C$25*[1]Price_conversion!$C$31/[1]Price_conversion!$B$46 -> 4.1349245 | D48: =D15*[1]Price_conversion!$C$25*[1]Price_conversion!$C$31/[1]Price_conversion!$B$46 -> 4.6968132 | E48: =E15*[1]Price_conversion!$C$25*[1]Price_conversion!$C$31/[1]Price_conversion!$B$46 -> 4.6968132 | F48: =F15*[1]Price_conversion!$C$25*[1]Price_conversion!$C$31/[1]Price_conversion!$B$46 -> 4.8264798
A49: High prices | B49: =B16*[1]Price_conversion!$C$25*[1]Price_conversion!$C$31/[1]Price_conversion!$B$46 -> 3.256073 | C49: =C16*[1]Price_conversion!$C$25*[1]Price_conversion!$C$31/[1]Price_conversion!$B$46 -> 5.6621092 | D49: =D16*[1]Price_conversion!$C$25*[1]Price_conversion!$C$31/[1]Price_conversion!$B$46 -> 6.5841829 | E49: =E16*[1]Price_conversion!$C$25*[1]Price_conversion!$C$31/[1]Price_conversion!$B$46 -> 6.051109 | F49: =F16*[1]Price_conversion!$C$25*[1]Price_conversion!$C$31/[1]Price_conversion!$B$46 -> 5.762961
A50: Low Prices | B50: =B17*[1]Price_conversion!$C$25*[1]Price_conversion!$C$31/[1]Price_conversion!$B$46 -> 3.256073 | C50: =C17*[1]Price_conversion!$C$25*[1]Price_conversion!$C$31/[1]Price_conversion!$B$46 -> 3.1552211 | D50: =D17*[1]Price_conversion!$C$25*[1]Price_conversion!$C$31/[1]Price_conversion!$B$46 -> 3.4289618 | E50: =E17*[1]Price_conversion!$C$25*[1]Price_conversion!$C$31/[1]Price_conversion!$B$46 -> 3.1984433 | F50: =F17*[1]Price_conversion!$C$25*[1]Price_conversion!$C$31/[1]Price_conversion!$B$46 -> 3.32811
A51: PRIMES in eur 2000/GJ
A52: Reference | B52: 2010 | C52: 2020 | D52: 2030 | E52: 2040 | F52: 2050
A53: Oil | B53: =B40 -> 12.188662 | C53: =C40 -> 12.736144 | D53: =D40 -> 15.257439 | E53: =E40 -> 16.741402 | F53: =F40 -> 18.268586
A54: Gas | B54: =B44 -> 7.7079603 | C54: =C44 -> 8.9469969 | D54: =D44 -> 11.03607 | E54: =E44 -> 12.505625 | F54: =F44 -> 14.176884
A55: Coal | B55: =B48 -> 3.256073 | C55: =C48 -> 4.1349245 | D55: =D48 -> 4.6968132 | E55: =E48 -> 4.6968132 | F55: =F48 -> 4.8264798
A56: High prices
A57: Oil | B57: =B41 -> 12.188662 | C57: =C41 -> 19.046586 | D57: =D41 -> 21.510252 | E57: =E41 -> 21.438215 | F57: =F41 -> 23.383214
A58: Gas | B58: =B45 -> 7.7079603 | C58: =C45 -> 12.318329 | D58: =D45 -> 14.623513 | E58: =E45 -> 16.078661 | F58: =F45 -> 18.585549
A59: Coal | B59: =B49 -> 3.256073 | C59: =C49 -> 5.6621092 | D59: =D49 -> 6.5841829 | E59: =E49 -> 6.051109 | F59: =F49 -> 5.762961
A60: Low prices
A61: Oil | B61: =B42 -> 12.188662 | C61: =C42 -> 11.353033 | D61: =D42 -> 13.182773 | E61: =E42 -> 12.664107 | F61: =F42 -> 12.087811
A62: Gas | B62: =B46 -> 7.7079603 | C62: =C46 -> 6.2960349 | D62: =D46 -> 7.3333678 | E62: =E46 -> 7.1892938 | F62: =F46 -> 7.7944047
A63: Coal | B63: =B50 -> 3.256073 | C63: =C50 -> 3.1552211 | D63: =D50 -> 3.4289618 | E63: =E50 -> 3.1984433 | F63: =F50 -> 3.32811

Sheet Worldprices
A1: Source: Energy 2050 Roadmap. Impact assessment 1 - including Part 1 of Annex 1 "Scenarios - assumptions and results" [SEC(2011)1565/1]
C3: (IEA Europe E15 Import Costs) | D3: PRIMES (euro2000/GJ)
C4: 2000 | D4: 2000 | E4: 2001 | F4: 2005 | G4: 2010 | H4: 2015 | I4: 2020 | J4: 2025 | K4: 2030 | L4: =K4+5 -> 2035 | M4: =L4+5 -> 2040 | N4: =M4+5 -> 2045 | O4: =N4+5 -> 2050
A5: ($/boe) | B5: oil | C5: 27.89 | D5: 3.5163711 | E5: 2.9455134 | F5: 5.967172 | G5: ='REF2016 Prices'!B40 -> 9.8196721 | H5: =AVERAGE(G5,I5) -> 9.5648361 | I5: ='REF2016 Prices'!C40 -> 9.31 | J5: =AVERAGE(I5,K5) -> 11.48 | K5: ='REF2016 Prices'!D40 -> 13.65 | L5: =AVERAGE(K5,M5) -> 14.05 | M5: ='REF2016 Prices'!E40 -> 14.45 | N5: =AVERAGE(M5,O5) -> 15.96 | O5: ='REF2016 Prices'!F40 -> 17.47
A6: ($/MBTU) | B6: gas | C6: 2.78 | D6: 2.450666 | E6: 3.182487 | F6: 4.063408 | G6: ='REF2016 Prices'!B44 -> 6.1967213 | H6: =AVERAGE(G6,I6) -> 9.7933607 | I6: ='REF2016 Prices'!C44 -> 13.39 | J6: =AVERAGE(I6,K6) -> 10.195 | K6: ='REF2016 Prices'!D44 -> 7 | L6: =AVERAGE(K6,M6) -> 7 | M6: ='REF2016 Prices'!E44 -> 7 | N6: =AVERAGE(M6,O6) -> 7 | O6: ='REF2016 Prices'!F44 -> 7
A7: ($/ton) | B7: coal | C7: 34.93 | D7: 0.97036858 | E7: 1.0380398 | F7: 1.4745067 | G7: ='REF2016 Prices'!B48 -> 2.6229508 | H7: =AVERAGE(G7,I7) -> 2.9964754 | I7: ='REF2016 Prices'!C48 -> 3.37 | J7: =AVERAGE(I7,K7) -> 3.06 | K7: ='REF2016 Prices'!D48 -> 2.75 | L7: =AVERAGE(K7,M7) -> 2.84 | M7: ='REF2016 Prices'!E48 -> 2.93 | N7: =AVERAGE(M7,O7) -> 3.105 | O7: ='REF2016 Prices'!F48 -> 3.28
B8: coking coal | C8: 47.85 | D8: These in yellow are still from POLES as we do not have these prices in EU2050 Roadmap
A10: Conversion to EURO per GJ for 2000
A11: in EURO2000/GJ
A12: conversion factor | C12: 2000 | D12: 2001 | E12: 2005 | F12: 2010 | G12: 2015 | H12: 2020 | I12: 2025 | J12: 2030 | K12: =J12+5 -> 2035 | L12: =K12+5 -> 2040 | M12: =L12+5 -> 2045 | N12: =M12+5 -> 2050
A13: ='common data'!B19 -> 6.1 | B13: oil | C13: =C5/A13/'common data'!B54 -> 4.9503369 | D13: =C13*E5/D5 -> 4.1466851 | E13: =D13*F5/E5 -> 8.4005671 | F13: =G5 -> 9.8196721 | G13: =H5 -> 9.5648361 | H13: =I5 -> 9.31 | I13: =J5 -> 11.48 | J13: =K5 -> 13.65 | K13: =L5 -> 14.05 | L13: =M5 -> 14.45 | M13: =N5 -> 15.96 | N13: =O5 -> 17.47
A14: ='common data'!B20 -> 1.054 | B14: gas | C14: =C6/A14/'common data'!B54 -> 2.8557505 | D14: =C14*E6/D6 -> 3.7085383 | E14: =D14*F6/E6 -> 4.7350718 | F14: =G6 -> 6.1967213 | G14: =H6 -> 9.7933607 | H14: =I6 -> 13.39 | I14: =J6 -> 10.195 | J14: =K6 -> 7 | K14: =L6 -> 7 | L14: =M6 -> 7 | M14: =N6 -> 7 | N14: =O6 -> 7
A15: ='common data'!B23 -> 28.1 | B15: coal | C15: =C7/A15/'common data'!B54 -> 1.3458862 | D15: =C15*E7/D7 -> 1.4397452 | E15: =D15*F7/E7 -> 2.045118 | F15: =G7 -> 2.6229508 | G15: =H7 -> 2.9964754 | H15: =I7 -> 3.37 | I15: =J7 -> 3.06 | J15: =K7 -> 2.75 | K15: =L7 -> 2.84 | L15: =M7 -> 2.93 | M15: =N7 -> 3.105 | N15: =O7 -> 3.28
C16: The prices in yellow are estimated from 2000 real prices from an unclear source and assuming the same growth rate as from the POLES prices from 2000-2005. SSimoes ESE-IET 09/April 2013
A18: Going from Crude/Coal to Refined Products
A19: Coal to coke | B19: 1.27
A20: Coal to brown coal | B20: 0.95
A21: Coal to Lignite | B21: =B20 -> 0.95
A22: Crude to Heavy Fuel | B22: 0.81 | D22: =B22*$C$13-$C$13 -> -0.94056401
A23: Crude to Light Distillate | B23: 1.3 | D23: =B23*$C$13-$C$13 -> 1.4851011
A24: Crude to LPG | B24: 1.1 | D24: =B24*$C$13-$C$13 -> 0.49503369
A25: Crude to Gasoline | B25: 1.4 | D25: =B25*$C$13-$C$13 -> 1.9801348
A26: Crude to Naphta, Fdst & NEU | B26: 1 | D26: =B26*$C$13-$C$13 -> 0
A29: Prices for TIMES
A31: Price for Import of Fuels (basic import price to which to add the delivery cost to have the final consumer price without taxes)
A32: EURO/GJ
C33: 2000 | D33: 2001 | E33: 2005 | F33: 2010 | G33: 2015 | H33: 2020 | I33: 2025 | J33: 2030 | K33: =J33+5 -> 2035 | L33: =K33+5 -> 2040 | M33: =L33+5 -> 2045 | N33: =M33+5 -> 2050
A34: Coal | C34: =C15 -> 1.3458862 | D34: =C34*D15/C15 -> 1.4397452 | E34: =D34*E15/D15 -> 2.045118 | F34: =E34*F15/E15 -> 2.6229508 | G34: =F34*G15/F15 -> 2.9964754 | H34: =G34*H15/G15 -> 3.37 | I34: =H34*I15/H15 -> 3.06 | J34: =I34*J15/I15 -> 2.75 | K34: =J34*K15/J15 -> 2.84 | ... N34: =M34*N15/M15 -> 3.28
A35: Coke (rel coal) | C35: =$B19*C34 -> 1.7092755 | D35: =$B19*D34 -> 1.8284764 | E35: =$B19*E34 -> 2.5972998 | F35: =$B19*F34 -> 3.3311475 | G35: =$B19*G34 -> 3.8055238 | H35: =$B19*H34 -> 4.2799 | I35: =$B19*I34 -> 3.8862 | J35: =$B19*J34 -> 3.4925 | ... N35: =$B19*N34 -> 4.1656
A36: Brown coal | C36: =$B20*C34 -> 1.2785919 | D36: =$B20*D34 -> 1.3677579 | E36: =$B20*E34 -> 1.9428621 | F36: =$B20*F34 -> 2.4918033 | G36: =$B20*G34 -> 2.8466516 | H36: =$B20*H34 -> 3.2015 | I36: =$B20*I34 -> 2.907 | J36: =$B20*J34 -> 2.6125 | ... N36: =$B20*N34 -> 3.116
A37: Lignite | C37: =$B21*C34 -> 1.2785919 | D37: =$B21*D34 -> 1.3677579 | E37: =$B21*E34 -> 1.9428621 | F37: =$B21*F34 -> 2.4918033 | G37: =$B21*G34 -> 2.8466516 | H37: =$B21*H34 -> 3.2015 | I37: =$B21*I34 -> 2.907 | J37: =$B21*J34 -> 2.6125 | ... N37: =$B21*N34 -> 3.116
A38: Crude | C38: =C13 -> 4.9503369 | D38: =C38*D13/C13 -> 4.1466851 | E38: =D38*E13/D13 -> 8.4005671 | F38: =E38*F13/E13 -> 9.8196721 | G38: =F38*G13/F13 -> 9.5648361 | H38: =G38*H13/G13 -> 9.31 | I38: =H38*I13/H13 -> 11.48 | J38: =I38*J13/I13 -> 13.65 | K38: =J38*K13/J13 -> 14.05 | ... N38: =M38*N13/M13 -> 17.47
A39: Heavy Distillate Oil | C39: =$B22*C38 -> 4.0097729 | D39: =$B22*D38 -> 3.358815 | E39: =$B22*E38 -> 6.8044594 | F39: =$B22*F38 -> 7.9539344 | G39: =$B22*G38 -> 7.7475172 | H39: =$B22*H38 -> 7.5411 | I39: =$B22*I38 -> 9.2988 | J39: =$B22*J38 -> 11.0565 | ... N39: =$B22*N38 -> 14.1507
A40: Light Distilate Oil | C40: =$B23*C38 -> 6.435438 | D40: =$B23*D38 -> 5.3906907 | E40: =$B23*E38 -> 10.920737 | F40: =$B23*F38 -> 12.765574 | G40: =$B23*G38 -> 12.434287 | H40: =$B23*H38 -> 12.103 | I40: =$B23*I38 -> 14.924 | J40: =$B23*J38 -> 17.745 | ... N40: =$B23*N38 -> 22.711
A41: LPG | C41: =$B24*C38 -> 5.4453706 | D41: =$B24*D38 -> 4.5613537 | E41: =$B24*E38 -> 9.2406239 | F41: =$B24*F38 -> 10.801639 | G41: =$B24*G38 -> 10.52132 | H41: =$B24*H38 -> 10.241 | I41: =$B24*I38 -> 12.628 | J41: =$B24*J38 -> 15.015 | ... N41: =$B24*N38 -> 19.217
A42: Gasoline | C42: =$B25*C38 -> 6.9304716 | D42: =$B25*D38 -> 5.8053592 | E42: =$B25*E38 -> 11.760794 | F42: =$B25*F38 -> 13.747541 | G42: =$B25*G38 -> 13.39077 | H42: =$B25*H38 -> 13.034 | I42: =$B25*I38 -> 16.072 | J42: =$B25*J38 -> 19.11 | ... N42: =$B25*N38 -> 24.458
A43: Kerosene | C43: =C42 -> 6.9304716 | D43: =D42 -> 5.8053592 | E43: =E42 -> 11.760794 | F43: =F42 -> 13.747541 | G43: =G42 -> 13.39077 | H43: =H42 -> 13.034 | I43: =I42 -> 16.072 | J43: =J42 -> 19.11 | ... N43: =N42 -> 24.458
A44: other oil products | C44: =$B$26*C$38 -> 4.9503369 | D44: =$B$26*D$38 -> 4.1466851 | E44: =$B$26*E$38 -> 8.4005671 | F44: =$B$26*F$38 -> 9.8196721 | G44: =$B$26*G$38 -> 9.5648361 | H44: =$B$26*H$38 -> 9.31 | I44: =$B$26*I$38 -> 11.48 | J44: =$B$26*J$38 -> 13.65 | ... N44: =$B$26*N$38 -> 17.47
A45: Naphta | C45: =$B$26*C$38 -> 4.9503369 | D45: =$B$26*D$38 -> 4.1466851 | E45: =$B$26*E$38 -> 8.4005671 | F45: =$B$26*F$38 -> 9.8196721 | G45: =$B$26*G$38 -> 9.5648361 | H45: =$B$26*H$38 -> 9.31 | I45: =$B$26*I$38 -> 11.48 | J45: =$B$26*J$38 -> 13.65 | ... N45: =$B$26*N$38 -> 17.47
A46: Feedstock | C46: =$B$26*C$38 -> 4.9503369 | D46: =$B$26*D$38 -> 4.1466851 | E46: =$B$26*E$38 -> 8.4005671 | F46: =$B$26*F$38 -> 9.8196721 | G46: =$B$26*G$38 -> 9.5648361 | H46: =$B$26*H$38 -> 9.31 | I46: =$B$26*I$38 -> 11.48 | J46: =$B$26*J$38 -> 13.65 | ... N46: =$B$26*N$38 -> 17.47
A47: Non energy use | C47: =$B$26*C$38 -> 4.9503369 | D47: =$B$26*D$38 -> 4.1466851 | E47: =$B$26*E$38 -> 8.4005671 | F47: =$B$26*F$38 -> 9.8196721 | G47: =$B$26*G$38 -> 9.5648361 | H47: =$B$26*H$38 -> 9.31 | I47: =$B$26*I$38 -> 11.48 | J47: =$B$26*J$38 -> 13.65 | ... N47: =$B$26*N$38 -> 17.47
A48: Natural Gas | C48: =C14 -> 2.8557505 | D48: =C48*D14/C14 -> 3.7085383 | E48: =D48*E14/D14 -> 4.7350718 | F48: =E48*F14/E14 -> 6.1967213 | G48: =F48*G14/F14 -> 9.7933607 | H48: =G48*H14/G14 -> 13.39 | I48: =H48*I14/H14 -> 10.195 | J48: =I48*J14/I14 -> 7 | K48: =J48*K14/J14 -> 7 | ... N48: =M48*N14/M14 -> 7
A49: LWR Fabricated Fuel | C49: 0.8 | D49: =C49 -> 0.8 | E49: =D49 -> 0.8 | F49: =E49 -> 0.8 | G49: =F49 -> 0.8 | H49: =G49 -> 0.8 | I49: =H49 -> 0.8 | J49: =I49 -> 0.8 | K49: =J49 -> 0.8 | ... N49: =M49 -> 0.8
A51: Municipal Waste | C51: 1.9831482 | D51: 1.9831482 | E51: 1.9831482 | F51: 1.9831482 | G51: 1.9831482 | H51: 1.9831482 | I51: 1.9831482 | J51: 1.9831482 | K51: 1.9831482 | L51: 1.9831482 | M51: 1.9831482 | N51: 1.9831482
A61: Table with the prices to be used for the import table for VEDA
B62: Technology | C62: ="IMP"&C63&"*" -> IMPCOAHAR* | D62: ="IMP"&D63&"*" -> IMPCOACOK* | E62: ="IMP"&E63&"*" -> IMPCOABRO* | F62: ="IMP"&F63&"*" -> IMPCOALIG* | G62: ="IMP"&G63 -> IMPOILCRD | H62: ="IMP"&H63 -> IMPOILHFO | I62: ="IMP"&I63 -> IMPOILDST | J62: ="IMP"&J63 -> IMPOILLPG | K62: ="IMP"&K63 -> IMPOILGSL | L62: ="IMP"&L63 -> IMPOILKER | M62: ="IMP"&M63 -> IMPOILOTH | N62: ="IMP"&N63 -> IMPOILNAP | ... R62: ="IMP"&R63 -> IMPBIOWOO | S62: ="IMP"&S63&"B" -> IMPBIOWOOB | T62: ="IMP"&T63 -> IMPNUCRSV | U62: ="MIN"&U63 -> MINBIOMUN
B63: Fuel | C63: COAHAR | D63: COACOK | E63: COABRO | F63: COALIG | G63: OILCRD | H63: OILHFO | I63: OILDST | J63: OILLPG | K63: OILGSL | L63: OILKER | M63: OILOTH | N63: OILNAP | O63: OILFDS | P63: OILNEU | Q63: GASNAT | R63: BIOWOO | S63: BIOWOO | T63: NUCRSV | U63: BIOMUN
A64: Level | B64: 2000 | C64: =$C34 -> 1.3458862 | D64: =$C35 -> 1.7092755 | E64: =$C36 -> 1.2785919 | F64: =$C37 -> 1.2785919 | G64: =$C38 -> 4.9503369 | H64: =$C39 -> 4.0097729 | I64: =$C40 -> 6.435438 | J64: =$C41 -> 5.4453706 | K64: =$C42 -> 6.9304716 | L64: =$C43 -> 6.9304716 | M64: =$C44 -> 4.9503369 | N64: =$C45 -> 4.9503369 | O64: =$C46 -> 4.9503369 | P64: =$C47 -> 4.9503369 | Q64: =$C48 -> 2.8557505 | R64: =$C101 -> 3.0314706 | S64: =$C102 -> 3.6377647 | T64: =$C49 -> 0.8 | U64: =$C51 -> 1.9831482
B65: 2001 | C65: =$D$34 -> 1.4397452 | D65: =$D$35 -> 1.8284764 | E65: =$D$36 -> 1.3677579 | F65: =$D$37 -> 1.3677579 | G65: =$D$38 -> 4.1466851 | H65: =$D$39 -> 3.358815 | I65: =$D$40 -> 5.3906907 | J65: =$D$41 -> 4.5613537 | K65: =$D$42 -> 5.8053592 | L65: =$D$43 -> 5.8053592 | M65: =$D$44 -> 4.1466851 | N65: =$D$45 -> 4.1466851 | O65: =$D$46 -> 4.1466851 | P65: =$D$47 -> 4.1466851 | Q65: =$D$48 -> 3.7085383 | R65: =$D$101 -> 3.0860371 | S65: =$D$102 -> 3.7032445 | T65: =$D$49 -> 0.8 | U65: =$D$51 -> 1.9831482
B66: 2005 | C66: =$E$34 -> 2.045118 | D66: =$E$35 -> 2.5972998 | E66: =$E$36 -> 1.9428621 | F66: =$E$37 -> 1.9428621 | G66: =$E$38 -> 8.4005671 | H66: =$E$39 -> 6.8044594 | I66: =$E$40 -> 10.920737 | J66: =$E$41 -> 9.2406239 | K66: =$E$42 -> 11.760794 | L66: =$E$43 -> 11.760794 | M66: =$E$44 -> 8.4005671 | N66: =$E$45 -> 8.4005671 | O66: =$E$46 -> 8.4005671 | P66: =$E$47 -> 8.4005671 | Q66: =$E$48 -> 4.7350718 | R66: =$E$101 -> 3.3143033 | S66: =$E$102 -> 3.977164 | T66: =$E$49 -> 0.8 | U66: =$E$51 -> 1.9831482
B67: 2010 | C67: =$F$34 -> 2.6229508 | D67: =$F$35 -> 3.3311475 | E67: =$F$36 -> 2.4918033 | F67: =$F$37 -> 2.4918033 | G67: =$F$38 -> 9.8196721 | H67: =$F$39 -> 7.9539344 | I67: =$F$40 -> 12.765574 | J67: =$F$41 -> 10.801639 | K67: =$F$42 -> 13.747541 | L67: =$F$43 -> 13.747541 | M67: =$F$44 -> 9.8196721 | N67: =$F$45 -> 9.8196721 | O67: =$F$46 -> 9.8196721 | P67: =$F$47 -> 9.8196721 | Q67: =$F$48 -> 6.1967213 | R67: =$F$101 -> 3.623524 | S67: =$F$102 -> 4.3482288 | T67: =$F$49 -> 0.8 | U67: =$F$51 -> 1.9831482
B68: 2015 | C68: =$G$34 -> 2.9964754 | D68: =$G$35 -> 3.8055238 | E68: =$G$36 -> 2.8466516 | F68: =$G$37 -> 2.8466516 | G68: =$G$38 -> 9.5648361 | H68: =$G$39 -> 7.7475172 | I68: =$G$40 -> 12.434287 | J68: =$G$41 -> 10.52132 | K68: =$G$42 -> 13.39077 | L68: =$G$43 -> 13.39077 | M68: =$G$44 -> 9.5648361 | N68: =$G$45 -> 9.5648361 | O68: =$G$46 -> 9.5648361 | P68: =$G$47 -> 9.5648361 | Q68: =$G$48 -> 9.7933607 | R68: =$G$101 -> 3.9615946 | S68: =$G$102 -> 4.7539135 | T68: =$G$49 -> 0.8 | U68: =$G$51 -> 1.9831482
B69: 2020 | C69: =$H$34 -> 3.37 | D69: =$H$35 -> 4.2799 | E69: =$H$36 -> 3.2015 | F69: =$H$37 -> 3.2015 | G69: =$H$38 -> 9.31 | H69: =$H$39 -> 7.5411 | I69: =$H$40 -> 12.103 | J69: =$H$41 -> 10.241 | K69: =$H$42 -> 13.034 | L69: =$H$43 -> 13.034 | M69: =$H$44 -> 9.31 | N69: =$H$45 -> 9.31 | O69: =$H$46 -> 9.31 | P69: =$H$47 -> 9.31 | Q69: =$H$48 -> 13.39 | R69: =$H$101 -> 4.3312068 | S69: =$H$102 -> 5.1974481 | T69: =$H$49 -> 0.8 | U69: =$H$51 -> 1.9831482
B70: 2025 | C70: =$I$34 -> 3.06 | D70: =$I$35 -> 3.8862 | E70: =$I$36 -> 2.907 | F70: =$I$37 -> 2.907 | G70: =$I$38 -> 11.48 | H70: =$I$39 -> 9.2988 | I70: =$I$40 -> 14.924 | J70: =$I$41 -> 12.628 | K70: =$I$42 -> 16.072 | L70: =$I$43 -> 16.072 | M70: =$I$44 -> 11.48 | N70: =$I$45 -> 11.48 | O70: =$I$46 -> 11.48 | P70: =$I$47 -> 11.48 | Q70: =$I$48 -> 10.195 | R70: =$I$101 -> 4.7353034 | S70: =$I$102 -> 5.6823641 | T70: =$I$49 -> 0.8 | U70: =$I$51 -> 1.9831482
B71: 2030 | C71: =$J$34 -> 2.75 | D71: =$J$35 -> 3.4925 | E71: =$J$36 -> 2.6125 | F71: =$J$37 -> 2.6125 | G71: =$J$38 -> 13.65 | H71: =$J$39 -> 11.0565 | I71: =$J$40 -> 17.745 | J71: =$J$41 -> 15.015 | K71: =$J$42 -> 19.11 | L71: =$J$43 -> 19.11 | M71: =$J$44 -> 13.65 | N71: =$J$45 -> 13.65 | O71: =$J$46 -> 13.65 | P71: =$J$47 -> 13.65 | Q71: =$J$48 -> 7 | R71: =$J$101 -> 5.1771017 | S71: =$J$102 -> 6.2125221 | T71: =$J$49 -> 0.8 | U71: =$J$51 -> 1.9831482
B72: 2035 | C72: =$K$34 -> 2.84 | D72: =$K$35 -> 3.6068 | E72: =$K$36 -> 2.698 | F72: =$K$37 -> 2.698 | G72: =$K$38 -> 14.05 | H72: =$K$39 -> 11.3805 | I72: =$K$40 -> 18.265 | J72: =$K$41 -> 15.455 | K72: =$K$42 -> 19.67 | L72: =$K$43 -> 19.67 | M72: =$K$44 -> 14.05 | N72: =$K$45 -> 14.05 | O72: =$K$46 -> 14.05 | P72: =$K$47 -> 14.05 | Q72: =$K$48 -> 7 | R72: =$K$101 -> 5.6601194 | S72: =$K$102 -> 6.7921432 | T72: =$K$49 -> 0.8 | U72: =$K$51 -> 1.9831482
B73: 2040 | C73: =$L$34 -> 2.93 | D73: =$L$35 -> 3.7211 | E73: =$L$36 -> 2.7835 | F73: =$L$37 -> 2.7835 | G73: =$L$38 -> 14.45 | H73: =$L$39 -> 11.7045 | I73: =$L$40 -> 18.785 | J73: =$L$41 -> 15.895 | K73: =$L$42 -> 20.23 | L73: =$L$43 -> 20.23 | M73: =$L$44 -> 14.45 | N73: =$L$45 -> 14.45 | O73: =$L$46 -> 14.45 | P73: =$L$47 -> 14.45 | Q73: =$L$48 -> 7 | R73: =$L$101 -> 6.188202 | S73: =$L$102 -> 7.4258424 | T73: =$L$49 -> 0.8 | U73: =$L$51 -> 1.9831482
B74: 2045 | C74: =$M$34 -> 3.105 | D74: =$M$35 -> 3.94335 | E74: =$M$36 -> 2.94975 | F74: =$M$37 -> 2.94975 | G74: =$M$38 -> 15.96 | H74: =$M$39 -> 12.9276 | I74: =$M$40 -> 20.748 | J74: =$M$41 -> 17.556 | K74: =$M$42 -> 22.344 | L74: =$M$43 -> 22.344 | M74: =$M$44 -> 15.96 | N74: =$M$45 -> 15.96 | O74: =$M$46 -> 15.96 | P74: =$M$47 -> 15.96 | Q74: =$M$48 -> 7 | R74: =$M$101 -> 6.7655541 | S74: =$M$102 -> 8.1186649 | T74: =$M$49 -> 0.8 | U74: =$M$51 -> 1.9831482
B75: 2050 | C75: =$N$34 -> 3.28 | D75: =$N$35 -> 4.1656 | E75: =$N$36 -> 3.116 | F75: =$N$37 -> 3.116 | G75: =$N$38 -> 17.47 | H75: =$N$39 -> 14.1507 | I75: =$N$40 -> 22.711 | J75: =$N$41 -> 19.217 | K75: =$N$42 -> 24.458 | L75: =$N$43 -> 24.458 | M75: =$N$44 -> 17.47 | N75: =$N$45 -> 17.47 | O75: =$N$46 -> 17.47 | P75: =$N$47 -> 17.47 | Q75: =$N$48 -> 7 | R75: =$N$101 -> 7.3967725 | S75: =$N$102 -> 8.876127 | T75: =$N$49 -> 0.8 | U75: =$N$51 -> 1.9831482
A78: Growth of oil and gas price for evolution of domestic produced oil and gas
A99: BIOfuel and mining biocrop are put in the BIOCOST scenario
A101: BioWood imp | C101: =C107*1.1 -> 3.0314706 | D101: =D107*1.1 -> 3.0860371 | E101: =E107*1.1 -> 3.3143033 | F101: =F107*1.1 -> 3.623524 | G101: =G107*1.1 -> 3.9615946 | H101: =H107*1.1 -> 4.3312068 | I101: =I107*1.1 -> 4.7353034 | J101: =J107*1.1 -> 5.1771017 | ... N101: =N107*1.1 -> 7.3967725
A102: WOODB +20% | B102: 1.2 | C102: =C101*$B$102 -> 3.6377647 | D102: =D101*$B$102 -> 3.7032445 | E102: =E101*$B$102 -> 3.977164 | F102: =F101*$B$102 -> 4.3482288 | G102: =G101*$B$102 -> 4.7539135 | H102: =H101*$B$102 -> 5.1974481 | I102: =I101*$B$102 -> 5.6823641 | J102: =J101*$B$102 -> 6.2125221 | ... N102: =N101*$B$102 -> 8.876127
A103: from Belgium source
A106: Wood residue | B106: 0.02 | C106: 1.1 | D106: =C106*(1+$B$106) -> 1.122 | E106: =D106*(1+$B$106)^4 -> 1.2144889 | F106: =E106*(1+$B$106)^5 -> 1.3408939 | G106: =F106*(1+$B$106)^5 -> 1.4804552 | H106: =G106*(1+$B$106)^5 -> 1.6345421 | I106: =H106*(1+$B$106)^5 -> 1.8046666 | J106: =I106*(1+$B$106)^5 -> 1.9924977 | K106: =J106*(1+$B$106)^5 -> 2.1998785 | L106: =K106*(1+$B$106)^5 -> 2.4288436 | M106: =L106*(1+$B$106)^5 -> 2.6816396 | N106: =M106*(1+$B$106)^5 -> 2.9607468
A107: Bio Wood nat | B107: 0.018 | C107: 2.7558824 | D107: =C107*(1+$B$107) -> 2.8054882 | E107: =D107*(1+$B$107)^4 -> 3.013003 | F107: =E107*(1+$B$107)^5 -> 3.2941127 | G107: =F107*(1+$B$107)^5 -> 3.6014496 | H107: =G107*(1+$B$107)^5 -> 3.9374607 | I107: =H107*(1+$B$107)^5 -> 4.3048213 | J107: =I107*(1+$B$107)^5 -> 4.7064561 | K107: =J107*(1+$B$107)^5 -> 5.145563 | L107: =K107*(1+$B$107)^5 -> 5.6256381 | M107: =L107*(1+$B$107)^5 -> 6.1505037 | N107: =M107*(1+$B$107)^5 -> 6.7243386
A108: Bio Wood nat (MINWOO3) | C108: =C107*1.3 -> 3.5826471 | D108: =C108*(1+$B$107) -> 3.6471347 | E108: =D108*(1+$B$107)^4 -> 3.9169039 | F108: =E108*(1+$B$107)^5 -> 4.2823465 | G108: =F108*(1+$B$107)^5 -> 4.6818845 | H108: =G108*(1+$B$107)^5 -> 5.1186989 | I108: =H108*(1+$B$107)^5 -> 5.5962676 | J108: =I108*(1+$B$107)^5 -> 6.118393 | K108: =J108*(1+$B$107)^5 -> 6.689232 | L108: =K108*(1+$B$107)^5 -> 7.3133296 | M108: =L108*(1+$B$107)^5 -> 7.9956548 | N108: =M108*(1+$B$107)^5 -> 8.7416402
B109: gr per year

Sheet MaterialPrices
A1: Materials which need prices are those which have an influence on technology choices
A3: The materials in TIMES are
B5: tech | C5: mat | F5: M€/Mt
A6: MAT | B6: MINMISORE1 | C6: MISORE | D6: Iron and Steel: Ore | F6: 80 | G6: =F6 -> 80 | H6: prices 2007, google
B7: MINMISSCR1 | C7: MISSCR | D7: Iron and Steel: Scrap Iron | F7: =390/3 -> 130 | G7: =F7 -> 130 | H7: one third of steel price
B8: MINMISOXY1 | C8: MISOXY | D8: Iron and Steel: Oxygen | F8: 10 | G8: =F8 -> 10 | H8: (density is about 1.4 kg/Nm3)
B9: MINMISQLI1 | C9: MISQLI | D9: Iron and Steel: Quick Lime | F9: 70 | G9: =F9 -> 70
B10: MINMLMSTN1 | C10: MLMSTN | D10: Lime: Limestone | F10: 50 | G10: =F10 -> 50
B11: MINMGHRYC1 | C11: MGHRYC | D11: Glass: Recycled | F11: 10 | G11: =F11 -> 10
B12: MINMPPWOO1 | C12: MPPWOO | D12: Paper: Wood | F12: 81 | G12: 200 | H12: Stookwaarde: 15GJ/ton, geeft dus ongeveer 2 €/GJ | M12: from IER | N12: (BE = 30)
B13: MINMPPRYC1 | C13: MPPRYC | D13: Paper: Recycled | F13: =450/3 -> 150 | G13: =F13 -> 150 | H13: one third of paper price
B14: MINMPPNOH1 | C14: MPPNOH | D14: Paper: Sodium Hydraxide
B15: MINMPPOXY1 | C15: MPPOXY | D15: Paper: Oxygen | F15: 10 | G15: =F15 -> 10
B16: MINMPPKAO1 | C16: MPPKAO | D16: Paper: Kaolin | F16: 150 | G16: =F16 -> 150
B17: MINMPPGYP1 | C17: MPPGYP | D17: Paper: Gypsum | F17: 20 | G17: =F17 -> 20
B18: MINMALBAU1 | C18: MALBAU | F18: =0.1191*1000 -> 119.1
B19: MINMALSCR1 | C19: MALSCR | F19: =1.1645*1000 -> 1164.5
B20: MINMCUORE1 | C20: MCUORE | F20: =0.743*1000 -> 743
B21: MINMCUSCR1 | C21: MCUSCR | F21: =0.9839*1000 -> 983.9
A24: Voor biomass heb ik | C24: EURO/GJ
C25: 2000 | D25: 2005 | E25: 2010 | F25: 2015 | G25: 2020 | H25: 2025 | I25: 2030 | J25: 2035 | K25: 2040 | L25: 2045 | M25: 2050
A26: Municipal Waste | B26: BIOMUN | C26: 1.9831482 | D26: 1.9831482 | E26: 1.9831482 | F26: 1.9831482 | G26: 1.9831482 | H26: 1.9831482 | I26: 1.9831482 | J26: 1.9831482 | K26: 1.9831482 | L26: 1.9831482 | M26: 1.9831482
A27: Bio Wood nat | B27: BIOWOO | C27: 2.7558824 | D27: 3.013003 | E27: 3.2941127 | F27: 3.6014496 | G27: 3.9374607 | H27: 4.3048213 | I27: 4.7064561 | J27: 5.145563 | K27: 5.6256381 | L27: 6.1505037 | M27: 6.7243386 | O27: 0.018
A28: Wood residue | B28: BIOWOO | C28: 1.1 | D28: 1.2144889 | E28: 1.3408939 | F28: 1.4804552 | G28: 1.6345421 | H28: 1.8046666 | I28: 1.9924977 | J28: 2.1998785 | K28: 2.4288436 | L28: 2.6816396 | M28: 2.9607468 | O28: 0.02
A30: BioWood imp | B30: BIOWOO | C30: 3.0314706 | D30: 3.3143033 | E30: 3.623524 | F30: 3.9615946 | G30: 4.3312068 | H30: 4.7353034 | I30: 5.1771017 | J30: 5.6601194 | K30: 6.188202 | L30: 6.7655541 | M30: 7.3967725
A31: BioWoodImpB | B31: BIOWOO | C31: 3.6377647 | D31: 3.977164 | E31: 4.3482288 | F31: 4.7539135 | G31: 5.1974481 | H31: 5.6823641 | I31: 6.2125221 | J31: 6.7921432 | K31: 7.4258424 | L31: 8.1186649 | M31: 8.876127
B35: IISBOXFUR00 | C35: IIS.Blast Oxygen Furnace BOF.Regular.00. | G35: Simplified material cost
B36: MISRIR | D36: 0.85 | G36: =D36*D47*D61*F6 -> 104.72 | H36: €/ton
B37: MISSCR | D37: 0.25 | G37: =D37*F7 -> 32.5
B38: MISQLI | D38: 0.05 | G38: =SUM(G36:G37) -> 137.22
B39: MISOXY | D39: 0.05 | G39: 150 | H39: energy cost from Veda
B40: INDGAS | D40: 0.2
C41: MISCST | E41: 1
C42: GASBFG
B45: IISBLAFUR00 | C45: IIS.Iron Blast Furnace.00.
B46: MISPLT | D46: 0.04
B47: MISSNT | D47: 1.54
B48: MISOXY | D48: 0.05
B49: INDCOK | D49: =8.75-1.3 -> 7.45
B50: INDCOA | D50: 5.5
B51: INDHFO | D51: 0
B52: INDELC | D52: 0.17
B53: INDBFG | D53: =1.75-1.75 -> 0
C54: MISRIR | E54: 1
C55: MISBFS | E55: 0.25
C56: GASBFG | E56: =5-1.75 -> 3.25
B59: IISSINTER00 | C59: IIS.Sinter Production.00.
B61: MISORE | D61: 1
B62: INDCOK | D62: 1.16
B63: INDCOG | D63: 0.66
B64: INDELC | D64: 0.1
C65: MISSNT | E65: 1

Sheet INPUTtoVEDAMatPrices
A2: ~TFM_INS
A3: TimeSlice | B3: LimType | C3: Attribute | D3: Year | E3: AllRegions | F3: Pset_CO | G3: Pset_PN | H3: Cset_CN
A4: ANNUAL | C4: COST | E4: =MaterialPrices!G6 -> 80 | F4: =MaterialPrices!C6 -> MISORE | G4: =MaterialPrices!B6 -> MINMISORE1 | H4: =F4 -> MISORE
A5: ANNUAL | C5: COST | E5: =MaterialPrices!G7 -> 130 | F5: =MaterialPrices!C7 -> MISSCR | G5: =MaterialPrices!B7 -> MINMISSCR1 | H5: =F5 -> MISSCR
A6: ANNUAL | C6: COST | E6: =MaterialPrices!G8 -> 10 | F6: =MaterialPrices!C8 -> MISOXY | G6: =MaterialPrices!B8 -> MINMISOXY1 | H6: =F6 -> MISOXY
A7: ANNUAL | C7: COST | E7: =MaterialPrices!G9 -> 70 | F7: =MaterialPrices!C9 -> MISQLI | G7: =MaterialPrices!B9 -> MINMISQLI1 | H7: =F7 -> MISQLI
A8: ANNUAL | C8: COST | E8: =MaterialPrices!G10 -> 50 | F8: =MaterialPrices!C10 -> MLMSTN | G8: =MaterialPrices!B10 -> MINMLMSTN1 | H8: =F8 -> MLMSTN
A9: ANNUAL | C9: COST | E9: =MaterialPrices!G11 -> 10 | F9: =MaterialPrices!C11 -> MGHRYC | G9: =MaterialPrices!B11 -> MINMGHRYC1 | H9: =F9 -> MGHRYC
A10: ANNUAL | C10: COST | E10: =MaterialPrices!G12 -> 200 | F10: =MaterialPrices!C12 -> MPPWOO | G10: =MaterialPrices!B12 -> MINMPPWOO1 | H10: =F10 -> MPPWOO
A11: ANNUAL | C11: COST | E11: =MaterialPrices!G13 -> 150 | F11: =MaterialPrices!C13 -> MPPRYC | G11: =MaterialPrices!B13 -> MINMPPRYC1 | H11: =F11 -> MPPRYC
A12: ANNUAL | C12: COST | E12: =MaterialPrices!G14 -> 0 | F12: =MaterialPrices!C14 -> MPPNOH | G12: =MaterialPrices!B14 -> MINMPPNOH1 | H12: =F12 -> MPPNOH
A13: ANNUAL | C13: COST | E13: =MaterialPrices!G15 -> 10 | F13: =MaterialPrices!C15 -> MPPOXY | G13: =MaterialPrices!B15 -> MINMPPOXY1 | H13: =F13 -> MPPOXY
A14: ANNUAL | C14: COST | E14: =MaterialPrices!G16 -> 150 | F14: =MaterialPrices!C16 -> MPPKAO | G14: =MaterialPrices!B16 -> MINMPPKAO1 | H14: =F14 -> MPPKAO
A15: ANNUAL | C15: COST | E15: =MaterialPrices!G17 -> 20 | F15: =MaterialPrices!C17 -> MPPGYP | G15: =MaterialPrices!B17 -> MINMPPGYP1 | H15: =F15 -> MPPGYP
... A19: ANNUAL | C19: COST | E19: =MaterialPrices!G21 -> 0 | F19: =MaterialPrices!C21 -> MCUSCR | G19: =MaterialPrices!B21 -> MINMCUSCR1 | H19: =F19 -> MCUSCR

Sheet INPUTtoVEDA_importprice TR
A1: Adjustment factors derived from the computation of the delivery cost
H3: AT | I3: BE | K3: DE | L3: DK | M3: FI | N3: FR | O3: EL | P3: IE | Q3: IT | R3: NL | S3: PT | T3: ES | U3: SE | V3: UK | W3: HU | X3: PL | Y3: CZ | Z3: SK | AA3: CH | AB3: CY | AC3: EE | AD3: IS | AE3: LT | AF3: LU | AG3: LV | AH3: MT | AI3: RO | AJ3: SI | AK3: NO | AL3: AL | AM3: BH | AN3: HR | AO3: ME | AP3: MK | AQ3: RS | AR3: KS
D4: Coal | H4: 1 | I4: 0.935 | K4: 1 | L4: 1 | M4: 1 | N4: 1 | O4: 1 | P4: 0.85 | Q4: 0.95 | R4: 1 | S4: 0.85 | T4: 1 | U4: 1 | V4: 1 | W4: 1 | X4: 1 | Y4: 1 | Z4: 1 | AA4: 1 | AB4: 1 | AC4: 1 | AD4: 1 | AE4: 1 | AF4: 1 | AG4: 1 | AH4: 1 | AI4: 1 | AJ4: 1 | AK4: 1 | AL4: 1 | AM4: 1 | AN4: 1 | AO4: 1 | AP4: 1 | AQ4: 1 | AR4: 1
D5: Heavy Distillate Oil | H5: 0.9 | I5: 1 | K5: 1 | L5: 1 | M5: 1 | N5: 1 | O5: 1 | P5: 0.85 | Q5: 1 | R5: 1 | S5: 1 | T5: 1 | U5: 0.9 | V5: 0.9 | W5: 1 | X5: 1 | Y5: 1 | Z5: 1 | AA5: 1 | AB5: 1 | AC5: 1 | AD5: 1 | AE5: 1 | AF5: 1 | AG5: 1 | AH5: 1 | AI5: 1 | AJ5: 1 | AK5: 1 | AL5: 1 | AM5: 1 | AN5: 1 | AO5: 1 | AP5: 1 | AQ5: 1 | AR5: 1
D6: Light Distilate Oil | H6: 1 | I6: 1 | K6: 1 | L6: 1 | M6: 1 | N6: 1 | O6: 1 | P6: 1 | Q6: 1 | R6: 1 | S6: 1 | T6: 1 | U6: 1 | V6: 0.95 | W6: 1 | X6: 1 | Y6: 1 | Z6: 1 | AA6: 1 | AB6: 1 | AC6: 1 | AD6: 1 | AE6: 1 | AF6: 1 | AG6: 1 | AH6: 1 | AI6: 1 | AJ6: 1 | AK6: 1 | AL6: 1 | AM6: 1 | AN6: 1 | AO6: 1 | AP6: 1 | AQ6: 1 | AR6: 1
D7: Gasoline | H7: 1 | I7: 1 | K7: 1 | L7: 1 | M7: 1 | N7: 1 | O7: 1 | P7: 1 | Q7: 1 | R7: 1 | S7: 1 | T7: 1 | U7: 1 | V7: 0.95 | W7: 1 | X7: 1 | Y7: 1 | Z7: 1 | AA7: 1 | AB7: 1 | AC7: 1 | AD7: 1 | AE7: 1 | AF7: 1 | AG7: 1 | AH7: 1 | AI7: 1 | AJ7: 1 | AK7: 1 | AL7: 1 | AM7: 1 | AN7: 1 | AO7: 1 | AP7: 1 | AQ7: 1 | AR7: 1
D8: Natural Gas | H8: 1 | I8: 1 | K8: 1 | L8: 1 | M8: 1 | N8: 1 | O8: 1 | P8: 0.85 | Q8: 0.9 | R8: 1 | S8: 1 | T8: 1 | U8: 1 | V8: 0.9 | W8: 1 | X8: 1 | Y8: 1 | Z8: 1 | AA8: 1 | AB8: 1 | AC8: 1 | AD8: 1 | AE8: 1 | AF8: 1 | AG8: 1 | AH8: 1 | AI8: 1 | AJ8: 1 | AK8: 1 | AL8: 1 | AM8: 1 | AN8: 1 | AO8: 1 | AP8: 1 | AQ8: 1 | AR8: 1
A11: ~TFM_DINS
A12: TimeSlice | B12: Curr | C12: LimType | D12: Attribute | E12: Year | F12: Pset_PN | G12: Cset_CN | H12: AT | I12: BE | J12: BG | K12: DE | L12: DK | M12: FI | N12: FR | O12: EL | P12: IE | Q12: IT | R12: NL | S12: PT | T12: ES | U12: SE | V12: UK | W12: HU | X12: PL | Y12: CZ | Z12: SK | AA12: CH | AB12: CY | AC12: EE | AD12: IS | AE12: LT | AF12: LU | AG12: LV | AH12: MT | AI12: RO | AJ12: SI | AK12: NO | AL12: AL | AM12: BA | AN12: HR | AO12: ME | AP12: MK | AQ12: RS | AR12: KS
A13: ANNUAL | B13: EUR10 | D13: =IF(RIGHT(F13,6)="GASNAT","*","COST") -> COST | E13: 2010 | F13: =Worldprices!$G$62 -> IMPOILCRD | G13: =Worldprices!$G$63 -> OILCRD | H13: =Worldprices!$G$67*H$5 -> 8.8377049 | I13: =Worldprices!$G$67*I$5 -> 9.8196721 | J13: =AI13 -> 9.8196721 | K13: =Worldprices!$G$67*K$5 -> 9.8196721 | L13: =Worldprices!$G$67*L$5 -> 9.8196721 | M13: =Worldprices!$G$67*M$5 -> 9.8196721 | N13: =Worldprices!$G$67*N$5 -> 9.8196721 | O13: =Worldprices!$G$67*O$5 -> 9.8196721 | P13: =Worldprices!$G$67*P$5 -> 8.3467213 | Q13: =Worldprices!$G$67*Q$5 -> 9.8196721 | R13: =Worldprices!$G$67*R$5 -> 9.8196721 | ... AQ13: =Worldprices!$G$67*AQ$5 -> 9.8196721 | AR13: =AQ13 -> 9.8196721
A14: ANNUAL | B14: EUR10 | D14: =IF(RIGHT(F14,6)="GASNAT","*","COST") -> COST | E14: 2010 | F14: =Worldprices!$H$62 -> IMPOILHFO | G14: =Worldprices!$H$63 -> OILHFO | H14: =Worldprices!$H$67*H$5 -> 7.158541 | I14: =Worldprices!$H$67*I$5 -> 7.9539344 | J14: =AI14 -> 7.9539344 | K14: =Worldprices!$H$67*K$5 -> 7.9539344 | L14: =Worldprices!$H$67*L$5 -> 7.9539344 | M14: =Worldprices!$H$67*M$5 -> 7.9539344 | N14: =Worldprices!$H$67*N$5 -> 7.9539344 | O14: =Worldprices!$H$67*O$5 -> 7.9539344 | P14: =Worldprices!$H$67*P$5 -> 6.7608443 | Q14: =Worldprices!$H$67*Q$5 -> 7.9539344 | R14: =Worldprices!$H$67*R$5 -> 7.9539344 | ... AQ14: =Worldprices!$H$67*AQ$5 -> 7.9539344 | AR14: =AQ14 -> 7.9539344
A15: ANNUAL | B15: EUR10 | D15: =IF(RIGHT(F15,6)="GASNAT","*","COST") -> COST | E15: 2010 | F15: =Worldprices!$I$62 -> IMPOILDST | G15: =Worldprices!$I$63 -> OILDST | H15: =Worldprices!$I$67*H$6 -> 12.765574 | I15: =Worldprices!$I$67*I$6 -> 12.765574 | J15: =AI15 -> 12.765574 | K15: =Worldprices!$I$67*K$6 -> 12.765574 | L15: =Worldprices!$I$67*L$6 -> 12.765574 | M15: =Worldprices!$I$67*M$6 -> 12.765574 | N15: =Worldprices!$I$67*N$6 -> 12.765574 | O15: =Worldprices!$I$67*O$6 -> 12.765574 | P15: =Worldprices!$I$67*P$6 -> 12.765574 | Q15: =Worldprices!$I$67*Q$6 -> 12.765574 | R15: =Worldprices!$I$67*R$6 -> 12.765574 | ... AQ15: =Worldprices!$I$67*AQ$6 -> 12.765574 | AR15: =AQ15 -> 12.765574
A16: ANNUAL | B16: EUR10 | D16: =IF(RIGHT(F16,6)="GASNAT","*","COST") -> COST | E16: 2010 | F16: =Worldprices!$J$62 -> IMPOILLPG | G16: =Worldprices!$J$63 -> OILLPG | H16: =Worldprices!$J$67*H$7 -> 10.801639 | I16: =Worldprices!$J$67*I$7 -> 10.801639 | J16: =AI16 -> 10.801639 | K16: =Worldprices!$J$67*K$7 -> 10.801639 | L16: =Worldprices!$J$67*L$7 -> 10.801639 | M16: =Worldprices!$J$67*M$7 -> 10.801639 | N16: =Worldprices!$J$67*N$7 -> 10.801639 | O16: =Worldprices!$J$67*O$7 -> 10.801639 | P16: =Worldprices!$J$67*P$7 -> 10.801639 | Q16: =Worldprices!$J$67*Q$7 -> 10.801639 | R16: =Worldprices!$J$67*R$7 -> 10.801639 | ... AQ16: =Worldprices!$J$67*AQ$7 -> 10.801639 | AR16: =AQ16 -> 10.801639
A17: ANNUAL | B17: EUR10 | D17: =IF(RIGHT(F17,6)="GASNAT","*","COST") -> COST | E17: 2010 | F17: =Worldprices!$K$62 -> IMPOILGSL | G17: =Worldprices!$K$63 -> OILGSL | H17: =Worldprices!$K$67*H$7 -> 13.747541 | I17: =Worldprices!$K$67*I$7 -> 13.747541 | J17: =AI17 -> 13.747541 | K17: =Worldprices!$K$67*K$7 -> 13.747541 | L17: =Worldprices!$K$67*L$7 -> 13.747541 | M17: =Worldprices!$K$67*M$7 -> 13.747541 | N17: =Worldprices!$K$67*N$7 -> 13.747541 | O17: =Worldprices!$K$67*O$7 -> 13.747541 | P17: =Worldprices!$K$67*P$7 -> 13.747541 | Q17: =Worldprices!$K$67*Q$7 -> 13.747541 | R17: =Worldprices!$K$67*R$7 -> 13.747541 | ... AQ17: =Worldprices!$K$67*AQ$7 -> 13.747541 | AR17: =AQ17 -> 13.747541
A18: ANNUAL | B18: EUR10 | D18: =IF(RIGHT(F18,6)="GASNAT","*","COST") -> COST | E18: 2010 | F18: =Worldprices!$L$62 -> IMPOILKER | G18: =Worldprices!$L$63 -> OILKER | H18: =Worldprices!$L$67*H$7 -> 13.747541 | I18: =Worldprices!$L$67*I$7 -> 13.747541 | J18: =AI18 -> 13.747541 | K18: =Worldprices!$L$67*K$7 -> 13.747541 | L18: =Worldprices!$L$67*L$7 -> 13.747541 | M18: =Worldprices!$L$67*M$7 -> 13.747541 | N18: =Worldprices!$L$67*N$7 -> 13.747541 | O18: =Worldprices!$L$67*O$7 -> 13.747541 | P18: =Worldprices!$L$67*P$7 -> 13.747541 | Q18: =Worldprices!$L$67*Q$7 -> 13.747541 | R18: =Worldprices!$L$67*R$7 -> 13.747541 | ... AQ18: =Worldprices!$L$67*AQ$7 -> 13.747541 | AR18: =AQ18 -> 13.747541
A19: ANNUAL | B19: EUR10 | D19: =IF(RIGHT(F19,6)="GASNAT","*","COST") -> * | E19: 2010 | F19: =Worldprices!$Q$62 -> IMPGASNAT | G19: =Worldprices!$Q$63 -> GASNAT | H19: =Worldprices!$Q$67*H$8 -> 6.1967213 | I19: =Worldprices!$Q$67*I$8 -> 6.1967213 | J19: =AI19 -> 6.1967213 | K19: =Worldprices!$Q$67*K$8 -> 6.1967213 | L19: =Worldprices!$Q$67*L$8 -> 6.1967213 | M19: =Worldprices!$Q$67*M$8 -> 6.1967213 | N19: =Worldprices!$Q$67*N$8 -> 6.1967213 | O19: =Worldprices!$Q$67*O$8 -> 6.1967213 | P19: =Worldprices!$Q$67*P$8 -> 5.2672131 | Q19: =Worldprices!$Q$67*Q$8 -> 5.5770492 | R19: =Worldprices!$Q$67*R$8 -> 6.1967213 | ... AQ19: =Worldprices!$Q$67*AQ$8 -> 6.1967213 | AR19: =AQ19 -> 6.1967213
A20: ANNUAL | B20: EUR10 | D20: =IF(RIGHT(F20,6)="GASNAT","*","COST") -> COST | E20: 2015 | F20: =Worldprices!$G$62 -> IMPOILCRD | G20: =Worldprices!$G$63 -> OILCRD | H20: =Worldprices!$G$68*H$5 -> 8.6083525 | I20: =Worldprices!$G$68*I$5 -> 9.5648361 | J20: =AI20 -> 9.5648361 | K20: =Worldprices!$G$68*K$5 -> 9.5648361 | L20: =Worldprices!$G$68*L$5 -> 9.5648361 | M20: =Worldprices!$G$68*M$5 -> 9.5648361 | N20: =Worldprices!$G$68*N$5 -> 9.5648361 | O20: =Worldprices!$G$68*O$5 -> 9.5648361 | P20: =Worldprices!$G$68*P$5 -> 8.1301107 | Q20: =Worldprices!$G$68*Q$5 -> 9.5648361 | R20: =Worldprices!$G$68*R$5 -> 9.5648361 | ... AQ20: =Worldprices!$G$68*AQ$5 -> 9.5648361 | AR20: =AQ20 -> 9.5648361
A21: ANNUAL | B21: EUR10 | D21: =IF(RIGHT(F21,6)="GASNAT","*","COST") -> COST | E21: 2015 | F21: =Worldprices!$H$62 -> IMPOILHFO | G21: =Worldprices!$H$63 -> OILHFO | H21: =Worldprices!$H$68*H$5 -> 6.9727655 | I21: =Worldprices!$H$68*I$5 -> 7.7475172 | J21: =AI21 -> 7.7475172 | K21: =Worldprices!$H$68*K$5 -> 7.7475172 | L21: =Worldprices!$H$68*L$5 -> 7.7475172 | M21: =Worldprices!$H$68*M$5 -> 7.7475172 | N21: =Worldprices!$H$68*N$5 -> 7.7475172 | O21: =Worldprices!$H$68*O$5 -> 7.7475172 | P21: =Worldprices!$H$68*P$5 -> 6.5853896 | Q21: =Worldprices!$H$68*Q$5 -> 7.7475172 | R21: =Worldprices!$H$68*R$5 -> 7.7475172 | ... AQ21: =Worldprices!$H$68*AQ$5 -> 7.7475172 | AR21: =AQ21 -> 7.7475172
A22: ANNUAL | B22: EUR10 | D22: =IF(RIGHT(F22,6)="GASNAT","*","COST") -> COST | E22: 2015 | F22: =Worldprices!$I$62 -> IMPOILDST | G22: =Worldprices!$I$63 -> OILDST | H22: =Worldprices!$I$68*H$6 -> 12.434287 | I22: =Worldprices!$I$68*I$6 -> 12.434287 | J22: =AI22 -> 12.434287 | K22: =Worldprices!$I$68*K$6 -> 12.434287 | L22: =Worldprices!$I$68*L$6 -> 12.434287 | M22: =Worldprices!$I$68*M$6 -> 12.434287 | N22: =Worldprices!$I$68*N$6 -> 12.434287 | O22: =Worldprices!$I$68*O$6 -> 12.434287 | P22: =Worldprices!$I$68*P$6 -> 12.434287 | Q22: =Worldprices!$I$68*Q$6 -> 12.434287 | R22: =Worldprices!$I$68*R$6 -> 12.434287 | ... AQ22: =Worldprices!$I$68*AQ$6 -> 12.434287 | AR22: =AQ22 -> 12.434287
A23: ANNUAL | B23: EUR10 | D23: =IF(RIGHT(F23,6)="GASNAT","*","COST") -> COST | E23: 2015 | F23: =Worldprices!$J$62 -> IMPOILLPG | G23: =Worldprices!$J$63 -> OILLPG | H23: =Worldprices!$J$68*H$7 -> 10.52132 | I23: =Worldprices!$J$68*I$7 -> 10.52132 | J23: =AI23 -> 10.52132 | K23: =Worldprices!$J$68*K$7 -> 10.52132 | L23: =Worldprices!$J$68*L$7 -> 10.52132 | M23: =Worldprices!$J$68*M$7 -> 10.52132 | N23: =Worldprices!$J$68*N$7 -> 10.52132 | O23: =Worldprices!$J$68*O$7 -> 10.52132 | P23: =Worldprices!$J$68*P$7 -> 10.52132 | Q23: =Worldprices!$J$68*Q$7 -> 10.52132 | R23: =Worldprices!$J$68*R$7 -> 10.52132 | ... AQ23: =Worldprices!$J$68*AQ$7 -> 10.52132 | AR23: =AQ23 -> 10.52132
A24: ANNUAL | B24: EUR10 | D24: =IF(RIGHT(F24,6)="GASNAT","*","COST") -> COST | E24: 2015 | F24: =Worldprices!$K$62 -> IMPOILGSL | G24: =Worldprices!$K$63 -> OILGSL | H24: =Worldprices!$K$68*H$7 -> 13.39077 | I24: =Worldprices!$K$68*I$7 -> 13.39077 | J24: =AI24 -> 13.39077 | K24: =Worldprices!$K$68*K$7 -> 13.39077 | L24: =Worldprices!$K$68*L$7 -> 13.39077 | M24: =Worldprices!$K$68*M$7 -> 13.39077 | N24: =Worldprices!$K$68*N$7 -> 13.39077 | O24: =Worldprices!$K$68*O$7 -> 13.39077 | P24: =Worldprices!$K$68*P$7 -> 13.39077 | Q24: =Worldprices!$K$68*Q$7 -> 13.39077 | R24: =Worldprices!$K$68*R$7 -> 13.39077 | ... AQ24: =Worldprices!$K$68*AQ$7 -> 13.39077 | AR24: =AQ24 -> 13.39077
A25: ANNUAL | B25: EUR10 | D25: =IF(RIGHT(F25,6)="GASNAT","*","COST") -> COST | E25: 2015 | F25: =Worldprices!$L$62 -> IMPOILKER | G25: =Worldprices!$L$63 -> OILKER | H25: =Worldprices!$L$68*H$7 -> 13.39077 | I25: =Worldprices!$L$68*I$7 -> 13.39077 | J25: =AI25 -> 13.39077 | K25: =Worldprices!$L$68*K$7 -> 13.39077 | L25: =Worldprices!$L$68*L$7 -> 13.39077 | M25: =Worldprices!$L$68*M$7 -> 13.39077 | N25: =Worldprices!$L$68*N$7 -> 13.39077 | O25: =Worldprices!$L$68*O$7 -> 13.39077 | P25: =Worldprices!$L$68*P$7 -> 13.39077 | Q25: =Worldprices!$L$68*Q$7 -> 13.39077 | R25: =Worldprices!$L$68*R$7 -> 13.39077 | ... AQ25: =Worldprices!$L$68*AQ$7 -> 13.39077 | AR25: =AQ25 -> 13.39077
A26: ANNUAL | B26: EUR10 | D26: =IF(RIGHT(F26,6)="GASNAT","*","COST") -> * | E26: 2015 | F26: =Worldprices!$Q$62 -> IMPGASNAT | G26: =Worldprices!$Q$63 -> GASNAT | H26: =Worldprices!$Q$68*H$8 -> 9.7933607 | I26: =Worldprices!$Q$68*I$8 -> 9.7933607 | J26: =AI26 -> 9.7933607 | K26: =Worldprices!$Q$68*K$8 -> 9.7933607 | L26: =Worldprices!$Q$68*L$8 -> 9.7933607 | M26: =Worldprices!$Q$68*M$8 -> 9.7933607 | N26: =Worldprices!$Q$68*N$8 -> 9.7933607 | O26: =Worldprices!$Q$68*O$8 -> 9.7933607 | P26: =Worldprices!$Q$68*P$8 -> 8.3243566 | Q26: =Worldprices!$Q$68*Q$8 -> 8.8140246 | R26: =Worldprices!$Q$68*R$8 -> 9.7933607 | ... AQ26: =Worldprices!$Q$68*AQ$8 -> 9.7933607 | AR26: =AQ26 -> 9.7933607
A27: ANNUAL | B27: EUR10 | D27: =IF(RIGHT(F27,6)="GASNAT","*","COST") -> COST | E27: 2020 | F27: =Worldprices!$G$62 -> IMPOILCRD | G27: =Worldprices!$G$63 -> OILCRD | H27: =Worldprices!$G$69*H$5 -> 8.379 | I27: =Worldprices!$G$69*I$5 -> 9.31 | J27: =AI27 -> 9.31 | K27: =Worldprices!$G$69*K$5 -> 9.31 | L27: =Worldprices!$G$69*L$5 -> 9.31 | M27: =Worldprices!$G$69*M$5 -> 9.31 | N27: =Worldprices!$G$69*N$5 -> 9.31 | O27: =Worldprices!$G$69*O$5 -> 9.31 | P27: =Worldprices!$G$69*P$5 -> 7.9135 | Q27: =Worldprices!$G$69*Q$5 -> 9.31 | R27: =Worldprices!$G$69*R$5 -> 9.31 | ... AQ27: =Worldprices!$G$69*AQ$5 -> 9.31 | AR27: =AQ27 -> 9.31
A28: ANNUAL | B28: EUR10 | D28: =IF(RIGHT(F28,6)="GASNAT","*","COST") -> COST | E28: 2020 | F28: =Worldprices!$H$62 -> IMPOILHFO | G28: =Worldprices!$H$63 -> OILHFO | H28: =Worldprices!$H$69*H$5 -> 6.78699 | I28: =Worldprices!$H$69*I$5 -> 7.5411 | J28: =AI28 -> 7.5411 | K28: =Worldprices!$H$69*K$5 -> 7.5411 | L28: =Worldprices!$H$69*L$5 -> 7.5411 | M28: =Worldprices!$H$69*M$5 -> 7.5411 | N28: =Worldprices!$H$69*N$5 -> 7.5411 | O28: =Worldprices!$H$69*O$5 -> 7.5411 | P28: =Worldprices!$H$69*P$5 -> 6.409935 | Q28: =Worldprices!$H$69*Q$5 -> 7.5411 | R28: =Worldprices!$H$69*R$5 -> 7.5411 | ... AQ28: =Worldprices!$H$69*AQ$5 -> 7.5411 | AR28: =AQ28 -> 7.5411
A29: ANNUAL | B29: EUR10 | D29: =IF(RIGHT(F29,6)="GASNAT","*","COST") -> COST | E29: 2020 | F29: =Worldprices!$I$62 -> IMPOILDST | G29: =Worldprices!$I$63 -> OILDST | H29: =Worldprices!$I$69*H$6 -> 12.103 | I29: =Worldprices!$I$69*I$6 -> 12.103 | J29: =AI29 -> 12.103 | K29: =Worldprices!$I$69*K$6 -> 12.103 | L29: =Worldprices!$I$69*L$6 -> 12.103 | M29: =Worldprices!$I$69*M$6 -> 12.103 | N29: =Worldprices!$I$69*N$6 -> 12.103 | O29: =Worldprices!$I$69*O$6 -> 12.103 | P29: =Worldprices!$I$69*P$6 -> 12.103 | Q29: =Worldprices!$I$69*Q$6 -> 12.103 | R29: =Worldprices!$I$69*R$6 -> 12.103 | ... AQ29: =Worldprices!$I$69*AQ$6 -> 12.103 | AR29: =AQ29 -> 12.103
A30: ANNUAL | B30: EUR10 | D30: =IF(RIGHT(F30,6)="GASNAT","*","COST") -> COST | E30: 2020 | F30: =Worldprices!$J$62 -> IMPOILLPG | G30: =Worldprices!$J$63 -> OILLPG | H30: =Worldprices!$J$69*H$7 -> 10.241 | I30: =Worldprices!$J$69*I$7 -> 10.241 | J30: =AI30 -> 10.241 | K30: =Worldprices!$J$69*K$7 -> 10.241 | L30: =Worldprices!$J$69*L$7 -> 10.241 | M30: =Worldprices!$J$69*M$7 -> 10.241 | N30: =Worldprices!$J$69*N$7 -> 10.241 | O30: =Worldprices!$J$69*O$7 -> 10.241 | P30: =Worldprices!$J$69*P$7 -> 10.241 | Q30: =Worldprices!$J$69*Q$7 -> 10.241 | R30: =Worldprices!$J$69*R$7 -> 10.241 | ... AQ30: =Worldprices!$J$69*AQ$7 -> 10.241 | AR30: =AQ30 -> 10.241
A31: ANNUAL | B31: EUR10 | D31: =IF(RIGHT(F31,6)="GASNAT","*","COST") -> COST | E31: 2020 | F31: =Worldprices!$K$62 -> IMPOILGSL | G31: =Worldprices!$K$63 -> OILGSL | H31: =Worldprices!$K$69*H$7 -> 13.034 | I31: =Worldprices!$K$69*I$7 -> 13.034 | J31: =AI31 -> 13.034 | K31: =Worldprices!$K$69*K$7 -> 13.034 | L31: =Worldprices!$K$69*L$7 -> 13.034 | M31: =Worldprices!$K$69*M$7 -> 13.034 | N31: =Worldprices!$K$69*N$7 -> 13.034 | O31: =Worldprices!$K$69*O$7 -> 13.034 | P31: =Worldprices!$K$69*P$7 -> 13.034 | Q31: =Worldprices!$K$69*Q$7 -> 13.034 | R31: =Worldprices!$K$69*R$7 -> 13.034 | ... AQ31: =Worldprices!$K$69*AQ$7 -> 13.034 | AR31: =AQ31 -> 13.034
A32: ANNUAL | B32: EUR10 | D32: =IF(RIGHT(F32,6)="GASNAT","*","COST") -> COST | E32: 2020 | F32: =Worldprices!$L$62 -> IMPOILKER | G32: =Worldprices!$L$63 -> OILKER | H32: =Worldprices!$L$69*H$7 -> 13.034 | I32: =Worldprices!$L$69*I$7 -> 13.034 | J32: =AI32 -> 13.034 | K32: =Worldprices!$L$69*K$7 -> 13.034 | L32: =Worldprices!$L$69*L$7 -> 13.034 | M32: =Worldprices!$L$69*M$7 -> 13.034 | N32: =Worldprices!$L$69*N$7 -> 13.034 | O32: =Worldprices!$L$69*O$7 -> 13.034 | P32: =Worldprices!$L$69*P$7 -> 13.034 | Q32: =Worldprices!$L$69*Q$7 -> 13.034 | R32: =Worldprices!$L$69*R$7 -> 13.034 | ... AQ32: =Worldprices!$L$69*AQ$7 -> 13.034 | AR32: =AQ32 -> 13.034
A33: ANNUAL | B33: EUR10 | D33: =IF(RIGHT(F33,6)="GASNAT","*","COST") -> * | E33: 2020 | F33: =Worldprices!$Q$62 -> IMPGASNAT | G33: =Worldprices!$Q$63 -> GASNAT | H33: =Worldprices!$Q$69*H$8 -> 13.39 | I33: =Worldprices!$Q$69*I$8 -> 13.39 | J33: =AI33 -> 13.39 | K33: =Worldprices!$Q$69*K$8 -> 13.39 | L33: =Worldprices!$Q$69*L$8 -> 13.39 | M33: =Worldprices!$Q$69*M$8 -> 13.39 | N33: =Worldprices!$Q$69*N$8 -> 13.39 | O33: =Worldprices!$Q$69*O$8 -> 13.39 | P33: =Worldprices!$Q$69*P$8 -> 11.3815 | Q33: =Worldprices!$Q$69*Q$8 -> 12.051 | R33: =Worldprices!$Q$69*R$8 -> 13.39 | ... AQ33: =Worldprices!$Q$69*AQ$8 -> 13.39 | AR33: =AQ33 -> 13.39
A34: ANNUAL | B34: EUR10 | D34: =IF(RIGHT(F34,6)="GASNAT","*","COST") -> COST | E34: 2025 | F34: =Worldprices!$G$62 -> IMPOILCRD | G34: =Worldprices!$G$63 -> OILCRD | H34: =Worldprices!$G$70*H$5 -> 10.332 | I34: =Worldprices!$G$70*I$5 -> 11.48 | J34: =AI34 -> 11.48 | K34: =Worldprices!$G$70*K$5 -> 11.48 | L34: =Worldprices!$G$70*L$5 -> 11.48 | M34: =Worldprices!$G$70*M$5 -> 11.48 | N34: =Worldprices!$G$70*N$5 -> 11.48 | O34: =Worldprices!$G$70*O$5 -> 11.48 | P34: =Worldprices!$G$70*P$5 -> 9.758 | Q34: =Worldprices!$G$70*Q$5 -> 11.48 | R34: =Worldprices!$G$70*R$5 -> 11.48 | ... AQ34: =Worldprices!$G$70*AQ$5 -> 11.48 | AR34: =AQ34 -> 11.48
A35: ANNUAL | B35: EUR10 | D35: =IF(RIGHT(F35,6)="GASNAT","*","COST") -> COST | E35: 2025 | F35: =Worldprices!$H$62 -> IMPOILHFO | G35: =Worldprices!$H$63 -> OILHFO | H35: =Worldprices!$H$70*H$5 -> 8.36892 | I35: =Worldprices!$H$70*I$5 -> 9.2988 | J35: =AI35 -> 9.2988 | K35: =Worldprices!$H$70*K$5 -> 9.2988 | L35: =Worldprices!$H$70*L$5 -> 9.2988 | M35: =Worldprices!$H$70*M$5 -> 9.2988 | N35: =Worldprices!$H$70*N$5 -> 9.2988 | O35: =Worldprices!$H$70*O$5 -> 9.2988 | P35: =Worldprices!$H$70*P$5 -> 7.90398 | Q35: =Worldprices!$H$70*Q$5 -> 9.2988 | R35: =Worldprices!$H$70*R$5 -> 9.2988 | ... AQ35: =Worldprices!$H$70*AQ$5 -> 9.2988 | AR35: =AQ35 -> 9.2988
A36: ANNUAL | B36: EUR10 | D36: =IF(RIGHT(F36,6)="GASNAT","*","COST") -> COST | E36: 2025 | F36: =Worldprices!$I$62 -> IMPOILDST | G36: =Worldprices!$I$63 -> OILDST | H36: =Worldprices!$I$70*H$6 -> 14.924 | I36: =Worldprices!$I$70*I$6 -> 14.924 | J36: =AI36 -> 14.924 | K36: =Worldprices!$I$70*K$6 -> 14.924 | L36: =Worldprices!$I$70*L$6 -> 14.924 | M36: =Worldprices!$I$70*M$6 -> 14.924 | N36: =Worldprices!$I$70*N$6 -> 14.924 | O36: =Worldprices!$I$70*O$6 -> 14.924 | P36: =Worldprices!$I$70*P$6 -> 14.924 | Q36: =Worldprices!$I$70*Q$6 -> 14.924 | R36: =Worldprices!$I$70*R$6 -> 14.924 | ... AQ36: =Worldprices!$I$70*AQ$6 -> 14.924 | AR36: =AQ36 -> 14.924
A37: ANNUAL | B37: EUR10 | D37: =IF(RIGHT(F37,6)="GASNAT","*","COST") -> COST | E37: 2025 | F37: =Worldprices!$J$62 -> IMPOILLPG | G37: =Worldprices!$J$63 -> OILLPG | H37: =Worldprices!$J$70*H$7 -> 12.628 | I37: =Worldprices!$J$70*I$7 -> 12.628 | J37: =AI37 -> 12.628 | K37: =Worldprices!$J$70*K$7 -> 12.628 | L37: =Worldprices!$J$70*L$7 -> 12.628 | M37: =Worldprices!$J$70*M$7 -> 12.628 | N37: =Worldprices!$J$70*N$7 -> 12.628 | O37: =Worldprices!$J$70*O$7 -> 12.628 | P37: =Worldprices!$J$70*P$7 -> 12.628 | Q37: =Worldprices!$J$70*Q$7 -> 12.628 | R37: =Worldprices!$J$70*R$7 -> 12.628 | ... AQ37: =Worldprices!$J$70*AQ$7 -> 12.628 | AR37: =AQ37 -> 12.628
A38: ANNUAL | B38: EUR10 | D38: =IF(RIGHT(F38,6)="GASNAT","*","COST") -> COST | E38: 2025 | F38: =Worldprices!$K$62 -> IMPOILGSL | G38: =Worldprices!$K$63 -> OILGSL | H38: =Worldprices!$K$70*H$7 -> 16.072 | I38: =Worldprices!$K$70*I$7 -> 16.072 | J38: =AI38 -> 16.072 | K38: =Worldprices!$K$70*K$7 -> 16.072 | L38: =Worldprices!$K$70*L$7 -> 16.072 | M38: =Worldprices!$K$70*M$7 -> 16.072 | N38: =Worldprices!$K$70*N$7 -> 16.072 | O38: =Worldprices!$K$70*O$7 -> 16.072 | P38: =Worldprices!$K$70*P$7 -> 16.072 | Q38: =Worldprices!$K$70*Q$7 -> 16.072 | R38: =Worldprices!$K$70*R$7 -> 16.072 | ... AQ38: =Worldprices!$K$70*AQ$7 -> 16.072 | AR38: =AQ38 -> 16.072
A39: ANNUAL | B39: EUR10 | D39: =IF(RIGHT(F39,6)="GASNAT","*","COST") -> COST | E39: 2025 | F39: =Worldprices!$L$62 -> IMPOILKER | G39: =Worldprices!$L$63 -> OILKER | H39: =Worldprices!$L$70*H$7 -> 16.072 | I39: =Worldprices!$L$70*I$7 -> 16.072 | J39: =AI39 -> 16.072 | K39: =Worldprices!$L$70*K$7 -> 16.072 | L39: =Worldprices!$L$70*L$7 -> 16.072 | M39: =Worldprices!$L$70*M$7 -> 16.072 | N39: =Worldprices!$L$70*N$7 -> 16.072 | O39: =Worldprices!$L$70*O$7 -> 16.072 | P39: =Worldprices!$L$70*P$7 -> 16.072 | Q39: =Worldprices!$L$70*Q$7 -> 16.072 | R39: =Worldprices!$L$70*R$7 -> 16.072 | ... AQ39: =Worldprices!$L$70*AQ$7 -> 16.072 | AR39: =AQ39 -> 16.072
A40: ANNUAL | B40: EUR10 | D40: =IF(RIGHT(F40,6)="GASNAT","*","COST") -> * | E40: 2025 | F40: =Worldprices!$Q$62 -> IMPGASNAT | G40: =Worldprices!$Q$63 -> GASNAT | H40: =Worldprices!$Q$70*H$8 -> 10.195 | I40: =Worldprices!$Q$70*I$8 -> 10.195 | J40: =AI40 -> 10.195 | K40: =Worldprices!$Q$70*K$8 -> 10.195 | L40: =Worldprices!$Q$70*L$8 -> 10.195 | M40: =Worldprices!$Q$70*M$8 -> 10.195 | N40: =Worldprices!$Q$70*N$8 -> 10.195 | O40: =Worldprices!$Q$70*O$8 -> 10.195 | P40: =Worldprices!$Q$70*P$8 -> 8.66575 | Q40: =Worldprices!$Q$70*Q$8 -> 9.1755 | R40: =Worldprices!$Q$70*R$8 -> 10.195 | ... AQ40: =Worldprices!$Q$70*AQ$8 -> 10.195 | AR40: =AQ40 -> 10.195
A41: ANNUAL | B41: EUR10 | D41: =IF(RIGHT(F41,6)="GASNAT","*","COST") -> COST | E41: 2030 | F41: =Worldprices!$G$62 -> IMPOILCRD | G41: =Worldprices!$G$63 -> OILCRD | H41: =Worldprices!$G$71*H$5 -> 12.285 | I41: =Worldprices!$G$71*I$5 -> 13.65 | J41: =AI41 -> 13.65 | K41: =Worldprices!$G$71*K$5 -> 13.65 | L41: =Worldprices!$G$71*L$5 -> 13.65 | M41: =Worldprices!$G$71*M$5 -> 13.65 | N41: =Worldprices!$G$71*N$5 -> 13.65 | O41: =Worldprices!$G$71*O$5 -> 13.65 | P41: =Worldprices!$G$71*P$5 -> 11.6025 | Q41: =Worldprices!$G$71*Q$5 -> 13.65 | R41: =Worldprices!$G$71*R$5 -> 13.65 | ... AQ41: =Worldprices!$G$71*AQ$5 -> 13.65 | AR41: =AQ41 -> 13.65
A42: ANNUAL | B42: EUR10 | D42: =IF(RIGHT(F42,6)="GASNAT","*","COST") -> COST | E42: 2030 | F42: =Worldprices!$H$62 -> IMPOILHFO | G42: =Worldprices!$H$63 -> OILHFO | H42: =Worldprices!$H$71*H$5 -> 9.95085 | I42: =Worldprices!$H$71*I$5 -> 11.0565 | J42: =AI42 -> 11.0565 | K42: =Worldprices!$H$71*K$5 -> 11.0565 | L42: =Worldprices!$H$71*L$5 -> 11.0565 | M42: =Worldprices!$H$71*M$5 -> 11.0565 | N42: =Worldprices!$H$71*N$5 -> 11.0565 | O42: =Worldprices!$H$71*O$5 -> 11.0565 | P42: =Worldprices!$H$71*P$5 -> 9.398025 | Q42: =Worldprices!$H$71*Q$5 -> 11.0565 | R42: =Worldprices!$H$71*R$5 -> 11.0565 | ... AQ42: =Worldprices!$H$71*AQ$5 -> 11.0565 | AR42: =AQ42 -> 11.0565
A43: ANNUAL | B43: EUR10 | D43: =IF(RIGHT(F43,6)="GASNAT","*","COST") -> COST | E43: 2030 | F43: =Worldprices!$I$62 -> IMPOILDST | G43: =Worldprices!$I$63 -> OILDST | H43: =Worldprices!$I$71*H$6 -> 17.745 | I43: =Worldprices!$I$71*I$6 -> 17.745 | J43: =AI43 -> 17.745 | K43: =Worldprices!$I$71*K$6 -> 17.745 | L43: =Worldprices!$I$71*L$6 -> 17.745 | M43: =Worldprices!$I$71*M$6 -> 17.745 | N43: =Worldprices!$I$71*N$6 -> 17.745 | O43: =Worldprices!$I$71*O$6 -> 17.745 | P43: =Worldprices!$I$71*P$6 -> 17.745 | Q43: =Worldprices!$I$71*Q$6 -> 17.745 | R43: =Worldprices!$I$71*R$6 -> 17.745 | ... AQ43: =Worldprices!$I$71*AQ$6 -> 17.745 | AR43: =AQ43 -> 17.745
A44: ANNUAL | B44: EUR10 | D44: =IF(RIGHT(F44,6)="GASNAT","*","COST") -> COST | E44: 2030 | F44: =Worldprices!$J$62 -> IMPOILLPG | G44: =Worldprices!$J$63 -> OILLPG | H44: =Worldprices!$J$71*H$7 -> 15.015 | I44: =Worldprices!$J$71*I$7 -> 15.015 | J44: =AI44 -> 15.015 | K44: =Worldprices!$J$71*K$7 -> 15.015 | L44: =Worldprices!$J$71*L$7 -> 15.015 | M44: =Worldprices!$J$71*M$7 -> 15.015 | N44: =Worldprices!$J$71*N$7 -> 15.015 | O44: =Worldprices!$J$71*O$7 -> 15.015 | P44: =Worldprices!$J$71*P$7 -> 15.015 | Q44: =Worldprices!$J$71*Q$7 -> 15.015 | R44: =Worldprices!$J$71*R$7 -> 15.015 | ... AQ44: =Worldprices!$J$71*AQ$7 -> 15.015 | AR44: =AQ44 -> 15.015
A45: ANNUAL | B45: EUR10 | D45: =IF(RIGHT(F45,6)="GASNAT","*","COST") -> COST | E45: 2030 | F45: =Worldprices!$K$62 -> IMPOILGSL | G45: =Worldprices!$K$63 -> OILGSL | H45: =Worldprices!$K$71*H$7 -> 19.11 | I45: =Worldprices!$K$71*I$7 -> 19.11 | J45: =AI45 -> 19.11 | K45: =Worldprices!$K$71*K$7 -> 19.11 | L45: =Worldprices!$K$71*L$7 -> 19.11 | M45: =Worldprices!$K$71*M$7 -> 19.11 | N45: =Worldprices!$K$71*N$7 -> 19.11 | O45: =Worldprices!$K$71*O$7 -> 19.11 | P45: =Worldprices!$K$71*P$7 -> 19.11 | Q45: =Worldprices!$K$71*Q$7 -> 19.11 | R45: =Worldprices!$K$71*R$7 -> 19.11 | ... AQ45: =Worldprices!$K$71*AQ$7 -> 19.11 | AR45: =AQ45 -> 19.11
A46: ANNUAL | B46: EUR10 | D46: =IF(RIGHT(F46,6)="GASNAT","*","COST") -> COST | E46: 2030 | F46: =Worldprices!$L$62 -> IMPOILKER | G46: =Worldprices!$L$63 -> OILKER | H46: =Worldprices!$L$71*H$7 -> 19.11 | I46: =Worldprices!$L$71*I$7 -> 19.11 | J46: =AI46 -> 19.11 | K46: =Worldprices!$L$71*K$7 -> 19.11 | L46: =Worldprices!$L$71*L$7 -> 19.11 | M46: =Worldprices!$L$71*M$7 -> 19.11 | N46: =Worldprices!$L$71*N$7 -> 19.11 | O46: =Worldprices!$L$71*O$7 -> 19.11 | P46: =Worldprices!$L$71*P$7 -> 19.11 | Q46: =Worldprices!$L$71*Q$7 -> 19.11 | R46: =Worldprices!$L$71*R$7 -> 19.11 | ... AQ46: =Worldprices!$L$71*AQ$7 -> 19.11 | AR46: =AQ46 -> 19.11
A47: ANNUAL | B47: EUR10 | D47: =IF(RIGHT(F47,6)="GASNAT","*","COST") -> * | E47: 2030 | F47: =Worldprices!$Q$62 -> IMPGASNAT | G47: =Worldprices!$Q$63 -> GASNAT | H47: =Worldprices!$Q$71*H$8 -> 7 | I47: =Worldprices!$Q$71*I$8 -> 7 | J47: =AI47 -> 7 | K47: =Worldprices!$Q$71*K$8 -> 7 | L47: =Worldprices!$Q$71*L$8 -> 7 | M47: =Worldprices!$Q$71*M$8 -> 7 | N47: =Worldprices!$Q$71*N$8 -> 7 | O47: =Worldprices!$Q$71*O$8 -> 7 | P47: =Worldprices!$Q$71*P$8 -> 5.95 | Q47: =Worldprices!$Q$71*Q$8 -> 6.3 | R47: =Worldprices!$Q$71*R$8 -> 7 | ... AQ47: =Worldprices!$Q$71*AQ$8 -> 7 | AR47: =AQ47 -> 7
A48: ANNUAL | B48: EUR10 | D48: =IF(RIGHT(F48,6)="GASNAT","*","COST") -> COST | E48: 2035 | F48: =Worldprices!$G$62 -> IMPOILCRD | G48: =Worldprices!$G$63 -> OILCRD | H48: =Worldprices!$G$72*H$5 -> 12.645 | I48: =Worldprices!$G$72*I$5 -> 14.05 | J48: =AI48 -> 14.05 | K48: =Worldprices!$G$72*K$5 -> 14.05 | L48: =Worldprices!$G$72*L$5 -> 14.05 | M48: =Worldprices!$G$72*M$5 -> 14.05 | N48: =Worldprices!$G$72*N$5 -> 14.05 | O48: =Worldprices!$G$72*O$5 -> 14.05 | P48: =Worldprices!$G$72*P$5 -> 11.9425 | Q48: =Worldprices!$G$72*Q$5 -> 14.05 | R48: =Worldprices!$G$72*R$5 -> 14.05 | ... AQ48: =Worldprices!$G$72*AQ$5 -> 14.05 | AR48: =AQ48 -> 14.05
A49: ANNUAL | B49: EUR10 | D49: =IF(RIGHT(F49,6)="GASNAT","*","COST") -> COST | E49: 2035 | F49: =Worldprices!$H$62 -> IMPOILHFO | G49: =Worldprices!$H$63 -> OILHFO | H49: =Worldprices!$H$72*H$5 -> 10.24245 | I49: =Worldprices!$H$72*I$5 -> 11.3805 | J49: =AI49 -> 11.3805 | K49: =Worldprices!$H$72*K$5 -> 11.3805 | L49: =Worldprices!$H$72*L$5 -> 11.3805 | M49: =Worldprices!$H$72*M$5 -> 11.3805 | N49: =Worldprices!$H$72*N$5 -> 11.3805 | O49: =Worldprices!$H$72*O$5 -> 11.3805 | P49: =Worldprices!$H$72*P$5 -> 9.673425 | Q49: =Worldprices!$H$72*Q$5 -> 11.3805 | R49: =Worldprices!$H$72*R$5 -> 11.3805 | ... AQ49: =Worldprices!$H$72*AQ$5 -> 11.3805 | AR49: =AQ49 -> 11.3805
A50: ANNUAL | B50: EUR10 | D50: =IF(RIGHT(F50,6)="GASNAT","*","COST") -> COST | E50: 2035 | F50: =Worldprices!$I$62 -> IMPOILDST | G50: =Worldprices!$I$63 -> OILDST | H50: =Worldprices!$I$72*H$6 -> 18.265 | I50: =Worldprices!$I$72*I$6 -> 18.265 | J50: =AI50 -> 18.265 | K50: =Worldprices!$I$72*K$6 -> 18.265 | L50: =Worldprices!$I$72*L$6 -> 18.265 | M50: =Worldprices!$I$72*M$6 -> 18.265 | N50: =Worldprices!$I$72*N$6 -> 18.265 | O50: =Worldprices!$I$72*O$6 -> 18.265 | P50: =Worldprices!$I$72*P$6 -> 18.265 | Q50: =Worldprices!$I$72*Q$6 -> 18.265 | R50: =Worldprices!$I$72*R$6 -> 18.265 | ... AQ50: =Worldprices!$I$72*AQ$6 -> 18.265 | AR50: =AQ50 -> 18.265
A51: ANNUAL | B51: EUR10 | D51: =IF(RIGHT(F51,6)="GASNAT","*","COST") -> COST | E51: 2035 | F51: =Worldprices!$J$62 -> IMPOILLPG | G51: =Worldprices!$J$63 -> OILLPG | H51: =Worldprices!$J$72*H$7 -> 15.455 | I51: =Worldprices!$J$72*I$7 -> 15.455 | J51: =AI51 -> 15.455 | K51: =Worldprices!$J$72*K$7 -> 15.455 | L51: =Worldprices!$J$72*L$7 -> 15.455 | M51: =Worldprices!$J$72*M$7 -> 15.455 | N51: =Worldprices!$J$72*N$7 -> 15.455 | O51: =Worldprices!$J$72*O$7 -> 15.455 | P51: =Worldprices!$J$72*P$7 -> 15.455 | Q51: =Worldprices!$J$72*Q$7 -> 15.455 | R51: =Worldprices!$J$72*R$7 -> 15.455 | ... AQ51: =Worldprices!$J$72*AQ$7 -> 15.455 | AR51: =AQ51 -> 15.455
A52: ANNUAL | B52: EUR10 | D52: =IF(RIGHT(F52,6)="GASNAT","*","COST") -> COST | E52: 2035 | F52: =Worldprices!$K$62 -> IMPOILGSL | G52: =Worldprices!$K$63 -> OILGSL | H52: =Worldprices!$K$72*H$7 -> 19.67 | I52: =Worldprices!$K$72*I$7 -> 19.67 | J52: =AI52 -> 19.67 | K52: =Worldprices!$K$72*K$7 -> 19.67 | L52: =Worldprices!$K$72*L$7 -> 19.67 | M52: =Worldprices!$K$72*M$7 -> 19.67 | N52: =Worldprices!$K$72*N$7 -> 19.67 | O52: =Worldprices!$K$72*O$7 -> 19.67 | P52: =Worldprices!$K$72*P$7 -> 19.67 | Q52: =Worldprices!$K$72*Q$7 -> 19.67 | R52: =Worldprices!$K$72*R$7 -> 19.67 | ... AQ52: =Worldprices!$K$72*AQ$7 -> 19.67 | AR52: =AQ52 -> 19.67
A53: ANNUAL | B53: EUR10 | D53: =IF(RIGHT(F53,6)="GASNAT","*","COST") -> COST | E53: 2035 | F53: =Worldprices!$L$62 -> IMPOILKER | G53: =Worldprices!$L$63 -> OILKER | H53: =Worldprices!$L$72*H$7 -> 19.67 | I53: =Worldprices!$L$72*I$7 -> 19.67 | J53: =AI53 -> 19.67 | K53: =Worldprices!$L$72*K$7 -> 19.67 | L53: =Worldprices!$L$72*L$7 -> 19.67 | M53: =Worldprices!$L$72*M$7 -> 19.67 | N53: =Worldprices!$L$72*N$7 -> 19.67 | O53: =Worldprices!$L$72*O$7 -> 19.67 | P53: =Worldprices!$L$72*P$7 -> 19.67 | Q53: =Worldprices!$L$72*Q$7 -> 19.67 | R53: =Worldprices!$L$72*R$7 -> 19.67 | ... AQ53: =Worldprices!$L$72*AQ$7 -> 19.67 | AR53: =AQ53 -> 19.67
A54: ANNUAL | B54: EUR10 | D54: =IF(RIGHT(F54,6)="GASNAT","*","COST") -> * | E54: 2035 | F54: =Worldprices!$Q$62 -> IMPGASNAT | G54: =Worldprices!$Q$63 -> GASNAT | H54: =Worldprices!$Q$72*H$8 -> 7 | I54: =Worldprices!$Q$72*I$8 -> 7 | J54: =AI54 -> 7 | K54: =Worldprices!$Q$72*K$8 -> 7 | L54: =Worldprices!$Q$72*L$8 -> 7 | M54: =Worldprices!$Q$72*M$8 -> 7 | N54: =Worldprices!$Q$72*N$8 -> 7 | O54: =Worldprices!$Q$72*O$8 -> 7 | P54: =Worldprices!$Q$72*P$8 -> 5.95 | Q54: =Worldprices!$Q$72*Q$8 -> 6.3 | R54: =Worldprices!$Q$72*R$8 -> 7 | ... AQ54: =Worldprices!$Q$72*AQ$8 -> 7 | AR54: =AQ54 -> 7
A55: ANNUAL | B55: EUR10 | D55: =IF(RIGHT(F55,6)="GASNAT","*","COST") -> COST | E55: 2040 | F55: =Worldprices!$G$62 -> IMPOILCRD | G55: =Worldprices!$G$63 -> OILCRD | H55: =Worldprices!$G$73*H$5 -> 13.005 | I55: =Worldprices!$G$73*I$5 -> 14.45 | J55: =AI55 -> 14.45 | K55: =Worldprices!$G$73*K$5 -> 14.45 | L55: =Worldprices!$G$73*L$5 -> 14.45 | M55: =Worldprices!$G$73*M$5 -> 14.45 | N55: =Worldprices!$G$73*N$5 -> 14.45 | O55: =Worldprices!$G$73*O$5 -> 14.45 | P55: =Worldprices!$G$73*P$5 -> 12.2825 | Q55: =Worldprices!$G$73*Q$5 -> 14.45 | R55: =Worldprices!$G$73*R$5 -> 14.45 | ... AQ55: =Worldprices!$G$73*AQ$5 -> 14.45 | AR55: =AQ55 -> 14.45
A56: ANNUAL | B56: EUR10 | D56: =IF(RIGHT(F56,6)="GASNAT","*","COST") -> COST | E56: 2040 | F56: =Worldprices!$H$62 -> IMPOILHFO | G56: =Worldprices!$H$63 -> OILHFO | H56: =Worldprices!$H$73*H$5 -> 10.53405 | I56: =Worldprices!$H$73*I$5 -> 11.7045 | J56: =AI56 -> 11.7045 | K56: =Worldprices!$H$73*K$5 -> 11.7045 | L56: =Worldprices!$H$73*L$5 -> 11.7045 | M56: =Worldprices!$H$73*M$5 -> 11.7045 | N56: =Worldprices!$H$73*N$5 -> 11.7045 | O56: =Worldprices!$H$73*O$5 -> 11.7045 | P56: =Worldprices!$H$73*P$5 -> 9.948825 | Q56: =Worldprices!$H$73*Q$5 -> 11.7045 | R56: =Worldprices!$H$73*R$5 -> 11.7045 | ... AQ56: =Worldprices!$H$73*AQ$5 -> 11.7045 | AR56: =AQ56 -> 11.7045
A57: ANNUAL | B57: EUR10 | D57: =IF(RIGHT(F57,6)="GASNAT","*","COST") -> COST | E57: 2040 | F57: =Worldprices!$I$62 -> IMPOILDST | G57: =Worldprices!$I$63 -> OILDST | H57: =Worldprices!$I$73*H$6 -> 18.785 | I57: =Worldprices!$I$73*I$6 -> 18.785 | J57: =AI57 -> 18.785 | K57: =Worldprices!$I$73*K$6 -> 18.785 | L57: =Worldprices!$I$73*L$6 -> 18.785 | M57: =Worldprices!$I$73*M$6 -> 18.785 | N57: =Worldprices!$I$73*N$6 -> 18.785 | O57: =Worldprices!$I$73*O$6 -> 18.785 | P57: =Worldprices!$I$73*P$6 -> 18.785 | Q57: =Worldprices!$I$73*Q$6 -> 18.785 | R57: =Worldprices!$I$73*R$6 -> 18.785 | ... AQ57: =Worldprices!$I$73*AQ$6 -> 18.785 | AR57: =AQ57 -> 18.785
A58: ANNUAL | B58: EUR10 | D58: =IF(RIGHT(F58,6)="GASNAT","*","COST") -> COST | E58: 2040 | F58: =Worldprices!$J$62 -> IMPOILLPG | G58: =Worldprices!$J$63 -> OILLPG | H58: =Worldprices!$J$73*H$7 -> 15.895 | I58: =Worldprices!$J$73*I$7 -> 15.895 | J58: =AI58 -> 15.895 | K58: =Worldprices!$J$73*K$7 -> 15.895 | L58: =Worldprices!$J$73*L$7 -> 15.895 | M58: =Worldprices!$J$73*M$7 -> 15.895 | N58: =Worldprices!$J$73*N$7 -> 15.895 | O58: =Worldprices!$J$73*O$7 -> 15.895 | P58: =Worldprices!$J$73*P$7 -> 15.895 | Q58: =Worldprices!$J$73*Q$7 -> 15.895 | R58: =Worldprices!$J$73*R$7 -> 15.895 | ... AQ58: =Worldprices!$J$73*AQ$7 -> 15.895 | AR58: =AQ58 -> 15.895
A59: ANNUAL | B59: EUR10 | D59: =IF(RIGHT(F59,6)="GASNAT","*","COST") -> COST | E59: 2040 | F59: =Worldprices!$K$62 -> IMPOILGSL | G59: =Worldprices!$K$63 -> OILGSL | H59: =Worldprices!$K$73*H$7 -> 20.23 | I59: =Worldprices!$K$73*I$7 -> 20.23 | J59: =AI59 -> 20.23 | K59: =Worldprices!$K$73*K$7 -> 20.23 | L59: =Worldprices!$K$73*L$7 -> 20.23 | M59: =Worldprices!$K$73*M$7 -> 20.23 | N59: =Worldprices!$K$73*N$7 -> 20.23 | O59: =Worldprices!$K$73*O$7 -> 20.23 | P59: =Worldprices!$K$73*P$7 -> 20.23 | Q59: =Worldprices!$K$73*Q$7 -> 20.23 | R59: =Worldprices!$K$73*R$7 -> 20.23 | ... AQ59: =Worldprices!$K$73*AQ$7 -> 20.23 | AR59: =AQ59 -> 20.23
A60: ANNUAL | B60: EUR10 | D60: =IF(RIGHT(F60,6)="GASNAT","*","COST") -> COST | E60: 2040 | F60: =Worldprices!$L$62 -> IMPOILKER | G60: =Worldprices!$L$63 -> OILKER | H60: =Worldprices!$L$73*H$7 -> 20.23 | I60: =Worldprices!$L$73*I$7 -> 20.23 | J60: =AI60 -> 20.23 | K60: =Worldprices!$L$73*K$7 -> 20.23 | L60: =Worldprices!$L$73*L$7 -> 20.23 | M60: =Worldprices!$L$73*M$7 -> 20.23 | N60: =Worldprices!$L$73*N$7 -> 20.23 | O60: =Worldprices!$L$73*O$7 -> 20.23 | P60: =Worldprices!$L$73*P$7 -> 20.23 | Q60: =Worldprices!$L$73*Q$7 -> 20.23 | R60: =Worldprices!$L$73*R$7 -> 20.23 | ... AQ60: =Worldprices!$L$73*AQ$7 -> 20.23 | AR60: =AQ60 -> 20.23
A61: ANNUAL | B61: EUR10 | D61: =IF(RIGHT(F61,6)="GASNAT","*","COST") -> * | E61: 2040 | F61: =Worldprices!$Q$62 -> IMPGASNAT | G61: =Worldprices!$Q$63 -> GASNAT | H61: =Worldprices!$Q$73*H$8 -> 7 | I61: =Worldprices!$Q$73*I$8 -> 7 | J61: =AI61 -> 7 | K61: =Worldprices!$Q$73*K$8 -> 7 | L61: =Worldprices!$Q$73*L$8 -> 7 | M61: =Worldprices!$Q$73*M$8 -> 7 | N61: =Worldprices!$Q$73*N$8 -> 7 | O61: =Worldprices!$Q$73*O$8 -> 7 | P61: =Worldprices!$Q$73*P$8 -> 5.95 | Q61: =Worldprices!$Q$73*Q$8 -> 6.3 | R61: =Worldprices!$Q$73*R$8 -> 7 | ... AQ61: =Worldprices!$Q$73*AQ$8 -> 7 | AR61: =AQ61 -> 7
A62: ANNUAL | B62: EUR10 | D62: =IF(RIGHT(F62,6)="GASNAT","*","COST") -> COST | E62: 2045 | F62: =Worldprices!$G$62 -> IMPOILCRD | G62: =Worldprices!$G$63 -> OILCRD | H62: =Worldprices!$G$74*H$5 -> 14.364 | I62: =Worldprices!$G$74*I$5 -> 15.96 | J62: =AI62 -> 15.96 | K62: =Worldprices!$G$74*K$5 -> 15.96 | L62: =Worldprices!$G$74*L$5 -> 15.96 | M62: =Worldprices!$G$74*M$5 -> 15.96 | N62: =Worldprices!$G$74*N$5 -> 15.96 | O62: =Worldprices!$G$74*O$5 -> 15.96 | P62: =Worldprices!$G$74*P$5 -> 13.566 | Q62: =Worldprices!$G$74*Q$5 -> 15.96 | R62: =Worldprices!$G$74*R$5 -> 15.96 | ... AQ62: =Worldprices!$G$74*AQ$5 -> 15.96 | AR62: =AQ62 -> 15.96
A63: ANNUAL | B63: EUR10 | D63: =IF(RIGHT(F63,6)="GASNAT","*","COST") -> COST | E63: 2045 | F63: =Worldprices!$H$62 -> IMPOILHFO | G63: =Worldprices!$H$63 -> OILHFO | H63: =Worldprices!$H$74*H$5 -> 11.63484 | I63: =Worldprices!$H$74*I$5 -> 12.9276 | J63: =AI63 -> 12.9276 | K63: =Worldprices!$H$74*K$5 -> 12.9276 | L63: =Worldprices!$H$74*L$5 -> 12.9276 | M63: =Worldprices!$H$74*M$5 -> 12.9276 | N63: =Worldprices!$H$74*N$5 -> 12.9276 | O63: =Worldprices!$H$74*O$5 -> 12.9276 | P63: =Worldprices!$H$74*P$5 -> 10.98846 | Q63: =Worldprices!$H$74*Q$5 -> 12.9276 | R63: =Worldprices!$H$74*R$5 -> 12.9276 | ... AQ63: =Worldprices!$H$74*AQ$5 -> 12.9276 | AR63: =AQ63 -> 12.9276
A64: ANNUAL | B64: EUR10 | D64: =IF(RIGHT(F64,6)="GASNAT","*","COST") -> COST | E64: 2045 | F64: =Worldprices!$I$62 -> IMPOILDST | G64: =Worldprices!$I$63 -> OILDST | H64: =Worldprices!$I$74*H$6 -> 20.748 | I64: =Worldprices!$I$74*I$6 -> 20.748 | J64: =AI64 -> 20.748 | K64: =Worldprices!$I$74*K$6 -> 20.748 | L64: =Worldprices!$I$74*L$6 -> 20.748 | M64: =Worldprices!$I$74*M$6 -> 20.748 | N64: =Worldprices!$I$74*N$6 -> 20.748 | O64: =Worldprices!$I$74*O$6 -> 20.748 | P64: =Worldprices!$I$74*P$6 -> 20.748 | Q64: =Worldprices!$I$74*Q$6 -> 20.748 | R64: =Worldprices!$I$74*R$6 -> 20.748 | ... AQ64: =Worldprices!$I$74*AQ$6 -> 20.748 | AR64: =AQ64 -> 20.748
A65: ANNUAL | B65: EUR10 | D65: =IF(RIGHT(F65,6)="GASNAT","*","COST") -> COST | E65: 2045 | F65: =Worldprices!$J$62 -> IMPOILLPG | G65: =Worldprices!$J$63 -> OILLPG | H65: =Worldprices!$J$74*H$7 -> 17.556 | I65: =Worldprices!$J$74*I$7 -> 17.556 | J65: =AI65 -> 17.556 | K65: =Worldprices!$J$74*K$7 -> 17.556 | L65: =Worldprices!$J$74*L$7 -> 17.556 | M65: =Worldprices!$J$74*M$7 -> 17.556 | N65: =Worldprices!$J$74*N$7 -> 17.556 | O65: =Worldprices!$J$74*O$7 -> 17.556 | P65: =Worldprices!$J$74*P$7 -> 17.556 | Q65: =Worldprices!$J$74*Q$7 -> 17.556 | R65: =Worldprices!$J$74*R$7 -> 17.556 | ... AQ65: =Worldprices!$J$74*AQ$7 -> 17.556 | AR65: =AQ65 -> 17.556
A66: ANNUAL | B66: EUR10 | D66: =IF(RIGHT(F66,6)="GASNAT","*","COST") -> COST | E66: 2045 | F66: =Worldprices!$K$62 -> IMPOILGSL | G66: =Worldprices!$K$63 -> OILGSL | H66: =Worldprices!$K$74*H$7 -> 22.344 | I66: =Worldprices!$K$74*I$7 -> 22.344 | J66: =AI66 -> 22.344 | K66: =Worldprices!$K$74*K$7 -> 22.344 | L66: =Worldprices!$K$74*L$7 -> 22.344 | M66: =Worldprices!$K$74*M$7 -> 22.344 | N66: =Worldprices!$K$74*N$7 -> 22.344 | O66: =Worldprices!$K$74*O$7 -> 22.344 | P66: =Worldprices!$K$74*P$7 -> 22.344 | Q66: =Worldprices!$K$74*Q$7 -> 22.344 | R66: =Worldprices!$K$74*R$7 -> 22.344 | ... AQ66: =Worldprices!$K$74*AQ$7 -> 22.344 | AR66: =AQ66 -> 22.344
A67: ANNUAL | B67: EUR10 | D67: =IF(RIGHT(F67,6)="GASNAT","*","COST") -> COST | E67: 2045 | F67: =Worldprices!$L$62 -> IMPOILKER | G67: =Worldprices!$L$63 -> OILKER | H67: =Worldprices!$L$74*H$7 -> 22.344 | I67: =Worldprices!$L$74*I$7 -> 22.344 | J67: =AI67 -> 22.344 | K67: =Worldprices!$L$74*K$7 -> 22.344 | L67: =Worldprices!$L$74*L$7 -> 22.344 | M67: =Worldprices!$L$74*M$7 -> 22.344 | N67: =Worldprices!$L$74*N$7 -> 22.344 | O67: =Worldprices!$L$74*O$7 -> 22.344 | P67: =Worldprices!$L$74*P$7 -> 22.344 | Q67: =Worldprices!$L$74*Q$7 -> 22.344 | R67: =Worldprices!$L$74*R$7 -> 22.344 | ... AQ67: =Worldprices!$L$74*AQ$7 -> 22.344 | AR67: =AQ67 -> 22.344
A68: ANNUAL | B68: EUR10 | D68: =IF(RIGHT(F68,6)="GASNAT","*","COST") -> * | E68: 2045 | F68: =Worldprices!$Q$62 -> IMPGASNAT | G68: =Worldprices!$Q$63 -> GASNAT | H68: =Worldprices!$Q$74*H$8 -> 7 | I68: =Worldprices!$Q$74*I$8 -> 7 | J68: =AI68 -> 7 | K68: =Worldprices!$Q$74*K$8 -> 7 | L68: =Worldprices!$Q$74*L$8 -> 7 | M68: =Worldprices!$Q$74*M$8 -> 7 | N68: =Worldprices!$Q$74*N$8 -> 7 | O68: =Worldprices!$Q$74*O$8 -> 7 | P68: =Worldprices!$Q$74*P$8 -> 5.95 | Q68: =Worldprices!$Q$74*Q$8 -> 6.3 | R68: =Worldprices!$Q$74*R$8 -> 7 | ... AQ68: =Worldprices!$Q$74*AQ$8 -> 7 | AR68: =AQ68 -> 7
A69: ANNUAL | B69: EUR10 | D69: =IF(RIGHT(F69,6)="GASNAT","*","COST") -> COST | E69: 2050 | F69: =Worldprices!$G$62 -> IMPOILCRD | G69: =Worldprices!$G$63 -> OILCRD | H69: =Worldprices!$G$75*H$5 -> 15.723 | I69: =Worldprices!$G$75*I$5 -> 17.47 | J69: =AI69 -> 17.47 | K69: =Worldprices!$G$75*K$5 -> 17.47 | L69: =Worldprices!$G$75*L$5 -> 17.47 | M69: =Worldprices!$G$75*M$5 -> 17.47 | N69: =Worldprices!$G$75*N$5 -> 17.47 | O69: =Worldprices!$G$75*O$5 -> 17.47 | P69: =Worldprices!$G$75*P$5 -> 14.8495 | Q69: =Worldprices!$G$75*Q$5 -> 17.47 | R69: =Worldprices!$G$75*R$5 -> 17.47 | ... AQ69: =Worldprices!$G$75*AQ$5 -> 17.47 | AR69: =AQ69 -> 17.47
A70: ANNUAL | B70: EUR10 | D70: =IF(RIGHT(F70,6)="GASNAT","*","COST") -> COST | E70: 2050 | F70: =Worldprices!$H$62 -> IMPOILHFO | G70: =Worldprices!$H$63 -> OILHFO | H70: =Worldprices!$H$75*H$5 -> 12.73563 | I70: =Worldprices!$H$75*I$5 -> 14.1507 | J70: =AI70 -> 14.1507 | K70: =Worldprices!$H$75*K$5 -> 14.1507 | L70: =Worldprices!$H$75*L$5 -> 14.1507 | M70: =Worldprices!$H$75*M$5 -> 14.1507 | N70: =Worldprices!$H$75*N$5 -> 14.1507 | O70: =Worldprices!$H$75*O$5 -> 14.1507 | P70: =Worldprices!$H$75*P$5 -> 12.028095 | Q70: =Worldprices!$H$75*Q$5 -> 14.1507 | R70: =Worldprices!$H$75*R$5 -> 14.1507 | ... AQ70: =Worldprices!$H$75*AQ$5 -> 14.1507 | AR70: =AQ70 -> 14.1507
A71: ANNUAL | B71: EUR10 | D71: =IF(RIGHT(F71,6)="GASNAT","*","COST") -> COST | E71: 2050 | F71: =Worldprices!$I$62 -> IMPOILDST | G71: =Worldprices!$I$63 -> OILDST | H71: =Worldprices!$I$75*H$6 -> 22.711 | I71: =Worldprices!$I$75*I$6 -> 22.711 | J71: =AI71 -> 22.711 | K71: =Worldprices!$I$75*K$6 -> 22.711 | L71: =Worldprices!$I$75*L$6 -> 22.711 | M71: =Worldprices!$I$75*M$6 -> 22.711 | N71: =Worldprices!$I$75*N$6 -> 22.711 | O71: =Worldprices!$I$75*O$6 -> 22.711 | P71: =Worldprices!$I$75*P$6 -> 22.711 | Q71: =Worldprices!$I$75*Q$6 -> 22.711 | R71: =Worldprices!$I$75*R$6 -> 22.711 | ... AQ71: =Worldprices!$I$75*AQ$6 -> 22.711 | AR71: =AQ71 -> 22.711
A72: ANNUAL | B72: EUR10 | D72: =IF(RIGHT(F72,6)="GASNAT","*","COST") -> COST | E72: 2050 | F72: =Worldprices!$J$62 -> IMPOILLPG | G72: =Worldprices!$J$63 -> OILLPG | H72: =Worldprices!$J$75*H$7 -> 19.217 | I72: =Worldprices!$J$75*I$7 -> 19.217 | J72: =AI72 -> 19.217 | K72: =Worldprices!$J$75*K$7 -> 19.217 | L72: =Worldprices!$J$75*L$7 -> 19.217 | M72: =Worldprices!$J$75*M$7 -> 19.217 | N72: =Worldprices!$J$75*N$7 -> 19.217 | O72: =Worldprices!$J$75*O$7 -> 19.217 | P72: =Worldprices!$J$75*P$7 -> 19.217 | Q72: =Worldprices!$J$75*Q$7 -> 19.217 | R72: =Worldprices!$J$75*R$7 -> 19.217 | ... AQ72: =Worldprices!$J$75*AQ$7 -> 19.217 | AR72: =AQ72 -> 19.217
A73: ANNUAL | B73: EUR10 | D73: =IF(RIGHT(F73,6)="GASNAT","*","COST") -> COST | E73: 2050 | F73: =Worldprices!$K$62 -> IMPOILGSL | G73: =Worldprices!$K$63 -> OILGSL | H73: =Worldprices!$K$75*H$7 -> 24.458 | I73: =Worldprices!$K$75*I$7 -> 24.458 | J73: =AI73 -> 24.458 | K73: =Worldprices!$K$75*K$7 -> 24.458 | L73: =Worldprices!$K$75*L$7 -> 24.458 | M73: =Worldprices!$K$75*M$7 -> 24.458 | N73: =Worldprices!$K$75*N$7 -> 24.458 | O73: =Worldprices!$K$75*O$7 -> 24.458 | P73: =Worldprices!$K$75*P$7 -> 24.458 | Q73: =Worldprices!$K$75*Q$7 -> 24.458 | R73: =Worldprices!$K$75*R$7 -> 24.458 | ... AQ73: =Worldprices!$K$75*AQ$7 -> 24.458 | AR73: =AQ73 -> 24.458
A74: ANNUAL | B74: EUR10 | D74: =IF(RIGHT(F74,6)="GASNAT","*","COST") -> COST | E74: 2050 | F74: =Worldprices!$L$62 -> IMPOILKER | G74: =Worldprices!$L$63 -> OILKER | H74: =Worldprices!$L$75*H$7 -> 24.458 | I74: =Worldprices!$L$75*I$7 -> 24.458 | J74: =AI74 -> 24.458 | K74: =Worldprices!$L$75*K$7 -> 24.458 | L74: =Worldprices!$L$75*L$7 -> 24.458 | M74: =Worldprices!$L$75*M$7 -> 24.458 | N74: =Worldprices!$L$75*N$7 -> 24.458 | O74: =Worldprices!$L$75*O$7 -> 24.458 | P74: =Worldprices!$L$75*P$7 -> 24.458 | Q74: =Worldprices!$L$75*Q$7 -> 24.458 | R74: =Worldprices!$L$75*R$7 -> 24.458 | ... AQ74: =Worldprices!$L$75*AQ$7 -> 24.458 | AR74: =AQ74 -> 24.458
A75: ANNUAL | B75: EUR10 | D75: =IF(RIGHT(F75,6)="GASNAT","*","COST") -> * | E75: 2050 | F75: =Worldprices!$Q$62 -> IMPGASNAT | G75: =Worldprices!$Q$63 -> GASNAT | H75: =Worldprices!$Q$75*H$8 -> 7 | I75: =Worldprices!$Q$75*I$8 -> 7 | J75: =AI75 -> 7 | K75: =Worldprices!$Q$75*K$8 -> 7 | L75: =Worldprices!$Q$75*L$8 -> 7 | M75: =Worldprices!$Q$75*M$8 -> 7 | N75: =Worldprices!$Q$75*N$8 -> 7 | O75: =Worldprices!$Q$75*O$8 -> 7 | P75: =Worldprices!$Q$75*P$8 -> 5.95 | Q75: =Worldprices!$Q$75*Q$8 -> 6.3 | R75: =Worldprices!$Q$75*R$8 -> 7 | ... AQ75: =Worldprices!$Q$75*AQ$8 -> 7 | AR75: =AQ75 -> 7
A76: ANNUAL | B76: EUR10 | D76: * | E76: EXPORT PRICES: 1% less than above
A77: ANNUAL | B77: EUR10 | D77: =IF(RIGHT(F77,6)="GASNAT","*","COST") -> COST | E77: =E13 -> 2010 | F77: ="EXP"&G77 -> EXPOILCRD | G77: =G13 -> OILCRD | H77: =H13*0.99 -> 8.7493279 | I77: =I13*0.99 -> 9.7214754 | J77: =J13*0.99 -> 9.7214754 | K77: =K13*0.99 -> 9.7214754 | L77: =L13*0.99 -> 9.7214754 | M77: =M13*0.99 -> 9.7214754 | N77: =N13*0.99 -> 9.7214754 | O77: =O13*0.99 -> 9.7214754 | ... AQ77: =AQ13*0.99 -> 9.7214754 | AR77: =AQ77 -> 9.7214754
A78: ANNUAL | B78: EUR10 | D78: =IF(RIGHT(F78,6)="GASNAT","*","COST") -> COST | E78: =E14 -> 2010 | F78: ="EXP"&G78 -> EXPOILHFO | G78: =G14 -> OILHFO | H78: =H14*0.99 -> 7.0869556 | I78: =I14*0.99 -> 7.8743951 | J78: =J14*0.99 -> 7.8743951 | K78: =K14*0.99 -> 7.8743951 | L78: =L14*0.99 -> 7.8743951 | M78: =M14*0.99 -> 7.8743951 | N78: =N14*0.99 -> 7.8743951 | O78: =O14*0.99 -> 7.8743951 | ... AQ78: =AQ14*0.99 -> 7.8743951 | AR78: =AQ78 -> 7.8743951
A79: ANNUAL | B79: EUR10 | D79: =IF(RIGHT(F79,6)="GASNAT","*","COST") -> COST | E79: =E15 -> 2010 | F79: ="EXP"&G79 -> EXPOILDST | G79: =G15 -> OILDST | H79: =H15*0.99 -> 12.637918 | I79: =I15*0.99 -> 12.637918 | J79: =J15*0.99 -> 12.637918 | K79: =K15*0.99 -> 12.637918 | L79: =L15*0.99 -> 12.637918 | M79: =M15*0.99 -> 12.637918 | N79: =N15*0.99 -> 12.637918 | O79: =O15*0.99 -> 12.637918 | ... AQ79: =AQ15*0.99 -> 12.637918 | AR79: =AQ79 -> 12.637918
A80: ANNUAL | B80: EUR10 | D80: =IF(RIGHT(F80,6)="GASNAT","*","COST") -> COST | E80: =E16 -> 2010 | F80: ="EXP"&G80 -> EXPOILLPG | G80: =G16 -> OILLPG | H80: =H16*0.99 -> 10.693623 | I80: =I16*0.99 -> 10.693623 | J80: =J16*0.99 -> 10.693623 | K80: =K16*0.99 -> 10.693623 | L80: =L16*0.99 -> 10.693623 | M80: =M16*0.99 -> 10.693623 | N80: =N16*0.99 -> 10.693623 | O80: =O16*0.99 -> 10.693623 | ... AQ80: =AQ16*0.99 -> 10.693623 | AR80: =AQ80 -> 10.693623
A81: ANNUAL | B81: EUR10 | D81: =IF(RIGHT(F81,6)="GASNAT","*","COST") -> COST | E81: =E17 -> 2010 | F81: ="EXP"&G81 -> EXPOILGSL | G81: =G17 -> OILGSL | H81: =H17*0.99 -> 13.610066 | I81: =I17*0.99 -> 13.610066 | J81: =J17*0.99 -> 13.610066 | K81: =K17*0.99 -> 13.610066 | L81: =L17*0.99 -> 13.610066 | M81: =M17*0.99 -> 13.610066 | N81: =N17*0.99 -> 13.610066 | O81: =O17*0.99 -> 13.610066 | ... AQ81: =AQ17*0.99 -> 13.610066 | AR81: =AQ81 -> 13.610066
A82: ANNUAL | B82: EUR10 | D82: =IF(RIGHT(F82,6)="GASNAT","*","COST") -> COST | E82: =E18 -> 2010 | F82: ="EXP"&G82 -> EXPOILKER | G82: =G18 -> OILKER | H82: =H18*0.99 -> 13.610066 | I82: =I18*0.99 -> 13.610066 | J82: =J18*0.99 -> 13.610066 | K82: =K18*0.99 -> 13.610066 | L82: =L18*0.99 -> 13.610066 | M82: =M18*0.99 -> 13.610066 | N82: =N18*0.99 -> 13.610066 | O82: =O18*0.99 -> 13.610066 | ... AQ82: =AQ18*0.99 -> 13.610066 | AR82: =AQ82 -> 13.610066
A83: ANNUAL | B83: EUR10 | D83: =IF(RIGHT(F83,6)="GASNAT","*","COST") -> * | E83: =E19 -> 2010 | F83: ="EXP"&G83 -> EXPGASNAT | G83: =G19 -> GASNAT | H83: =H19*0.99 -> 6.1347541 | I83: =I19*0.99 -> 6.1347541 | J83: =J19*0.99 -> 6.1347541 | K83: =K19*0.99 -> 6.1347541 | L83: =L19*0.99 -> 6.1347541 | M83: =M19*0.99 -> 6.1347541 | N83: =N19*0.99 -> 6.1347541 | O83: =O19*0.99 -> 6.1347541 | ... AQ83: =AQ19*0.99 -> 6.1347541 | AR83: =AQ83 -> 6.1347541
A84: ANNUAL | B84: EUR10 | D84: =IF(RIGHT(F84,6)="GASNAT","*","COST") -> COST | E84: =E20 -> 2015 | F84: ="EXP"&G84 -> EXPOILCRD | G84: =G20 -> OILCRD | H84: =H20*0.99 -> 8.5222689 | I84: =I20*0.99 -> 9.4691877 | J84: =J20*0.99 -> 9.4691877 | K84: =K20*0.99 -> 9.4691877 | L84: =L20*0.99 -> 9.4691877 | M84: =M20*0.99 -> 9.4691877 | N84: =N20*0.99 -> 9.4691877 | O84: =O20*0.99 -> 9.4691877 | ... AQ84: =AQ20*0.99 -> 9.4691877 | AR84: =AQ84 -> 9.4691877
A85: ANNUAL | B85: EUR10 | D85: =IF(RIGHT(F85,6)="GASNAT","*","COST") -> COST | E85: =E21 -> 2015 | F85: ="EXP"&G85 -> EXPOILHFO | G85: =G21 -> OILHFO | H85: =H21*0.99 -> 6.9030378 | I85: =I21*0.99 -> 7.670042 | J85: =J21*0.99 -> 7.670042 | K85: =K21*0.99 -> 7.670042 | L85: =L21*0.99 -> 7.670042 | M85: =M21*0.99 -> 7.670042 | N85: =N21*0.99 -> 7.670042 | O85: =O21*0.99 -> 7.670042 | ... AQ85: =AQ21*0.99 -> 7.670042 | AR85: =AQ85 -> 7.670042
A86: ANNUAL | B86: EUR10 | D86: =IF(RIGHT(F86,6)="GASNAT","*","COST") -> COST | E86: =E22 -> 2015 | F86: ="EXP"&G86 -> EXPOILDST | G86: =G22 -> OILDST | H86: =H22*0.99 -> 12.309944 | I86: =I22*0.99 -> 12.309944 | J86: =J22*0.99 -> 12.309944 | K86: =K22*0.99 -> 12.309944 | L86: =L22*0.99 -> 12.309944 | M86: =M22*0.99 -> 12.309944 | N86: =N22*0.99 -> 12.309944 | O86: =O22*0.99 -> 12.309944 | ... AQ86: =AQ22*0.99 -> 12.309944 | AR86: =AQ86 -> 12.309944
A87: ANNUAL | B87: EUR10 | D87: =IF(RIGHT(F87,6)="GASNAT","*","COST") -> COST | E87: =E23 -> 2015 | F87: ="EXP"&G87 -> EXPOILLPG | G87: =G23 -> OILLPG | H87: =H23*0.99 -> 10.416106 | I87: =I23*0.99 -> 10.416106 | J87: =J23*0.99 -> 10.416106 | K87: =K23*0.99 -> 10.416106 | L87: =L23*0.99 -> 10.416106 | M87: =M23*0.99 -> 10.416106 | N87: =N23*0.99 -> 10.416106 | O87: =O23*0.99 -> 10.416106 | ... AQ87: =AQ23*0.99 -> 10.416106 | AR87: =AQ87 -> 10.416106
A88: ANNUAL | B88: EUR10 | D88: =IF(RIGHT(F88,6)="GASNAT","*","COST") -> COST | E88: =E24 -> 2015 | F88: ="EXP"&G88 -> EXPOILGSL | G88: =G24 -> OILGSL | H88: =H24*0.99 -> 13.256863 | I88: =I24*0.99 -> 13.256863 | J88: =J24*0.99 -> 13.256863 | K88: =K24*0.99 -> 13.256863 | L88: =L24*0.99 -> 13.256863 | M88: =M24*0.99 -> 13.256863 | N88: =N24*0.99 -> 13.256863 | O88: =O24*0.99 -> 13.256863 | ... AQ88: =AQ24*0.99 -> 13.256863 | AR88: =AQ88 -> 13.256863
... A139: ANNUAL | B139: EUR10 | D139: =IF(RIGHT(F139,6)="GASNAT","*","COST") -> * | E139: =E75 -> 2050 | F139: ="EXP"&G139 -> EXPGASNAT | G139: =G75 -> GASNAT | H139: =H75*0.99 -> 6.93 | I139: =I75*0.99 -> 6.93 | J139: =J75*0.99 -> 6.93 | K139: =K75*0.99 -> 6.93 | L139: =L75*0.99 -> 6.93 | M139: =M75*0.99 -> 6.93 | N139: =N75*0.99 -> 6.93 | O139: =O75*0.99 -> 6.93 | ... AQ139: =AQ75*0.99 -> 6.93 | AR139: =AQ139 -> 6.93
A143: ~TFM_INS
A144: =A12 -> TimeSlice | B144: Curr | C144: =C12 -> LimType | D144: =D12 -> Attribute | E144: =E12 -> Year | F144: =F12 -> Pset_PN | G144: =G12 -> Cset_CN | H144: =H12 -> AT | I144: =I12 -> BE | J144: =J12 -> BG | ... AQ144: =AQ12 -> RS | AR144: KS
A145: =A19 -> ANNUAL | B145: EUR10 | D145: COST | E145: =E19 -> 2010 | F145: IMPGAS*,-*BkStp | G145: =G19 -> GASNAT | H145: =H19 -> 6.1967213 | I145: =I19 -> 6.1967213 | J145: =J19 -> 6.1967213 | K145: =K19 -> 6.1967213 | L145: =L19 -> 6.1967213 | M145: =M19 -> 6.1967213 | N145: =N19 -> 6.1967213 | ... AQ145: =AQ19 -> 6.1967213 | AR145: =AQ145 -> 6.1967213
A146: =A26 -> ANNUAL | B146: EUR10 | D146: COST | E146: =E26 -> 2015 | F146: IMPGAS*,-*BkStp | G146: =G26 -> GASNAT | H146: =H26 -> 9.7933607 | I146: =I26 -> 9.7933607 | J146: =J26 -> 9.7933607 | K146: =K26 -> 9.7933607 | L146: =L26 -> 9.7933607 | M146: =M26 -> 9.7933607 | N146: =N26 -> 9.7933607 | ... AQ146: =AQ26 -> 9.7933607 | AR146: =AQ146 -> 9.7933607
A147: =A33 -> ANNUAL | B147: EUR10 | D147: COST | E147: =E33 -> 2020 | F147: IMPGAS*,-*BkStp | G147: =G33 -> GASNAT | H147: =H33 -> 13.39 | I147: =I33 -> 13.39 | J147: =J33 -> 13.39 | K147: =K33 -> 13.39 | L147: =L33 -> 13.39 | M147: =M33 -> 13.39 | N147: =N33 -> 13.39 | ... AQ147: =AQ33 -> 13.39 | AR147: =AQ147 -> 13.39
A148: =A40 -> ANNUAL | B148: EUR10 | D148: COST | E148: =E40 -> 2025 | F148: IMPGAS*,-*BkStp | G148: =G40 -> GASNAT | H148: =H40 -> 10.195 | I148: =I40 -> 10.195 | J148: =J40 -> 10.195 | K148: =K40 -> 10.195 | L148: =L40 -> 10.195 | M148: =M40 -> 10.195 | N148: =N40 -> 10.195 | ... AQ148: =AQ40 -> 10.195 | AR148: =AQ148 -> 10.195
A149: =A47 -> ANNUAL | B149: EUR10 | D149: COST | E149: =E47 -> 2030 | F149: IMPGAS*,-*BkStp | G149: =G47 -> GASNAT | H149: =H47 -> 7 | I149: =I47 -> 7 | J149: =J47 -> 7 | K149: =K47 -> 7 | L149: =L47 -> 7 | M149: =M47 -> 7 | N149: =N47 -> 7 | ... AQ149: =AQ47 -> 7 | AR149: =AQ149 -> 7
A150: =A54 -> ANNUAL | B150: EUR10 | D150: COST | E150: =E54 -> 2035 | F150: IMPGAS*,-*BkStp | G150: =G54 -> GASNAT | H150: =H54 -> 7 | I150: =I54 -> 7 | J150: =J54 -> 7 | K150: =K54 -> 7 | L150: =L54 -> 7 | M150: =M54 -> 7 | N150: =N54 -> 7 | ... AQ150: =AQ54 -> 7 | AR150: =AQ150 -> 7
A151: =A61 -> ANNUAL | B151: EUR10 | D151: COST | E151: =E61 -> 2040 | F151: IMPGAS*,-*BkStp | G151: =G61 -> GASNAT | H151: =H61 -> 7 | I151: =I61 -> 7 | J151: =J61 -> 7 | K151: =K61 -> 7 | L151: =L61 -> 7 | M151: =M61 -> 7 | N151: =N61 -> 7 | ... AQ151: =AQ61 -> 7 | AR151: =AQ151 -> 7
A152: =A68 -> ANNUAL | B152: EUR10 | D152: COST | E152: =E68 -> 2045 | F152: IMPGAS*,-*BkStp | G152: =G68 -> GASNAT | H152: =H68 -> 7 | I152: =I68 -> 7 | J152: =J68 -> 7 | K152: =K68 -> 7 | L152: =L68 -> 7 | M152: =M68 -> 7 | N152: =N68 -> 7 | ... AQ152: =AQ68 -> 7 | AR152: =AQ152 -> 7
A153: =A75 -> ANNUAL | B153: EUR10 | D153: COST | E153: =E75 -> 2050 | F153: IMPGAS*,-*BkStp | G153: =G75 -> GASNAT | H153: =H75 -> 7 | I153: =I75 -> 7 | J153: =J75 -> 7 | K153: =K75 -> 7 | L153: =L75 -> 7 | M153: =M75 -> 7 | N153: =N75 -> 7 | ... AQ153: =AQ75 -> 7 | AR153: =AQ153 -> 7
A154: =A145 -> ANNUAL | B154: EUR10 | D154: =D145 -> COST | E154: =E145 -> 2010 | F154: IMPLNG* | G154: GASLNG | H154: =H145*1.1 -> 6.8163934 | I154: =I145*1.1 -> 6.8163934 | J154: =J145*1.1 -> 6.8163934 | K154: =K145*1.1 -> 6.8163934 | L154: =L145*1.1 -> 6.8163934 | M154: =M145*1.1 -> 6.8163934 | N154: =N145*1.1 -> 6.8163934 | O154: =O145*1.1 -> 6.8163934 | ... AQ154: =AQ145*1.1 -> 6.8163934 | AR154: =AQ154 -> 6.8163934
A155: =A146 -> ANNUAL | B155: EUR10 | D155: =D146 -> COST | E155: =E146 -> 2015 | F155: IMPLNG* | G155: GASLNG | H155: =H146*1.1 -> 10.772697 | I155: =I146*1.1 -> 10.772697 | J155: =J146*1.1 -> 10.772697 | K155: =K146*1.1 -> 10.772697 | L155: =L146*1.1 -> 10.772697 | M155: =M146*1.1 -> 10.772697 | N155: =N146*1.1 -> 10.772697 | O155: =O146*1.1 -> 10.772697 | ... AQ155: =AQ146*1.1 -> 10.772697 | AR155: =AQ155 -> 10.772697
A156: =A147 -> ANNUAL | B156: EUR10 | D156: =D147 -> COST | E156: =E147 -> 2020 | F156: IMPLNG* | G156: GASLNG | H156: =H147*1.1 -> 14.729 | I156: =I147*1.1 -> 14.729 | J156: =J147*1.1 -> 14.729 | K156: =K147*1.1 -> 14.729 | L156: =L147*1.1 -> 14.729 | M156: =M147*1.1 -> 14.729 | N156: =N147*1.1 -> 14.729 | O156: =O147*1.1 -> 14.729 | ... AQ156: =AQ147*1.1 -> 14.729 | AR156: =AQ156 -> 14.729
...

Sheet INPUTtoVEDA_miningprice
B2: ~TFM_FILL
B3: Operation_Sum_Avg_Count | C3: Scenario Name | D3: TimeSlice | E3: LimType | F3: Attribute | G3: Year | H3: Other_Indexes | I3: Pset_PN | J3: AllRegions | K3: AT | L3: BE | M3: BG | N3: CH | O3: CY | P3: CZ | Q3: DE | R3: DK | S3: EE | T3: ES | U3: FI | V3: FR | W3: EL | X3: HU | Y3: IE | Z3: IS | AA3: IT | AB3: LT | AC3: LU | AD3: LV | AE3: MT | AF3: NL | AG3: NO | AH3: PL | AI3: PT | AJ3: RO | AK3: SE | AL3: SI | AM3: SK | AN3: UK | AO3: AL | AP3: BA | AQ3: HR | AR3: KS | AS3: ME | AT3: MK | AU3: RS
B4: A | C4: BASE | F4: COST | I4: MINCOHRSV1 | M4: 1.85 | P4: 1.39775 | Q4: 1.85 | T4: 1.85 | V4: 2.64495 | X4: 2.64495 | Z4: 1.2 | AA4: 1.85 | AH4: 1.39775 | AJ4: 1.39775 | AL4: 1.85 | AN4: 1.365 | AU4: 1.85
B5: A | C5: BASE | F5: COST | I5: MINCOHRSV2 | P5: 1.85 | Q5: 2.64495 | T5: 2.775 | AA5: 2.64495 | AG5: 1.39775 | AH5: 1.85 | AJ5: 1.39775 | AL5: 2.64495 | AN5: 1.39775
B6: A | C6: BASE | F6: COST | I6: MINCOHRSV3 | T6: 2.64495 | AA6: 2.64495 | AJ6: 1.85
B7: A | C7: BASE | F7: COST | I7: MINCOLRSV1 | K7: 1.097 | M7: 1.29865 | P7: 1.097 | Q7: 1.22 | S7: 1.097 | T7: 1.5 | U7: 0.994 | W7: 1.5 | X7: 1.2 | Y7: 1.097 | AA7: 1.22 | AB7: 1.097 | AD7: 1.097 | AH7: 1.097 | AJ7: 1.097 | AK7: 1.22 | AL7: 1.22 | AM7: 1.22 | AO7: 1.22 | AP7: 1.22 | AR7: 1.22 | AS7: 1.22 | AT7: 1.22 | AU7: 1.22
B8: A | C8: BASE | F8: COST | I8: MINCOLRSV2 | P8: 1.22 | Q8: 1.5 | S8: 1.22 | T8: 2.25 | U8: 0.994 | W8: 1.5 | Y8: 1.097 | AA8: 1.5 | AH8: 1.22 | AJ8: 1.22 | AL8: 1.4973 | AP8: 1.5
B9: A | C9: BASE | F9: COST | I9: MINCOLRSV3 | S9: 1.22 | T9: 1.5 | U9: 1.22 | AA9: 1.5 | AJ9: 1.22
B10: A | C10: BASE | F10: COST | I10: MINGASRSV1 | K10: 1.825 | M10: 1.825 | P10: 1.825 | Q10: 1.825 | R10: 1.0504166 | T10: 1.825 | V10: 1.825 | W10: 2.6 | X10: 1.825 | Y10: 1.0504166 | AF10: 1.0504166 | AG10: 1.0504166 | AH10: 1.825 | AI10: 1.825 | AJ10: 1.825 | AK10: 1.825 | AM10: 1.825 | AN10: 1.0504166 | AO10: 1.825 | AQ10: 1.825 | AU10: 1.825
B11: A | C11: BASE | F11: \I: | I11: MINGASRSV2
B12: A | C12: BASE | F12: \I: | I12: MINGASRSV3
B13: A | C13: BASE | F13: COST | I13: MINGASRSV4 | K13: 2.6 | M13: 2.6 | P13: 2.6 | Q13: 2.6 | R13: 1.825 | T13: 2.6 | V13: 2.6 | W13: 2.6 | X13: 2.6 | Y13: 1.8717496 | AF13: 1.0504166 | AG13: 1.0504166 | AH13: 2.6 | AI13: 1.825 | AJ13: 2.6 | AK13: 1.825 | AM13: 2.6 | AN13: 1.825
B14: A | C14: BASE | F14: \I: | I14: MINGASRSV5
B15: A | C15: BASE | F15: \I: | I15: MINGASRSV6
B16: A | C16: BASE | F16: COST | I16: MINGASRSV7 | K16: 2.6 | P16: 2.6 | Q16: 2.6 | R16: 1.825 | T16: 2.6 | V16: 2.6 | X16: 2.6 | AF16: 1.825 | AG16: 1.0504166 | AH16: 2.6 | AJ16: 2.6 | AL16: 1.825 | AN16: 1.825
B17: A | C17: BASE | F17: \I: | I17: MINGASRSV8
B18: A | C18: BASE | F18: \I: | I18: MINGASRSV9
B19: A | C19: BASE | F19: COST | I19: MINOILRSV1 | K19: 3 | M19: 1.8046779 | P19: 3 | Q19: 3 | R19: 1.8046779 | T19: 3 | V19: 3 | W19: 3 | X19: 3 | AB19: 3 | AF19: 1.8046779 | AG19: 1.8046779 | AH19: 3 | AJ19: 3 | AM19: 3 | AN19: 1.8046779 | AO19: 3 | AQ19: 3 | AU19: 3
B20: A | C20: BASE | F20: COST | I20: MINOILRSV2 | AB20: 3
B21: A | C21: BASE | F21: \I: | I21: MINOILRSV3
B22: A | C22: BASE | F22: COST | I22: MINOILRSV4 | K22: 3 | M22: 3 | P22: 3 | Q22: 3 | R22: 3 | T22: 4.5 | V22: 3.3 | W22: 3.3 | X22: 3.3 | AF22: 2.7070168 | AG22: 2.7070168 | AH22: 3 | AJ22: 4.5 | AM22: 3 | AN22: 2.7070168
B23: A | C23: BASE | F23: \I: | I23: MINOILRSV5
B24: A | C24: BASE | F24: \I: | I24: MINOILRSV6
B25: A | C25: BASE | F25: COST | I25: MINOILRSV7 | M25: 3.3 | P25: 3.3 | Q25: 3.3 | R25: 3 | T25: 5.25 | V25: 3.3 | X25: 3.3 | AF25: 3.1581863 | AG25: 3.1581863 | AH25: 3 | AJ25: 5.25 | AM25: 3.3 | AN25: 3.1581863
B26: A | C26: BASE | F26: \I: | I26: MINOILRSV8
B27: A | C27: BASE | F27: \I: | I27: MINOILRSV9
A31: Growth rate Import GASNAT and Crude oil
B32: GASNAT | C32: CRUDE
A33: =Worldprices!B65 -> 2001 | B33: =Worldprices!Q65/Worldprices!Q64 -> 1.2986213 | C33: =Worldprices!G65/Worldprices!G64 -> 0.83765716
A34: =Worldprices!B66 -> 2005 | B34: =Worldprices!Q66/Worldprices!Q65 -> 1.2768027 | C34: =Worldprices!G66/Worldprices!G65 -> 2.0258512
A35: =Worldprices!B67 -> 2010 | B35: =Worldprices!Q67/Worldprices!Q66 -> 1.3086858 | C35: =Worldprices!G67/Worldprices!G66 -> 1.1689297
A36: =Worldprices!B68 -> 2015 | B36: =Worldprices!Q68/Worldprices!Q67 -> 1.5804101 | C36: =Worldprices!G68/Worldprices!G67 -> 0.97404841
A37: =Worldprices!B69 -> 2020 | B37: =Worldprices!Q69/Worldprices!Q68 -> 1.3672528 | C37: =Worldprices!G69/Worldprices!G68 -> 0.97335699
A38: =Worldprices!B70 -> 2025 | B38: =Worldprices!Q70/Worldprices!Q69 -> 0.7613891 | C38: =Worldprices!G70/Worldprices!G69 -> 1.2330827
A39: =Worldprices!B71 -> 2030 | B39: =Worldprices!Q71/Worldprices!Q70 -> 0.68661108 | C39: =Worldprices!G71/Worldprices!G70 -> 1.1890244
A40: =Worldprices!B72 -> 2035 | B40: =Worldprices!Q72/Worldprices!Q71 -> 1 | C40: =Worldprices!G72/Worldprices!G71 -> 1.029304
A41: =Worldprices!B73 -> 2040 | B41: =Worldprices!Q73/Worldprices!Q72 -> 1 | C41: =Worldprices!G73/Worldprices!G72 -> 1.0284698
A42: =Worldprices!B74 -> 2045 | B42: =Worldprices!Q74/Worldprices!Q73 -> 1 | C42: =Worldprices!G74/Worldprices!G73 -> 1.1044983
A43: =Worldprices!B75 -> 2050 | B43: =Worldprices!Q75/Worldprices!Q74 -> 1 | C43: =Worldprices!G75/Worldprices!G74 -> 1.0946115
E45: ~TFM_INS
E46: TimeSlice | F46: LimType | G46: Attribute | H46: Year | I46: Pset_PN | J46: Cset_CN | K46: AT | L46: BE | M46: BG | N46: CH | O46: CY | P46: CZ | Q46: DE | R46: DK | S46: EE | T46: ES | U46: FI | V46: FR | W46: EL | X46: HU | Y46: IE | Z46: IS | AA46: IT | AB46: LT | AC46: LU | AD46: LV | AE46: MT | AF46: NL | AG46: NO | AH46: PL | AI46: PT | AJ46: RO | AK46: SE | AL46: SI | AM46: SK | AN46: UK | AO46: AL | AP46: BA | AQ46: HR | AR46: KS | AS46: ME | AT46: MK | AU46: RS
E47: ANNUAL | G47: COST | H47: =A$33 -> 2001 | I47: =I$10 -> MINGASRSV1 | J47: GASRSV | K47: =IF(K$10=0,"",K10*$B33) -> 2.3699838 | L47: =IF(L$10=0,"",L10*$B33) | M47: =IF(M$10=0,"",M10*$B33) -> 2.3699838 | N47: =IF(N$10=0,"",N10*$B33) | O47: =IF(O$10=0,"",O10*$B33) | P47: =IF(P$10=0,"",P10*$B33) -> 2.3699838 | Q47: =IF(Q$10=0,"",Q10*$B33) -> 2.3699838 | R47: =IF(R$10=0,"",R10*$B33) -> 1.3640933 | ... AU47: =IF(AU$10=0,"",AU10*$B33) -> 2.3699838
E48: ANNUAL | G48: COST | H48: =A$34 -> 2005 | I48: =I$10 -> MINGASRSV1 | J48: GASRSV | K48: =IF(K$10=0,"",K47*$B34) -> 3.0260018 | L48: =IF(L$10=0,"",L47*$B34) | M48: =IF(M$10=0,"",M47*$B34) -> 3.0260018 | N48: =IF(N$10=0,"",N47*$B34) | O48: =IF(O$10=0,"",O47*$B34) | P48: =IF(P$10=0,"",P47*$B34) -> 3.0260018 | Q48: =IF(Q$10=0,"",Q47*$B34) -> 3.0260018 | R48: =IF(R$10=0,"",R47*$B34) -> 1.7416781 | ... AU48: =IF(AU$10=0,"",AU47*$B34) -> 3.0260018
E49: ANNUAL | G49: COST | H49: =A$35 -> 2010 | I49: =I$10 -> MINGASRSV1 | J49: GASRSV | K49: =IF(K$10=0,"",K48*$B35) -> 3.9600856 | L49: =IF(L$10=0,"",L48*$B35) | M49: =IF(M$10=0,"",M48*$B35) -> 3.9600856 | N49: =IF(N$10=0,"",N48*$B35) | O49: =IF(O$10=0,"",O48*$B35) | P49: =IF(P$10=0,"",P48*$B35) -> 3.9600856 | Q49: =IF(Q$10=0,"",Q48*$B35) -> 3.9600856 | R49: =IF(R$10=0,"",R48*$B35) -> 2.2793094 | ... AU49: =IF(AU$10=0,"",AU48*$B35) -> 3.9600856
E50: ANNUAL | G50: COST | H50: =A$36 -> 2015 | I50: =I$10 -> MINGASRSV1 | J50: GASRSV | K50: =IF(K$10=0,"",K49*$B36) -> 6.2585591 | L50: =IF(L$10=0,"",L49*$B36) | M50: =IF(M$10=0,"",M49*$B36) -> 6.2585591 | N50: =IF(N$10=0,"",N49*$B36) | O50: =IF(O$10=0,"",O49*$B36) | P50: =IF(P$10=0,"",P49*$B36) -> 6.2585591 | Q50: =IF(Q$10=0,"",Q49*$B36) -> 6.2585591 | R50: =IF(R$10=0,"",R49*$B36) -> 3.6022435 | ... AU50: =IF(AU$10=0,"",AU49*$B36) -> 6.2585591
E51: ANNUAL | G51: COST | H51: =A$37 -> 2020 | I51: =I$10 -> MINGASRSV1 | J51: GASRSV | K51: =IF(K$10=0,"",K50*$B37) -> 8.5570326 | L51: =IF(L$10=0,"",L50*$B37) | M51: =IF(M$10=0,"",M50*$B37) -> 8.5570326 | N51: =IF(N$10=0,"",N50*$B37) | O51: =IF(O$10=0,"",O50*$B37) | P51: =IF(P$10=0,"",P50*$B37) -> 8.5570326 | Q51: =IF(Q$10=0,"",Q50*$B37) -> 8.5570326 | R51: =IF(R$10=0,"",R50*$B37) -> 4.9251776 | ... AU51: =IF(AU$10=0,"",AU50*$B37) -> 8.5570326
E52: ANNUAL | G52: COST | H52: =A$38 -> 2025 | I52: =I$10 -> MINGASRSV1 | J52: GASRSV | K52: =IF(K$10=0,"",K51*$B38) -> 6.5152313 | L52: =IF(L$10=0,"",L51*$B38) | M52: =IF(M$10=0,"",M51*$B38) -> 6.5152313 | N52: =IF(N$10=0,"",N51*$B38) | O52: =IF(O$10=0,"",O51*$B38) | P52: =IF(P$10=0,"",P51*$B38) -> 6.5152313 | Q52: =IF(Q$10=0,"",Q51*$B38) -> 6.5152313 | R52: =IF(R$10=0,"",R51*$B38) -> 3.7499765 | ... AU52: =IF(AU$10=0,"",AU51*$B38) -> 6.5152313
E53: ANNUAL | G53: COST | H53: =A$39 -> 2030 | I53: =I$10 -> MINGASRSV1 | J53: GASRSV | K53: =IF(K$10=0,"",K52*$B39) -> 4.47343 | L53: =IF(L$10=0,"",L52*$B39) | M53: =IF(M$10=0,"",M52*$B39) -> 4.47343 | N53: =IF(N$10=0,"",N52*$B39) | O53: =IF(O$10=0,"",O52*$B39) | P53: =IF(P$10=0,"",P52*$B39) -> 4.47343 | Q53: =IF(Q$10=0,"",Q52*$B39) -> 4.47343 | R53: =IF(R$10=0,"",R52*$B39) -> 2.5747754 | ... AU53: =IF(AU$10=0,"",AU52*$B39) -> 4.47343
E54: ANNUAL | G54: COST | H54: =A$40 -> 2035 | I54: =I$10 -> MINGASRSV1 | J54: GASRSV | K54: =IF(K$10=0,"",K53*$B40) -> 4.47343 | L54: =IF(L$10=0,"",L53*$B40) | M54: =IF(M$10=0,"",M53*$B40) -> 4.47343 | N54: =IF(N$10=0,"",N53*$B40) | O54: =IF(O$10=0,"",O53*$B40) | P54: =IF(P$10=0,"",P53*$B40) -> 4.47343 | Q54: =IF(Q$10=0,"",Q53*$B40) -> 4.47343 | R54: =IF(R$10=0,"",R53*$B40) -> 2.5747754 | ... AU54: =IF(AU$10=0,"",AU53*$B40) -> 4.47343
E55: ANNUAL | G55: COST | H55: =A$41 -> 2040 | I55: =I$10 -> MINGASRSV1 | J55: GASRSV | K55: =IF(K$10=0,"",K54*$B41) -> 4.47343 | L55: =IF(L$10=0,"",L54*$B41) | M55: =IF(M$10=0,"",M54*$B41) -> 4.47343 | N55: =IF(N$10=0,"",N54*$B41) | O55: =IF(O$10=0,"",O54*$B41) | P55: =IF(P$10=0,"",P54*$B41) -> 4.47343 | Q55: =IF(Q$10=0,"",Q54*$B41) -> 4.47343 | R55: =IF(R$10=0,"",R54*$B41) -> 2.5747754 | ... AU55: =IF(AU$10=0,"",AU54*$B41) -> 4.47343
E56: ANNUAL | G56: COST | H56: =A$42 -> 2045 | I56: =I$10 -> MINGASRSV1 | J56: GASRSV | K56: =IF(K$10=0,"",K55*$B42) -> 4.47343 | L56: =IF(L$10=0,"",L55*$B42) | M56: =IF(M$10=0,"",M55*$B42) -> 4.47343 | N56: =IF(N$10=0,"",N55*$B42) | O56: =IF(O$10=0,"",O55*$B42) | P56: =IF(P$10=0,"",P55*$B42) -> 4.47343 | Q56: =IF(Q$10=0,"",Q55*$B42) -> 4.47343 | R56: =IF(R$10=0,"",R55*$B42) -> 2.5747754 | ... AU56: =IF(AU$10=0,"",AU55*$B42) -> 4.47343
E57: ANNUAL | G57: COST | H57: =A$43 -> 2050 | I57: =I$10 -> MINGASRSV1 | J57: GASRSV | K57: =IF(K$10=0,"",K56*$B43) -> 4.47343 | L57: =IF(L$10=0,"",L56*$B43) | M57: =IF(M$10=0,"",M56*$B43) -> 4.47343 | N57: =IF(N$10=0,"",N56*$B43) | O57: =IF(O$10=0,"",O56*$B43) | P57: =IF(P$10=0,"",P56*$B43) -> 4.47343 | Q57: =IF(Q$10=0,"",Q56*$B43) -> 4.47343 | R57: =IF(R$10=0,"",R56*$B43) -> 2.5747754 | ... AU57: =IF(AU$10=0,"",AU56*$B43) -> 4.47343
E58: ANNUAL | G58: COST | H58: =A$33 -> 2001 | I58: =I$11 -> MINGASRSV2 | J58: GASRSV | K58: =IF(K$11=0,"",K$11*$B$33) | L58: =IF(L$11=0,"",L$11*$B$33) | M58: =IF(M$11=0,"",M$11*$B$33) | N58: =IF(N$11=0,"",N$11*$B$33) | O58: =IF(O$11=0,"",O$11*$B$33) | P58: =IF(P$11=0,"",P$11*$B$33) | Q58: =IF(Q$11=0,"",Q$11*$B$33) | R58: =IF(R$11=0,"",R$11*$B$33) | ... AU58: =IF(AU$11=0,"",AU$11*$B$33)
E59: ANNUAL | G59: COST | H59: =A$34 -> 2005 | I59: =I$11 -> MINGASRSV2 | J59: GASRSV | K59: =IF(K$11=0,"",K58*$B$34) | L59: =IF(L$11=0,"",L58*$B$34) | M59: =IF(M$11=0,"",M58*$B$34) | N59: =IF(N$11=0,"",N58*$B$34) | O59: =IF(O$11=0,"",O58*$B$34) | P59: =IF(P$11=0,"",P58*$B$34) | Q59: =IF(Q$11=0,"",Q58*$B$34) | R59: =IF(R$11=0,"",R58*$B$34) | ... AU59: =IF(AU$11=0,"",AU58*$B$34)
E60: ANNUAL | G60: COST | H60: =A$35 -> 2010 | I60: =I$11 -> MINGASRSV2 | J60: GASRSV | K60: =IF(K$11=0,"",K59*$B$35) | L60: =IF(L$11=0,"",L59*$B$35) | M60: =IF(M$11=0,"",M59*$B$35) | N60: =IF(N$11=0,"",N59*$B$35) | O60: =IF(O$11=0,"",O59*$B$35) | P60: =IF(P$11=0,"",P59*$B$35) | Q60: =IF(Q$11=0,"",Q59*$B$35) | R60: =IF(R$11=0,"",R59*$B$35) | ... AU60: =IF(AU$11=0,"",AU59*$B$35)
E61: ANNUAL | G61: COST | H61: =A$36 -> 2015 | I61: =I$11 -> MINGASRSV2 | J61: GASRSV | K61: =IF(K$11=0,"",K60*$B$36) | L61: =IF(L$11=0,"",L60*$B$36) | M61: =IF(M$11=0,"",M60*$B$36) | N61: =IF(N$11=0,"",N60*$B$36) | O61: =IF(O$11=0,"",O60*$B$36) | P61: =IF(P$11=0,"",P60*$B$36) | Q61: =IF(Q$11=0,"",Q60*$B$36) | R61: =IF(R$11=0,"",R60*$B$36) | ... AU61: =IF(AU$11=0,"",AU60*$B$36)
E62: ANNUAL | G62: COST | H62: =A$37 -> 2020 | I62: =I$11 -> MINGASRSV2 | J62: GASRSV | K62: =IF(K$11=0,"",K61*$B$37) | L62: =IF(L$11=0,"",L61*$B$37) | M62: =IF(M$11=0,"",M61*$B$37) | N62: =IF(N$11=0,"",N61*$B$37) | O62: =IF(O$11=0,"",O61*$B$37) | P62: =IF(P$11=0,"",P61*$B$37) | Q62: =IF(Q$11=0,"",Q61*$B$37) | R62: =IF(R$11=0,"",R61*$B$37) | ... AU62: =IF(AU$11=0,"",AU61*$B$37)
E63: ANNUAL | G63: COST | H63: =A$38 -> 2025 | I63: =I$11 -> MINGASRSV2 | J63: GASRSV | K63: =IF(K$11=0,"",K62*$B$38) | L63: =IF(L$11=0,"",L62*$B$38) | M63: =IF(M$11=0,"",M62*$B$38) | N63: =IF(N$11=0,"",N62*$B$38) | O63: =IF(O$11=0,"",O62*$B$38) | P63: =IF(P$11=0,"",P62*$B$38) | Q63: =IF(Q$11=0,"",Q62*$B$38) | R63: =IF(R$11=0,"",R62*$B$38) | ... AU63: =IF(AU$11=0,"",AU62*$B$38)
E64: ANNUAL | G64: COST | H64: =A$39 -> 2030 | I64: =I$11 -> MINGASRSV2 | J64: GASRSV | K64: =IF(K$11=0,"",K63*$B$39) | L64: =IF(L$11=0,"",L63*$B$39) | M64: =IF(M$11=0,"",M63*$B$39) | N64: =IF(N$11=0,"",N63*$B$39) | O64: =IF(O$11=0,"",O63*$B$39) | P64: =IF(P$11=0,"",P63*$B$39) | Q64: =IF(Q$11=0,"",Q63*$B$39) | R64: =IF(R$11=0,"",R63*$B$39) | ... AU64: =IF(AU$11=0,"",AU63*$B$39)
E65: ANNUAL | G65: COST | H65: =A$40 -> 2035 | I65: =I$11 -> MINGASRSV2 | J65: GASRSV | K65: =IF(K$11=0,"",K64*$B$40) | L65: =IF(L$11=0,"",L64*$B$40) | M65: =IF(M$11=0,"",M64*$B$40) | N65: =IF(N$11=0,"",N64*$B$40) | O65: =IF(O$11=0,"",O64*$B$40) | P65: =IF(P$11=0,"",P64*$B$40) | Q65: =IF(Q$11=0,"",Q64*$B$40) | R65: =IF(R$11=0,"",R64*$B$40) | ... AU65: =IF(AU$11=0,"",AU64*$B$40)
E66: ANNUAL | G66: COST | H66: =A$41 -> 2040 | I66: =I$11 -> MINGASRSV2 | J66: GASRSV | K66: =IF(K$11=0,"",K65*$B$41) | L66: =IF(L$11=0,"",L65*$B$41) | M66: =IF(M$11=0,"",M65*$B$41) | N66: =IF(N$11=0,"",N65*$B$41) | O66: =IF(O$11=0,"",O65*$B$41) | P66: =IF(P$11=0,"",P65*$B$41) | Q66: =IF(Q$11=0,"",Q65*$B$41) | R66: =IF(R$11=0,"",R65*$B$41) | ... AU66: =IF(AU$11=0,"",AU65*$B$41)
E67: ANNUAL | G67: COST | H67: =A$42 -> 2045 | I67: =I$11 -> MINGASRSV2 | J67: GASRSV | K67: =IF(K$11=0,"",K66*$B$42) | L67: =IF(L$11=0,"",L66*$B$42) | M67: =IF(M$11=0,"",M66*$B$42) | N67: =IF(N$11=0,"",N66*$B$42) | O67: =IF(O$11=0,"",O66*$B$42) | P67: =IF(P$11=0,"",P66*$B$42) | Q67: =IF(Q$11=0,"",Q66*$B$42) | R67: =IF(R$11=0,"",R66*$B$42) | ... AU67: =IF(AU$11=0,"",AU66*$B$42)
E68: ANNUAL | G68: COST | H68: =A$43 -> 2050 | I68: =I$11 -> MINGASRSV2 | J68: GASRSV | K68: =IF(K$11=0,"",K67*$B$43) | L68: =IF(L$11=0,"",L67*$B$43) | M68: =IF(M$11=0,"",M67*$B$43) | N68: =IF(N$11=0,"",N67*$B$43) | O68: =IF(O$11=0,"",O67*$B$43) | P68: =IF(P$11=0,"",P67*$B$43) | Q68: =IF(Q$11=0,"",Q67*$B$43) | R68: =IF(R$11=0,"",R67*$B$43) | ... AU68: =IF(AU$11=0,"",AU67*$B$43)
E69: ANNUAL | G69: COST | H69: =A$33 -> 2001 | I69: =I$12 -> MINGASRSV3 | J69: GASRSV | K69: =IF(K$12=0,"",K$12*$B$33) | L69: =IF(L$12=0,"",L$12*$B$33) | M69: =IF(M$12=0,"",M$12*$B$33) | N69: =IF(N$12=0,"",N$12*$B$33) | O69: =IF(O$12=0,"",O$12*$B$33) | P69: =IF(P$12=0,"",P$12*$B$33) | Q69: =IF(Q$12=0,"",Q$12*$B$33) | R69: =IF(R$12=0,"",R$12*$B$33) | ... AU69: =IF(AU$12=0,"",AU$12*$B$33)
E70: ANNUAL | G70: COST | H70: =A$34 -> 2005 | I70: =I$12 -> MINGASRSV3 | J70: GASRSV | K70: =IF(K$12=0,"",K69*$B$34) | L70: =IF(L$12=0,"",L69*$B$34) | M70: =IF(M$12=0,"",M69*$B$34) | N70: =IF(N$12=0,"",N69*$B$34) | O70: =IF(O$12=0,"",O69*$B$34) | P70: =IF(P$12=0,"",P69*$B$34) | Q70: =IF(Q$12=0,"",Q69*$B$34) | R70: =IF(R$12=0,"",R69*$B$34) | ... AU70: =IF(AU$12=0,"",AU69*$B$34)
E71: ANNUAL | G71: COST | H71: =A$35 -> 2010 | I71: =I$12 -> MINGASRSV3 | J71: GASRSV | K71: =IF(K$12=0,"",K70*$B$35) | L71: =IF(L$12=0,"",L70*$B$35) | M71: =IF(M$12=0,"",M70*$B$35) | N71: =IF(N$12=0,"",N70*$B$35) | O71: =IF(O$12=0,"",O70*$B$35) | P71: =IF(P$12=0,"",P70*$B$35) | Q71: =IF(Q$12=0,"",Q70*$B$35) | R71: =IF(R$12=0,"",R70*$B$35) | ... AU71: =IF(AU$12=0,"",AU70*$B$35)
E72: ANNUAL | G72: COST | H72: =A$36 -> 2015 | I72: =I$12 -> MINGASRSV3 | J72: GASRSV | K72: =IF(K$12=0,"",K71*$B$36) | L72: =IF(L$12=0,"",L71*$B$36) | M72: =IF(M$12=0,"",M71*$B$36) | N72: =IF(N$12=0,"",N71*$B$36) | O72: =IF(O$12=0,"",O71*$B$36) | P72: =IF(P$12=0,"",P71*$B$36) | Q72: =IF(Q$12=0,"",Q71*$B$36) | R72: =IF(R$12=0,"",R71*$B$36) | ... AU72: =IF(AU$12=0,"",AU71*$B$36)
E73: ANNUAL | G73: COST | H73: =A$37 -> 2020 | I73: =I$12 -> MINGASRSV3 | J73: GASRSV | K73: =IF(K$12=0,"",K72*$B$37) | L73: =IF(L$12=0,"",L72*$B$37) | M73: =IF(M$12=0,"",M72*$B$37) | N73: =IF(N$12=0,"",N72*$B$37) | O73: =IF(O$12=0,"",O72*$B$37) | P73: =IF(P$12=0,"",P72*$B$37) | Q73: =IF(Q$12=0,"",Q72*$B$37) | R73: =IF(R$12=0,"",R72*$B$37) | ... AU73: =IF(AU$12=0,"",AU72*$B$37)
E74: ANNUAL | G74: COST | H74: =A$38 -> 2025 | I74: =I$12 -> MINGASRSV3 | J74: GASRSV | K74: =IF(K$12=0,"",K73*$B$38) | L74: =IF(L$12=0,"",L73*$B$38) | M74: =IF(M$12=0,"",M73*$B$38) | N74: =IF(N$12=0,"",N73*$B$38) | O74: =IF(O$12=0,"",O73*$B$38) | P74: =IF(P$12=0,"",P73*$B$38) | Q74: =IF(Q$12=0,"",Q73*$B$38) | R74: =IF(R$12=0,"",R73*$B$38) | ... AU74: =IF(AU$12=0,"",AU73*$B$38)
E75: ANNUAL | G75: COST | H75: =A$39 -> 2030 | I75: =I$12 -> MINGASRSV3 | J75: GASRSV | K75: =IF(K$12=0,"",K74*$B$39) | L75: =IF(L$12=0,"",L74*$B$39) | M75: =IF(M$12=0,"",M74*$B$39) | N75: =IF(N$12=0,"",N74*$B$39) | O75: =IF(O$12=0,"",O74*$B$39) | P75: =IF(P$12=0,"",P74*$B$39) | Q75: =IF(Q$12=0,"",Q74*$B$39) | R75: =IF(R$12=0,"",R74*$B$39) | ... AU75: =IF(AU$12=0,"",AU74*$B$39)
E76: ANNUAL | G76: COST | H76: =A$40 -> 2035 | I76: =I$12 -> MINGASRSV3 | J76: GASRSV | K76: =IF(K$12=0,"",K75*$B$40) | L76: =IF(L$12=0,"",L75*$B$40) | M76: =IF(M$12=0,"",M75*$B$40) | N76: =IF(N$12=0,"",N75*$B$40) | O76: =IF(O$12=0,"",O75*$B$40) | P76: =IF(P$12=0,"",P75*$B$40) | Q76: =IF(Q$12=0,"",Q75*$B$40) | R76: =IF(R$12=0,"",R75*$B$40) | ... AU76: =IF(AU$12=0,"",AU75*$B$40)
E77: ANNUAL | G77: COST | H77: =A$41 -> 2040 | I77: =I$12 -> MINGASRSV3 | J77: GASRSV | K77: =IF(K$12=0,"",K76*$B$41) | L77: =IF(L$12=0,"",L76*$B$41) | M77: =IF(M$12=0,"",M76*$B$41) | N77: =IF(N$12=0,"",N76*$B$41) | O77: =IF(O$12=0,"",O76*$B$41) | P77: =IF(P$12=0,"",P76*$B$41) | Q77: =IF(Q$12=0,"",Q76*$B$41) | R77: =IF(R$12=0,"",R76*$B$41) | ... AU77: =IF(AU$12=0,"",AU76*$B$41)
E78: ANNUAL | G78: COST | H78: =A$42 -> 2045 | I78: =I$12 -> MINGASRSV3 | J78: GASRSV | K78: =IF(K$12=0,"",K77*$B$42) | L78: =IF(L$12=0,"",L77*$B$42) | M78: =IF(M$12=0,"",M77*$B$42) | N78: =IF(N$12=0,"",N77*$B$42) | O78: =IF(O$12=0,"",O77*$B$42) | P78: =IF(P$12=0,"",P77*$B$42) | Q78: =IF(Q$12=0,"",Q77*$B$42) | R78: =IF(R$12=0,"",R77*$B$42) | ... AU78: =IF(AU$12=0,"",AU77*$B$42)
E79: ANNUAL | G79: COST | H79: =A$43 -> 2050 | I79: =I$12 -> MINGASRSV3 | J79: GASRSV | K79: =IF(K$12=0,"",K78*$B$43) | L79: =IF(L$12=0,"",L78*$B$43) | M79: =IF(M$12=0,"",M78*$B$43) | N79: =IF(N$12=0,"",N78*$B$43) | O79: =IF(O$12=0,"",O78*$B$43) | P79: =IF(P$12=0,"",P78*$B$43) | Q79: =IF(Q$12=0,"",Q78*$B$43) | R79: =IF(R$12=0,"",R78*$B$43) | ... AU79: =IF(AU$12=0,"",AU78*$B$43)
E80: ANNUAL | G80: COST | H80: =A$33 -> 2001 | I80: =I$13 -> MINGASRSV4 | J80: GASRSV | K80: =IF(K$13=0,"",K$13*$B$33) -> 3.3764153 | L80: =IF(L$13=0,"",L$13*$B$33) | M80: =IF(M$13=0,"",M$13*$B$33) -> 3.3764153 | N80: =IF(N$13=0,"",N$13*$B$33) | O80: =IF(O$13=0,"",O$13*$B$33) | P80: =IF(P$13=0,"",P$13*$B$33) -> 3.3764153 | Q80: =IF(Q$13=0,"",Q$13*$B$33) -> 3.3764153 | R80: =IF(R$13=0,"",R$13*$B$33) -> 2.3699838 | ... AU80: =IF(AU$13=0,"",AU$13*$B$33)
E81: ANNUAL | G81: COST | H81: =A$34 -> 2005 | I81: =I$13 -> MINGASRSV4 | J81: GASRSV | K81: =IF(K$13=0,"",K80*$B$34) -> 4.3110162 | L81: =IF(L$13=0,"",L80*$B$34) | M81: =IF(M$13=0,"",M80*$B$34) -> 4.3110162 | N81: =IF(N$13=0,"",N80*$B$34) | O81: =IF(O$13=0,"",O80*$B$34) | P81: =IF(P$13=0,"",P80*$B$34) -> 4.3110162 | Q81: =IF(Q$13=0,"",Q80*$B$34) -> 4.3110162 | R81: =IF(R$13=0,"",R80*$B$34) -> 3.0260018 | ... AU81: =IF(AU$13=0,"",AU80*$B$34)
E82: ANNUAL | G82: COST | H82: =A$35 -> 2010 | I82: =I$13 -> MINGASRSV4 | J82: GASRSV | K82: =IF(K$13=0,"",K81*$B$35) -> 5.6417658 | L82: =IF(L$13=0,"",L81*$B$35) | M82: =IF(M$13=0,"",M81*$B$35) -> 5.6417658 | N82: =IF(N$13=0,"",N81*$B$35) | O82: =IF(O$13=0,"",O81*$B$35) | P82: =IF(P$13=0,"",P81*$B$35) -> 5.6417658 | Q82: =IF(Q$13=0,"",Q81*$B$35) -> 5.6417658 | R82: =IF(R$13=0,"",R81*$B$35) -> 3.9600856 | ... AU82: =IF(AU$13=0,"",AU81*$B$35)
E83: ANNUAL | G83: COST | H83: =A$36 -> 2015 | I83: =I$13 -> MINGASRSV4 | J83: GASRSV | K83: =IF(K$13=0,"",K82*$B$36) -> 8.9163033 | L83: =IF(L$13=0,"",L82*$B$36) | M83: =IF(M$13=0,"",M82*$B$36) -> 8.9163033 | N83: =IF(N$13=0,"",N82*$B$36) | O83: =IF(O$13=0,"",O82*$B$36) | P83: =IF(P$13=0,"",P82*$B$36) -> 8.9163033 | Q83: =IF(Q$13=0,"",Q82*$B$36) -> 8.9163033 | R83: =IF(R$13=0,"",R82*$B$36) -> 6.2585591 | ... AU83: =IF(AU$13=0,"",AU82*$B$36)
E84: ANNUAL | G84: COST | H84: =A$37 -> 2020 | I84: =I$13 -> MINGASRSV4 | J84: GASRSV | K84: =IF(K$13=0,"",K83*$B$37) -> 12.190841 | L84: =IF(L$13=0,"",L83*$B$37) | M84: =IF(M$13=0,"",M83*$B$37) -> 12.190841 | N84: =IF(N$13=0,"",N83*$B$37) | O84: =IF(O$13=0,"",O83*$B$37) | P84: =IF(P$13=0,"",P83*$B$37) -> 12.190841 | Q84: =IF(Q$13=0,"",Q83*$B$37) -> 12.190841 | R84: =IF(R$13=0,"",R83*$B$37) -> 8.5570326 | ... AU84: =IF(AU$13=0,"",AU83*$B$37)
E85: ANNUAL | G85: COST | H85: =A$38 -> 2025 | I85: =I$13 -> MINGASRSV4 | J85: GASRSV | K85: =IF(K$13=0,"",K84*$B$38) -> 9.2819734 | L85: =IF(L$13=0,"",L84*$B$38) | M85: =IF(M$13=0,"",M84*$B$38) -> 9.2819734 | N85: =IF(N$13=0,"",N84*$B$38) | O85: =IF(O$13=0,"",O84*$B$38) | P85: =IF(P$13=0,"",P84*$B$38) -> 9.2819734 | Q85: =IF(Q$13=0,"",Q84*$B$38) -> 9.2819734 | R85: =IF(R$13=0,"",R84*$B$38) -> 6.5152313 | ... AU85: =IF(AU$13=0,"",AU84*$B$38)
E86: ANNUAL | G86: COST | H86: =A$39 -> 2030 | I86: =I$13 -> MINGASRSV4 | J86: GASRSV | K86: =IF(K$13=0,"",K85*$B$39) -> 6.3731058 | L86: =IF(L$13=0,"",L85*$B$39) | M86: =IF(M$13=0,"",M85*$B$39) -> 6.3731058 | N86: =IF(N$13=0,"",N85*$B$39) | O86: =IF(O$13=0,"",O85*$B$39) | P86: =IF(P$13=0,"",P85*$B$39) -> 6.3731058 | Q86: =IF(Q$13=0,"",Q85*$B$39) -> 6.3731058 | R86: =IF(R$13=0,"",R85*$B$39) -> 4.47343 | ... AU86: =IF(AU$13=0,"",AU85*$B$39)
E87: ANNUAL | G87: COST | H87: =A$40 -> 2035 | I87: =I$13 -> MINGASRSV4 | J87: GASRSV | K87: =IF(K$13=0,"",K86*$B$40) -> 6.3731058 | L87: =IF(L$13=0,"",L86*$B$40) | M87: =IF(M$13=0,"",M86*$B$40) -> 6.3731058 | N87: =IF(N$13=0,"",N86*$B$40) | O87: =IF(O$13=0,"",O86*$B$40) | P87: =IF(P$13=0,"",P86*$B$40) -> 6.3731058 | Q87: =IF(Q$13=0,"",Q86*$B$40) -> 6.3731058 | R87: =IF(R$13=0,"",R86*$B$40) -> 4.47343 | ... AU87: =IF(AU$13=0,"",AU86*$B$40)
E88: ANNUAL | G88: COST | H88: =A$41 -> 2040 | I88: =I$13 -> MINGASRSV4 | J88: GASRSV | K88: =IF(K$13=0,"",K87*$B$41) -> 6.3731058 | L88: =IF(L$13=0,"",L87*$B$41) | M88: =IF(M$13=0,"",M87*$B$41) -> 6.3731058 | N88: =IF(N$13=0,"",N87*$B$41) | O88: =IF(O$13=0,"",O87*$B$41) | P88: =IF(P$13=0,"",P87*$B$41) -> 6.3731058 | Q88: =IF(Q$13=0,"",Q87*$B$41) -> 6.3731058 | R88: =IF(R$13=0,"",R87*$B$41) -> 4.47343 | ... AU88: =IF(AU$13=0,"",AU87*$B$41)
E89: ANNUAL | G89: COST | H89: =A$42 -> 2045 | I89: =I$13 -> MINGASRSV4 | J89: GASRSV | K89: =IF(K$13=0,"",K88*$B$42) -> 6.3731058 | L89: =IF(L$13=0,"",L88*$B$42) | M89: =IF(M$13=0,"",M88*$B$42) -> 6.3731058 | N89: =IF(N$13=0,"",N88*$B$42) | O89: =IF(O$13=0,"",O88*$B$42) | P89: =IF(P$13=0,"",P88*$B$42) -> 6.3731058 | Q89: =IF(Q$13=0,"",Q88*$B$42) -> 6.3731058 | R89: =IF(R$13=0,"",R88*$B$42) -> 4.47343 | ... AU89: =IF(AU$13=0,"",AU88*$B$42)
E90: ANNUAL | G90: COST | H90: =A$43 -> 2050 | I90: =I$13 -> MINGASRSV4 | J90: GASRSV | K90: =IF(K$13=0,"",K89*$B$43) -> 6.3731058 | L90: =IF(L$13=0,"",L89*$B$43) | M90: =IF(M$13=0,"",M89*$B$43) -> 6.3731058 | N90: =IF(N$13=0,"",N89*$B$43) | O90: =IF(O$13=0,"",O89*$B$43) | P90: =IF(P$13=0,"",P89*$B$43) -> 6.3731058 | Q90: =IF(Q$13=0,"",Q89*$B$43) -> 6.3731058 | R90: =IF(R$13=0,"",R89*$B$43) -> 4.47343 | ... AU90: =IF(AU$13=0,"",AU89*$B$43)
E91: ANNUAL | G91: COST | H91: =A$33 -> 2001 | I91: =I$14 -> MINGASRSV5 | J91: GASRSV | K91: =IF(K$14=0,"",K$14*$B$33) | L91: =IF(L$14=0,"",L$14*$B$33) | M91: =IF(M$14=0,"",M$14*$B$33) | N91: =IF(N$14=0,"",N$14*$B$33) | O91: =IF(O$14=0,"",O$14*$B$33) | P91: =IF(P$14=0,"",P$14*$B$33) | Q91: =IF(Q$14=0,"",Q$14*$B$33) | R91: =IF(R$14=0,"",R$14*$B$33) | ... AU91: =IF(AU$14=0,"",AU$14*$B$33)
E92: ANNUAL | G92: COST | H92: =A$34 -> 2005 | I92: =I$14 -> MINGASRSV5 | J92: GASRSV | K92: =IF(K$14=0,"",K91*$B$34) | L92: =IF(L$14=0,"",L91*$B$34) | M92: =IF(M$14=0,"",M91*$B$34) | N92: =IF(N$14=0,"",N91*$B$34) | O92: =IF(O$14=0,"",O91*$B$34) | P92: =IF(P$14=0,"",P91*$B$34) | Q92: =IF(Q$14=0,"",Q91*$B$34) | R92: =IF(R$14=0,"",R91*$B$34) | ... AU92: =IF(AU$14=0,"",AU91*$B$34)
E93: ANNUAL | G93: COST | H93: =A$35 -> 2010 | I93: =I$14 -> MINGASRSV5 | J93: GASRSV | K93: =IF(K$14=0,"",K92*$B$35) | L93: =IF(L$14=0,"",L92*$B$35) | M93: =IF(M$14=0,"",M92*$B$35) | N93: =IF(N$14=0,"",N92*$B$35) | O93: =IF(O$14=0,"",O92*$B$35) | P93: =IF(P$14=0,"",P92*$B$35) | Q93: =IF(Q$14=0,"",Q92*$B$35) | R93: =IF(R$14=0,"",R92*$B$35) | ... AU93: =IF(AU$14=0,"",AU92*$B$35)
E94: ANNUAL | G94: COST | H94: =A$36 -> 2015 | I94: =I$14 -> MINGASRSV5 | J94: GASRSV | K94: =IF(K$14=0,"",K93*$B$36) | L94: =IF(L$14=0,"",L93*$B$36) | M94: =IF(M$14=0,"",M93*$B$36) | N94: =IF(N$14=0,"",N93*$B$36) | O94: =IF(O$14=0,"",O93*$B$36) | P94: =IF(P$14=0,"",P93*$B$36) | Q94: =IF(Q$14=0,"",Q93*$B$36) | R94: =IF(R$14=0,"",R93*$B$36) | ... AU94: =IF(AU$14=0,"",AU93*$B$36)
E95: ANNUAL | G95: COST | H95: =A$37 -> 2020 | I95: =I$14 -> MINGASRSV5 | J95: GASRSV | K95: =IF(K$14=0,"",K94*$B$37) | L95: =IF(L$14=0,"",L94*$B$37) | M95: =IF(M$14=0,"",M94*$B$37) | N95: =IF(N$14=0,"",N94*$B$37) | O95: =IF(O$14=0,"",O94*$B$37) | P95: =IF(P$14=0,"",P94*$B$37) | Q95: =IF(Q$14=0,"",Q94*$B$37) | R95: =IF(R$14=0,"",R94*$B$37) | ... AU95: =IF(AU$14=0,"",AU94*$B$37)
E96: ANNUAL | G96: COST | H96: =A$38 -> 2025 | I96: =I$14 -> MINGASRSV5 | J96: GASRSV | K96: =IF(K$14=0,"",K95*$B$38) | L96: =IF(L$14=0,"",L95*$B$38) | M96: =IF(M$14=0,"",M95*$B$38) | N96: =IF(N$14=0,"",N95*$B$38) | O96: =IF(O$14=0,"",O95*$B$38) | P96: =IF(P$14=0,"",P95*$B$38) | Q96: =IF(Q$14=0,"",Q95*$B$38) | R96: =IF(R$14=0,"",R95*$B$38) | ... AU96: =IF(AU$14=0,"",AU95*$B$38)
E97: ANNUAL | G97: COST | H97: =A$39 -> 2030 | I97: =I$14 -> MINGASRSV5 | J97: GASRSV | K97: =IF(K$14=0,"",K96*$B$39) | L97: =IF(L$14=0,"",L96*$B$39) | M97: =IF(M$14=0,"",M96*$B$39) | N97: =IF(N$14=0,"",N96*$B$39) | O97: =IF(O$14=0,"",O96*$B$39) | P97: =IF(P$14=0,"",P96*$B$39) | Q97: =IF(Q$14=0,"",Q96*$B$39) | R97: =IF(R$14=0,"",R96*$B$39) | ... AU97: =IF(AU$14=0,"",AU96*$B$39)
E98: ANNUAL | G98: COST | H98: =A$40 -> 2035 | I98: =I$14 -> MINGASRSV5 | J98: GASRSV | K98: =IF(K$14=0,"",K97*$B$40) | L98: =IF(L$14=0,"",L97*$B$40) | M98: =IF(M$14=0,"",M97*$B$40) | N98: =IF(N$14=0,"",N97*$B$40) | O98: =IF(O$14=0,"",O97*$B$40) | P98: =IF(P$14=0,"",P97*$B$40) | Q98: =IF(Q$14=0,"",Q97*$B$40) | R98: =IF(R$14=0,"",R97*$B$40) | ... AU98: =IF(AU$14=0,"",AU97*$B$40)
E99: ANNUAL | G99: COST | H99: =A$41 -> 2040 | I99: =I$14 -> MINGASRSV5 | J99: GASRSV | K99: =IF(K$14=0,"",K98*$B$41) | L99: =IF(L$14=0,"",L98*$B$41) | M99: =IF(M$14=0,"",M98*$B$41) | N99: =IF(N$14=0,"",N98*$B$41) | O99: =IF(O$14=0,"",O98*$B$41) | P99: =IF(P$14=0,"",P98*$B$41) | Q99: =IF(Q$14=0,"",Q98*$B$41) | R99: =IF(R$14=0,"",R98*$B$41) | ... AU99: =IF(AU$14=0,"",AU98*$B$41)
E100: ANNUAL | G100: COST | H100: =A$42 -> 2045 | I100: =I$14 -> MINGASRSV5 | J100: GASRSV | K100: =IF(K$14=0,"",K99*$B$42) | L100: =IF(L$14=0,"",L99*$B$42) | M100: =IF(M$14=0,"",M99*$B$42) | N100: =IF(N$14=0,"",N99*$B$42) | O100: =IF(O$14=0,"",O99*$B$42) | P100: =IF(P$14=0,"",P99*$B$42) | Q100: =IF(Q$14=0,"",Q99*$B$42) | R100: =IF(R$14=0,"",R99*$B$42) | ... AU100: =IF(AU$14=0,"",AU99*$B$42)
E101: ANNUAL | G101: COST | H101: =A$43 -> 2050 | I101: =I$14 -> MINGASRSV5 | J101: GASRSV | K101: =IF(K$14=0,"",K100*$B$43) | L101: =IF(L$14=0,"",L100*$B$43) | M101: =IF(M$14=0,"",M100*$B$43) | N101: =IF(N$14=0,"",N100*$B$43) | O101: =IF(O$14=0,"",O100*$B$43) | P101: =IF(P$14=0,"",P100*$B$43) | Q101: =IF(Q$14=0,"",Q100*$B$43) | R101: =IF(R$14=0,"",R100*$B$43) | ... AU101: =IF(AU$14=0,"",AU100*$B$43)
E102: ANNUAL | G102: COST | H102: =A$33 -> 2001 | I102: =I$15 -> MINGASRSV6 | J102: GASRSV | K102: =IF(K$15=0,"",K$15*$B$33) | L102: =IF(L$15=0,"",L$15*$B$33) | M102: =IF(M$15=0,"",M$15*$B$33) | N102: =IF(N$15=0,"",N$15*$B$33) | O102: =IF(O$15=0,"",O$15*$B$33) | P102: =IF(P$15=0,"",P$15*$B$33) | Q102: =IF(Q$15=0,"",Q$15*$B$33) | R102: =IF(R$15=0,"",R$15*$B$33) | ... AU102: =IF(AU$15=0,"",AU$15*$B$33)
E103: ANNUAL | G103: COST | H103: =A$34 -> 2005 | I103: =I$15 -> MINGASRSV6 | J103: GASRSV | K103: =IF(K$15=0,"",K102*$B$34) | L103: =IF(L$15=0,"",L102*$B$34) | M103: =IF(M$15=0,"",M102*$B$34) | N103: =IF(N$15=0,"",N102*$B$34) | O103: =IF(O$15=0,"",O102*$B$34) | P103: =IF(P$15=0,"",P102*$B$34) | Q103: =IF(Q$15=0,"",Q102*$B$34) | R103: =IF(R$15=0,"",R102*$B$34) | ... AU103: =IF(AU$15=0,"",AU102*$B$34)
E104: ANNUAL | G104: COST | H104: =A$35 -> 2010 | I104: =I$15 -> MINGASRSV6 | J104: GASRSV | K104: =IF(K$15=0,"",K103*$B$35) | L104: =IF(L$15=0,"",L103*$B$35) | M104: =IF(M$15=0,"",M103*$B$35) | N104: =IF(N$15=0,"",N103*$B$35) | O104: =IF(O$15=0,"",O103*$B$35) | P104: =IF(P$15=0,"",P103*$B$35) | Q104: =IF(Q$15=0,"",Q103*$B$35) | R104: =IF(R$15=0,"",R103*$B$35) | ... AU104: =IF(AU$15=0,"",AU103*$B$35)
E105: ANNUAL | G105: COST | H105: =A$36 -> 2015 | I105: =I$15 -> MINGASRSV6 | J105: GASRSV | K105: =IF(K$15=0,"",K104*$B$36) | L105: =IF(L$15=0,"",L104*$B$36) | M105: =IF(M$15=0,"",M104*$B$36) | N105: =IF(N$15=0,"",N104*$B$36) | O105: =IF(O$15=0,"",O104*$B$36) | P105: =IF(P$15=0,"",P104*$B$36) | Q105: =IF(Q$15=0,"",Q104*$B$36) | R105: =IF(R$15=0,"",R104*$B$36) | ... AU105: =IF(AU$15=0,"",AU104*$B$36)
...

Sheet INPUTtoVEDA_importpriceNT
A1: ='INPUTtoVEDA_importprice TR'!A1 -> Adjustment factors derived from the computation of the delivery cost
G3: ='INPUTtoVEDA_importprice TR'!H3 -> AT | H3: ='INPUTtoVEDA_importprice TR'!I3 -> BE | I3: BG | J3: ='INPUTtoVEDA_importprice TR'!K3 -> DE | K3: ='INPUTtoVEDA_importprice TR'!L3 -> DK | L3: ='INPUTtoVEDA_importprice TR'!M3 -> FI | M3: ='INPUTtoVEDA_importprice TR'!N3 -> FR | N3: ='INPUTtoVEDA_importprice TR'!O3 -> EL | O3: ='INPUTtoVEDA_importprice TR'!P3 -> IE | P3: ='INPUTtoVEDA_importprice TR'!Q3 -> IT | Q3: ='INPUTtoVEDA_importprice TR'!R3 -> NL | ... AJ3: ='INPUTtoVEDA_importprice TR'!AK3 -> NO | AK3: AL | AL3: BA | AM3: HR | AN3: ME | AO3: MK | AP3: RS | AQ3: KS
C4: ='INPUTtoVEDA_importprice TR'!D4 -> Coal | G4: ='INPUTtoVEDA_importprice TR'!H4 -> 1 | H4: ='INPUTtoVEDA_importprice TR'!I4 -> 0.935 | I4: 1 | J4: ='INPUTtoVEDA_importprice TR'!K4 -> 1 | K4: ='INPUTtoVEDA_importprice TR'!L4 -> 1 | L4: ='INPUTtoVEDA_importprice TR'!M4 -> 1 | M4: ='INPUTtoVEDA_importprice TR'!N4 -> 1 | N4: ='INPUTtoVEDA_importprice TR'!O4 -> 1 | O4: ='INPUTtoVEDA_importprice TR'!P4 -> 0.85 | P4: ='INPUTtoVEDA_importprice TR'!Q4 -> 0.95 | Q4: ='INPUTtoVEDA_importprice TR'!R4 -> 1 | ... AP4: ='INPUTtoVEDA_importprice TR'!AQ4 -> 1 | AQ4: 1
C5: ='INPUTtoVEDA_importprice TR'!D5 -> Heavy Distillate Oil | G5: ='INPUTtoVEDA_importprice TR'!H5 -> 0.9 | H5: ='INPUTtoVEDA_importprice TR'!I5 -> 1 | I5: 1 | J5: ='INPUTtoVEDA_importprice TR'!K5 -> 1 | K5: ='INPUTtoVEDA_importprice TR'!L5 -> 1 | L5: ='INPUTtoVEDA_importprice TR'!M5 -> 1 | M5: ='INPUTtoVEDA_importprice TR'!N5 -> 1 | N5: ='INPUTtoVEDA_importprice TR'!O5 -> 1 | O5: ='INPUTtoVEDA_importprice TR'!P5 -> 0.85 | P5: ='INPUTtoVEDA_importprice TR'!Q5 -> 1 | Q5: ='INPUTtoVEDA_importprice TR'!R5 -> 1 | ... AP5: ='INPUTtoVEDA_importprice TR'!AQ5 -> 1 | AQ5: 1
C6: ='INPUTtoVEDA_importprice TR'!D6 -> Light Distilate Oil | G6: ='INPUTtoVEDA_importprice TR'!H6 -> 1 | H6: ='INPUTtoVEDA_importprice TR'!I6 -> 1 | I6: 1 | J6: ='INPUTtoVEDA_importprice TR'!K6 -> 1 | K6: ='INPUTtoVEDA_importprice TR'!L6 -> 1 | L6: ='INPUTtoVEDA_importprice TR'!M6 -> 1 | M6: ='INPUTtoVEDA_importprice TR'!N6 -> 1 | N6: ='INPUTtoVEDA_importprice TR'!O6 -> 1 | O6: ='INPUTtoVEDA_importprice TR'!P6 -> 1 | P6: ='INPUTtoVEDA_importprice TR'!Q6 -> 1 | Q6: ='INPUTtoVEDA_importprice TR'!R6 -> 1 | ... AP6: ='INPUTtoVEDA_importprice TR'!AQ6 -> 1 | AQ6: 1
C7: ='INPUTtoVEDA_importprice TR'!D7 -> Gasoline | G7: ='INPUTtoVEDA_importprice TR'!H7 -> 1 | H7: ='INPUTtoVEDA_importprice TR'!I7 -> 1 | I7: 1 | J7: ='INPUTtoVEDA_importprice TR'!K7 -> 1 | K7: ='INPUTtoVEDA_importprice TR'!L7 -> 1 | L7: ='INPUTtoVEDA_importprice TR'!M7 -> 1 | M7: ='INPUTtoVEDA_importprice TR'!N7 -> 1 | N7: ='INPUTtoVEDA_importprice TR'!O7 -> 1 | O7: ='INPUTtoVEDA_importprice TR'!P7 -> 1 | P7: ='INPUTtoVEDA_importprice TR'!Q7 -> 1 | Q7: ='INPUTtoVEDA_importprice TR'!R7 -> 1 | ... AP7: ='INPUTtoVEDA_importprice TR'!AQ7 -> 1 | AQ7: 1
C8: Wood Imp. | G8: 1 | H8: 1 | I8: 1 | J8: 1 | K8: 1 | L8: 1 | M8: 1 | N8: 1 | O8: 1 | P8: 1 | Q8: 1 | R8: 1 | S8: 1 | T8: 1 | U8: 1 | V8: 1 | W8: 1 | X8: 1 | Y8: 1 | Z8: 1 | AA8: 1 | AB8: 1 | AC8: 1 | AD8: 1 | AE8: 1 | AF8: 1 | AG8: 1 | AH8: 1 | AI8: 1 | AJ8: 1 | AK8: 1 | AL8: 1 | AM8: 1 | AN8: 1 | AO8: 1 | AP8: 1 | AQ8: 1
C9: Wood Dom. | G9: 1 | H9: 1 | I9: 1 | J9: 1 | K9: 1 | L9: 1 | M9: 1 | N9: 1 | O9: 1 | P9: 1 | Q9: 1 | R9: 1 | S9: 1.5 | T9: 1 | U9: 1 | V9: 1 | W9: 1 | X9: 1 | Y9: 1 | Z9: 1 | AA9: 1 | AB9: 1 | AC9: 1 | AD9: 1 | AE9: 1 | AF9: 1 | AG9: 1 | AH9: 1 | AI9: 1 | AJ9: 1 | AK9: 1 | AL9: 1 | AM9: 1 | AN9: 1 | AO9: 1 | AP9: 1 | AQ9: 1
C10: Mun Waste | G10: 1 | H10: 1 | I10: 1 | J10: 1 | K10: 1 | L10: 1 | M10: 1 | N10: 1 | O10: 1 | P10: 1 | Q10: 1 | R10: 1 | S10: 1 | T10: 1 | U10: 1 | V10: 1 | W10: 1 | X10: 1 | Y10: 1 | Z10: 1 | AA10: 1 | AB10: 1 | AC10: 1 | AD10: 1 | AE10: 1 | AF10: 1 | AG10: 1 | AH10: 1 | AI10: 1 | AJ10: 1 | AK10: 1 | AL10: 1 | AM10: 1 | AN10: 1 | AO10: 1 | AP10: 1 | AQ10: 1
C11: GASNAT | G11: ='INPUTtoVEDA_importprice TR'!H8 -> 1 | H11: ='INPUTtoVEDA_importprice TR'!I8 -> 1 | I11: ='INPUTtoVEDA_importprice TR'!J8 -> 0 | J11: ='INPUTtoVEDA_importprice TR'!K8 -> 1 | K11: ='INPUTtoVEDA_importprice TR'!L8 -> 1 | L11: ='INPUTtoVEDA_importprice TR'!M8 -> 1 | M11: ='INPUTtoVEDA_importprice TR'!N8 -> 1 | N11: ='INPUTtoVEDA_importprice TR'!O8 -> 1 | ... AP11: ='INPUTtoVEDA_importprice TR'!AQ8 -> 1 | AQ11: 11
A12: ~TFM_INS
A13: TimeSlice | B13: Curr | C13: Attribute | D13: Year | E13: Pset_PN | F13: Cset_CN | G13: AT | H13: BE | I13: BG | J13: DE | K13: DK | L13: FI | M13: FR | N13: EL | O13: IE | P13: IT | Q13: NL | R13: PT | S13: ES | T13: SE | U13: UK | V13: HU | W13: PL | X13: CZ | Y13: SK | Z13: CH | AA13: CY | AB13: EE | AC13: IS | AD13: LT | AE13: LU | AF13: LV | AG13: MT | AH13: RO | AI13: SI | AJ13: NO | AK13: AL | AL13: BA | AM13: HR | AN13: ME | AO13: MK | AP13: RS | AQ13: KS
A14: ANNUAL | B14: EUR10 | C14: COST | D14: 2010 | E14: =Worldprices!$C$62 -> IMPCOAHAR* | F14: =Worldprices!$C$63 -> COAHAR | G14: =Worldprices!$C$67*G$4 -> 2.6229508 | H14: =Worldprices!$C$67*H$4 -> 2.452459 | I14: =AH14 -> 2.6229508 | J14: =Worldprices!$C$67*J$4 -> 2.6229508 | K14: =Worldprices!$C$67*K$4 -> 2.6229508 | L14: =Worldprices!$C$67*L$4 -> 2.6229508 | M14: =Worldprices!$C$67*M$4 -> 2.6229508 | N14: =Worldprices!$C$67*N$4 -> 2.6229508 | O14: =Worldprices!$C$67*O$4 -> 2.2295082 | P14: =Worldprices!$C$67*P$4 -> 2.4918033 | Q14: =Worldprices!$C$67*Q$4 -> 2.6229508 | ... AP14: =Worldprices!$C$67*AP$4 -> 2.6229508 | AQ14: =AP14 -> 2.6229508
A15: ANNUAL | B15: EUR10 | C15: COST | D15: 2010 | E15: =Worldprices!$D$62 -> IMPCOACOK* | F15: =Worldprices!$D$63 -> COACOK | G15: =Worldprices!$D$67*G$4 -> 3.3311475 | H15: =Worldprices!$D$67*H$4 -> 3.114623 | I15: =AH15 -> 3.3311475 | J15: =Worldprices!$D$67*J$4 -> 3.3311475 | K15: =Worldprices!$D$67*K$4 -> 3.3311475 | L15: =Worldprices!$D$67*L$4 -> 3.3311475 | M15: =Worldprices!$D$67*M$4 -> 3.3311475 | N15: =Worldprices!$D$67*N$4 -> 3.3311475 | O15: =Worldprices!$D$67*O$4 -> 2.8314754 | P15: =Worldprices!$D$67*P$4 -> 3.1645902 | Q15: =Worldprices!$D$67*Q$4 -> 3.3311475 | ... AP15: =Worldprices!$D$67*AP$4 -> 3.3311475 | AQ15: =AP15 -> 3.3311475
A16: ANNUAL | B16: EUR10 | C16: COST | D16: 2010 | E16: =Worldprices!$E$62 -> IMPCOABRO* | F16: =Worldprices!$E$63 -> COABRO | G16: =Worldprices!$E$67*G$4 -> 2.4918033 | H16: =Worldprices!$E$67*H$4 -> 2.3298361 | I16: =AH16 -> 2.4918033 | J16: =Worldprices!$E$67*J$4 -> 2.4918033 | K16: =Worldprices!$E$67*K$4 -> 2.4918033 | L16: =Worldprices!$E$67*L$4 -> 2.4918033 | M16: =Worldprices!$E$67*M$4 -> 2.4918033 | N16: =Worldprices!$E$67*N$4 -> 2.4918033 | O16: =Worldprices!$E$67*O$4 -> 2.1180328 | P16: =Worldprices!$E$67*P$4 -> 2.3672131 | Q16: =Worldprices!$E$67*Q$4 -> 2.4918033 | ... AP16: =Worldprices!$E$67*AP$4 -> 2.4918033 | AQ16: =AP16 -> 2.4918033
A17: ANNUAL | B17: EUR10 | C17: COST | D17: 2010 | E17: =Worldprices!$F$62 -> IMPCOALIG* | F17: =Worldprices!$F$63 -> COALIG | G17: =Worldprices!$F$67*G$4 -> 2.4918033 | H17: =Worldprices!$F$67*H$4 -> 2.3298361 | I17: =AH17 -> 2.4918033 | J17: =Worldprices!$F$67*J$4 -> 2.4918033 | K17: =Worldprices!$F$67*K$4 -> 2.4918033 | L17: =Worldprices!$F$67*L$4 -> 2.4918033 | M17: =Worldprices!$F$67*M$4 -> 2.4918033 | N17: =Worldprices!$F$67*N$4 -> 2.4918033 | O17: =Worldprices!$F$67*O$4 -> 2.1180328 | P17: =Worldprices!$F$67*P$4 -> 2.3672131 | Q17: =Worldprices!$F$67*Q$4 -> 2.4918033 | ... AP17: =Worldprices!$F$67*AP$4 -> 2.4918033 | AQ17: =AP17 -> 2.4918033
A18: ANNUAL | B18: EUR10 | C18: COST | D18: 2010 | E18: =Worldprices!$M$62 -> IMPOILOTH | F18: =Worldprices!$M$63 -> OILOTH | G18: =Worldprices!$M$67*G$6 -> 9.8196721 | H18: =Worldprices!$M$67*H$6 -> 9.8196721 | I18: =AH18 -> 9.8196721 | J18: =Worldprices!$M$67*J$6 -> 9.8196721 | K18: =Worldprices!$M$67*K$6 -> 9.8196721 | L18: =Worldprices!$M$67*L$6 -> 9.8196721 | M18: =Worldprices!$M$67*M$6 -> 9.8196721 | N18: =Worldprices!$M$67*N$6 -> 9.8196721 | O18: =Worldprices!$M$67*O$6 -> 9.8196721 | P18: =Worldprices!$M$67*P$6 -> 9.8196721 | Q18: =Worldprices!$M$67*Q$6 -> 9.8196721 | ... AP18: =Worldprices!$M$67*AP$6 -> 9.8196721 | AQ18: =AP18 -> 9.8196721
A19: ANNUAL | B19: EUR10 | C19: COST | D19: 2010 | E19: =Worldprices!$N$62 -> IMPOILNAP | F19: =Worldprices!$N$63 -> OILNAP | G19: =Worldprices!$N$67*G$6 -> 9.8196721 | H19: =Worldprices!$N$67*H$6 -> 9.8196721 | I19: =AH19 -> 9.8196721 | J19: =Worldprices!$N$67*J$6 -> 9.8196721 | K19: =Worldprices!$N$67*K$6 -> 9.8196721 | L19: =Worldprices!$N$67*L$6 -> 9.8196721 | M19: =Worldprices!$N$67*M$6 -> 9.8196721 | N19: =Worldprices!$N$67*N$6 -> 9.8196721 | O19: =Worldprices!$N$67*O$6 -> 9.8196721 | P19: =Worldprices!$N$67*P$6 -> 9.8196721 | Q19: =Worldprices!$N$67*Q$6 -> 9.8196721 | ... AP19: =Worldprices!$N$67*AP$6 -> 9.8196721 | AQ19: =AP19 -> 9.8196721
A20: ANNUAL | B20: EUR10 | C20: COST | D20: 2010 | E20: =Worldprices!$O$62 -> IMPOILFDS | F20: =Worldprices!$O$63 -> OILFDS | G20: =Worldprices!$O$67*G$6 -> 9.8196721 | H20: =Worldprices!$O$67*H$6 -> 9.8196721 | I20: =AH20 -> 9.8196721 | J20: =Worldprices!$O$67*J$6 -> 9.8196721 | K20: =Worldprices!$O$67*K$6 -> 9.8196721 | L20: =Worldprices!$O$67*L$6 -> 9.8196721 | M20: =Worldprices!$O$67*M$6 -> 9.8196721 | N20: =Worldprices!$O$67*N$6 -> 9.8196721 | O20: =Worldprices!$O$67*O$6 -> 9.8196721 | P20: =Worldprices!$O$67*P$6 -> 9.8196721 | Q20: =Worldprices!$O$67*Q$6 -> 9.8196721 | ... AP20: =Worldprices!$O$67*AP$6 -> 9.8196721 | AQ20: =AP20 -> 9.8196721
A21: ANNUAL | B21: EUR10 | C21: COST | D21: 2010 | E21: =Worldprices!$P$62 -> IMPOILNEU | F21: =Worldprices!$P$63 -> OILNEU | G21: =Worldprices!$P$67*G$6 -> 9.8196721 | H21: =Worldprices!$P$67*H$6 -> 9.8196721 | I21: =AH21 -> 9.8196721 | J21: =Worldprices!$P$67*J$6 -> 9.8196721 | K21: =Worldprices!$P$67*K$6 -> 9.8196721 | L21: =Worldprices!$P$67*L$6 -> 9.8196721 | M21: =Worldprices!$P$67*M$6 -> 9.8196721 | N21: =Worldprices!$P$67*N$6 -> 9.8196721 | O21: =Worldprices!$P$67*O$6 -> 9.8196721 | P21: =Worldprices!$P$67*P$6 -> 9.8196721 | Q21: =Worldprices!$P$67*Q$6 -> 9.8196721 | ... AP21: =Worldprices!$P$67*AP$6 -> 9.8196721 | AQ21: =AP21 -> 9.8196721
A22: ANNUAL | B22: EUR10 | C22: *COST | D22: 2010 | E22: =Worldprices!$R$62 -> IMPBIOWOO | F22: =Worldprices!$R$63 -> BIOWOO | G22: =Worldprices!$R$67*G$8 -> 3.623524 | H22: =Worldprices!$R$67*H$8 -> 3.623524 | I22: =AH22 -> 3.623524 | J22: =Worldprices!$R$67*J$8 -> 3.623524 | K22: =Worldprices!$R$67*K$8 -> 3.623524 | L22: =Worldprices!$R$67*L$8 -> 3.623524 | M22: =Worldprices!$R$67*M$8 -> 3.623524 | N22: =Worldprices!$R$67*N$8 -> 3.623524 | O22: =Worldprices!$R$67*O$8 -> 3.623524 | P22: =Worldprices!$R$67*P$8 -> 3.623524 | Q22: =Worldprices!$R$67*Q$8 -> 3.623524 | ... AP22: =Worldprices!$R$67*AP$8 -> 3.623524 | AQ22: =AP22 -> 3.623524
A23: ANNUAL | B23: EUR10 | C23: COST | D23: 2015 | E23: =Worldprices!$C$62 -> IMPCOAHAR* | F23: =Worldprices!$C$63 -> COAHAR | G23: =Worldprices!$C$68*G$4 -> 2.9964754 | H23: =Worldprices!$C$68*H$4 -> 2.8017045 | I23: =AH23 -> 2.9964754 | J23: =Worldprices!$C$68*J$4 -> 2.9964754 | K23: =Worldprices!$C$68*K$4 -> 2.9964754 | L23: =Worldprices!$C$68*L$4 -> 2.9964754 | M23: =Worldprices!$C$68*M$4 -> 2.9964754 | N23: =Worldprices!$C$68*N$4 -> 2.9964754 | O23: =Worldprices!$C$68*O$4 -> 2.5470041 | P23: =Worldprices!$C$68*P$4 -> 2.8466516 | Q23: =Worldprices!$C$68*Q$4 -> 2.9964754 | ... AP23: =Worldprices!$C$68*AP$4 -> 2.9964754 | AQ23: =AP23 -> 2.9964754
A24: ANNUAL | B24: EUR10 | C24: COST | D24: 2015 | E24: =Worldprices!$D$62 -> IMPCOACOK* | F24: =Worldprices!$D$63 -> COACOK | G24: =Worldprices!$D$68*G$4 -> 3.8055238 | H24: =Worldprices!$D$68*H$4 -> 3.5581647 | I24: =AH24 -> 3.8055238 | J24: =Worldprices!$D$68*J$4 -> 3.8055238 | K24: =Worldprices!$D$68*K$4 -> 3.8055238 | L24: =Worldprices!$D$68*L$4 -> 3.8055238 | M24: =Worldprices!$D$68*M$4 -> 3.8055238 | N24: =Worldprices!$D$68*N$4 -> 3.8055238 | O24: =Worldprices!$D$68*O$4 -> 3.2346952 | P24: =Worldprices!$D$68*P$4 -> 3.6152476 | Q24: =Worldprices!$D$68*Q$4 -> 3.8055238 | ... AP24: =Worldprices!$D$68*AP$4 -> 3.8055238 | AQ24: =AP24 -> 3.8055238
A25: ANNUAL | B25: EUR10 | C25: COST | D25: 2015 | E25: =Worldprices!$E$62 -> IMPCOABRO* | F25: =Worldprices!$E$63 -> COABRO | G25: =Worldprices!$E$68*G$4 -> 2.8466516 | H25: =Worldprices!$E$68*H$4 -> 2.6616193 | I25: =AH25 -> 2.8466516 | J25: =Worldprices!$E$68*J$4 -> 2.8466516 | K25: =Worldprices!$E$68*K$4 -> 2.8466516 | L25: =Worldprices!$E$68*L$4 -> 2.8466516 | M25: =Worldprices!$E$68*M$4 -> 2.8466516 | N25: =Worldprices!$E$68*N$4 -> 2.8466516 | O25: =Worldprices!$E$68*O$4 -> 2.4196539 | P25: =Worldprices!$E$68*P$4 -> 2.7043191 | Q25: =Worldprices!$E$68*Q$4 -> 2.8466516 | ... AP25: =Worldprices!$E$68*AP$4 -> 2.8466516 | AQ25: =AP25 -> 2.8466516
A26: ANNUAL | B26: EUR10 | C26: COST | D26: 2015 | E26: =Worldprices!$F$62 -> IMPCOALIG* | F26: =Worldprices!$F$63 -> COALIG | G26: =Worldprices!$F$68*G$4 -> 2.8466516 | H26: =Worldprices!$F$68*H$4 -> 2.6616193 | I26: =AH26 -> 2.8466516 | J26: =Worldprices!$F$68*J$4 -> 2.8466516 | K26: =Worldprices!$F$68*K$4 -> 2.8466516 | L26: =Worldprices!$F$68*L$4 -> 2.8466516 | M26: =Worldprices!$F$68*M$4 -> 2.8466516 | N26: =Worldprices!$F$68*N$4 -> 2.8466516 | O26: =Worldprices!$F$68*O$4 -> 2.4196539 | P26: =Worldprices!$F$68*P$4 -> 2.7043191 | Q26: =Worldprices!$F$68*Q$4 -> 2.8466516 | ... AP26: =Worldprices!$F$68*AP$4 -> 2.8466516 | AQ26: =AP26 -> 2.8466516
A27: ANNUAL | B27: EUR10 | C27: COST | D27: 2015 | E27: =Worldprices!$M$62 -> IMPOILOTH | F27: =Worldprices!$M$63 -> OILOTH | G27: =Worldprices!$M$68*G$6 -> 9.5648361 | H27: =Worldprices!$M$68*H$6 -> 9.5648361 | I27: =AH27 -> 9.5648361 | J27: =Worldprices!$M$68*J$6 -> 9.5648361 | K27: =Worldprices!$M$68*K$6 -> 9.5648361 | L27: =Worldprices!$M$68*L$6 -> 9.5648361 | M27: =Worldprices!$M$68*M$6 -> 9.5648361 | N27: =Worldprices!$M$68*N$6 -> 9.5648361 | O27: =Worldprices!$M$68*O$6 -> 9.5648361 | P27: =Worldprices!$M$68*P$6 -> 9.5648361 | Q27: =Worldprices!$M$68*Q$6 -> 9.5648361 | ... AP27: =Worldprices!$M$68*AP$6 -> 9.5648361 | AQ27: =AP27 -> 9.5648361
A28: ANNUAL | B28: EUR10 | C28: COST | D28: 2015 | E28: =Worldprices!$N$62 -> IMPOILNAP | F28: =Worldprices!$N$63 -> OILNAP | G28: =Worldprices!$N$68*G$6 -> 9.5648361 | H28: =Worldprices!$N$68*H$6 -> 9.5648361 | I28: =AH28 -> 9.5648361 | J28: =Worldprices!$N$68*J$6 -> 9.5648361 | K28: =Worldprices!$N$68*K$6 -> 9.5648361 | L28: =Worldprices!$N$68*L$6 -> 9.5648361 | M28: =Worldprices!$N$68*M$6 -> 9.5648361 | N28: =Worldprices!$N$68*N$6 -> 9.5648361 | O28: =Worldprices!$N$68*O$6 -> 9.5648361 | P28: =Worldprices!$N$68*P$6 -> 9.5648361 | Q28: =Worldprices!$N$68*Q$6 -> 9.5648361 | ... AP28: =Worldprices!$N$68*AP$6 -> 9.5648361 | AQ28: =AP28 -> 9.5648361
A29: ANNUAL | B29: EUR10 | C29: COST | D29: 2015 | E29: =Worldprices!$O$62 -> IMPOILFDS | F29: =Worldprices!$O$63 -> OILFDS | G29: =Worldprices!$O$68*G$6 -> 9.5648361 | H29: =Worldprices!$O$68*H$6 -> 9.5648361 | I29: =AH29 -> 9.5648361 | J29: =Worldprices!$O$68*J$6 -> 9.5648361 | K29: =Worldprices!$O$68*K$6 -> 9.5648361 | L29: =Worldprices!$O$68*L$6 -> 9.5648361 | M29: =Worldprices!$O$68*M$6 -> 9.5648361 | N29: =Worldprices!$O$68*N$6 -> 9.5648361 | O29: =Worldprices!$O$68*O$6 -> 9.5648361 | P29: =Worldprices!$O$68*P$6 -> 9.5648361 | Q29: =Worldprices!$O$68*Q$6 -> 9.5648361 | ... AP29: =Worldprices!$O$68*AP$6 -> 9.5648361 | AQ29: =AP29 -> 9.5648361
A30: ANNUAL | B30: EUR10 | C30: COST | D30: 2015 | E30: =Worldprices!$P$62 -> IMPOILNEU | F30: =Worldprices!$P$63 -> OILNEU | G30: =Worldprices!$P$68*G$6 -> 9.5648361 | H30: =Worldprices!$P$68*H$6 -> 9.5648361 | I30: =AH30 -> 9.5648361 | J30: =Worldprices!$P$68*J$6 -> 9.5648361 | K30: =Worldprices!$P$68*K$6 -> 9.5648361 | L30: =Worldprices!$P$68*L$6 -> 9.5648361 | M30: =Worldprices!$P$68*M$6 -> 9.5648361 | N30: =Worldprices!$P$68*N$6 -> 9.5648361 | O30: =Worldprices!$P$68*O$6 -> 9.5648361 | P30: =Worldprices!$P$68*P$6 -> 9.5648361 | Q30: =Worldprices!$P$68*Q$6 -> 9.5648361 | ... AP30: =Worldprices!$P$68*AP$6 -> 9.5648361 | AQ30: =AP30 -> 9.5648361
A31: ANNUAL | B31: EUR10 | C31: *COST | D31: 2015 | E31: =Worldprices!$R$62 -> IMPBIOWOO | F31: =Worldprices!$R$63 -> BIOWOO | G31: =Worldprices!$R$68*G$8 -> 3.9615946 | H31: =Worldprices!$R$68*H$8 -> 3.9615946 | I31: =AH31 -> 3.9615946 | J31: =Worldprices!$R$68*J$8 -> 3.9615946 | K31: =Worldprices!$R$68*K$8 -> 3.9615946 | L31: =Worldprices!$R$68*L$8 -> 3.9615946 | M31: =Worldprices!$R$68*M$8 -> 3.9615946 | N31: =Worldprices!$R$68*N$8 -> 3.9615946 | O31: =Worldprices!$R$68*O$8 -> 3.9615946 | P31: =Worldprices!$R$68*P$8 -> 3.9615946 | Q31: =Worldprices!$R$68*Q$8 -> 3.9615946 | ... AP31: =Worldprices!$R$68*AP$8 -> 3.9615946 | AQ31: =AP31 -> 3.9615946
A32: ANNUAL | B32: EUR10 | C32: COST | D32: 2020 | E32: =Worldprices!$C$62 -> IMPCOAHAR* | F32: =Worldprices!$C$63 -> COAHAR | G32: =Worldprices!$C$69*G$4 -> 3.37 | H32: =Worldprices!$C$69*H$4 -> 3.15095 | I32: =AH32 -> 3.37 | J32: =Worldprices!$C$69*J$4 -> 3.37 | K32: =Worldprices!$C$69*K$4 -> 3.37 | L32: =Worldprices!$C$69*L$4 -> 3.37 | M32: =Worldprices!$C$69*M$4 -> 3.37 | N32: =Worldprices!$C$69*N$4 -> 3.37 | O32: =Worldprices!$C$69*O$4 -> 2.8645 | P32: =Worldprices!$C$69*P$4 -> 3.2015 | Q32: =Worldprices!$C$69*Q$4 -> 3.37 | ... AP32: =Worldprices!$C$69*AP$4 -> 3.37 | AQ32: =AP32 -> 3.37
A33: ANNUAL | B33: EUR10 | C33: COST | D33: 2020 | E33: =Worldprices!$D$62 -> IMPCOACOK* | F33: =Worldprices!$D$63 -> COACOK | G33: =Worldprices!$D$69*G$4 -> 4.2799 | H33: =Worldprices!$D$69*H$4 -> 4.0017065 | I33: =AH33 -> 4.2799 | J33: =Worldprices!$D$69*J$4 -> 4.2799 | K33: =Worldprices!$D$69*K$4 -> 4.2799 | L33: =Worldprices!$D$69*L$4 -> 4.2799 | M33: =Worldprices!$D$69*M$4 -> 4.2799 | N33: =Worldprices!$D$69*N$4 -> 4.2799 | O33: =Worldprices!$D$69*O$4 -> 3.637915 | P33: =Worldprices!$D$69*P$4 -> 4.065905 | Q33: =Worldprices!$D$69*Q$4 -> 4.2799 | ... AP33: =Worldprices!$D$69*AP$4 -> 4.2799 | AQ33: =AP33 -> 4.2799
A34: ANNUAL | B34: EUR10 | C34: COST | D34: 2020 | E34: =Worldprices!$E$62 -> IMPCOABRO* | F34: =Worldprices!$E$63 -> COABRO | G34: =Worldprices!$E$69*G$4 -> 3.2015 | H34: =Worldprices!$E$69*H$4 -> 2.9934025 | I34: =AH34 -> 3.2015 | J34: =Worldprices!$E$69*J$4 -> 3.2015 | K34: =Worldprices!$E$69*K$4 -> 3.2015 | L34: =Worldprices!$E$69*L$4 -> 3.2015 | M34: =Worldprices!$E$69*M$4 -> 3.2015 | N34: =Worldprices!$E$69*N$4 -> 3.2015 | O34: =Worldprices!$E$69*O$4 -> 2.721275 | P34: =Worldprices!$E$69*P$4 -> 3.041425 | Q34: =Worldprices!$E$69*Q$4 -> 3.2015 | ... AP34: =Worldprices!$E$69*AP$4 -> 3.2015 | AQ34: =AP34 -> 3.2015
A35: ANNUAL | B35: EUR10 | C35: COST | D35: 2020 | E35: =Worldprices!$F$62 -> IMPCOALIG* | F35: =Worldprices!$F$63 -> COALIG | G35: =Worldprices!$F$69*G$4 -> 3.2015 | H35: =Worldprices!$F$69*H$4 -> 2.9934025 | I35: =AH35 -> 3.2015 | J35: =Worldprices!$F$69*J$4 -> 3.2015 | K35: =Worldprices!$F$69*K$4 -> 3.2015 | L35: =Worldprices!$F$69*L$4 -> 3.2015 | M35: =Worldprices!$F$69*M$4 -> 3.2015 | N35: =Worldprices!$F$69*N$4 -> 3.2015 | O35: =Worldprices!$F$69*O$4 -> 2.721275 | P35: =Worldprices!$F$69*P$4 -> 3.041425 | Q35: =Worldprices!$F$69*Q$4 -> 3.2015 | ... AP35: =Worldprices!$F$69*AP$4 -> 3.2015 | AQ35: =AP35 -> 3.2015
A36: ANNUAL | B36: EUR10 | C36: COST | D36: 2020 | E36: =Worldprices!$M$62 -> IMPOILOTH | F36: =Worldprices!$M$63 -> OILOTH | G36: =Worldprices!$M$69*G$6 -> 9.31 | H36: =Worldprices!$M$69*H$6 -> 9.31 | I36: =AH36 -> 9.31 | J36: =Worldprices!$M$69*J$6 -> 9.31 | K36: =Worldprices!$M$69*K$6 -> 9.31 | L36: =Worldprices!$M$69*L$6 -> 9.31 | M36: =Worldprices!$M$69*M$6 -> 9.31 | N36: =Worldprices!$M$69*N$6 -> 9.31 | O36: =Worldprices!$M$69*O$6 -> 9.31 | P36: =Worldprices!$M$69*P$6 -> 9.31 | Q36: =Worldprices!$M$69*Q$6 -> 9.31 | ... AP36: =Worldprices!$M$69*AP$6 -> 9.31 | AQ36: =AP36 -> 9.31
A37: ANNUAL | B37: EUR10 | C37: COST | D37: 2020 | E37: =Worldprices!$N$62 -> IMPOILNAP | F37: =Worldprices!$N$63 -> OILNAP | G37: =Worldprices!$N$69*G$6 -> 9.31 | H37: =Worldprices!$N$69*H$6 -> 9.31 | I37: =AH37 -> 9.31 | J37: =Worldprices!$N$69*J$6 -> 9.31 | K37: =Worldprices!$N$69*K$6 -> 9.31 | L37: =Worldprices!$N$69*L$6 -> 9.31 | M37: =Worldprices!$N$69*M$6 -> 9.31 | N37: =Worldprices!$N$69*N$6 -> 9.31 | O37: =Worldprices!$N$69*O$6 -> 9.31 | P37: =Worldprices!$N$69*P$6 -> 9.31 | Q37: =Worldprices!$N$69*Q$6 -> 9.31 | ... AP37: =Worldprices!$N$69*AP$6 -> 9.31 | AQ37: =AP37 -> 9.31
A38: ANNUAL | B38: EUR10 | C38: COST | D38: 2020 | E38: =Worldprices!$O$62 -> IMPOILFDS | F38: =Worldprices!$O$63 -> OILFDS | G38: =Worldprices!$O$69*G$6 -> 9.31 | H38: =Worldprices!$O$69*H$6 -> 9.31 | I38: =AH38 -> 9.31 | J38: =Worldprices!$O$69*J$6 -> 9.31 | K38: =Worldprices!$O$69*K$6 -> 9.31 | L38: =Worldprices!$O$69*L$6 -> 9.31 | M38: =Worldprices!$O$69*M$6 -> 9.31 | N38: =Worldprices!$O$69*N$6 -> 9.31 | O38: =Worldprices!$O$69*O$6 -> 9.31 | P38: =Worldprices!$O$69*P$6 -> 9.31 | Q38: =Worldprices!$O$69*Q$6 -> 9.31 | ... AP38: =Worldprices!$O$69*AP$6 -> 9.31 | AQ38: =AP38 -> 9.31
A39: ANNUAL | B39: EUR10 | C39: COST | D39: 2020 | E39: =Worldprices!$P$62 -> IMPOILNEU | F39: =Worldprices!$P$63 -> OILNEU | G39: =Worldprices!$P$69*G$6 -> 9.31 | H39: =Worldprices!$P$69*H$6 -> 9.31 | I39: =AH39 -> 9.31 | J39: =Worldprices!$P$69*J$6 -> 9.31 | K39: =Worldprices!$P$69*K$6 -> 9.31 | L39: =Worldprices!$P$69*L$6 -> 9.31 | M39: =Worldprices!$P$69*M$6 -> 9.31 | N39: =Worldprices!$P$69*N$6 -> 9.31 | O39: =Worldprices!$P$69*O$6 -> 9.31 | P39: =Worldprices!$P$69*P$6 -> 9.31 | Q39: =Worldprices!$P$69*Q$6 -> 9.31 | ... AP39: =Worldprices!$P$69*AP$6 -> 9.31 | AQ39: =AP39 -> 9.31
A40: ANNUAL | B40: EUR10 | C40: *COST | D40: 2020 | E40: =Worldprices!$R$62 -> IMPBIOWOO | F40: =Worldprices!$R$63 -> BIOWOO | G40: =Worldprices!$R$69*G$8 -> 4.3312068 | H40: =Worldprices!$R$69*H$8 -> 4.3312068 | I40: =AH40 -> 4.3312068 | J40: =Worldprices!$R$69*J$8 -> 4.3312068 | K40: =Worldprices!$R$69*K$8 -> 4.3312068 | L40: =Worldprices!$R$69*L$8 -> 4.3312068 | M40: =Worldprices!$R$69*M$8 -> 4.3312068 | N40: =Worldprices!$R$69*N$8 -> 4.3312068 | O40: =Worldprices!$R$69*O$8 -> 4.3312068 | P40: =Worldprices!$R$69*P$8 -> 4.3312068 | Q40: =Worldprices!$R$69*Q$8 -> 4.3312068 | ... AP40: =Worldprices!$R$69*AP$8 -> 4.3312068 | AQ40: =AP40 -> 4.3312068
A41: ANNUAL | B41: EUR10 | C41: COST | D41: 2025 | E41: =Worldprices!$C$62 -> IMPCOAHAR* | F41: =Worldprices!$C$63 -> COAHAR | G41: =Worldprices!$C$70*G$4 -> 3.06 | H41: =Worldprices!$C$70*H$4 -> 2.8611 | I41: =AH41 -> 3.06 | J41: =Worldprices!$C$70*J$4 -> 3.06 | K41: =Worldprices!$C$70*K$4 -> 3.06 | L41: =Worldprices!$C$70*L$4 -> 3.06 | M41: =Worldprices!$C$70*M$4 -> 3.06 | N41: =Worldprices!$C$70*N$4 -> 3.06 | O41: =Worldprices!$C$70*O$4 -> 2.601 | P41: =Worldprices!$C$70*P$4 -> 2.907 | Q41: =Worldprices!$C$70*Q$4 -> 3.06 | ... AP41: =Worldprices!$C$70*AP$4 -> 3.06 | AQ41: =AP41 -> 3.06
A42: ANNUAL | B42: EUR10 | C42: COST | D42: 2025 | E42: =Worldprices!$D$62 -> IMPCOACOK* | F42: =Worldprices!$D$63 -> COACOK | G42: =Worldprices!$D$70*G$4 -> 3.8862 | H42: =Worldprices!$D$70*H$4 -> 3.633597 | I42: =AH42 -> 3.8862 | J42: =Worldprices!$D$70*J$4 -> 3.8862 | K42: =Worldprices!$D$70*K$4 -> 3.8862 | L42: =Worldprices!$D$70*L$4 -> 3.8862 | M42: =Worldprices!$D$70*M$4 -> 3.8862 | N42: =Worldprices!$D$70*N$4 -> 3.8862 | O42: =Worldprices!$D$70*O$4 -> 3.30327 | P42: =Worldprices!$D$70*P$4 -> 3.69189 | Q42: =Worldprices!$D$70*Q$4 -> 3.8862 | ... AP42: =Worldprices!$D$70*AP$4 -> 3.8862 | AQ42: =AP42 -> 3.8862
A43: ANNUAL | B43: EUR10 | C43: COST | D43: 2025 | E43: =Worldprices!$E$62 -> IMPCOABRO* | F43: =Worldprices!$E$63 -> COABRO | G43: =Worldprices!$E$70*G$4 -> 2.907 | H43: =Worldprices!$E$70*H$4 -> 2.718045 | I43: =AH43 -> 2.907 | J43: =Worldprices!$E$70*J$4 -> 2.907 | K43: =Worldprices!$E$70*K$4 -> 2.907 | L43: =Worldprices!$E$70*L$4 -> 2.907 | M43: =Worldprices!$E$70*M$4 -> 2.907 | N43: =Worldprices!$E$70*N$4 -> 2.907 | O43: =Worldprices!$E$70*O$4 -> 2.47095 | P43: =Worldprices!$E$70*P$4 -> 2.76165 | Q43: =Worldprices!$E$70*Q$4 -> 2.907 | ... AP43: =Worldprices!$E$70*AP$4 -> 2.907 | AQ43: =AP43 -> 2.907
A44: ANNUAL | B44: EUR10 | C44: COST | D44: 2025 | E44: =Worldprices!$F$62 -> IMPCOALIG* | F44: =Worldprices!$F$63 -> COALIG | G44: =Worldprices!$F$70*G$4 -> 2.907 | H44: =Worldprices!$F$70*H$4 -> 2.718045 | I44: =AH44 -> 2.907 | J44: =Worldprices!$F$70*J$4 -> 2.907 | K44: =Worldprices!$F$70*K$4 -> 2.907 | L44: =Worldprices!$F$70*L$4 -> 2.907 | M44: =Worldprices!$F$70*M$4 -> 2.907 | N44: =Worldprices!$F$70*N$4 -> 2.907 | O44: =Worldprices!$F$70*O$4 -> 2.47095 | P44: =Worldprices!$F$70*P$4 -> 2.76165 | Q44: =Worldprices!$F$70*Q$4 -> 2.907 | ... AP44: =Worldprices!$F$70*AP$4 -> 2.907 | AQ44: =AP44 -> 2.907
A45: ANNUAL | B45: EUR10 | C45: COST | D45: 2025 | E45: =Worldprices!$M$62 -> IMPOILOTH | F45: =Worldprices!$M$63 -> OILOTH | G45: =Worldprices!$M$70*G$6 -> 11.48 | H45: =Worldprices!$M$70*H$6 -> 11.48 | I45: =AH45 -> 11.48 | J45: =Worldprices!$M$70*J$6 -> 11.48 | K45: =Worldprices!$M$70*K$6 -> 11.48 | L45: =Worldprices!$M$70*L$6 -> 11.48 | M45: =Worldprices!$M$70*M$6 -> 11.48 | N45: =Worldprices!$M$70*N$6 -> 11.48 | O45: =Worldprices!$M$70*O$6 -> 11.48 | P45: =Worldprices!$M$70*P$6 -> 11.48 | Q45: =Worldprices!$M$70*Q$6 -> 11.48 | ... AP45: =Worldprices!$M$70*AP$6 -> 11.48 | AQ45: =AP45 -> 11.48
A46: ANNUAL | B46: EUR10 | C46: COST | D46: 2025 | E46: =Worldprices!$N$62 -> IMPOILNAP | F46: =Worldprices!$N$63 -> OILNAP | G46: =Worldprices!$N$70*G$6 -> 11.48 | H46: =Worldprices!$N$70*H$6 -> 11.48 | I46: =AH46 -> 11.48 | J46: =Worldprices!$N$70*J$6 -> 11.48 | K46: =Worldprices!$N$70*K$6 -> 11.48 | L46: =Worldprices!$N$70*L$6 -> 11.48 | M46: =Worldprices!$N$70*M$6 -> 11.48 | N46: =Worldprices!$N$70*N$6 -> 11.48 | O46: =Worldprices!$N$70*O$6 -> 11.48 | P46: =Worldprices!$N$70*P$6 -> 11.48 | Q46: =Worldprices!$N$70*Q$6 -> 11.48 | ... AP46: =Worldprices!$N$70*AP$6 -> 11.48 | AQ46: =AP46 -> 11.48
A47: ANNUAL | B47: EUR10 | C47: COST | D47: 2025 | E47: =Worldprices!$O$62 -> IMPOILFDS | F47: =Worldprices!$O$63 -> OILFDS | G47: =Worldprices!$O$70*G$6 -> 11.48 | H47: =Worldprices!$O$70*H$6 -> 11.48 | I47: =AH47 -> 11.48 | J47: =Worldprices!$O$70*J$6 -> 11.48 | K47: =Worldprices!$O$70*K$6 -> 11.48 | L47: =Worldprices!$O$70*L$6 -> 11.48 | M47: =Worldprices!$O$70*M$6 -> 11.48 | N47: =Worldprices!$O$70*N$6 -> 11.48 | O47: =Worldprices!$O$70*O$6 -> 11.48 | P47: =Worldprices!$O$70*P$6 -> 11.48 | Q47: =Worldprices!$O$70*Q$6 -> 11.48 | ... AP47: =Worldprices!$O$70*AP$6 -> 11.48 | AQ47: =AP47 -> 11.48
A48: ANNUAL | B48: EUR10 | C48: COST | D48: 2025 | E48: =Worldprices!$P$62 -> IMPOILNEU | F48: =Worldprices!$P$63 -> OILNEU | G48: =Worldprices!$P$70*G$6 -> 11.48 | H48: =Worldprices!$P$70*H$6 -> 11.48 | I48: =AH48 -> 11.48 | J48: =Worldprices!$P$70*J$6 -> 11.48 | K48: =Worldprices!$P$70*K$6 -> 11.48 | L48: =Worldprices!$P$70*L$6 -> 11.48 | M48: =Worldprices!$P$70*M$6 -> 11.48 | N48: =Worldprices!$P$70*N$6 -> 11.48 | O48: =Worldprices!$P$70*O$6 -> 11.48 | P48: =Worldprices!$P$70*P$6 -> 11.48 | Q48: =Worldprices!$P$70*Q$6 -> 11.48 | ... AP48: =Worldprices!$P$70*AP$6 -> 11.48 | AQ48: =AP48 -> 11.48
A49: ANNUAL | B49: EUR10 | C49: *COST | D49: 2025 | E49: =Worldprices!$R$62 -> IMPBIOWOO | F49: =Worldprices!$R$63 -> BIOWOO | G49: =Worldprices!$R$70*G$8 -> 4.7353034 | H49: =Worldprices!$R$70*H$8 -> 4.7353034 | I49: =AH49 -> 4.7353034 | J49: =Worldprices!$R$70*J$8 -> 4.7353034 | K49: =Worldprices!$R$70*K$8 -> 4.7353034 | L49: =Worldprices!$R$70*L$8 -> 4.7353034 | M49: =Worldprices!$R$70*M$8 -> 4.7353034 | N49: =Worldprices!$R$70*N$8 -> 4.7353034 | O49: =Worldprices!$R$70*O$8 -> 4.7353034 | P49: =Worldprices!$R$70*P$8 -> 4.7353034 | Q49: =Worldprices!$R$70*Q$8 -> 4.7353034 | ... AP49: =Worldprices!$R$70*AP$8 -> 4.7353034 | AQ49: =AP49 -> 4.7353034
A50: ANNUAL | B50: EUR10 | C50: COST | D50: 2030 | E50: =Worldprices!$C$62 -> IMPCOAHAR* | F50: =Worldprices!$C$63 -> COAHAR | G50: =Worldprices!$C$71*G$4 -> 2.75 | H50: =Worldprices!$C$71*H$4 -> 2.57125 | I50: =AH50 -> 2.75 | J50: =Worldprices!$C$71*J$4 -> 2.75 | K50: =Worldprices!$C$71*K$4 -> 2.75 | L50: =Worldprices!$C$71*L$4 -> 2.75 | M50: =Worldprices!$C$71*M$4 -> 2.75 | N50: =Worldprices!$C$71*N$4 -> 2.75 | O50: =Worldprices!$C$71*O$4 -> 2.3375 | P50: =Worldprices!$C$71*P$4 -> 2.6125 | Q50: =Worldprices!$C$71*Q$4 -> 2.75 | ... AP50: =Worldprices!$C$71*AP$4 -> 2.75 | AQ50: =AP50 -> 2.75
A51: ANNUAL | B51: EUR10 | C51: COST | D51: 2030 | E51: =Worldprices!$D$62 -> IMPCOACOK* | F51: =Worldprices!$D$63 -> COACOK | G51: =Worldprices!$D$71*G$4 -> 3.4925 | H51: =Worldprices!$D$71*H$4 -> 3.2654875 | I51: =AH51 -> 3.4925 | J51: =Worldprices!$D$71*J$4 -> 3.4925 | K51: =Worldprices!$D$71*K$4 -> 3.4925 | L51: =Worldprices!$D$71*L$4 -> 3.4925 | M51: =Worldprices!$D$71*M$4 -> 3.4925 | N51: =Worldprices!$D$71*N$4 -> 3.4925 | O51: =Worldprices!$D$71*O$4 -> 2.968625 | P51: =Worldprices!$D$71*P$4 -> 3.317875 | Q51: =Worldprices!$D$71*Q$4 -> 3.4925 | ... AP51: =Worldprices!$D$71*AP$4 -> 3.4925 | AQ51: =AP51 -> 3.4925
A52: ANNUAL | B52: EUR10 | C52: COST | D52: 2030 | E52: =Worldprices!$E$62 -> IMPCOABRO* | F52: =Worldprices!$E$63 -> COABRO | G52: =Worldprices!$E$71*G$4 -> 2.6125 | H52: =Worldprices!$E$71*H$4 -> 2.4426875 | I52: =AH52 -> 2.6125 | J52: =Worldprices!$E$71*J$4 -> 2.6125 | K52: =Worldprices!$E$71*K$4 -> 2.6125 | L52: =Worldprices!$E$71*L$4 -> 2.6125 | M52: =Worldprices!$E$71*M$4 -> 2.6125 | N52: =Worldprices!$E$71*N$4 -> 2.6125 | O52: =Worldprices!$E$71*O$4 -> 2.220625 | P52: =Worldprices!$E$71*P$4 -> 2.481875 | Q52: =Worldprices!$E$71*Q$4 -> 2.6125 | ... AP52: =Worldprices!$E$71*AP$4 -> 2.6125 | AQ52: =AP52 -> 2.6125
A53: ANNUAL | B53: EUR10 | C53: COST | D53: 2030 | E53: =Worldprices!$F$62 -> IMPCOALIG* | F53: =Worldprices!$F$63 -> COALIG | G53: =Worldprices!$F$71*G$4 -> 2.6125 | H53: =Worldprices!$F$71*H$4 -> 2.4426875 | I53: =AH53 -> 2.6125 | J53: =Worldprices!$F$71*J$4 -> 2.6125 | K53: =Worldprices!$F$71*K$4 -> 2.6125 | L53: =Worldprices!$F$71*L$4 -> 2.6125 | M53: =Worldprices!$F$71*M$4 -> 2.6125 | N53: =Worldprices!$F$71*N$4 -> 2.6125 | O53: =Worldprices!$F$71*O$4 -> 2.220625 | P53: =Worldprices!$F$71*P$4 -> 2.481875 | Q53: =Worldprices!$F$71*Q$4 -> 2.6125 | ... AP53: =Worldprices!$F$71*AP$4 -> 2.6125 | AQ53: =AP53 -> 2.6125
A54: ANNUAL | B54: EUR10 | C54: COST | D54: 2030 | E54: =Worldprices!$M$62 -> IMPOILOTH | F54: =Worldprices!$M$63 -> OILOTH | G54: =Worldprices!$M$71*G$6 -> 13.65 | H54: =Worldprices!$M$71*H$6 -> 13.65 | I54: =AH54 -> 13.65 | J54: =Worldprices!$M$71*J$6 -> 13.65 | K54: =Worldprices!$M$71*K$6 -> 13.65 | L54: =Worldprices!$M$71*L$6 -> 13.65 | M54: =Worldprices!$M$71*M$6 -> 13.65 | N54: =Worldprices!$M$71*N$6 -> 13.65 | O54: =Worldprices!$M$71*O$6 -> 13.65 | P54: =Worldprices!$M$71*P$6 -> 13.65 | Q54: =Worldprices!$M$71*Q$6 -> 13.65 | ... AP54: =Worldprices!$M$71*AP$6 -> 13.65 | AQ54: =AP54 -> 13.65
A55: ANNUAL | B55: EUR10 | C55: COST | D55: 2030 | E55: =Worldprices!$N$62 -> IMPOILNAP | F55: =Worldprices!$N$63 -> OILNAP | G55: =Worldprices!$N$71*G$6 -> 13.65 | H55: =Worldprices!$N$71*H$6 -> 13.65 | I55: =AH55 -> 13.65 | J55: =Worldprices!$N$71*J$6 -> 13.65 | K55: =Worldprices!$N$71*K$6 -> 13.65 | L55: =Worldprices!$N$71*L$6 -> 13.65 | M55: =Worldprices!$N$71*M$6 -> 13.65 | N55: =Worldprices!$N$71*N$6 -> 13.65 | O55: =Worldprices!$N$71*O$6 -> 13.65 | P55: =Worldprices!$N$71*P$6 -> 13.65 | Q55: =Worldprices!$N$71*Q$6 -> 13.65 | ... AP55: =Worldprices!$N$71*AP$6 -> 13.65 | AQ55: =AP55 -> 13.65
A56: ANNUAL | B56: EUR10 | C56: COST | D56: 2030 | E56: =Worldprices!$O$62 -> IMPOILFDS | F56: =Worldprices!$O$63 -> OILFDS | G56: =Worldprices!$O$71*G$6 -> 13.65 | H56: =Worldprices!$O$71*H$6 -> 13.65 | I56: =AH56 -> 13.65 | J56: =Worldprices!$O$71*J$6 -> 13.65 | K56: =Worldprices!$O$71*K$6 -> 13.65 | L56: =Worldprices!$O$71*L$6 -> 13.65 | M56: =Worldprices!$O$71*M$6 -> 13.65 | N56: =Worldprices!$O$71*N$6 -> 13.65 | O56: =Worldprices!$O$71*O$6 -> 13.65 | P56: =Worldprices!$O$71*P$6 -> 13.65 | Q56: =Worldprices!$O$71*Q$6 -> 13.65 | ... AP56: =Worldprices!$O$71*AP$6 -> 13.65 | AQ56: =AP56 -> 13.65
A57: ANNUAL | B57: EUR10 | C57: COST | D57: 2030 | E57: =Worldprices!$P$62 -> IMPOILNEU | F57: =Worldprices!$P$63 -> OILNEU | G57: =Worldprices!$P$71*G$6 -> 13.65 | H57: =Worldprices!$P$71*H$6 -> 13.65 | I57: =AH57 -> 13.65 | J57: =Worldprices!$P$71*J$6 -> 13.65 | K57: =Worldprices!$P$71*K$6 -> 13.65 | L57: =Worldprices!$P$71*L$6 -> 13.65 | M57: =Worldprices!$P$71*M$6 -> 13.65 | N57: =Worldprices!$P$71*N$6 -> 13.65 | O57: =Worldprices!$P$71*O$6 -> 13.65 | P57: =Worldprices!$P$71*P$6 -> 13.65 | Q57: =Worldprices!$P$71*Q$6 -> 13.65 | ... AP57: =Worldprices!$P$71*AP$6 -> 13.65 | AQ57: =AP57 -> 13.65
A58: ANNUAL | B58: EUR10 | C58: *COST | D58: 2030 | E58: =Worldprices!$R$62 -> IMPBIOWOO | F58: =Worldprices!$R$63 -> BIOWOO | G58: =Worldprices!$R$71*G$8 -> 5.1771017 | H58: =Worldprices!$R$71*H$8 -> 5.1771017 | I58: =AH58 -> 5.1771017 | J58: =Worldprices!$R$71*J$8 -> 5.1771017 | K58: =Worldprices!$R$71*K$8 -> 5.1771017 | L58: =Worldprices!$R$71*L$8 -> 5.1771017 | M58: =Worldprices!$R$71*M$8 -> 5.1771017 | N58: =Worldprices!$R$71*N$8 -> 5.1771017 | O58: =Worldprices!$R$71*O$8 -> 5.1771017 | P58: =Worldprices!$R$71*P$8 -> 5.1771017 | Q58: =Worldprices!$R$71*Q$8 -> 5.1771017 | ... AP58: =Worldprices!$R$71*AP$8 -> 5.1771017 | AQ58: =AP58 -> 5.1771017
A59: ANNUAL | B59: EUR10 | C59: COST | D59: 2035 | E59: =Worldprices!$C$62 -> IMPCOAHAR* | F59: =Worldprices!$C$63 -> COAHAR | G59: =Worldprices!$C$72*G$4 -> 2.84 | H59: =Worldprices!$C$72*H$4 -> 2.6554 | I59: =AH59 -> 2.84 | J59: =Worldprices!$C$72*J$4 -> 2.84 | K59: =Worldprices!$C$72*K$4 -> 2.84 | L59: =Worldprices!$C$72*L$4 -> 2.84 | M59: =Worldprices!$C$72*M$4 -> 2.84 | N59: =Worldprices!$C$72*N$4 -> 2.84 | O59: =Worldprices!$C$72*O$4 -> 2.414 | P59: =Worldprices!$C$72*P$4 -> 2.698 | Q59: =Worldprices!$C$72*Q$4 -> 2.84 | ... AP59: =Worldprices!$C$72*AP$4 -> 2.84 | AQ59: =AP59 -> 2.84
A60: ANNUAL | B60: EUR10 | C60: COST | D60: 2035 | E60: =Worldprices!$D$62 -> IMPCOACOK* | F60: =Worldprices!$D$63 -> COACOK | G60: =Worldprices!$D$72*G$4 -> 3.6068 | H60: =Worldprices!$D$72*H$4 -> 3.372358 | I60: =AH60 -> 3.6068 | J60: =Worldprices!$D$72*J$4 -> 3.6068 | K60: =Worldprices!$D$72*K$4 -> 3.6068 | L60: =Worldprices!$D$72*L$4 -> 3.6068 | M60: =Worldprices!$D$72*M$4 -> 3.6068 | N60: =Worldprices!$D$72*N$4 -> 3.6068 | O60: =Worldprices!$D$72*O$4 -> 3.06578 | P60: =Worldprices!$D$72*P$4 -> 3.42646 | Q60: =Worldprices!$D$72*Q$4 -> 3.6068 | ... AP60: =Worldprices!$D$72*AP$4 -> 3.6068 | AQ60: =AP60 -> 3.6068
A61: ANNUAL | B61: EUR10 | C61: COST | D61: 2035 | E61: =Worldprices!$E$62 -> IMPCOABRO* | F61: =Worldprices!$E$63 -> COABRO | G61: =Worldprices!$E$72*G$4 -> 2.698 | H61: =Worldprices!$E$72*H$4 -> 2.52263 | I61: =AH61 -> 2.698 | J61: =Worldprices!$E$72*J$4 -> 2.698 | K61: =Worldprices!$E$72*K$4 -> 2.698 | L61: =Worldprices!$E$72*L$4 -> 2.698 | M61: =Worldprices!$E$72*M$4 -> 2.698 | N61: =Worldprices!$E$72*N$4 -> 2.698 | O61: =Worldprices!$E$72*O$4 -> 2.2933 | P61: =Worldprices!$E$72*P$4 -> 2.5631 | Q61: =Worldprices!$E$72*Q$4 -> 2.698 | ... AP61: =Worldprices!$E$72*AP$4 -> 2.698 | AQ61: =AP61 -> 2.698
A62: ANNUAL | B62: EUR10 | C62: COST | D62: 2035 | E62: =Worldprices!$F$62 -> IMPCOALIG* | F62: =Worldprices!$F$63 -> COALIG | G62: =Worldprices!$F$72*G$4 -> 2.698 | H62: =Worldprices!$F$72*H$4 -> 2.52263 | I62: =AH62 -> 2.698 | J62: =Worldprices!$F$72*J$4 -> 2.698 | K62: =Worldprices!$F$72*K$4 -> 2.698 | L62: =Worldprices!$F$72*L$4 -> 2.698 | M62: =Worldprices!$F$72*M$4 -> 2.698 | N62: =Worldprices!$F$72*N$4 -> 2.698 | O62: =Worldprices!$F$72*O$4 -> 2.2933 | P62: =Worldprices!$F$72*P$4 -> 2.5631 | Q62: =Worldprices!$F$72*Q$4 -> 2.698 | ... AP62: =Worldprices!$F$72*AP$4 -> 2.698 | AQ62: =AP62 -> 2.698
A63: ANNUAL | B63: EUR10 | C63: COST | D63: 2035 | E63: =Worldprices!$M$62 -> IMPOILOTH | F63: =Worldprices!$M$63 -> OILOTH | G63: =Worldprices!$M$72*G$6 -> 14.05 | H63: =Worldprices!$M$72*H$6 -> 14.05 | I63: =AH63 -> 14.05 | J63: =Worldprices!$M$72*J$6 -> 14.05 | K63: =Worldprices!$M$72*K$6 -> 14.05 | L63: =Worldprices!$M$72*L$6 -> 14.05 | M63: =Worldprices!$M$72*M$6 -> 14.05 | N63: =Worldprices!$M$72*N$6 -> 14.05 | O63: =Worldprices!$M$72*O$6 -> 14.05 | P63: =Worldprices!$M$72*P$6 -> 14.05 | Q63: =Worldprices!$M$72*Q$6 -> 14.05 | ... AP63: =Worldprices!$M$72*AP$6 -> 14.05 | AQ63: =AP63 -> 14.05
A64: ANNUAL | B64: EUR10 | C64: COST | D64: 2035 | E64: =Worldprices!$N$62 -> IMPOILNAP | F64: =Worldprices!$N$63 -> OILNAP | G64: =Worldprices!$N$72*G$6 -> 14.05 | H64: =Worldprices!$N$72*H$6 -> 14.05 | I64: =AH64 -> 14.05 | J64: =Worldprices!$N$72*J$6 -> 14.05 | K64: =Worldprices!$N$72*K$6 -> 14.05 | L64: =Worldprices!$N$72*L$6 -> 14.05 | M64: =Worldprices!$N$72*M$6 -> 14.05 | N64: =Worldprices!$N$72*N$6 -> 14.05 | O64: =Worldprices!$N$72*O$6 -> 14.05 | P64: =Worldprices!$N$72*P$6 -> 14.05 | Q64: =Worldprices!$N$72*Q$6 -> 14.05 | ... AP64: =Worldprices!$N$72*AP$6 -> 14.05 | AQ64: =AP64 -> 14.05
A65: ANNUAL | B65: EUR10 | C65: COST | D65: 2035 | E65: =Worldprices!$O$62 -> IMPOILFDS | F65: =Worldprices!$O$63 -> OILFDS | G65: =Worldprices!$O$72*G$6 -> 14.05 | H65: =Worldprices!$O$72*H$6 -> 14.05 | I65: =AH65 -> 14.05 | J65: =Worldprices!$O$72*J$6 -> 14.05 | K65: =Worldprices!$O$72*K$6 -> 14.05 | L65: =Worldprices!$O$72*L$6 -> 14.05 | M65: =Worldprices!$O$72*M$6 -> 14.05 | N65: =Worldprices!$O$72*N$6 -> 14.05 | O65: =Worldprices!$O$72*O$6 -> 14.05 | P65: =Worldprices!$O$72*P$6 -> 14.05 | Q65: =Worldprices!$O$72*Q$6 -> 14.05 | ... AP65: =Worldprices!$O$72*AP$6 -> 14.05 | AQ65: =AP65 -> 14.05
A66: ANNUAL | B66: EUR10 | C66: COST | D66: 2035 | E66: =Worldprices!$P$62 -> IMPOILNEU | F66: =Worldprices!$P$63 -> OILNEU | G66: =Worldprices!$P$72*G$6 -> 14.05 | H66: =Worldprices!$P$72*H$6 -> 14.05 | I66: =AH66 -> 14.05 | J66: =Worldprices!$P$72*J$6 -> 14.05 | K66: =Worldprices!$P$72*K$6 -> 14.05 | L66: =Worldprices!$P$72*L$6 -> 14.05 | M66: =Worldprices!$P$72*M$6 -> 14.05 | N66: =Worldprices!$P$72*N$6 -> 14.05 | O66: =Worldprices!$P$72*O$6 -> 14.05 | P66: =Worldprices!$P$72*P$6 -> 14.05 | Q66: =Worldprices!$P$72*Q$6 -> 14.05 | ... AP66: =Worldprices!$P$72*AP$6 -> 14.05 | AQ66: =AP66 -> 14.05
A67: ANNUAL | B67: EUR10 | C67: *COST | D67: 2035 | E67: =Worldprices!$R$62 -> IMPBIOWOO | F67: =Worldprices!$R$63 -> BIOWOO | G67: =Worldprices!$R$72*G$8 -> 5.6601194 | H67: =Worldprices!$R$72*H$8 -> 5.6601194 | I67: =AH67 -> 5.6601194 | J67: =Worldprices!$R$72*J$8 -> 5.6601194 | K67: =Worldprices!$R$72*K$8 -> 5.6601194 | L67: =Worldprices!$R$72*L$8 -> 5.6601194 | M67: =Worldprices!$R$72*M$8 -> 5.6601194 | N67: =Worldprices!$R$72*N$8 -> 5.6601194 | O67: =Worldprices!$R$72*O$8 -> 5.6601194 | P67: =Worldprices!$R$72*P$8 -> 5.6601194 | Q67: =Worldprices!$R$72*Q$8 -> 5.6601194 | ... AP67: =Worldprices!$R$72*AP$8 -> 5.6601194 | AQ67: =AP67 -> 5.6601194
A68: ANNUAL | B68: EUR10 | C68: COST | D68: 2040 | E68: =Worldprices!$C$62 -> IMPCOAHAR* | F68: =Worldprices!$C$63 -> COAHAR | G68: =Worldprices!$C$73*G$4 -> 2.93 | H68: =Worldprices!$C$73*H$4 -> 2.73955 | I68: =AH68 -> 2.93 | J68: =Worldprices!$C$73*J$4 -> 2.93 | K68: =Worldprices!$C$73*K$4 -> 2.93 | L68: =Worldprices!$C$73*L$4 -> 2.93 | M68: =Worldprices!$C$73*M$4 -> 2.93 | N68: =Worldprices!$C$73*N$4 -> 2.93 | O68: =Worldprices!$C$73*O$4 -> 2.4905 | P68: =Worldprices!$C$73*P$4 -> 2.7835 | Q68: =Worldprices!$C$73*Q$4 -> 2.93 | ... AP68: =Worldprices!$C$73*AP$4 -> 2.93 | AQ68: =AP68 -> 2.93
A69: ANNUAL | B69: EUR10 | C69: COST | D69: 2040 | E69: =Worldprices!$D$62 -> IMPCOACOK* | F69: =Worldprices!$D$63 -> COACOK | G69: =Worldprices!$D$73*G$4 -> 3.7211 | H69: =Worldprices!$D$73*H$4 -> 3.4792285 | I69: =AH69 -> 3.7211 | J69: =Worldprices!$D$73*J$4 -> 3.7211 | K69: =Worldprices!$D$73*K$4 -> 3.7211 | L69: =Worldprices!$D$73*L$4 -> 3.7211 | M69: =Worldprices!$D$73*M$4 -> 3.7211 | N69: =Worldprices!$D$73*N$4 -> 3.7211 | O69: =Worldprices!$D$73*O$4 -> 3.162935 | P69: =Worldprices!$D$73*P$4 -> 3.535045 | Q69: =Worldprices!$D$73*Q$4 -> 3.7211 | ... AP69: =Worldprices!$D$73*AP$4 -> 3.7211 | AQ69: =AP69 -> 3.7211
A70: ANNUAL | B70: EUR10 | C70: COST | D70: 2040 | E70: =Worldprices!$E$62 -> IMPCOABRO* | F70: =Worldprices!$E$63 -> COABRO | G70: =Worldprices!$E$73*G$4 -> 2.7835 | H70: =Worldprices!$E$73*H$4 -> 2.6025725 | I70: =AH70 -> 2.7835 | J70: =Worldprices!$E$73*J$4 -> 2.7835 | K70: =Worldprices!$E$73*K$4 -> 2.7835 | L70: =Worldprices!$E$73*L$4 -> 2.7835 | M70: =Worldprices!$E$73*M$4 -> 2.7835 | N70: =Worldprices!$E$73*N$4 -> 2.7835 | O70: =Worldprices!$E$73*O$4 -> 2.365975 | P70: =Worldprices!$E$73*P$4 -> 2.644325 | Q70: =Worldprices!$E$73*Q$4 -> 2.7835 | ... AP70: =Worldprices!$E$73*AP$4 -> 2.7835 | AQ70: =AP70 -> 2.7835
A71: ANNUAL | B71: EUR10 | C71: COST | D71: 2040 | E71: =Worldprices!$F$62 -> IMPCOALIG* | F71: =Worldprices!$F$63 -> COALIG | G71: =Worldprices!$F$73*G$4 -> 2.7835 | H71: =Worldprices!$F$73*H$4 -> 2.6025725 | I71: =AH71 -> 2.7835 | J71: =Worldprices!$F$73*J$4 -> 2.7835 | K71: =Worldprices!$F$73*K$4 -> 2.7835 | L71: =Worldprices!$F$73*L$4 -> 2.7835 | M71: =Worldprices!$F$73*M$4 -> 2.7835 | N71: =Worldprices!$F$73*N$4 -> 2.7835 | O71: =Worldprices!$F$73*O$4 -> 2.365975 | P71: =Worldprices!$F$73*P$4 -> 2.644325 | Q71: =Worldprices!$F$73*Q$4 -> 2.7835 | ... AP71: =Worldprices!$F$73*AP$4 -> 2.7835 | AQ71: =AP71 -> 2.7835
A72: ANNUAL | B72: EUR10 | C72: COST | D72: 2040 | E72: =Worldprices!$M$62 -> IMPOILOTH | F72: =Worldprices!$M$63 -> OILOTH | G72: =Worldprices!$M$73*G$6 -> 14.45 | H72: =Worldprices!$M$73*H$6 -> 14.45 | I72: =AH72 -> 14.45 | J72: =Worldprices!$M$73*J$6 -> 14.45 | K72: =Worldprices!$M$73*K$6 -> 14.45 | L72: =Worldprices!$M$73*L$6 -> 14.45 | M72: =Worldprices!$M$73*M$6 -> 14.45 | N72: =Worldprices!$M$73*N$6 -> 14.45 | O72: =Worldprices!$M$73*O$6 -> 14.45 | P72: =Worldprices!$M$73*P$6 -> 14.45 | Q72: =Worldprices!$M$73*Q$6 -> 14.45 | ... AP72: =Worldprices!$M$73*AP$6 -> 14.45 | AQ72: =AP72 -> 14.45
A73: ANNUAL | B73: EUR10 | C73: COST | D73: 2040 | E73: =Worldprices!$N$62 -> IMPOILNAP | F73: =Worldprices!$N$63 -> OILNAP | G73: =Worldprices!$N$73*G$6 -> 14.45 | H73: =Worldprices!$N$73*H$6 -> 14.45 | I73: =AH73 -> 14.45 | J73: =Worldprices!$N$73*J$6 -> 14.45 | K73: =Worldprices!$N$73*K$6 -> 14.45 | L73: =Worldprices!$N$73*L$6 -> 14.45 | M73: =Worldprices!$N$73*M$6 -> 14.45 | N73: =Worldprices!$N$73*N$6 -> 14.45 | O73: =Worldprices!$N$73*O$6 -> 14.45 | P73: =Worldprices!$N$73*P$6 -> 14.45 | Q73: =Worldprices!$N$73*Q$6 -> 14.45 | ... AP73: =Worldprices!$N$73*AP$6 -> 14.45 | AQ73: =AP73 -> 14.45
A74: ANNUAL | B74: EUR10 | C74: COST | D74: 2040 | E74: =Worldprices!$O$62 -> IMPOILFDS | F74: =Worldprices!$O$63 -> OILFDS | G74: =Worldprices!$O$73*G$6 -> 14.45 | H74: =Worldprices!$O$73*H$6 -> 14.45 | I74: =AH74 -> 14.45 | J74: =Worldprices!$O$73*J$6 -> 14.45 | K74: =Worldprices!$O$73*K$6 -> 14.45 | L74: =Worldprices!$O$73*L$6 -> 14.45 | M74: =Worldprices!$O$73*M$6 -> 14.45 | N74: =Worldprices!$O$73*N$6 -> 14.45 | O74: =Worldprices!$O$73*O$6 -> 14.45 | P74: =Worldprices!$O$73*P$6 -> 14.45 | Q74: =Worldprices!$O$73*Q$6 -> 14.45 | ... AP74: =Worldprices!$O$73*AP$6 -> 14.45 | AQ74: =AP74 -> 14.45
A75: ANNUAL | B75: EUR10 | C75: COST | D75: 2040 | E75: =Worldprices!$P$62 -> IMPOILNEU | F75: =Worldprices!$P$63 -> OILNEU | G75: =Worldprices!$P$73*G$6 -> 14.45 | H75: =Worldprices!$P$73*H$6 -> 14.45 | I75: =AH75 -> 14.45 | J75: =Worldprices!$P$73*J$6 -> 14.45 | K75: =Worldprices!$P$73*K$6 -> 14.45 | L75: =Worldprices!$P$73*L$6 -> 14.45 | M75: =Worldprices!$P$73*M$6 -> 14.45 | N75: =Worldprices!$P$73*N$6 -> 14.45 | O75: =Worldprices!$P$73*O$6 -> 14.45 | P75: =Worldprices!$P$73*P$6 -> 14.45 | Q75: =Worldprices!$P$73*Q$6 -> 14.45 | ... AP75: =Worldprices!$P$73*AP$6 -> 14.45 | AQ75: =AP75 -> 14.45
A76: ANNUAL | B76: EUR10 | C76: *COST | D76: 2040 | E76: =Worldprices!$R$62 -> IMPBIOWOO | F76: =Worldprices!$R$63 -> BIOWOO | G76: =Worldprices!$R$73*G$8 -> 6.188202 | H76: =Worldprices!$R$73*H$8 -> 6.188202 | I76: =AH76 -> 6.188202 | J76: =Worldprices!$R$73*J$8 -> 6.188202 | K76: =Worldprices!$R$73*K$8 -> 6.188202 | L76: =Worldprices!$R$73*L$8 -> 6.188202 | M76: =Worldprices!$R$73*M$8 -> 6.188202 | N76: =Worldprices!$R$73*N$8 -> 6.188202 | O76: =Worldprices!$R$73*O$8 -> 6.188202 | P76: =Worldprices!$R$73*P$8 -> 6.188202 | Q76: =Worldprices!$R$73*Q$8 -> 6.188202 | ... AP76: =Worldprices!$R$73*AP$8 -> 6.188202 | AQ76: =AP76 -> 6.188202
A77: ANNUAL | B77: EUR10 | C77: COST | D77: 2045 | E77: =Worldprices!$C$62 -> IMPCOAHAR* | F77: =Worldprices!$C$63 -> COAHAR | G77: =Worldprices!$C$74*G$4 -> 3.105 | H77: =Worldprices!$C$74*H$4 -> 2.903175 | I77: =AH77 -> 3.105 | J77: =Worldprices!$C$74*J$4 -> 3.105 | K77: =Worldprices!$C$74*K$4 -> 3.105 | L77: =Worldprices!$C$74*L$4 -> 3.105 | M77: =Worldprices!$C$74*M$4 -> 3.105 | N77: =Worldprices!$C$74*N$4 -> 3.105 | O77: =Worldprices!$C$74*O$4 -> 2.63925 | P77: =Worldprices!$C$74*P$4 -> 2.94975 | Q77: =Worldprices!$C$74*Q$4 -> 3.105 | ... AP77: =Worldprices!$C$74*AP$4 -> 3.105 | AQ77: =AP77 -> 3.105
A78: ANNUAL | B78: EUR10 | C78: COST | D78: 2045 | E78: =Worldprices!$D$62 -> IMPCOACOK* | F78: =Worldprices!$D$63 -> COACOK | G78: =Worldprices!$D$74*G$4 -> 3.94335 | H78: =Worldprices!$D$74*H$4 -> 3.6870323 | I78: =AH78 -> 3.94335 | J78: =Worldprices!$D$74*J$4 -> 3.94335 | K78: =Worldprices!$D$74*K$4 -> 3.94335 | L78: =Worldprices!$D$74*L$4 -> 3.94335 | M78: =Worldprices!$D$74*M$4 -> 3.94335 | N78: =Worldprices!$D$74*N$4 -> 3.94335 | O78: =Worldprices!$D$74*O$4 -> 3.3518475 | P78: =Worldprices!$D$74*P$4 -> 3.7461825 | Q78: =Worldprices!$D$74*Q$4 -> 3.94335 | ... AP78: =Worldprices!$D$74*AP$4 -> 3.94335 | AQ78: =AP78 -> 3.94335
A79: ANNUAL | B79: EUR10 | C79: COST | D79: 2045 | E79: =Worldprices!$E$62 -> IMPCOABRO* | F79: =Worldprices!$E$63 -> COABRO | G79: =Worldprices!$E$74*G$4 -> 2.94975 | H79: =Worldprices!$E$74*H$4 -> 2.7580163 | I79: =AH79 -> 2.94975 | J79: =Worldprices!$E$74*J$4 -> 2.94975 | K79: =Worldprices!$E$74*K$4 -> 2.94975 | L79: =Worldprices!$E$74*L$4 -> 2.94975 | M79: =Worldprices!$E$74*M$4 -> 2.94975 | N79: =Worldprices!$E$74*N$4 -> 2.94975 | O79: =Worldprices!$E$74*O$4 -> 2.5072875 | P79: =Worldprices!$E$74*P$4 -> 2.8022625 | Q79: =Worldprices!$E$74*Q$4 -> 2.94975 | ... AP79: =Worldprices!$E$74*AP$4 -> 2.94975 | AQ79: =AP79 -> 2.94975
A80: ANNUAL | B80: EUR10 | C80: COST | D80: 2045 | E80: =Worldprices!$F$62 -> IMPCOALIG* | F80: =Worldprices!$F$63 -> COALIG | G80: =Worldprices!$F$74*G$4 -> 2.94975 | H80: =Worldprices!$F$74*H$4 -> 2.7580163 | I80: =AH80 -> 2.94975 | J80: =Worldprices!$F$74*J$4 -> 2.94975 | K80: =Worldprices!$F$74*K$4 -> 2.94975 | L80: =Worldprices!$F$74*L$4 -> 2.94975 | M80: =Worldprices!$F$74*M$4 -> 2.94975 | N80: =Worldprices!$F$74*N$4 -> 2.94975 | O80: =Worldprices!$F$74*O$4 -> 2.5072875 | P80: =Worldprices!$F$74*P$4 -> 2.8022625 | Q80: =Worldprices!$F$74*Q$4 -> 2.94975 | ... AP80: =Worldprices!$F$74*AP$4 -> 2.94975 | AQ80: =AP80 -> 2.94975
A81: ANNUAL | B81: EUR10 | C81: COST | D81: 2045 | E81: =Worldprices!$M$62 -> IMPOILOTH | F81: =Worldprices!$M$63 -> OILOTH | G81: =Worldprices!$M$74*G$6 -> 15.96 | H81: =Worldprices!$M$74*H$6 -> 15.96 | I81: =AH81 -> 15.96 | J81: =Worldprices!$M$74*J$6 -> 15.96 | K81: =Worldprices!$M$74*K$6 -> 15.96 | L81: =Worldprices!$M$74*L$6 -> 15.96 | M81: =Worldprices!$M$74*M$6 -> 15.96 | N81: =Worldprices!$M$74*N$6 -> 15.96 | O81: =Worldprices!$M$74*O$6 -> 15.96 | P81: =Worldprices!$M$74*P$6 -> 15.96 | Q81: =Worldprices!$M$74*Q$6 -> 15.96 | ... AP81: =Worldprices!$M$74*AP$6 -> 15.96 | AQ81: =AP81 -> 15.96
A82: ANNUAL | B82: EUR10 | C82: COST | D82: 2045 | E82: =Worldprices!$N$62 -> IMPOILNAP | F82: =Worldprices!$N$63 -> OILNAP | G82: =Worldprices!$N$74*G$6 -> 15.96 | H82: =Worldprices!$N$74*H$6 -> 15.96 | I82: =AH82 -> 15.96 | J82: =Worldprices!$N$74*J$6 -> 15.96 | K82: =Worldprices!$N$74*K$6 -> 15.96 | L82: =Worldprices!$N$74*L$6 -> 15.96 | M82: =Worldprices!$N$74*M$6 -> 15.96 | N82: =Worldprices!$N$74*N$6 -> 15.96 | O82: =Worldprices!$N$74*O$6 -> 15.96 | P82: =Worldprices!$N$74*P$6 -> 15.96 | Q82: =Worldprices!$N$74*Q$6 -> 15.96 | ... AP82: =Worldprices!$N$74*AP$6 -> 15.96 | AQ82: =AP82 -> 15.96
A83: ANNUAL | B83: EUR10 | C83: COST | D83: 2045 | E83: =Worldprices!$O$62 -> IMPOILFDS | F83: =Worldprices!$O$63 -> OILFDS | G83: =Worldprices!$O$74*G$6 -> 15.96 | H83: =Worldprices!$O$74*H$6 -> 15.96 | I83: =AH83 -> 15.96 | J83: =Worldprices!$O$74*J$6 -> 15.96 | K83: =Worldprices!$O$74*K$6 -> 15.96 | L83: =Worldprices!$O$74*L$6 -> 15.96 | M83: =Worldprices!$O$74*M$6 -> 15.96 | N83: =Worldprices!$O$74*N$6 -> 15.96 | O83: =Worldprices!$O$74*O$6 -> 15.96 | P83: =Worldprices!$O$74*P$6 -> 15.96 | Q83: =Worldprices!$O$74*Q$6 -> 15.96 | ... AP83: =Worldprices!$O$74*AP$6 -> 15.96 | AQ83: =AP83 -> 15.96
A84: ANNUAL | B84: EUR10 | C84: COST | D84: 2045 | E84: =Worldprices!$P$62 -> IMPOILNEU | F84: =Worldprices!$P$63 -> OILNEU | G84: =Worldprices!$P$74*G$6 -> 15.96 | H84: =Worldprices!$P$74*H$6 -> 15.96 | I84: =AH84 -> 15.96 | J84: =Worldprices!$P$74*J$6 -> 15.96 | K84: =Worldprices!$P$74*K$6 -> 15.96 | L84: =Worldprices!$P$74*L$6 -> 15.96 | M84: =Worldprices!$P$74*M$6 -> 15.96 | N84: =Worldprices!$P$74*N$6 -> 15.96 | O84: =Worldprices!$P$74*O$6 -> 15.96 | P84: =Worldprices!$P$74*P$6 -> 15.96 | Q84: =Worldprices!$P$74*Q$6 -> 15.96 | ... AP84: =Worldprices!$P$74*AP$6 -> 15.96 | AQ84: =AP84 -> 15.96
A85: ANNUAL | B85: EUR10 | C85: *COST | D85: 2045 | E85: =Worldprices!$R$62 -> IMPBIOWOO | F85: =Worldprices!$R$63 -> BIOWOO | G85: =Worldprices!$R$74*G$8 -> 6.7655541 | H85: =Worldprices!$R$74*H$8 -> 6.7655541 | I85: =AH85 -> 6.7655541 | J85: =Worldprices!$R$74*J$8 -> 6.7655541 | K85: =Worldprices!$R$74*K$8 -> 6.7655541 | L85: =Worldprices!$R$74*L$8 -> 6.7655541 | M85: =Worldprices!$R$74*M$8 -> 6.7655541 | N85: =Worldprices!$R$74*N$8 -> 6.7655541 | O85: =Worldprices!$R$74*O$8 -> 6.7655541 | P85: =Worldprices!$R$74*P$8 -> 6.7655541 | Q85: =Worldprices!$R$74*Q$8 -> 6.7655541 | ... AP85: =Worldprices!$R$74*AP$8 -> 6.7655541 | AQ85: =AP85 -> 6.7655541
A86: ANNUAL | B86: EUR10 | C86: COST | D86: 2050 | E86: =Worldprices!$C$62 -> IMPCOAHAR* | F86: =Worldprices!$C$63 -> COAHAR | G86: =Worldprices!$C$75*G$4 -> 3.28 | H86: =Worldprices!$C$75*H$4 -> 3.0668 | I86: =AH86 -> 3.28 | J86: =Worldprices!$C$75*J$4 -> 3.28 | K86: =Worldprices!$C$75*K$4 -> 3.28 | L86: =Worldprices!$C$75*L$4 -> 3.28 | M86: =Worldprices!$C$75*M$4 -> 3.28 | N86: =Worldprices!$C$75*N$4 -> 3.28 | O86: =Worldprices!$C$75*O$4 -> 2.788 | P86: =Worldprices!$C$75*P$4 -> 3.116 | Q86: =Worldprices!$C$75*Q$4 -> 3.28 | ... AP86: =Worldprices!$C$75*AP$4 -> 3.28 | AQ86: =AP86 -> 3.28
A87: ANNUAL | B87: EUR10 | C87: COST | D87: 2050 | E87: =Worldprices!$D$62 -> IMPCOACOK* | F87: =Worldprices!$D$63 -> COACOK | G87: =Worldprices!$D$75*G$4 -> 4.1656 | H87: =Worldprices!$D$75*H$4 -> 3.894836 | I87: =AH87 -> 4.1656 | J87: =Worldprices!$D$75*J$4 -> 4.1656 | K87: =Worldprices!$D$75*K$4 -> 4.1656 | L87: =Worldprices!$D$75*L$4 -> 4.1656 | M87: =Worldprices!$D$75*M$4 -> 4.1656 | N87: =Worldprices!$D$75*N$4 -> 4.1656 | O87: =Worldprices!$D$75*O$4 -> 3.54076 | P87: =Worldprices!$D$75*P$4 -> 3.95732 | Q87: =Worldprices!$D$75*Q$4 -> 4.1656 | ... AP87: =Worldprices!$D$75*AP$4 -> 4.1656 | AQ87: =AP87 -> 4.1656
A88: ANNUAL | B88: EUR10 | C88: COST | D88: 2050 | E88: =Worldprices!$E$62 -> IMPCOABRO* | F88: =Worldprices!$E$63 -> COABRO | G88: =Worldprices!$E$75*G$4 -> 3.116 | H88: =Worldprices!$E$75*H$4 -> 2.91346 | I88: =AH88 -> 3.116 | J88: =Worldprices!$E$75*J$4 -> 3.116 | K88: =Worldprices!$E$75*K$4 -> 3.116 | L88: =Worldprices!$E$75*L$4 -> 3.116 | M88: =Worldprices!$E$75*M$4 -> 3.116 | N88: =Worldprices!$E$75*N$4 -> 3.116 | O88: =Worldprices!$E$75*O$4 -> 2.6486 | P88: =Worldprices!$E$75*P$4 -> 2.9602 | Q88: =Worldprices!$E$75*Q$4 -> 3.116 | ... AP88: =Worldprices!$E$75*AP$4 -> 3.116 | AQ88: =AP88 -> 3.116
A89: ANNUAL | B89: EUR10 | C89: COST | D89: 2050 | E89: =Worldprices!$F$62 -> IMPCOALIG* | F89: =Worldprices!$F$63 -> COALIG | G89: =Worldprices!$F$75*G$4 -> 3.116 | H89: =Worldprices!$F$75*H$4 -> 2.91346 | I89: =AH89 -> 3.116 | J89: =Worldprices!$F$75*J$4 -> 3.116 | K89: =Worldprices!$F$75*K$4 -> 3.116 | L89: =Worldprices!$F$75*L$4 -> 3.116 | M89: =Worldprices!$F$75*M$4 -> 3.116 | N89: =Worldprices!$F$75*N$4 -> 3.116 | O89: =Worldprices!$F$75*O$4 -> 2.6486 | P89: =Worldprices!$F$75*P$4 -> 2.9602 | Q89: =Worldprices!$F$75*Q$4 -> 3.116 | ... AP89: =Worldprices!$F$75*AP$4 -> 3.116 | AQ89: =AP89 -> 3.116
A90: ANNUAL | B90: EUR10 | C90: COST | D90: 2050 | E90: =Worldprices!$M$62 -> IMPOILOTH | F90: =Worldprices!$M$63 -> OILOTH | G90: =Worldprices!$M$75*G$6 -> 17.47 | H90: =Worldprices!$M$75*H$6 -> 17.47 | I90: =AH90 -> 17.47 | J90: =Worldprices!$M$75*J$6 -> 17.47 | K90: =Worldprices!$M$75*K$6 -> 17.47 | L90: =Worldprices!$M$75*L$6 -> 17.47 | M90: =Worldprices!$M$75*M$6 -> 17.47 | N90: =Worldprices!$M$75*N$6 -> 17.47 | O90: =Worldprices!$M$75*O$6 -> 17.47 | P90: =Worldprices!$M$75*P$6 -> 17.47 | Q90: =Worldprices!$M$75*Q$6 -> 17.47 | ... AP90: =Worldprices!$M$75*AP$6 -> 17.47 | AQ90: =AP90 -> 17.47
A91: ANNUAL | B91: EUR10 | C91: COST | D91: 2050 | E91: =Worldprices!$N$62 -> IMPOILNAP | F91: =Worldprices!$N$63 -> OILNAP | G91: =Worldprices!$N$75*G$6 -> 17.47 | H91: =Worldprices!$N$75*H$6 -> 17.47 | I91: =AH91 -> 17.47 | J91: =Worldprices!$N$75*J$6 -> 17.47 | K91: =Worldprices!$N$75*K$6 -> 17.47 | L91: =Worldprices!$N$75*L$6 -> 17.47 | M91: =Worldprices!$N$75*M$6 -> 17.47 | N91: =Worldprices!$N$75*N$6 -> 17.47 | O91: =Worldprices!$N$75*O$6 -> 17.47 | P91: =Worldprices!$N$75*P$6 -> 17.47 | Q91: =Worldprices!$N$75*Q$6 -> 17.47 | ... AP91: =Worldprices!$N$75*AP$6 -> 17.47 | AQ91: =AP91 -> 17.47
A92: ANNUAL | B92: EUR10 | C92: COST | D92: 2050 | E92: =Worldprices!$O$62 -> IMPOILFDS | F92: =Worldprices!$O$63 -> OILFDS | G92: =Worldprices!$O$75*G$6 -> 17.47 | H92: =Worldprices!$O$75*H$6 -> 17.47 | I92: =AH92 -> 17.47 | J92: =Worldprices!$O$75*J$6 -> 17.47 | K92: =Worldprices!$O$75*K$6 -> 17.47 | L92: =Worldprices!$O$75*L$6 -> 17.47 | M92: =Worldprices!$O$75*M$6 -> 17.47 | N92: =Worldprices!$O$75*N$6 -> 17.47 | O92: =Worldprices!$O$75*O$6 -> 17.47 | P92: =Worldprices!$O$75*P$6 -> 17.47 | Q92: =Worldprices!$O$75*Q$6 -> 17.47 | ... AP92: =Worldprices!$O$75*AP$6 -> 17.47 | AQ92: =AP92 -> 17.47
A93: ANNUAL | B93: EUR10 | C93: COST | D93: 2050 | E93: =Worldprices!$P$62 -> IMPOILNEU | F93: =Worldprices!$P$63 -> OILNEU | G93: =Worldprices!$P$75*G$6 -> 17.47 | H93: =Worldprices!$P$75*H$6 -> 17.47 | I93: =AH93 -> 17.47 | J93: =Worldprices!$P$75*J$6 -> 17.47 | K93: =Worldprices!$P$75*K$6 -> 17.47 | L93: =Worldprices!$P$75*L$6 -> 17.47 | M93: =Worldprices!$P$75*M$6 -> 17.47 | N93: =Worldprices!$P$75*N$6 -> 17.47 | O93: =Worldprices!$P$75*O$6 -> 17.47 | P93: =Worldprices!$P$75*P$6 -> 17.47 | Q93: =Worldprices!$P$75*Q$6 -> 17.47 | ... AP93: =Worldprices!$P$75*AP$6 -> 17.47 | AQ93: =AP93 -> 17.47
A94: ANNUAL | B94: EUR10 | C94: *COST | D94: 2050 | E94: =Worldprices!$R$62 -> IMPBIOWOO | F94: =Worldprices!$R$63 -> BIOWOO | G94: =Worldprices!$R$75*G$8 -> 7.3967725 | H94: =Worldprices!$R$75*H$8 -> 7.3967725 | I94: =AH94 -> 7.3967725 | J94: =Worldprices!$R$75*J$8 -> 7.3967725 | K94: =Worldprices!$R$75*K$8 -> 7.3967725 | L94: =Worldprices!$R$75*L$8 -> 7.3967725 | M94: =Worldprices!$R$75*M$8 -> 7.3967725 | N94: =Worldprices!$R$75*N$8 -> 7.3967725 | O94: =Worldprices!$R$75*O$8 -> 7.3967725 | P94: =Worldprices!$R$75*P$8 -> 7.3967725 | Q94: =Worldprices!$R$75*Q$8 -> 7.3967725 | ... AP94: =Worldprices!$R$75*AP$8 -> 7.3967725 | AQ94: =AP94 -> 7.3967725
